Workbook
Name OLE_LINK1: 'Annex 3 Preserved charges'!#REF!

Sheet Overview
A2: Company and Licence name, charging year, effective from, status
B3: Company and Licence name | C3: Year | D3: Effective From | E3: Status
A4: Company and Licence name, charging year, effective from, status | B4: London Power Networks | C4: 2022/23 | D4: 1 April 2022 | E4: Final
A6: List of data tables in this workbook
A7: Worksheet | B7: Information
A8: Annex 1 LV, HV and Unmetered Supplies charges | B8: Annex 1 contains the charges to LV and HV Designated Properties and Unmetered Supplies.
A9: Annex 2 EHV charges | B9: ="Annex 2 contains the charges to Designated EHV Properties and charges applied to LDNOs with Designated EHV Properties/end-users embedded in networks within the " &B4 &" Licence area." -> Annex 2 contains the charges to Designated EHV Properties and charges applied to LDNOs with Designated EHV Properties/end-users embedded in networks within the London Power Networks Licence area.
A10: Annex 3 Preserved charges | B10: Annex 3 contains details of any preserved and additional charges that are valid at this time.
A11: Annex 4 LDNO charges | B11: ="Annex 4 contains charges that are levied on the owner of an embedded network within the "&B4&" Licence area. "&"Electricity suppliers and consumers who have properties connected to an embedded network should contact the embedded network owner to determine their distribution charges."&" The charges listed in this table are not payable by domestic consumers, business consumers or electricity suppliers." -> Annex 4 contains charges that are levied on the owner of an embedded network within the London Power Networks Licence area. Electricity suppliers and consumers who have properties connected to an embedded network should contact the embedded network owner to determine their distribution charges. The charges listed in this table are not payable by domestic consumers, business consumers or electricity suppliers.
A12: Annex 5 LLFs | B12: Annex 5 has been intentionally left blank as this charging statement is published a complete year before the LLFs have been audited. The line loss factors that are approved by the BSC Panel for the applicable year and consequently published on the Elexon website will take precedence and be used in Settlement. This annex will be re-published with these values once they are available.
A13: Annex 6 Charges for New or Amended Designated EHV Properties | B13: ="Annex 6 contains the charges for new or amended Designated EHV Properties and charges applied to LDNOs with new or amended Designated EHV Properties/end-users embedded in networks within the " &B4 &" Licence area." -> Annex 6 contains the charges for new or amended Designated EHV Properties and charges applied to LDNOs with new or amended Designated EHV Properties/end-users embedded in networks within the London Power Networks Licence area.
A14: Annex 7 Fixed adders for Supplier of Last Resort and Eligible Bad Debt pass-through costs | B14: Annex 7 contains the fixed adders to recover Supplier of Last Resort and Eligible Bad Debt pass-through costs. The Excess Supplier of Last Resort fixed adder relates to an increase to previously published charges only.
A15: Nodal prices | B15: Contains the underlying nodal costs used to calculate the current EDCM charges.
A16: Residual Charging Bandings | B16: Contains the four Residual charging band allocation for Customers
A17: Charge calculator | B17: Charge calculator is a tool to help you estimate your distribution charges using current consumption data and forecast consumption data.
A19: Notes to users of this spreadsheet
A21: Please use this spreadsheet with reference to the LC14 use of system charging statement.
A23: Notes to DNOs populating this spreadsheet
A25: DNOs must endeavour to maintain consistency in the structure of this spreadsheet. Any changes to the structure must be noted in the 'Notes to users of this spreadsheet'
A26: The drop down list on the charge calculator can be expanded by unprotecting the charge calculator sheet and selecting 'data', 'data validation...' and then expanding the 'source' data range. The sheet can then be protected.

Sheet Annex 1 LV, HV and UMS charges
A1: Back to Overview
A2: =Overview!B4& " - Effective from "&Overview!D4&" - "&Overview!E4&" LV and HV charges" -> London Power Networks - Effective from 1 April 2022 - Final LV and HV charges
A4: Time Bands for LV and HV Designated Properties | G4: Time Bands for Unmetered Properties
A5: Time periods | B5: Red Time Band | C5: Amber Time Band | E5: Green Time Band | I5: Black Time Band | J5: Yellow Time Band | K5: Green Time Band
A6: Monday to Friday (Including Bank Holidays) All Year | B6: 11:00 - 14:00 16:00 - 19:00 | C6: 07:00 - 11:00 14:00 - 16:00 19:00 - 23:00 | E6: 00:00 - 07:00 23:00 - 24:00 | G6: Monday to Friday (Including Bank Holidays) June to August Inclusive | I6: 11:00 - 14:00 | J6: 07:00 - 11:00 14:00 - 23:00 | K6: 00:00 - 07:00 23:00 - 24:00
A7: Saturday and Sunday All Year | E7: 00:00 - 24:00 | G7: Monday to Friday (Including Bank Holidays) November to February Inclusive | I7: 16:00 - 19:00 | J7: 07:00 - 16:00 19:00 - 23:00 | K7: 00:00 - 07:00 23:00 - 24:00
A8: Notes | B8: All the above times are in UK Clock time | G8: Monday to Friday (Including Bank Holidays) March, April, May and September, October | J8: 07:00 - 23:00 | K8: 00:00 - 07:00 23:00 - 24:00
G9: Saturday and Sunday All year | K9: 00:00 - 24:00
G10: Notes | I10: All the above times are in UK Clock time
A12: Tariff name | B12: Open LLFCs | C12: PCs | D12: Red/black unit charge p/kWh | E12: Amber/yellow unit charge p/kWh | F12: Green unit charge p/kWh | G12: Fixed charge p/MPAN/day | H12: Capacity charge p/kVA/day | I12: Exceeded capacity charge p/kVA/day | J12: Reactive power charge p/kVArh | K12: Closed LLFCs
A13: Domestic Aggregated with Residual | B13: 1 | C13: 0, 1, 2 | D13: 9.469 | E13: 1.785 | F13: 0.057 | G13: 10.86 | K13: 902, 903, 906, 907, 910
A14: Domestic Aggregated (Related MPAN) | B14: 2 | C14: 2 | D14: 9.469 | E14: 1.785 | F14: 0.057 | K14: 911, 914, 915
A15: Non-Domestic Aggregated No Residual | B15: 199 | C15: 0, 3, 4, 5-8 | D15: 5.793 | E15: 1.092 | F15: 0.035 | G15: 3.2
A16: Non-Domestic Aggregated Band 1 | B16: 201 | C16: 0, 3, 4, 5-8 | D16: 5.793 | E16: 1.092 | F16: 0.035 | G16: 2.43 | K16: 200, 400, 404, 952, 953, 956, 957, 960, 961, 970, 971
A17: Non-Domestic Aggregated Band 2 | B17: 202 | C17: 0, 3, 4, 5-8 | D17: 5.668 | E17: 0.967 | F17: 0 | G17: 0
A18: Non-Domestic Aggregated Band 3 | B18: 203 | C18: 0, 3, 4, 5-8 | D18: 5.519 | E18: 0.818 | F18: 0 | G18: 0
A19: Non-Domestic Aggregated Band 4 | B19: 204 | C19: 0, 3, 4, 5-8 | D19: 5.445 | E19: 0.744 | F19: 0 | G19: 0
A20: Non-Domestic Aggregated (related MPAN) | B20: 200 | C20: 4 | D20: 5.793 | E20: 1.092 | F20: 0.035 | K20: 964965
A21: LV Site Specific No Residual | B21: 70 | C21: 0 | D21: 4.769 | E21: 0.916 | F21: 0.031 | G21: 7.93 | H21: 4.29 | I21: 6.66 | J21: 0.409 | K21: 19
A22: LV Site Specific Band 1 | B22: 71 | C22: 0 | D22: 4.392 | E22: 0.539 | F22: 0.007 | G22: 2.07 | H22: 4.29 | I22: 6.66 | J22: 0.409 | K22: 9
A23: LV Site Specific Band 2 | B23: 72 | C23: 0 | D23: 4.382 | E23: 0.529 | F23: 0.007 | G23: 2.07 | H23: 4.29 | I23: 6.66 | J23: 0.409
A24: LV Site Specific Band 3 | B24: 73 | C24: 0 | D24: 4.372 | E24: 0.52 | F24: 0.007 | G24: 2.07 | H24: 4.29 | I24: 6.66 | J24: 0.409
A25: LV Site Specific Band 4 | B25: 74 | C25: 0 | D25: 4.365 | E25: 0.512 | F25: 0.007 | G25: 2.07 | H25: 4.29 | I25: 6.66 | J25: 0.409
A26: LV Sub Site Specific No Residual | B26: 80 | C26: 0 | D26: 3.237 | E26: 0.654 | F26: 0.024 | G26: 5.86 | H26: 7.53 | I26: 8.57 | J26: 0.241 | K26: 79
A27: LV Sub Site Specific Band 1 | B27: 81 | C27: 0 | D27: 2.86 | E27: 0.277 | F27: 0 | G27: 0 | H27: 7.53 | I27: 8.57 | J27: 0.241 | K27: 756
A28: LV Sub Site Specific Band 2 | B28: 82 | C28: 0 | D28: 2.85 | E28: 0.267 | F28: 0 | G28: 0 | H28: 7.53 | I28: 8.57 | J28: 0.241
A29: LV Sub Site Specific Band 3 | B29: 83 | C29: 0 | D29: 2.841 | E29: 0.257 | F29: 0 | G29: 0 | H29: 7.53 | I29: 8.57 | J29: 0.241
A30: LV Sub Site Specific Band 4 | B30: 84 | C30: 0 | D30: 2.833 | E30: 0.25 | F30: 0 | G30: 0 | H30: 7.53 | I30: 8.57 | J30: 0.241
A31: HV Site Specific No Residual | B31: 90 | C31: 0 | D31: 2.375 | E31: 0.462 | F31: 0.017 | G31: 78.57 | H31: 7.67 | I31: 8.62 | J31: 0.204 | K31: 89
A32: HV Site Specific Band 1 | B32: 91 | C32: 0 | D32: 2.023 | E32: 0.111 | F32: 0 | G32: 0 | H32: 7.67 | I32: 8.62 | J32: 0.204 | K32: 359
A33: HV Site Specific Band 2 | B33: 92 | C33: 0 | D33: 1.977 | E33: 0.065 | F33: 0 | G33: 0 | H33: 7.67 | I33: 8.62 | J33: 0.204
A34: HV Site Specific Band 3 | B34: 93 | C34: 0 | D34: 1.966 | E34: 0.053 | F34: 0 | G34: 0 | H34: 7.67 | I34: 8.62 | J34: 0.204
A35: HV Site Specific Band 4 | B35: 94 | C35: 0 | D35: 1.954 | E35: 0.042 | F35: 0 | G35: 0 | H35: 7.67 | I35: 8.62 | J35: 0.204
A36: Unmetered Supplies | B36: 350, 420, 421, 422, 423 | C36: 0, 1 or 8 | D36: 30.621 | E36: 2.281 | F36: 0.289 | K36: 424, 425, 426, 427, 428, 429, 430, 431, 432, 433, 434, 435
A37: LV Generation Aggregated | B37: 932 | C37: 0 | D37: -5.239 | E37: -0.987 | F37: -0.032 | G37: 0 | K37: 753, 763, 762
A38: LV Sub Generation Aggregated | C38: 0 | D38: -4.614 | E38: -0.879 | F38: -0.029 | G38: 0
A39: LV Generation Site Specific | B39: 980 | C39: 0 | D39: -5.239 | E39: -0.987 | F39: -0.032 | G39: 0 | J39: 0.361 | K39: 982
A40: LV Generation Site Specific no RP charge | B40: 981 | C40: 0 | D40: -5.239 | E40: -0.987 | F40: -0.032 | G40: 0 | K40: 983
A41: LV Sub Generation Site Specific | B41: 984 | C41: 0 | D41: -4.614 | E41: -0.879 | F41: -0.029 | G41: 0 | J41: 0.322 | K41: 986
A42: LV Sub Generation Site Specific no RP charge | B42: 985 | C42: 0 | D42: -4.614 | E42: -0.879 | F42: -0.029 | G42: 0 | K42: 987
A43: HV Generation Site Specific | B43: 988 | C43: 0 | D43: -2.954 | E43: -0.596 | F43: -0.022 | G43: 6.65 | J43: 0.28 | K43: 990
A44: HV Generation Site Specific no RP charge | B44: 989 | C44: 0 | D44: -2.954 | E44: -0.596 | F44: -0.022 | G44: 6.65 | K44: 991

Sheet Annex 2 EHV charges
A1: Back to Overview | F1: Note: The list of MPANs / MSIDs provided may be incomplete; the DNO reserves the right to apply the listed charges to any other MPANs / MSIDs associated with the site.
A2: =Overview!B4& " - Effective from "&Overview!D4&" - "&Overview!E4&" EDCM charges" -> London Power Networks - Effective from 1 April 2022 - Final EDCM charges
A4: Time Periods for Designated EHV Properties
A5: Time periods | D5: Super Red Time Band
A6: Monday to Friday (Including Bank Holidays) June to August Inclusive | D6: 11:00 - 14:00
A7: Monday to Friday (Including Bank Holidays) November to February Inclusive | D7: 16:00 - 19:00
A8: Notes | D8: All the above times are in UK Clock time
A10: Import Unique Identifier | B10: LLFC | C10: Import MPANs/MSIDs | D10: Export Unique Identifier | E10: LLFC | F10: Export MPANs/MSIDs | G10: Name | H10: Import Super Red unit charge (p/kWh) | I10: Import fixed charge (p/day) | J10: Import capacity charge (p/kVA/day) | K10: Import exceeded capacity charge (p/kVA/day) | L10: Export Super Red unit charge (p/kWh) | M10: Export fixed charge (p/day) | N10: Export capacity charge (p/kVA/day) | O10: Export exceeded capacity charge (p/kVA/day)
A11: 22BSHP | B11: 810 | C11: 1200062355497 1200062355502 | G11: 22BSHP | H11: 0.245 | I11: 6147.17 | J11: 1.13 | K11: 1.13
A12: BISHPC | B12: 811 | C12: 1200061143976 1200061143985 | G12: BISHPC | H12: 0.189 | I12: 17915.96 | J12: 1.53 | K12: 1.53
A13: BLMBGN | B13: 820 | C13: 1200061385700 1200061385710 | G13: BLMBGN | H13: 0.197 | I13: 5951.01 | J13: 1.8 | K13: 1.8
A14: BLMBGS | B14: 821 | C14: 1200061385729 1200061385738 | G14: BLMBGS | H14: 0.157 | I14: 1066.62 | J14: 1.31 | K14: 1.31
A15: BRDGTE | B15: 805 | C15: 1200061148014 1200061148023 | G15: BRDGTE | H15: 0.186 | I15: 5951.01 | J15: 2.58 | K15: 2.58
A16: BRKFLD | B16: 829 | C16: 1200061148060 1200061148079 | G16: BRKFLD | H16: 0.182 | I16: 6147.17 | J16: 1.81 | K16: 1.81
A17: BRMLEY | C17: MSID: 1630 | G17: BRMLEY | H17: 0 | I17: 43861.69 | J17: 3.12 | K17: 3.12
A18: CRLIMM | B18: 812 | C18: 1200062090483 1200062090492 | G18: CRLIMM | H18: 0 | I18: 51301.59 | J18: 0.98 | K18: 0.98
A19: DART11 | C19: MSID: 1032 | G19: DART11 | H19: 0.217 | I19: 5754.85 | J19: 5.11 | K19: 5.11
A20: DART33 | C20: MSID: 1032 | G20: DART33 | H20: 0.427 | I20: 17523.64 | J20: 5.27 | K20: 5.27
A21: EPNLEI | C21: MSID: 1628 | G21: EPNLEI | H21: 0 | I21: 43861.69 | J21: 3.51 | K21: 3.51
A22: FENAVE | B22: 813 | C22: 1200062132159 1200062132168 | G22: FENAVE | H22: 0.185 | I22: 6147.17 | J22: 1.62 | K22: 1.62
A23: FENCHS | B23: 800 | C23: 1200061144029 1200061144038 | G23: FENCHS | H23: 0.167 | I23: 6266.15 | J23: 2.57 | K23: 2.57
A24: GBLSWI | B24: 843 | C24: 1200050913681 1200050913690 1200050913706 1200050913715 | G24: GBLSWI | H24: 0 | I24: 51413.33 | J24: 2.05 | K24: 2.05
A25: KNGLPN | C25: MSID: 1027 | G25: KNGLPN | H25: 0 | I25: 5754.85 | J25: 0.9 | K25: 0.9
A26: LEDNHS | B26: 808 | C26: 1200061144065 1200061144074 | G26: LEDNHS | H26: 0.188 | I26: 6194.76 | J26: 1.4 | K26: 1.4
A27: LIMEST | B27: 814 | C27: 1200062132006 1200062132015 | G27: LIMEST | H27: 0.18 | I27: 6147.17 | J27: 1.69 | K27: 1.69
A28: LNWAL1 | B28: 816 | C28: 1200061148194 1200061148200 | G28: LNWAL1 | H28: 0.364 | I28: 1437.08 | J28: 2.82 | K28: 2.82
A29: LNWALL | B29: 816 | C29: 1200061953070 1200061953089 | G29: LNWALL | H29: 0.364 | I29: 6321.47 | J29: 1.54 | K29: 1.54
A30: LU_ACT | C30: MSID: 1631 | G30: LU_ACT | H30: 0 | I30: 5959.98 | J30: 2.22 | K30: 2.22
A31: LU_CAN | B31: 818 | C31: 1200060323207 1200060323216 | G31: LU_CAN | H31: 0 | I31: 50481.63 | J31: 1.09 | K31: 1.09
A32: LU_CHA | B32: 801 | C32: 1200061231921 1200061231930 1200061231940 1200061231959 | G32: LU_CHA | H32: 0 | I32: 51099.15 | J32: 1.28 | K32: 1.28
A33: LU_HOX | B33: 804 | C33: 1200060323191 | G33: LU_HOX | H33: 0 | I33: 50387.62 | J33: 0.47 | K33: 0.47
A34: LU_LOT | B34: 838 | C34: 1200050376902 1200050376911 | G34: LU_LOT | H34: 0 | I34: 76308.74 | J34: 2.13 | K34: 2.13
A35: LU_MAN | B35: 837 | C35: 1200010200926 | G35: LU_MAN | H35: 0.026 | I35: 66672.24 | J35: 1.44 | K35: 1.44
A36: LU_STE | B36: 839 | C36: 1200010157225 1200010157234 | G36: LU_STE | H36: 0 | I36: 50003.99 | J36: 2.93 | K36: 2.93
A37: MRKLNE | B37: 806 | C37: 1200061378624 1200061378633 | G37: MRKLNE | H37: 0.173 | I37: 1262.78 | J37: 1.83 | K37: 1.83
A38: NGC_BA | B38: 817 | C38: 1200010151863 1200010151872 | G38: NGC_BA | H38: 0.258 | I38: 870.46 | J38: 0.8 | K38: 0.8
A39: NR_BOW | B39: 807 | C39: 1200060280440 1200060280468 | G39: NR_BOW | H39: 0 | I39: 22833.28 | J39: 3.99 | K39: 3.99
A40: NR_BRO | B40: 847 | C40: 1200010251559 | G40: NR_BRO | H40: 0 | I40: 46038.69 | J40: 1.68 | K40: 1.68
A41: NR_CIT | B41: 846 | C41: 1200010251521 | G41: NR_CIT | H41: 2.651 | I41: 938.84 | J41: 2.08 | K41: 2.08
A42: NR_MAD | B42: 840 | C42: 1200010251540 | G42: NR_MAD | H42: 0 | I42: 1007.21 | J42: 0.78 | K42: 0.78
A43: NR_W11 | B43: 841 | C43: 1200010251512 | G43: NR_W11 | H43: 0 | I43: 23224.55 | J43: 1.91 | K43: 1.91
A44: NR_W25 | B44: 842 | C44: 1200010251498 | G44: NR_W25 | H44: 0.045 | I44: 22398.72 | J44: 2.37 | K44: 2.37
A45: NR_WES | B45: 848 | C45: 1200010251568 | D45: NR_WES | E45: 716 | F45: 1200052486875 | G45: NR_WES | H45: 0 | I45: 48741.78 | J45: 2.02 | K45: 2.02 | L45: 0 | M45: 387.31 | N45: 0.05 | O45: 0.05
A46: NR_WHI | B46: 849 | C46: 1200050493611 | G46: NR_WHI | H46: 4 | I46: 938.84 | J46: 2.55 | K46: 2.55
A47: NR_WIM | B47: 844 | C47: 1200010200874 | G47: NR_WIM | H47: 0 | I47: 52121.53 | J47: 2.05 | K47: 2.05
A48: TELEHW | B48: 809 | C48: 1200060951114 1200060951123 | G48: TELEHW | H48: 0 | I48: 44821.92 | J48: 1.6 | K48: 1.6
A49: THAMEB | B49: 828 | C49: 1200010146153 1200010146162 1200010146171 1200061197703 | D49: THAMEB | E49: 701 | F49: 1200050312030 1200050312040 1200061219394 | G49: THAMEB | H49: 0 | I49: 47159.57 | J49: 0.6 | K49: 0.6 | L49: 0 | M49: 0 | N49: 0 | O49: 0
A50: THAMEC | B50: 802 | C50: 1200061171324 1200061171333 | D50: THAMEC | E50: 702 | F50: 1200061171342 1200061171351 | G50: THAMEC | H50: 0 | I50: 46747.44 | J50: 1.17 | K50: 1.17 | L50: 0 | M50: 675.05 | N50: 0.05 | O50: 0.05
A51: TWCHST | B51: 819 | C51: 1200061990150 | G51: TWCHST | H51: 0 | I51: 9089.88 | J51: 0.53 | K51: 0.53
A52: TWGNCH | B52: 822 | C52: 1200061990319 | G52: TWGNCH | H52: 0 | I52: 1007.21 | J52: 0.59 | K52: 0.59
A53: TWKIRT | B53: 823 | C53: 1200061999491 1200061999507 1200062001242 1200062001251 | G53: TWKIRT | H53: 0.658 | I53: 17660.39 | J53: 1.06 | K53: 1.06
A54: VOLTDC | B54: 803 | C54: 1200061148032 1200061148041 | G54: VOLTDC | H54: 0.206 | I54: 6305.81 | J54: 1.53 | K54: 1.53
A55: BELVED | B55: 815 | C55: 1200060787109 | D55: BELVED | E55: 711 | F55: 1200060787118 | G55: BELVED | H55: 0 | I55: 44193.47 | J55: 0.47 | K55: 0.47 | L55: 0 | M55: 628.44 | N55: 0.05 | O55: 0.05
A56: SELCHP | B56: 827 | C56: 1200010175650 | D56: SELCHP | E56: 730 | F56: 1200010258304 | G56: SELCHP | H56: 0 | I56: 1163.32 | J56: 0.65 | K56: 0.65 | L56: 0 | M56: 3106.09 | N56: 0.05 | O56: 0.05
A57: TLRSLN | C57: MSID: 5538 | D57: TLRSLN | F57: MSID: 5538 | G57: TLRSLN | H57: 0 | I57: 903.03 | J57: 0.88 | K57: 0.88 | L57: -0.059 | M57: 3039.7 | N57: 0.05 | O57: 0.05

Sheet Annex 2a Import
A1: Note: The list of MPANs / MSIDs provided may be incomplete; the DNO reserves the right to apply the listed charges to any other MPANs / MSIDs associated with the site. Note: This table is automatically populated based on the content of the tab entitled 'Annex 2 EHV Charges'. The timebands are as shown in Annex 2.
A2: =Overview!B4& " - Effective from "&Overview!D4&" - "&Overview!E4&" EDCM import charges" -> London Power Networks - Effective from 1 April 2022 - Final EDCM import charges
A4: Import Unique Identifier | B4: LLFC | C4: Import MPANs/MSIDs | D4: Name | E4: ='Annex 2 EHV charges'!H10 -> Import Super Red unit charge (p/kWh) | F4: ='Annex 2 EHV charges'!I10 -> Import fixed charge (p/day) | G4: ='Annex 2 EHV charges'!J10 -> Import capacity charge (p/kVA/day) | H4: ='Annex 2 EHV charges'!K10 -> Import exceeded capacity charge (p/kVA/day)
A5: {=IFERROR(INDEX('Annex 2 EHV charges'!$A$11:$A$59, MATCH(0, IF(ISBLANK('Annex 2 EHV charges'!$A$11:$A$59),1, COUNTIF(A$4:$A4, 'Annex 2 EHV charges'!$A$11:$A$59)), 0)),"")} -> 22BSHP | B5: =IF($A5="","",VLOOKUP($A5,'Annex 2 EHV charges'!$A:$O,2,0)) -> 810 | C5: =IF($A5="","",VLOOKUP($A5,'Annex 2 EHV charges'!$A:$O,3,0)) -> 1200062355497 1200062355502 | D5: =IF($A5="","",VLOOKUP($A5,'Annex 2 EHV charges'!$A:$O,7,0)) -> 22BSHP | E5: =IFERROR(IF(VLOOKUP($A5,'Annex 2 EHV charges'!$A:$O,8,FALSE)=0,"",VLOOKUP($A5,'Annex 2 EHV charges'!$A:$O,8,FALSE)),"") -> 0.245 | F5: =IFERROR(IF(VLOOKUP($A5,'Annex 2 EHV charges'!$A:$O,9,FALSE)=0,"",VLOOKUP($A5,'Annex 2 EHV charges'!$A:$O,9,FALSE)),"") -> 6147.17 | G5: =IFERROR(IF(VLOOKUP($A5,'Annex 2 EHV charges'!$A:$O,10,FALSE)=0,"",VLOOKUP($A5,'Annex 2 EHV charges'!$A:$O,10,FALSE)),"") -> 1.13 | H5: =IFERROR(IF(VLOOKUP($A5,'Annex 2 EHV charges'!$A:$O,11,FALSE)=0,"",VLOOKUP($A5,'Annex 2 EHV charges'!$A:$O,11,FALSE)),"") -> 1.13
A6: {=IFERROR(INDEX('Annex 2 EHV charges'!$A$11:$A$59, MATCH(0, IF(ISBLANK('Annex 2 EHV charges'!$A$11:$A$59),1, COUNTIF(A$4:$A5, 'Annex 2 EHV charges'!$A$11:$A$59)), 0)),"")} -> BISHPC | B6: =IF($A6="","",VLOOKUP($A6,'Annex 2 EHV charges'!$A:$O,2,0)) -> 811 | C6: =IF($A6="","",VLOOKUP($A6,'Annex 2 EHV charges'!$A:$O,3,0)) -> 1200061143976 1200061143985 | D6: =IF($A6="","",VLOOKUP($A6,'Annex 2 EHV charges'!$A:$O,7,0)) -> BISHPC | E6: =IFERROR(IF(VLOOKUP($A6,'Annex 2 EHV charges'!$A:$O,8,FALSE)=0,"",VLOOKUP($A6,'Annex 2 EHV charges'!$A:$O,8,FALSE)),"") -> 0.189 | F6: =IFERROR(IF(VLOOKUP($A6,'Annex 2 EHV charges'!$A:$O,9,FALSE)=0,"",VLOOKUP($A6,'Annex 2 EHV charges'!$A:$O,9,FALSE)),"") -> 17915.96 | G6: =IFERROR(IF(VLOOKUP($A6,'Annex 2 EHV charges'!$A:$O,10,FALSE)=0,"",VLOOKUP($A6,'Annex 2 EHV charges'!$A:$O,10,FALSE)),"") -> 1.53 | H6: =IFERROR(IF(VLOOKUP($A6,'Annex 2 EHV charges'!$A:$O,11,FALSE)=0,"",VLOOKUP($A6,'Annex 2 EHV charges'!$A:$O,11,FALSE)),"") -> 1.53
A7: {=IFERROR(INDEX('Annex 2 EHV charges'!$A$11:$A$59, MATCH(0, IF(ISBLANK('Annex 2 EHV charges'!$A$11:$A$59),1, COUNTIF(A$4:$A6, 'Annex 2 EHV charges'!$A$11:$A$59)), 0)),"")} -> BLMBGN | B7: =IF($A7="","",VLOOKUP($A7,'Annex 2 EHV charges'!$A:$O,2,0)) -> 820 | C7: =IF($A7="","",VLOOKUP($A7,'Annex 2 EHV charges'!$A:$O,3,0)) -> 1200061385700 1200061385710 | D7: =IF($A7="","",VLOOKUP($A7,'Annex 2 EHV charges'!$A:$O,7,0)) -> BLMBGN | E7: =IFERROR(IF(VLOOKUP($A7,'Annex 2 EHV charges'!$A:$O,8,FALSE)=0,"",VLOOKUP($A7,'Annex 2 EHV charges'!$A:$O,8,FALSE)),"") -> 0.197 | F7: =IFERROR(IF(VLOOKUP($A7,'Annex 2 EHV charges'!$A:$O,9,FALSE)=0,"",VLOOKUP($A7,'Annex 2 EHV charges'!$A:$O,9,FALSE)),"") -> 5951.01 | G7: =IFERROR(IF(VLOOKUP($A7,'Annex 2 EHV charges'!$A:$O,10,FALSE)=0,"",VLOOKUP($A7,'Annex 2 EHV charges'!$A:$O,10,FALSE)),"") -> 1.8 | H7: =IFERROR(IF(VLOOKUP($A7,'Annex 2 EHV charges'!$A:$O,11,FALSE)=0,"",VLOOKUP($A7,'Annex 2 EHV charges'!$A:$O,11,FALSE)),"") -> 1.8
A8: {=IFERROR(INDEX('Annex 2 EHV charges'!$A$11:$A$59, MATCH(0, IF(ISBLANK('Annex 2 EHV charges'!$A$11:$A$59),1, COUNTIF(A$4:$A7, 'Annex 2 EHV charges'!$A$11:$A$59)), 0)),"")} -> BLMBGS | B8: =IF($A8="","",VLOOKUP($A8,'Annex 2 EHV charges'!$A:$O,2,0)) -> 821 | C8: =IF($A8="","",VLOOKUP($A8,'Annex 2 EHV charges'!$A:$O,3,0)) -> 1200061385729 1200061385738 | D8: =IF($A8="","",VLOOKUP($A8,'Annex 2 EHV charges'!$A:$O,7,0)) -> BLMBGS | E8: =IFERROR(IF(VLOOKUP($A8,'Annex 2 EHV charges'!$A:$O,8,FALSE)=0,"",VLOOKUP($A8,'Annex 2 EHV charges'!$A:$O,8,FALSE)),"") -> 0.157 | F8: =IFERROR(IF(VLOOKUP($A8,'Annex 2 EHV charges'!$A:$O,9,FALSE)=0,"",VLOOKUP($A8,'Annex 2 EHV charges'!$A:$O,9,FALSE)),"") -> 1066.62 | G8: =IFERROR(IF(VLOOKUP($A8,'Annex 2 EHV charges'!$A:$O,10,FALSE)=0,"",VLOOKUP($A8,'Annex 2 EHV charges'!$A:$O,10,FALSE)),"") -> 1.31 | H8: =IFERROR(IF(VLOOKUP($A8,'Annex 2 EHV charges'!$A:$O,11,FALSE)=0,"",VLOOKUP($A8,'Annex 2 EHV charges'!$A:$O,11,FALSE)),"") -> 1.31
A9: {=IFERROR(INDEX('Annex 2 EHV charges'!$A$11:$A$59, MATCH(0, IF(ISBLANK('Annex 2 EHV charges'!$A$11:$A$59),1, COUNTIF(A$4:$A8, 'Annex 2 EHV charges'!$A$11:$A$59)), 0)),"")} -> BRDGTE | B9: =IF($A9="","",VLOOKUP($A9,'Annex 2 EHV charges'!$A:$O,2,0)) -> 805 | C9: =IF($A9="","",VLOOKUP($A9,'Annex 2 EHV charges'!$A:$O,3,0)) -> 1200061148014 1200061148023 | D9: =IF($A9="","",VLOOKUP($A9,'Annex 2 EHV charges'!$A:$O,7,0)) -> BRDGTE | E9: =IFERROR(IF(VLOOKUP($A9,'Annex 2 EHV charges'!$A:$O,8,FALSE)=0,"",VLOOKUP($A9,'Annex 2 EHV charges'!$A:$O,8,FALSE)),"") -> 0.186 | F9: =IFERROR(IF(VLOOKUP($A9,'Annex 2 EHV charges'!$A:$O,9,FALSE)=0,"",VLOOKUP($A9,'Annex 2 EHV charges'!$A:$O,9,FALSE)),"") -> 5951.01 | G9: =IFERROR(IF(VLOOKUP($A9,'Annex 2 EHV charges'!$A:$O,10,FALSE)=0,"",VLOOKUP($A9,'Annex 2 EHV charges'!$A:$O,10,FALSE)),"") -> 2.58 | H9: =IFERROR(IF(VLOOKUP($A9,'Annex 2 EHV charges'!$A:$O,11,FALSE)=0,"",VLOOKUP($A9,'Annex 2 EHV charges'!$A:$O,11,FALSE)),"") -> 2.58
A10: {=IFERROR(INDEX('Annex 2 EHV charges'!$A$11:$A$59, MATCH(0, IF(ISBLANK('Annex 2 EHV charges'!$A$11:$A$59),1, COUNTIF(A$4:$A9, 'Annex 2 EHV charges'!$A$11:$A$59)), 0)),"")} -> BRKFLD | B10: =IF($A10="","",VLOOKUP($A10,'Annex 2 EHV charges'!$A:$O,2,0)) -> 829 | C10: =IF($A10="","",VLOOKUP($A10,'Annex 2 EHV charges'!$A:$O,3,0)) -> 1200061148060 1200061148079 | D10: =IF($A10="","",VLOOKUP($A10,'Annex 2 EHV charges'!$A:$O,7,0)) -> BRKFLD | E10: =IFERROR(IF(VLOOKUP($A10,'Annex 2 EHV charges'!$A:$O,8,FALSE)=0,"",VLOOKUP($A10,'Annex 2 EHV charges'!$A:$O,8,FALSE)),"") -> 0.182 | F10: =IFERROR(IF(VLOOKUP($A10,'Annex 2 EHV charges'!$A:$O,9,FALSE)=0,"",VLOOKUP($A10,'Annex 2 EHV charges'!$A:$O,9,FALSE)),"") -> 6147.17 | G10: =IFERROR(IF(VLOOKUP($A10,'Annex 2 EHV charges'!$A:$O,10,FALSE)=0,"",VLOOKUP($A10,'Annex 2 EHV charges'!$A:$O,10,FALSE)),"") -> 1.81 | H10: =IFERROR(IF(VLOOKUP($A10,'Annex 2 EHV charges'!$A:$O,11,FALSE)=0,"",VLOOKUP($A10,'Annex 2 EHV charges'!$A:$O,11,FALSE)),"") -> 1.81
A11: {=IFERROR(INDEX('Annex 2 EHV charges'!$A$11:$A$59, MATCH(0, IF(ISBLANK('Annex 2 EHV charges'!$A$11:$A$59),1, COUNTIF(A$4:$A10, 'Annex 2 EHV charges'!$A$11:$A$59)), 0)),"")} -> BRMLEY | B11: =IF($A11="","",VLOOKUP($A11,'Annex 2 EHV charges'!$A:$O,2,0)) -> 0 | C11: =IF($A11="","",VLOOKUP($A11,'Annex 2 EHV charges'!$A:$O,3,0)) -> MSID: 1630 | D11: =IF($A11="","",VLOOKUP($A11,'Annex 2 EHV charges'!$A:$O,7,0)) -> BRMLEY | E11: =IFERROR(IF(VLOOKUP($A11,'Annex 2 EHV charges'!$A:$O,8,FALSE)=0,"",VLOOKUP($A11,'Annex 2 EHV charges'!$A:$O,8,FALSE)),"") | F11: =IFERROR(IF(VLOOKUP($A11,'Annex 2 EHV charges'!$A:$O,9,FALSE)=0,"",VLOOKUP($A11,'Annex 2 EHV charges'!$A:$O,9,FALSE)),"") -> 43861.69 | G11: =IFERROR(IF(VLOOKUP($A11,'Annex 2 EHV charges'!$A:$O,10,FALSE)=0,"",VLOOKUP($A11,'Annex 2 EHV charges'!$A:$O,10,FALSE)),"") -> 3.12 | H11: =IFERROR(IF(VLOOKUP($A11,'Annex 2 EHV charges'!$A:$O,11,FALSE)=0,"",VLOOKUP($A11,'Annex 2 EHV charges'!$A:$O,11,FALSE)),"") -> 3.12
A12: {=IFERROR(INDEX('Annex 2 EHV charges'!$A$11:$A$59, MATCH(0, IF(ISBLANK('Annex 2 EHV charges'!$A$11:$A$59),1, COUNTIF(A$4:$A11, 'Annex 2 EHV charges'!$A$11:$A$59)), 0)),"")} -> CRLIMM | B12: =IF($A12="","",VLOOKUP($A12,'Annex 2 EHV charges'!$A:$O,2,0)) -> 812 | C12: =IF($A12="","",VLOOKUP($A12,'Annex 2 EHV charges'!$A:$O,3,0)) -> 1200062090483 1200062090492 | D12: =IF($A12="","",VLOOKUP($A12,'Annex 2 EHV charges'!$A:$O,7,0)) -> CRLIMM | E12: =IFERROR(IF(VLOOKUP($A12,'Annex 2 EHV charges'!$A:$O,8,FALSE)=0,"",VLOOKUP($A12,'Annex 2 EHV charges'!$A:$O,8,FALSE)),"") | F12: =IFERROR(IF(VLOOKUP($A12,'Annex 2 EHV charges'!$A:$O,9,FALSE)=0,"",VLOOKUP($A12,'Annex 2 EHV charges'!$A:$O,9,FALSE)),"") -> 51301.59 | G12: =IFERROR(IF(VLOOKUP($A12,'Annex 2 EHV charges'!$A:$O,10,FALSE)=0,"",VLOOKUP($A12,'Annex 2 EHV charges'!$A:$O,10,FALSE)),"") -> 0.98 | H12: =IFERROR(IF(VLOOKUP($A12,'Annex 2 EHV charges'!$A:$O,11,FALSE)=0,"",VLOOKUP($A12,'Annex 2 EHV charges'!$A:$O,11,FALSE)),"") -> 0.98
A13: {=IFERROR(INDEX('Annex 2 EHV charges'!$A$11:$A$59, MATCH(0, IF(ISBLANK('Annex 2 EHV charges'!$A$11:$A$59),1, COUNTIF(A$4:$A12, 'Annex 2 EHV charges'!$A$11:$A$59)), 0)),"")} -> DART11 | B13: =IF($A13="","",VLOOKUP($A13,'Annex 2 EHV charges'!$A:$O,2,0)) -> 0 | C13: =IF($A13="","",VLOOKUP($A13,'Annex 2 EHV charges'!$A:$O,3,0)) -> MSID: 1032 | D13: =IF($A13="","",VLOOKUP($A13,'Annex 2 EHV charges'!$A:$O,7,0)) -> DART11 | E13: =IFERROR(IF(VLOOKUP($A13,'Annex 2 EHV charges'!$A:$O,8,FALSE)=0,"",VLOOKUP($A13,'Annex 2 EHV charges'!$A:$O,8,FALSE)),"") -> 0.217 | F13: =IFERROR(IF(VLOOKUP($A13,'Annex 2 EHV charges'!$A:$O,9,FALSE)=0,"",VLOOKUP($A13,'Annex 2 EHV charges'!$A:$O,9,FALSE)),"") -> 5754.85 | G13: =IFERROR(IF(VLOOKUP($A13,'Annex 2 EHV charges'!$A:$O,10,FALSE)=0,"",VLOOKUP($A13,'Annex 2 EHV charges'!$A:$O,10,FALSE)),"") -> 5.11 | H13: =IFERROR(IF(VLOOKUP($A13,'Annex 2 EHV charges'!$A:$O,11,FALSE)=0,"",VLOOKUP($A13,'Annex 2 EHV charges'!$A:$O,11,FALSE)),"") -> 5.11
A14: {=IFERROR(INDEX('Annex 2 EHV charges'!$A$11:$A$59, MATCH(0, IF(ISBLANK('Annex 2 EHV charges'!$A$11:$A$59),1, COUNTIF(A$4:$A13, 'Annex 2 EHV charges'!$A$11:$A$59)), 0)),"")} -> DART33 | B14: =IF($A14="","",VLOOKUP($A14,'Annex 2 EHV charges'!$A:$O,2,0)) -> 0 | C14: =IF($A14="","",VLOOKUP($A14,'Annex 2 EHV charges'!$A:$O,3,0)) -> MSID: 1032 | D14: =IF($A14="","",VLOOKUP($A14,'Annex 2 EHV charges'!$A:$O,7,0)) -> DART33 | E14: =IFERROR(IF(VLOOKUP($A14,'Annex 2 EHV charges'!$A:$O,8,FALSE)=0,"",VLOOKUP($A14,'Annex 2 EHV charges'!$A:$O,8,FALSE)),"") -> 0.427 | F14: =IFERROR(IF(VLOOKUP($A14,'Annex 2 EHV charges'!$A:$O,9,FALSE)=0,"",VLOOKUP($A14,'Annex 2 EHV charges'!$A:$O,9,FALSE)),"") -> 17523.64 | G14: =IFERROR(IF(VLOOKUP($A14,'Annex 2 EHV charges'!$A:$O,10,FALSE)=0,"",VLOOKUP($A14,'Annex 2 EHV charges'!$A:$O,10,FALSE)),"") -> 5.27 | H14: =IFERROR(IF(VLOOKUP($A14,'Annex 2 EHV charges'!$A:$O,11,FALSE)=0,"",VLOOKUP($A14,'Annex 2 EHV charges'!$A:$O,11,FALSE)),"") -> 5.27
A15: {=IFERROR(INDEX('Annex 2 EHV charges'!$A$11:$A$59, MATCH(0, IF(ISBLANK('Annex 2 EHV charges'!$A$11:$A$59),1, COUNTIF(A$4:$A14, 'Annex 2 EHV charges'!$A$11:$A$59)), 0)),"")} -> EPNLEI | B15: =IF($A15="","",VLOOKUP($A15,'Annex 2 EHV charges'!$A:$O,2,0)) -> 0 | C15: =IF($A15="","",VLOOKUP($A15,'Annex 2 EHV charges'!$A:$O,3,0)) -> MSID: 1628 | D15: =IF($A15="","",VLOOKUP($A15,'Annex 2 EHV charges'!$A:$O,7,0)) -> EPNLEI | E15: =IFERROR(IF(VLOOKUP($A15,'Annex 2 EHV charges'!$A:$O,8,FALSE)=0,"",VLOOKUP($A15,'Annex 2 EHV charges'!$A:$O,8,FALSE)),"") | F15: =IFERROR(IF(VLOOKUP($A15,'Annex 2 EHV charges'!$A:$O,9,FALSE)=0,"",VLOOKUP($A15,'Annex 2 EHV charges'!$A:$O,9,FALSE)),"") -> 43861.69 | G15: =IFERROR(IF(VLOOKUP($A15,'Annex 2 EHV charges'!$A:$O,10,FALSE)=0,"",VLOOKUP($A15,'Annex 2 EHV charges'!$A:$O,10,FALSE)),"") -> 3.51 | H15: =IFERROR(IF(VLOOKUP($A15,'Annex 2 EHV charges'!$A:$O,11,FALSE)=0,"",VLOOKUP($A15,'Annex 2 EHV charges'!$A:$O,11,FALSE)),"") -> 3.51
A16: {=IFERROR(INDEX('Annex 2 EHV charges'!$A$11:$A$59, MATCH(0, IF(ISBLANK('Annex 2 EHV charges'!$A$11:$A$59),1, COUNTIF(A$4:$A15, 'Annex 2 EHV charges'!$A$11:$A$59)), 0)),"")} -> FENAVE | B16: =IF($A16="","",VLOOKUP($A16,'Annex 2 EHV charges'!$A:$O,2,0)) -> 813 | C16: =IF($A16="","",VLOOKUP($A16,'Annex 2 EHV charges'!$A:$O,3,0)) -> 1200062132159 1200062132168 | D16: =IF($A16="","",VLOOKUP($A16,'Annex 2 EHV charges'!$A:$O,7,0)) -> FENAVE | E16: =IFERROR(IF(VLOOKUP($A16,'Annex 2 EHV charges'!$A:$O,8,FALSE)=0,"",VLOOKUP($A16,'Annex 2 EHV charges'!$A:$O,8,FALSE)),"") -> 0.185 | F16: =IFERROR(IF(VLOOKUP($A16,'Annex 2 EHV charges'!$A:$O,9,FALSE)=0,"",VLOOKUP($A16,'Annex 2 EHV charges'!$A:$O,9,FALSE)),"") -> 6147.17 | G16: =IFERROR(IF(VLOOKUP($A16,'Annex 2 EHV charges'!$A:$O,10,FALSE)=0,"",VLOOKUP($A16,'Annex 2 EHV charges'!$A:$O,10,FALSE)),"") -> 1.62 | H16: =IFERROR(IF(VLOOKUP($A16,'Annex 2 EHV charges'!$A:$O,11,FALSE)=0,"",VLOOKUP($A16,'Annex 2 EHV charges'!$A:$O,11,FALSE)),"") -> 1.62
... A51: {=IFERROR(INDEX('Annex 2 EHV charges'!$A$11:$A$59, MATCH(0, IF(ISBLANK('Annex 2 EHV charges'!$A$11:$A$59),1, COUNTIF(A$4:$A50, 'Annex 2 EHV charges'!$A$11:$A$59)), 0)),"")} -> TLRSLN | B51: =IF($A51="","",VLOOKUP($A51,'Annex 2 EHV charges'!$A:$O,2,0)) -> 0 | C51: =IF($A51="","",VLOOKUP($A51,'Annex 2 EHV charges'!$A:$O,3,0)) -> MSID: 5538 | D51: =IF($A51="","",VLOOKUP($A51,'Annex 2 EHV charges'!$A:$O,7,0)) -> TLRSLN | E51: =IFERROR(IF(VLOOKUP($A51,'Annex 2 EHV charges'!$A:$O,8,FALSE)=0,"",VLOOKUP($A51,'Annex 2 EHV charges'!$A:$O,8,FALSE)),"") | F51: =IFERROR(IF(VLOOKUP($A51,'Annex 2 EHV charges'!$A:$O,9,FALSE)=0,"",VLOOKUP($A51,'Annex 2 EHV charges'!$A:$O,9,FALSE)),"") -> 903.03 | G51: =IFERROR(IF(VLOOKUP($A51,'Annex 2 EHV charges'!$A:$O,10,FALSE)=0,"",VLOOKUP($A51,'Annex 2 EHV charges'!$A:$O,10,FALSE)),"") -> 0.88 | H51: =IFERROR(IF(VLOOKUP($A51,'Annex 2 EHV charges'!$A:$O,11,FALSE)=0,"",VLOOKUP($A51,'Annex 2 EHV charges'!$A:$O,11,FALSE)),"") -> 0.88

Sheet Annex 2b Export
A1: Note: The list of MPANs / MSIDs provided may be incomplete; the DNO reserves the right to apply the listed charges to any other MPANs / MSIDs associated with the site. Note: This table is automatically populated based on the content of the tab entitled 'Annex 2 EHV Charges'. The timebands are as shown in Annex 2.
A2: =Overview!B4& " - Effective from "&Overview!D4&" - "&Overview!E4&" EDCM export charges" -> London Power Networks - Effective from 1 April 2022 - Final EDCM export charges
A4: Export Unique Identifier | B4: LLFC | C4: Export MPANs/MSIDs | D4: Name | E4: ='Annex 2 EHV charges'!L10 -> Export Super Red unit charge (p/kWh) | F4: ='Annex 2 EHV charges'!M10 -> Export fixed charge (p/day) | G4: ='Annex 2 EHV charges'!N10 -> Export capacity charge (p/kVA/day) | H4: ='Annex 2 EHV charges'!O10 -> Export exceeded capacity charge (p/kVA/day)
A5: {=IFERROR(INDEX('Annex 2 EHV charges'!$D$11:$D$59, MATCH(0, IF(ISBLANK('Annex 2 EHV charges'!$D$11:$D$59),1, COUNTIF(A$4:$A4, 'Annex 2 EHV charges'!$D$11:$D$59)), 0)),"")} -> NR_WES | B5: =IF($A5="","",VLOOKUP($A5,'Annex 2 EHV charges'!$D:$O,2,0)) -> 716 | C5: =IF($A5="","",VLOOKUP($A5,'Annex 2 EHV charges'!$D:$O,3,0)) -> 1200052486875 | D5: =IF($A5="","",VLOOKUP($A5,'Annex 2 EHV charges'!$D:$O,4,0)) -> NR_WES | E5: =IFERROR(IF(VLOOKUP($A5,'Annex 2 EHV charges'!$D:$O,9,FALSE)=0,"",VLOOKUP($A5,'Annex 2 EHV charges'!$D:$O,9,FALSE)),"") | F5: =IFERROR(IF(VLOOKUP($A5,'Annex 2 EHV charges'!$D:$O,10,FALSE)=0,"",VLOOKUP($A5,'Annex 2 EHV charges'!$D:$O,10,FALSE)),"") -> 387.31 | G5: =IFERROR(IF(VLOOKUP($A5,'Annex 2 EHV charges'!$D:$O,11,FALSE)=0,"",VLOOKUP($A5,'Annex 2 EHV charges'!$D:$O,11,FALSE)),"") -> 0.05 | H5: =IFERROR(IF(VLOOKUP($A5,'Annex 2 EHV charges'!$D:$O,12,FALSE)=0,"",VLOOKUP($A5,'Annex 2 EHV charges'!$D:$O,12,FALSE)),"") -> 0.05
A6: {=IFERROR(INDEX('Annex 2 EHV charges'!$D$11:$D$59, MATCH(0, IF(ISBLANK('Annex 2 EHV charges'!$D$11:$D$59),1, COUNTIF(A$4:$A5, 'Annex 2 EHV charges'!$D$11:$D$59)), 0)),"")} -> THAMEB | B6: =IF($A6="","",VLOOKUP($A6,'Annex 2 EHV charges'!$D:$O,2,0)) -> 701 | C6: =IF($A6="","",VLOOKUP($A6,'Annex 2 EHV charges'!$D:$O,3,0)) -> 1200050312030 1200050312040 1200061219394 | D6: =IF($A6="","",VLOOKUP($A6,'Annex 2 EHV charges'!$D:$O,4,0)) -> THAMEB | E6: =IFERROR(IF(VLOOKUP($A6,'Annex 2 EHV charges'!$D:$O,9,FALSE)=0,"",VLOOKUP($A6,'Annex 2 EHV charges'!$D:$O,9,FALSE)),"") | F6: =IFERROR(IF(VLOOKUP($A6,'Annex 2 EHV charges'!$D:$O,10,FALSE)=0,"",VLOOKUP($A6,'Annex 2 EHV charges'!$D:$O,10,FALSE)),"") | G6: =IFERROR(IF(VLOOKUP($A6,'Annex 2 EHV charges'!$D:$O,11,FALSE)=0,"",VLOOKUP($A6,'Annex 2 EHV charges'!$D:$O,11,FALSE)),"") | H6: =IFERROR(IF(VLOOKUP($A6,'Annex 2 EHV charges'!$D:$O,12,FALSE)=0,"",VLOOKUP($A6,'Annex 2 EHV charges'!$D:$O,12,FALSE)),"")
A7: {=IFERROR(INDEX('Annex 2 EHV charges'!$D$11:$D$59, MATCH(0, IF(ISBLANK('Annex 2 EHV charges'!$D$11:$D$59),1, COUNTIF(A$4:$A6, 'Annex 2 EHV charges'!$D$11:$D$59)), 0)),"")} -> THAMEC | B7: =IF($A7="","",VLOOKUP($A7,'Annex 2 EHV charges'!$D:$O,2,0)) -> 702 | C7: =IF($A7="","",VLOOKUP($A7,'Annex 2 EHV charges'!$D:$O,3,0)) -> 1200061171342 1200061171351 | D7: =IF($A7="","",VLOOKUP($A7,'Annex 2 EHV charges'!$D:$O,4,0)) -> THAMEC | E7: =IFERROR(IF(VLOOKUP($A7,'Annex 2 EHV charges'!$D:$O,9,FALSE)=0,"",VLOOKUP($A7,'Annex 2 EHV charges'!$D:$O,9,FALSE)),"") | F7: =IFERROR(IF(VLOOKUP($A7,'Annex 2 EHV charges'!$D:$O,10,FALSE)=0,"",VLOOKUP($A7,'Annex 2 EHV charges'!$D:$O,10,FALSE)),"") -> 675.05 | G7: =IFERROR(IF(VLOOKUP($A7,'Annex 2 EHV charges'!$D:$O,11,FALSE)=0,"",VLOOKUP($A7,'Annex 2 EHV charges'!$D:$O,11,FALSE)),"") -> 0.05 | H7: =IFERROR(IF(VLOOKUP($A7,'Annex 2 EHV charges'!$D:$O,12,FALSE)=0,"",VLOOKUP($A7,'Annex 2 EHV charges'!$D:$O,12,FALSE)),"") -> 0.05
A8: {=IFERROR(INDEX('Annex 2 EHV charges'!$D$11:$D$59, MATCH(0, IF(ISBLANK('Annex 2 EHV charges'!$D$11:$D$59),1, COUNTIF(A$4:$A7, 'Annex 2 EHV charges'!$D$11:$D$59)), 0)),"")} -> BELVED | B8: =IF($A8="","",VLOOKUP($A8,'Annex 2 EHV charges'!$D:$O,2,0)) -> 711 | C8: =IF($A8="","",VLOOKUP($A8,'Annex 2 EHV charges'!$D:$O,3,0)) -> 1200060787118 | D8: =IF($A8="","",VLOOKUP($A8,'Annex 2 EHV charges'!$D:$O,4,0)) -> BELVED | E8: =IFERROR(IF(VLOOKUP($A8,'Annex 2 EHV charges'!$D:$O,9,FALSE)=0,"",VLOOKUP($A8,'Annex 2 EHV charges'!$D:$O,9,FALSE)),"") | F8: =IFERROR(IF(VLOOKUP($A8,'Annex 2 EHV charges'!$D:$O,10,FALSE)=0,"",VLOOKUP($A8,'Annex 2 EHV charges'!$D:$O,10,FALSE)),"") -> 628.44 | G8: =IFERROR(IF(VLOOKUP($A8,'Annex 2 EHV charges'!$D:$O,11,FALSE)=0,"",VLOOKUP($A8,'Annex 2 EHV charges'!$D:$O,11,FALSE)),"") -> 0.05 | H8: =IFERROR(IF(VLOOKUP($A8,'Annex 2 EHV charges'!$D:$O,12,FALSE)=0,"",VLOOKUP($A8,'Annex 2 EHV charges'!$D:$O,12,FALSE)),"") -> 0.05
A9: {=IFERROR(INDEX('Annex 2 EHV charges'!$D$11:$D$59, MATCH(0, IF(ISBLANK('Annex 2 EHV charges'!$D$11:$D$59),1, COUNTIF(A$4:$A8, 'Annex 2 EHV charges'!$D$11:$D$59)), 0)),"")} -> SELCHP | B9: =IF($A9="","",VLOOKUP($A9,'Annex 2 EHV charges'!$D:$O,2,0)) -> 730 | C9: =IF($A9="","",VLOOKUP($A9,'Annex 2 EHV charges'!$D:$O,3,0)) -> 1200010258304 | D9: =IF($A9="","",VLOOKUP($A9,'Annex 2 EHV charges'!$D:$O,4,0)) -> SELCHP | E9: =IFERROR(IF(VLOOKUP($A9,'Annex 2 EHV charges'!$D:$O,9,FALSE)=0,"",VLOOKUP($A9,'Annex 2 EHV charges'!$D:$O,9,FALSE)),"") | F9: =IFERROR(IF(VLOOKUP($A9,'Annex 2 EHV charges'!$D:$O,10,FALSE)=0,"",VLOOKUP($A9,'Annex 2 EHV charges'!$D:$O,10,FALSE)),"") -> 3106.09 | G9: =IFERROR(IF(VLOOKUP($A9,'Annex 2 EHV charges'!$D:$O,11,FALSE)=0,"",VLOOKUP($A9,'Annex 2 EHV charges'!$D:$O,11,FALSE)),"") -> 0.05 | H9: =IFERROR(IF(VLOOKUP($A9,'Annex 2 EHV charges'!$D:$O,12,FALSE)=0,"",VLOOKUP($A9,'Annex 2 EHV charges'!$D:$O,12,FALSE)),"") -> 0.05
A10: {=IFERROR(INDEX('Annex 2 EHV charges'!$D$11:$D$59, MATCH(0, IF(ISBLANK('Annex 2 EHV charges'!$D$11:$D$59),1, COUNTIF(A$4:$A9, 'Annex 2 EHV charges'!$D$11:$D$59)), 0)),"")} -> TLRSLN | B10: =IF($A10="","",VLOOKUP($A10,'Annex 2 EHV charges'!$D:$O,2,0)) -> 0 | C10: =IF($A10="","",VLOOKUP($A10,'Annex 2 EHV charges'!$D:$O,3,0)) -> MSID: 5538 | D10: =IF($A10="","",VLOOKUP($A10,'Annex 2 EHV charges'!$D:$O,4,0)) -> TLRSLN | E10: =IFERROR(IF(VLOOKUP($A10,'Annex 2 EHV charges'!$D:$O,9,FALSE)=0,"",VLOOKUP($A10,'Annex 2 EHV charges'!$D:$O,9,FALSE)),"") -> -0.059 | F10: =IFERROR(IF(VLOOKUP($A10,'Annex 2 EHV charges'!$D:$O,10,FALSE)=0,"",VLOOKUP($A10,'Annex 2 EHV charges'!$D:$O,10,FALSE)),"") -> 3039.7 | G10: =IFERROR(IF(VLOOKUP($A10,'Annex 2 EHV charges'!$D:$O,11,FALSE)=0,"",VLOOKUP($A10,'Annex 2 EHV charges'!$D:$O,11,FALSE)),"") -> 0.05 | H10: =IFERROR(IF(VLOOKUP($A10,'Annex 2 EHV charges'!$D:$O,12,FALSE)=0,"",VLOOKUP($A10,'Annex 2 EHV charges'!$D:$O,12,FALSE)),"") -> 0.05

Sheet Annex 3 Preserved charges
A1: Back to Overview
A2: =Overview!B4& " - Effective from "&Overview!D4&" - "&Overview!E4&" LV and HV tariffs" -> London Power Networks - Effective from 1 April 2022 - Final LV and HV tariffs
A3: Supercustomer preserved charges/additional LLFCs
B4: Closed LLFCs | C4: PCs | D4: Red/black unit charge p/kWh | E4: Amber/yellow unit charge p/kWh | F4: Green unit charge p/kWh | G4: Fixed charge p/MPAN/day
A6: Notes: | B6: London Power Networks has no Preserved NHH Tariffs/Additional LLFC classes
A11: Site Specific preserved charges/additional LLFCs
B12: Closed LLFCs | C12: PCs | D12: Red/black unit charge p/kWh | E12: Amber/yellow unit charge p/kWh | F12: Green unit charge p/kWh | G12: Fixed charge p/MPAN/day | H12: Capacity charge p/kVA/day | I12: Exceeded capacity charge p/kVA/day | J12: Reactive power charge p/kVArh
A14: Notes: | B14: London Power Networks has no Preserved HH Tariffs/Additional LLFC classes

Sheet Annex 4 LDNO charges
A1: Back to Overview
A2: =Overview!B4& " - Effective from "&Overview!D4&" - "&Overview!E4&" LDNO tariffs" -> London Power Networks - Effective from 1 April 2022 - Final LDNO tariffs
A4: Time Bands for LV and HV Designated Properties | F4: Time Bands for Unmetered Properties
A5: Time periods | B5: Red Time Band | C5: Amber Time Band | D5: Green Time Band | H5: Black Time Band | I5: Yellow Time Band | J5: Green Time Band
A6: Monday to Friday (Including Bank Holidays) All Year | B6: 11:00 - 14:00 16:00 - 19:00 | C6: 07:00 - 11:00 14:00 - 16:00 19:00 - 23:00 | D6: 00:00 - 07:00 23:00 - 24:00 | F6: Monday to Friday (Including Bank Holidays) June to August Inclusive | H6: 11:00 - 14:00 | I6: 07:00 - 11:00 14:00 - 23:00 | J6: 00:00 - 07:00 23:00 - 24:00
A7: Saturday and Sunday All Year | D7: 00:00 - 24:00 | F7: Monday to Friday (Including Bank Holidays) November to February Inclusive | H7: 16:00 - 19:00 | I7: 07:00 - 16:00 19:00 - 23:00 | J7: 00:00 - 07:00 23:00 - 24:00
A8: Notes | B8: All the above times are in UK Clock time | F8: Monday to Friday (Including Bank Holidays) March, April, May and September, October | I8: 07:00 - 23:00 | J8: 00:00 - 07:00 23:00 - 24:00
F9: Saturday and Sunday All year | J9: 00:00 - 24:00
F10: Notes | H10: All the above times are in UK Clock time
A12: Tariff name | B12: Unique billing identifier | C12: PCs | D12: Red/black unit charge p/kWh | E12: Amber/yellow unit charge p/kWh | F12: Green unit charge p/kWh | G12: Fixed charge p/MPAN/day | H12: Capacity charge p/kVA/day | I12: Exceeded capacity charge p/kVA/day | J12: Reactive power charge p/kVArh
A13: LDNO LV: Domestic Aggregated with Residual | B13: A00 | C13: 0, 1, 2 | D13: 6.903 | E13: 1.301 | F13: 0.042 | G13: 10.56
A14: LDNO LV: Domestic Aggregated (Related MPAN) | B14: B00 | C14: 2 | D14: 6.903 | E14: 1.301 | F14: 0.042
A15: LDNO LV: Non-Domestic Aggregated No Residual | B15: C00 | C15: 0, 3, 4, 5-8 | D15: 4.223 | E15: 0.796 | F15: 0.026 | G15: 2.35
A16: LDNO LV: Non-Domestic Aggregated Band 1 | B16: C01 | C16: 0, 3, 4, 5-8 | D16: 4.223 | E16: 0.796 | F16: 0.026 | G16: 1.78
A17: LDNO LV: Non-Domestic Aggregated Band 2 | B17: C02 | C17: 0, 3, 4, 5-8 | D17: 4.132 | E17: 0.705 | F17: 0 | G17: 0.01
A18: LDNO LV: Non-Domestic Aggregated Band 3 | B18: C03 | C18: 0, 3, 4, 5-8 | D18: 4.024 | E18: 0.596 | F18: 0 | G18: 0.01
A19: LDNO LV: Non-Domestic Aggregated Band 4 | B19: C04 | C19: 0, 3, 4, 5-8 | D19: 3.969 | E19: 0.542 | F19: 0 | G19: 0.01
A20: LDNO LV: Non-Domestic Aggregated (related MPAN) | B20: D00 | C20: 4 | D20: 4.223 | E20: 0.796 | F20: 0.026
A21: LDNO LV: LV Site Specific No Residual | B21: E00 | C21: 0 | D21: 3.476 | E21: 0.668 | F21: 0.022 | G21: 5.79 | H21: 3.13 | I21: 4.86 | J21: 0.298
A22: LDNO LV: LV Site Specific Band 1 | B22: E01 | C22: 0 | D22: 3.202 | E22: 0.393 | F22: 0.005 | G22: 1.52 | H22: 3.13 | I22: 4.86 | J22: 0.298
A23: LDNO LV: LV Site Specific Band 2 | B23: E02 | C23: 0 | D23: 3.194 | E23: 0.386 | F23: 0.005 | G23: 1.52 | H23: 3.13 | I23: 4.86 | J23: 0.298
A24: LDNO LV: LV Site Specific Band 3 | B24: E03 | C24: 0 | D24: 3.187 | E24: 0.379 | F24: 0.005 | G24: 1.52 | H24: 3.13 | I24: 4.86 | J24: 0.298
A25: LDNO LV: LV Site Specific Band 4 | B25: E04 | C25: 0 | D25: 3.182 | E25: 0.373 | F25: 0.005 | G25: 1.52 | H25: 3.13 | I25: 4.86 | J25: 0.298
A26: LDNO LV: Unmetered Supplies | B26: U00 | C26: 0, 1 or 8 | D26: 22.323 | E26: 1.663 | F26: 0.21
A27: LDNO LV: LV Generation Aggregated | B27: F00 | C27: 0 | D27: -5.239 | E27: -0.987 | F27: -0.032 | G27: 0
A28: LDNO LV: LV Generation Site Specific | B28: G00 | C28: 0 | D28: -5.239 | E28: -0.987 | F28: -0.032 | G28: 0 | J28: 0.361
A29: LDNO HV: Domestic Aggregated with Residual | B29: A10 | C29: 0, 1, 2 | D29: 5.336 | E29: 1.006 | F29: 0.032 | G29: 10.38
A30: LDNO HV: Domestic Aggregated (Related MPAN) | B30: B10 | C30: 2 | D30: 5.336 | E30: 1.006 | F30: 0.032
A31: LDNO HV: Non-Domestic Aggregated No Residual | B31: C10 | C31: 0, 3, 4, 5-8 | D31: 3.264 | E31: 0.615 | F31: 0.02 | G31: 1.83
A32: LDNO HV: Non-Domestic Aggregated Band 1 | B32: C11 | C32: 0, 3, 4, 5-8 | D32: 3.264 | E32: 0.615 | F32: 0.02 | G32: 1.39
A33: LDNO HV: Non-Domestic Aggregated Band 2 | B33: C12 | C33: 0, 3, 4, 5-8 | D33: 3.194 | E33: 0.545 | F33: 0 | G33: 0.02
A34: LDNO HV: Non-Domestic Aggregated Band 3 | B34: C13 | C34: 0, 3, 4, 5-8 | D34: 3.11 | E34: 0.461 | F34: 0 | G34: 0.02
A35: LDNO HV: Non-Domestic Aggregated Band 4 | B35: C14 | C35: 0, 3, 4, 5-8 | D35: 3.068 | E35: 0.419 | F35: 0 | G35: 0.02
A36: LDNO HV: Non-Domestic Aggregated (related MPAN) | B36: D10 | C36: 4 | D36: 3.264 | E36: 0.615 | F36: 0.02
A37: LDNO HV: LV Site Specific No Residual | B37: E10 | C37: 0 | D37: 2.687 | E37: 0.516 | F37: 0.017 | G37: 4.49 | H37: 2.42 | I37: 3.75 | J37: 0.23
A38: LDNO HV: LV Site Specific Band 1 | B38: E11 | C38: 0 | D38: 2.475 | E38: 0.304 | F38: 0.004 | G38: 1.19 | H38: 2.42 | I38: 3.75 | J38: 0.23
A39: LDNO HV: LV Site Specific Band 2 | B39: E12 | C39: 0 | D39: 2.469 | E39: 0.298 | F39: 0.004 | G39: 1.19 | H39: 2.42 | I39: 3.75 | J39: 0.23
A40: LDNO HV: LV Site Specific Band 3 | B40: E13 | C40: 0 | D40: 2.464 | E40: 0.293 | F40: 0.004 | G40: 1.19 | H40: 2.42 | I40: 3.75 | J40: 0.23
A41: LDNO HV: LV Site Specific Band 4 | B41: E14 | C41: 0 | D41: 2.459 | E41: 0.289 | F41: 0.004 | G41: 1.19 | H41: 2.42 | I41: 3.75 | J41: 0.23
A42: LDNO HV: LV Sub Site Specific No Residual | B42: J10 | C42: 0 | D42: 2.539 | E42: 0.513 | F42: 0.019 | G42: 4.6 | H42: 5.9 | I42: 6.72 | J42: 0.189
A43: LDNO HV: LV Sub Site Specific Band 1 | B43: J11 | C43: 0 | D43: 2.243 | E43: 0.217 | F43: 0 | G43: 0.01 | H43: 5.9 | I43: 6.72 | J43: 0.189
A44: LDNO HV: LV Sub Site Specific Band 2 | B44: J12 | C44: 0 | D44: 2.235 | E44: 0.209 | F44: 0 | G44: 0.01 | H44: 5.9 | I44: 6.72 | J44: 0.189
A45: LDNO HV: LV Sub Site Specific Band 3 | B45: J13 | C45: 0 | D45: 2.228 | E45: 0.202 | F45: 0 | G45: 0.01 | H45: 5.9 | I45: 6.72 | J45: 0.189
A46: LDNO HV: LV Sub Site Specific Band 4 | B46: J14 | C46: 0 | D46: 2.222 | E46: 0.196 | F46: 0 | G46: 0.01 | H46: 5.9 | I46: 6.72 | J46: 0.189
A47: LDNO HV: HV Site Specific No Residual | B47: K10 | C47: 0 | D47: 2.071 | E47: 0.403 | F47: 0.015 | G47: 68.54 | H47: 6.69 | I47: 7.52 | J47: 0.178
A48: LDNO HV: HV Site Specific Band 1 | B48: K11 | C48: 0 | D48: 1.765 | E48: 0.097 | F48: 0 | G48: 0.01 | H48: 6.69 | I48: 7.52 | J48: 0.178
... A51: LDNO HV: HV Site Specific Band 4 | B51: K14 | C51: 0 | D51: 1.704 | E51: 0.037 | F51: 0 | G51: 0.01 | H51: 6.69 | I51: 7.52 | J51: 0.178
A52: LDNO HV: Unmetered Supplies | B52: U10 | C52: 0, 1 or 8 | D52: 17.255 | E52: 1.285 | F52: 0.163
A53: LDNO HV: LV Generation Aggregated | B53: F10 | C53: 0 | D53: -5.239 | E53: -0.987 | F53: -0.032 | G53: 0
A54: LDNO HV: LV Sub Generation Aggregated | B54: H10 | C54: 0 | D54: -4.614 | E54: -0.879 | F54: -0.029 | G54: 0
A55: LDNO HV: LV Generation Site Specific | B55: G10 | C55: 0 | D55: -5.239 | E55: -0.987 | F55: -0.032 | G55: 0 | J55: 0.361
A56: LDNO HV: LV Sub Generation Site Specific | B56: L10 | C56: 0 | D56: -4.614 | E56: -0.879 | F56: -0.029 | G56: 0 | J56: 0.322
A57: LDNO HV: HV Generation Site Specific | B57: M10 | C57: 0 | D57: -2.954 | E57: -0.596 | F57: -0.022 | G57: 0 | J57: 0.28
A58: LDNO HVplus: Domestic Aggregated with Residual | B58: A20 | C58: 0, 1, 2 | D58: 4.727 | E58: 0.891 | F58: 0.029 | G58: 10.31
A59: LDNO HVplus: Domestic Aggregated (Related MPAN) | B59: B20 | C59: 2 | D59: 4.727 | E59: 0.891 | F59: 0.029
A60: LDNO HVplus: Non-Domestic Aggregated No Residual | B60: C20 | C60: 0, 3, 4, 5-8 | D60: 2.892 | E60: 0.545 | F60: 0.017 | G60: 1.62
A61: LDNO HVplus: Non-Domestic Aggregated Band 1 | B61: C21 | C61: 0, 3, 4, 5-8 | D61: 2.892 | E61: 0.545 | F61: 0.017 | G61: 1.24
A62: LDNO HVplus: Non-Domestic Aggregated Band 2 | B62: C22 | C62: 0, 3, 4, 5-8 | D62: 2.83 | E62: 0.483 | F62: 0 | G62: 0.03
A63: LDNO HVplus: Non-Domestic Aggregated Band 3 | B63: C23 | C63: 0, 3, 4, 5-8 | D63: 2.755 | E63: 0.408 | F63: 0 | G63: 0.03
A64: LDNO HVplus: Non-Domestic Aggregated Band 4 | B64: C24 | C64: 0, 3, 4, 5-8 | D64: 2.718 | E64: 0.371 | F64: 0 | G64: 0.03
A65: LDNO HVplus: Non-Domestic Aggregated (related MPAN) | B65: D20 | C65: 4 | D65: 2.892 | E65: 0.545 | F65: 0.017
A66: LDNO HVplus: LV Site Specific No Residual | B66: E20 | C66: 0 | D66: 2.381 | E66: 0.457 | F66: 0.015 | G66: 3.98 | H66: 2.14 | I66: 3.33 | J66: 0.204
A67: LDNO HVplus: LV Site Specific Band 1 | B67: E21 | C67: 0 | D67: 2.193 | E67: 0.269 | F67: 0.003 | G67: 1.06 | H67: 2.14 | I67: 3.33 | J67: 0.204
A68: LDNO HVplus: LV Site Specific Band 2 | B68: E22 | C68: 0 | D68: 2.188 | E68: 0.264 | F68: 0.003 | G68: 1.06 | H68: 2.14 | I68: 3.33 | J68: 0.204
A69: LDNO HVplus: LV Site Specific Band 3 | B69: E23 | C69: 0 | D69: 2.183 | E69: 0.259 | F69: 0.003 | G69: 1.06 | H69: 2.14 | I69: 3.33 | J69: 0.204
A70: LDNO HVplus: LV Site Specific Band 4 | B70: E24 | C70: 0 | D70: 2.179 | E70: 0.256 | F70: 0.003 | G70: 1.06 | H70: 2.14 | I70: 3.33 | J70: 0.204
A71: LDNO HVplus: LV Sub Site Specific No Residual | B71: J20 | C71: 0 | D71: 2.234 | E71: 0.451 | F71: 0.017 | G71: 4.06 | H71: 5.19 | I71: 5.91 | J71: 0.166
A72: LDNO HVplus: LV Sub Site Specific Band 1 | B72: J21 | C72: 0 | D72: 1.974 | E72: 0.191 | F72: 0 | G72: 0.02 | H72: 5.19 | I72: 5.91 | J72: 0.166
A73: LDNO HVplus: LV Sub Site Specific Band 2 | B73: J22 | C73: 0 | D73: 1.967 | E73: 0.184 | F73: 0 | G73: 0.02 | H73: 5.19 | I73: 5.91 | J73: 0.166
A74: LDNO HVplus: LV Sub Site Specific Band 3 | B74: J23 | C74: 0 | D74: 1.96 | E74: 0.178 | F74: 0 | G74: 0.02 | H74: 5.19 | I74: 5.91 | J74: 0.166
A75: LDNO HVplus: LV Sub Site Specific Band 4 | B75: J24 | C75: 0 | D75: 1.955 | E75: 0.172 | F75: 0 | G75: 0.02 | H75: 5.19 | I75: 5.91 | J75: 0.166
A76: LDNO HVplus: HV Site Specific No Residual | B76: K20 | C76: 0 | D76: 1.815 | E76: 0.353 | F76: 0.013 | G76: 60.07 | H76: 5.86 | I76: 6.59 | J76: 0.156
A77: LDNO HVplus: HV Site Specific Band 1 | B77: K21 | C77: 0 | D77: 1.547 | E77: 0.085 | F77: 0 | G77: 0.01 | H77: 5.86 | I77: 6.59 | J77: 0.156
... A80: LDNO HVplus: HV Site Specific Band 4 | B80: K24 | C80: 0 | D80: 1.494 | E80: 0.032 | F80: 0 | G80: 0.01 | H80: 5.86 | I80: 6.59 | J80: 0.156
A81: LDNO HVplus: Unmetered Supplies | B81: U20 | C81: 0, 1 or 8 | D81: 15.288 | E81: 1.139 | F81: 0.144
A82: LDNO HVplus: LV Generation Aggregated | B82: F20 | C82: 0 | D82: -3.615 | E82: -0.681 | F82: -0.022 | G82: 0
A83: LDNO HVplus: LV Sub Generation Aggregated | B83: H20 | C83: 0 | D83: -3.527 | E83: -0.672 | F83: -0.022 | G83: 0
A84: LDNO HVplus: LV Generation Site Specific | B84: G20 | C84: 0 | D84: -3.615 | E84: -0.681 | F84: -0.022 | G84: 0 | J84: 0.249
A85: LDNO HVplus: LV Sub Generation Site Specific | B85: L20 | C85: 0 | D85: -3.527 | E85: -0.672 | F85: -0.022 | G85: 0 | J85: 0.246
A86: LDNO HVplus: HV Generation Site Specific | B86: M20 | C86: 0 | D86: -2.954 | E86: -0.596 | F86: -0.022 | G86: 6.65 | J86: 0.28
A87: LDNO EHV: Domestic Aggregated with Residual | B87: A30 | C87: 0, 1, 2 | D87: 3.647 | E87: 0.687 | F87: 0.022 | G87: 10.19
A88: LDNO EHV: Domestic Aggregated (Related MPAN) | B88: B30 | C88: 2 | D88: 3.647 | E88: 0.687 | F88: 0.022
A89: LDNO EHV: Non-Domestic Aggregated No Residual | B89: C30 | C89: 0, 3, 4, 5-8 | D89: 2.231 | E89: 0.421 | F89: 0.014 | G89: 1.26
A90: LDNO EHV: Non-Domestic Aggregated Band 1 | B90: C31 | C90: 0, 3, 4, 5-8 | D90: 2.231 | E90: 0.421 | F90: 0.014 | G90: 0.97
A91: LDNO EHV: Non-Domestic Aggregated Band 2 | B91: C32 | C91: 0, 3, 4, 5-8 | D91: 2.183 | E91: 0.372 | F91: 0 | G91: 0.03
A92: LDNO EHV: Non-Domestic Aggregated Band 3 | B92: C33 | C92: 0, 3, 4, 5-8 | D92: 2.126 | E92: 0.315 | F92: 0 | G92: 0.03
A93: LDNO EHV: Non-Domestic Aggregated Band 4 | B93: C34 | C93: 0, 3, 4, 5-8 | D93: 2.097 | E93: 0.286 | F93: 0 | G93: 0.03
A94: LDNO EHV: Non-Domestic Aggregated (related MPAN) | B94: D30 | C94: 4 | D94: 2.231 | E94: 0.421 | F94: 0.014
A95: LDNO EHV: LV Site Specific No Residual | B95: E30 | C95: 0 | D95: 1.837 | E95: 0.353 | F95: 0.012 | G95: 3.09 | H95: 1.65 | I95: 2.57 | J95: 0.157
A96: LDNO EHV: LV Site Specific Band 1 | B96: E31 | C96: 0 | D96: 1.692 | E96: 0.208 | F96: 0.003 | G96: 0.83 | H96: 1.65 | I96: 2.57 | J96: 0.157
A97: LDNO EHV: LV Site Specific Band 2 | B97: E32 | C97: 0 | D97: 1.688 | E97: 0.204 | F97: 0.003 | G97: 0.83 | H97: 1.65 | I97: 2.57 | J97: 0.157
A98: LDNO EHV: LV Site Specific Band 3 | B98: E33 | C98: 0 | D98: 1.684 | E98: 0.2 | F98: 0.003 | G98: 0.83 | H98: 1.65 | I98: 2.57 | J98: 0.157
A99: LDNO EHV: LV Site Specific Band 4 | B99: E34 | C99: 0 | D99: 1.681 | E99: 0.197 | F99: 0.003 | G99: 0.83 | H99: 1.65 | I99: 2.57 | J99: 0.157
A100: LDNO EHV: LV Sub Site Specific No Residual | B100: J30 | C100: 0 | D100: 1.723 | E100: 0.348 | F100: 0.013 | G100: 3.14 | H100: 4.01 | I100: 4.56 | J100: 0.128
A101: LDNO EHV: LV Sub Site Specific Band 1 | B101: J31 | C101: 0 | D101: 1.523 | E101: 0.148 | F101: 0 | G101: 0.02 | H101: 4.01 | I101: 4.56 | J101: 0.128
A102: LDNO EHV: LV Sub Site Specific Band 2 | B102: J32 | C102: 0 | D102: 1.517 | E102: 0.142 | F102: 0 | G102: 0.02 | H102: 4.01 | I102: 4.56 | J102: 0.128
A103: LDNO EHV: LV Sub Site Specific Band 3 | B103: J33 | C103: 0 | D103: 1.512 | E103: 0.137 | F103: 0 | G103: 0.02 | H103: 4.01 | I103: 4.56 | J103: 0.128
A104: LDNO EHV: LV Sub Site Specific Band 4 | B104: J34 | C104: 0 | D104: 1.508 | E104: 0.133 | F104: 0 | G104: 0.02 | H104: 4.01 | I104: 4.56 | J104: 0.128
A105: LDNO EHV: HV Site Specific No Residual | B105: K30 | C105: 0 | D105: 1.4 | E105: 0.273 | F105: 0.01 | G105: 46.35 | H105: 4.52 | I105: 5.08 | J105: 0.12
A106: LDNO EHV: HV Site Specific Band 1 | B106: K31 | C106: 0 | D106: 1.193 | E106: 0.066 | F106: 0 | G106: 0.02 | H106: 4.52 | I106: 5.08 | J106: 0.12
...

Sheet Annex 5 LLFs
A1: Back to Overview
A2: These line loss factors are illustrative based on the latest calculated values and are published in good faith. However, the line loss factors that are approved by the BSC Panel for the applicable year and consequently published on the Elexon website will take precedence and will be used in Settlement if they differ from these values.
A3: =Overview!B4& " - Illustrative LLFs for year beginning "&Overview!D4 -> London Power Networks - Illustrative LLFs for year beginning 1 April 2022
A4: Time periods | C4: Period 1 | D4: Period 2 | E4: Period 3 | F4: Period 4 | G4: Period 5
C5: Winter Peak | D5: Summer Peak | E5: Winter Shoulder | F5: Night | G5: Other
A6: Monday to Friday November to February | C6: 16:00 - 19:59 | E6: 07:00 - 15:59
A7: Monday to Friday June to August | D7: 07:00 - 19:59
A8: Monday to Friday March | E8: 07:00 - 19:59
A9: All Year | F9: 00:00 - 06:59 | G9: All Other Times
A10: Notes | C10: All the above times are in UK Clock time
A13: Generic demand and generation LLFs
A14: Metered voltage, respective periods and associated LLFCs
A15: Metered voltage | B15: Period 1 | C15: Period 2 | D15: Period 3 | E15: Period 4 | F15: Period 5 | G15: Associated LLFC
A16: Low-voltage network | B16: 1.11 | C16: 1.089 | D16: 1.101 | E16: 1.071 | F16: 1.089 | G16: 1, 2, 9, 19, 69, 70, 71, 72, 73, 74, 199, 200, 201, 202, 203, 204, 350, 400, 420, 421, 422, 423, 424, 425, 426, 427, 428, 429, 430, 431, 432, 433, 434, 435, 750, 762, 765, 902, 906, 911, 952, 956, 964, 980, 981, 982, 983, 932
A17: Low-voltage substation | B17: 1.061 | C17: 1.053 | D17: 1.057 | E17: 1.043 | F17: 1.051 | G17: 79, 80, 81, 82, 83, 84, 756, 781, 782, 984, 985, 986, 987
A18: High-voltage network | B18: 1.038 | C18: 1.033 | D18: 1.036 | E18: 1.026 | F18: 1.032 | G18: 89, 90, 91, 92, 93, 94, 359, 751, 767, 988, 989, 990, 991
A19: High-voltage substation | B19: 1.03 | C19: 1.028 | D19: 1.029 | E19: 1.025 | F19: 1.027 | G19: 771, 791, 792
A20: 33kV generic | B20: 1.022 | C20: 1.02 | D20: 1.021 | E20: 1.018 | F20: 1.02 | G20: 796, 797
A21: 132kV generic | B21: 1.002 | C21: 1.002 | D21: 1.002 | E21: 1.002 | F21: 1.002 | G21: 798, 799
A23: EHV site specific LLFs
A24: Demand
A25: Site | B25: Period 1 | C25: Period 2 | D25: Period 3 | E25: Period 4 | F25: Period 5 | G25: Associated LLFC
A26: FENCHS - Import | B26: 1.009 | C26: 1.007 | D26: 1.009 | E26: 1.006 | F26: 1.007 | G26: 800
A27: LU_CHA - Import | B27: 1.006 | C27: 1.006 | D27: 1.006 | E27: 1.006 | F27: 1.006 | G27: 801
A28: THAMEC - Import | B28: 1.001 | C28: 1.001 | D28: 1.001 | E28: 1.001 | F28: 1.001 | G28: 802
A29: VOLTDC - Import | B29: 1.006 | C29: 1.005 | D29: 1.006 | E29: 1.005 | F29: 1.006 | G29: 803
A30: LU_HOX - Import | B30: 1.022 | C30: 1.02 | D30: 1.021 | E30: 1.018 | F30: 1.02 | G30: 804
A31: BRDGTE - Import | B31: 1.012 | C31: 1.011 | D31: 1.012 | E31: 1.008 | F31: 1.008 | G31: 805
A32: MRKLNE - Import | B32: 1.007 | C32: 1.006 | D32: 1.007 | E32: 1.006 | F32: 1.006 | G32: 806
A33: NR_BOW - Import | B33: 1.012 | C33: 1.013 | D33: 1.013 | E33: 1.012 | F33: 1.013 | G33: 807
A34: Leadenhall St. - IMPORT | B34: 1.01 | C34: 1.007 | D34: 1.01 | E34: 1.006 | F34: 1.008 | G34: 808
A35: TELEHW - Import | B35: 1 | C35: 1 | D35: 1 | E35: 1 | F35: 1 | G35: 809
A36: 22BSHP - Import | B36: 1.014 | C36: 1.015 | D36: 1.015 | E36: 1.013 | F36: 1.013 | G36: 810
A37: BISHPC - Import | B37: 1.02 | C37: 1.019 | D37: 1.019 | E37: 1.019 | F37: 1.019 | G37: 811
... A65: NR_WHI - Import | B65: 1.04 | C65: 1.035 | D65: 1.044 | E65: 1.024 | F65: 1.033 | G65: 849
A67: EHV site specific LLFs
A68: Generation
A69: Site | B69: Period 1 | C69: Period 2 | D69: Period 3 | E69: Period 4 | F69: Period 5 | G69: Associated LLFC
A70: THAMEB - Export | B70: 0.999 | C70: 0.999 | D70: 0.999 | E70: 0.999 | F70: 0.999 | G70: 701
A71: THAMEC - Export | B71: 1 | C71: 0.999 | D71: 1 | E71: 0.999 | F71: 1 | G71: 702
A72: NR_W25 - Export | B72: 0.982 | C72: 0.982 | D72: 0.982 | E72: 0.982 | F72: 0.982 | G72: 703
A73: NR_BOW - Export | B73: 0.981 | C73: 0.981 | D73: 0.981 | E73: 0.981 | F73: 0.981 | G73: 707
A74: BELVED - Export | B74: 0.999 | C74: 0.998 | D74: 0.999 | E74: 0.998 | F74: 0.998 | G74: 711
A75: NR_WES - Export | B75: 0.979 | C75: 0.978 | D75: 0.978 | E75: 0.979 | F75: 0.979 | G75: 716
A76: SELCHP - Export | B76: 1 | C76: 1 | D76: 1 | E76: 1 | F76: 1 | G76: 730
A78: CVA site specific LLFs
A79: MSID | B79: Site | C79: Period 1 | D79: Period 2 | E79: Period 3 | F79: Period 4 | G79: Period 5
A80: 1027 | B80: Kingston | C80: 1.005 | D80: 1.005 | E80: 1.006 | F80: 1.005 | G80: 1.005
A81: 1436 | B81: Brimsdown - Buckhurst Hill | C81: 1.007 | D81: 1.005 | E81: 1.006 | F81: 1.004 | G81: 1.005
A82: 1608 | B82: Hurst 132 kV | C82: 1.002 | D82: 1.001 | E82: 1.001 | F82: 1.001 | G82: 1.001
A83: 1625 | B83: Bulwer Street (Willesden 66 KV) | C83: 1.008 | D83: 1.008 | E83: 1.008 | F83: 1.008 | G83: 1.008
A84: 5538 | B84: Taylors Lane Generation | C84: 1.061 | D84: 1.053 | E84: 1.057 | F84: 1.043 | G84: 1.051
A85: 7167 | B85: Townmead Road FMS Substation | C85: 1.008 | D85: 1.007 | E85: 1.007 | F85: 1.006 | G85: 1.007
A86: 7198 | B86: Barking Network Rail S/S - (Barking C) | C86: 1.027 | D86: 1.027 | E86: 1.027 | F86: 1.027 | G86: 1.027

Sheet Annex 6 New or Amended EHV
A1: Back to Overview | H1: Note: The list of MPANs/MSIDs provided may be incomplete; the DNO reserves the right to apply the listed charges to any other MPANs/MSIDs associated with the site. If sites appear in both Annex 2 and Annex 6, the charges in Annex 6 take precedence. Where an existing Designated EHV Property is modified and energised in the charging year, we may revise the EDCM charges for the modified Designated EHV Property.
A2: Annex 6 - Charges for New or Amended Designated EHV Properties
A4: =Overview!B4& " - Effective from "&Overview!D4&" - "&Overview!E4&" new designated EHV charges" -> London Power Networks - Effective from 1 April 2022 - Final new designated EHV charges
A5: Effective from date | B5: Import Unique Identifier | C5: LLFC | D5: Import MPANs/MSIDs | E5: Export Unique Identifier | F5: LLFC | G5: Export MPANs/MSIDs | H5: Name | I5: ='Annex 2 EHV charges'!H10 -> Import Super Red unit charge (p/kWh) | J5: ='Annex 2 EHV charges'!I10 -> Import fixed charge (p/day) | K5: ='Annex 2 EHV charges'!J10 -> Import capacity charge (p/kVA/day) | L5: ='Annex 2 EHV charges'!K10 -> Import exceeded capacity charge (p/kVA/day) | M5: ='Annex 2 EHV charges'!L10 -> Export Super Red unit charge (p/kWh) | N5: ='Annex 2 EHV charges'!M10 -> Export fixed charge (p/day) | O5: ='Annex 2 EHV charges'!N10 -> Export capacity charge (p/kVA/day) | P5: ='Annex 2 EHV charges'!O10 -> Export exceeded capacity charge (p/kVA/day)
A6: 01/04/2022 | B6: BELVED | C6: 815 | D6: 1200060787109 | E6: BELVED | F6: 711 | G6: 1200060787118 | H6: BELVED | I6: 0 | J6: 331.69 | K6: 0.46 | L6: 0.46 | M6: 0 | N6: 628.26 | O6: 0.05 | P6: 0.05
A7: 01/04/2022 | B7: SELCHP | C7: 827 | D7: 1200010175650 | E7: SELCHP | F7: 730 | G7: 1200010258304 | H7: SELCHP | I7: 0 | J7: 292.78 | K7: 0.64 | L7: 0.64 | M7: 0 | N7: 3105.2 | O7: 0.05 | P7: 0.05
A8: 01/04/2022 | B8: 21MOOR | C8: 854 | D8: 1200062747376 1200062747385 | H8: 21MOOR | I8: 0.364 | J8: 6073.31 | K8: 2.3 | L8: 2.3
A16: =Overview!B4& " - Effective from "&Overview!D4&" - "&Overview!E4&" new designated EHV line loss factors" -> London Power Networks - Effective from 1 April 2022 - Final new designated EHV line loss factors
A17: Effective from date | B17: Import Unique Identifier | C17: LLFC | D17: Import MPANs/MSIDs | E17: Export Unique Identifier | F17: LLFC | G17: Export MPANs/MSIDs | H17: Name | I17: Import LLF period 1 | J17: Import LLF period 2 | K17: Import LLF period 3 | L17: Import LLF period 4 | M17: Import LLF period 5 | N17: Export LLF period 1 | O17: Export LLF period 2 | P17: Export LLF period 3 | Q17: Export LLF period 4 | R17: Export LLF period 5
A18: 01/04/2022 | B18: BELVED | C18: 815 | D18: 1200060787109 | E18: BELVED | F18: 711 | G18: 1200060787118 | H18: BELVED | I18: 1.003 | J18: 1.003 | K18: 1.003 | L18: 1.003 | M18: 1.003 | N18: 0.999 | O18: 0.998 | P18: 0.999 | Q18: 0.998 | R18: 0.998
A19: 01/04/2022 | B19: SELCHP | C19: 827 | D19: 1200010175650 | E19: SELCHP | F19: 730 | G19: 1200010258304 | H19: SELCHP | I19: 1.025 | J19: 1.025 | K19: 1.025 | L19: 1.025 | M19: 1.025 | N19: 1 | O19: 1 | P19: 1 | Q19: 1 | R19: 1
A20: 01/04/2022 | B20: 21MOOR | C20: 854 | D20: 1200062747376 1200062747385 | H20: 21MOOR | I20: 1.022 | J20: 1.02 | K20: 1.021 | L20: 1.018 | M20: 1.02

Sheet Annex 7 Pass-Through Costs
A1: Back to Overview
A2: =Overview!B4& " - Effective from "&Overview!D4&" - "&Overview!E4&" Supplier of Last Resort and Eligible Bad Debt Pass-Through Costs" -> London Power Networks - Effective from 1 April 2022 - Final Supplier of Last Resort and Eligible Bad Debt Pass-Through Costs
A4: Tariff name | B4: Open LLFCs / LDNO unique billing identifier | C4: PCs | D4: Supplier of Last Resort Fixed charge adder* p/MPAN/day | E4: Excess Supplier of Last Resort Fixed charge adder** p/MPAN/day | F4: Eligible Bad Debt Fixed charge adder*** p/MPAN/day
A5: Domestic Aggregated with Residual | B5: =IFERROR(INDEX('Annex 1 LV, HV and UMS charges'!$B$12:$B$44,MATCH($A5,'Annex 1 LV, HV and UMS charges'!$A$12:$A$44,0)),IF(INDEX('Annex 4 LDNO charges'!$B$11:$B$202,MATCH($A5,'Annex 4 LDNO charges'!$A$11:$A$202,0))=0,"",INDEX('Annex 4 LDNO charges'!$B$11:$B$202,MATCH($A5,'Annex 4 LDNO charges'!$A$11:$A$202,0)))) -> 1 | C5: =IFERROR(INDEX('Annex 1 LV, HV and UMS charges'!$C$13:$C$44,MATCH($A5,'Annex 1 LV, HV and UMS charges'!$A$13:$A$44,0)),INDEX('Annex 4 LDNO charges'!$C$13:$C$202,MATCH($A5,'Annex 4 LDNO charges'!$A$13:$A$202,0))) -> 0, 1, 2 | D5: 0.05859276 | E5: 9.6543478 | F5: 0.052226762
A6: Non-Domestic Aggregated No Residual | B6: =IFERROR(INDEX('Annex 1 LV, HV and UMS charges'!$B$12:$B$44,MATCH($A6,'Annex 1 LV, HV and UMS charges'!$A$12:$A$44,0)),IF(INDEX('Annex 4 LDNO charges'!$B$11:$B$202,MATCH($A6,'Annex 4 LDNO charges'!$A$11:$A$202,0))=0,"",INDEX('Annex 4 LDNO charges'!$B$11:$B$202,MATCH($A6,'Annex 4 LDNO charges'!$A$11:$A$202,0)))) -> 199 | C6: =IFERROR(INDEX('Annex 1 LV, HV and UMS charges'!$C$13:$C$44,MATCH($A6,'Annex 1 LV, HV and UMS charges'!$A$13:$A$44,0)),INDEX('Annex 4 LDNO charges'!$C$13:$C$202,MATCH($A6,'Annex 4 LDNO charges'!$A$13:$A$202,0))) -> 0, 3, 4, 5-8 | F6: 0.052226762
A7: Non-Domestic Aggregated Band 1 | B7: =IFERROR(INDEX('Annex 1 LV, HV and UMS charges'!$B$12:$B$44,MATCH($A7,'Annex 1 LV, HV and UMS charges'!$A$12:$A$44,0)),IF(INDEX('Annex 4 LDNO charges'!$B$11:$B$202,MATCH($A7,'Annex 4 LDNO charges'!$A$11:$A$202,0))=0,"",INDEX('Annex 4 LDNO charges'!$B$11:$B$202,MATCH($A7,'Annex 4 LDNO charges'!$A$11:$A$202,0)))) -> 201 | C7: =IFERROR(INDEX('Annex 1 LV, HV and UMS charges'!$C$13:$C$44,MATCH($A7,'Annex 1 LV, HV and UMS charges'!$A$13:$A$44,0)),INDEX('Annex 4 LDNO charges'!$C$13:$C$202,MATCH($A7,'Annex 4 LDNO charges'!$A$13:$A$202,0))) -> 0, 3, 4, 5-8 | F7: 0.052226762
A8: Non-Domestic Aggregated Band 2 | B8: =IFERROR(INDEX('Annex 1 LV, HV and UMS charges'!$B$12:$B$44,MATCH($A8,'Annex 1 LV, HV and UMS charges'!$A$12:$A$44,0)),IF(INDEX('Annex 4 LDNO charges'!$B$11:$B$202,MATCH($A8,'Annex 4 LDNO charges'!$A$11:$A$202,0))=0,"",INDEX('Annex 4 LDNO charges'!$B$11:$B$202,MATCH($A8,'Annex 4 LDNO charges'!$A$11:$A$202,0)))) -> 202 | C8: =IFERROR(INDEX('Annex 1 LV, HV and UMS charges'!$C$13:$C$44,MATCH($A8,'Annex 1 LV, HV and UMS charges'!$A$13:$A$44,0)),INDEX('Annex 4 LDNO charges'!$C$13:$C$202,MATCH($A8,'Annex 4 LDNO charges'!$A$13:$A$202,0))) -> 0, 3, 4, 5-8 | F8: 0.052226762
A9: Non-Domestic Aggregated Band 3 | B9: =IFERROR(INDEX('Annex 1 LV, HV and UMS charges'!$B$12:$B$44,MATCH($A9,'Annex 1 LV, HV and UMS charges'!$A$12:$A$44,0)),IF(INDEX('Annex 4 LDNO charges'!$B$11:$B$202,MATCH($A9,'Annex 4 LDNO charges'!$A$11:$A$202,0))=0,"",INDEX('Annex 4 LDNO charges'!$B$11:$B$202,MATCH($A9,'Annex 4 LDNO charges'!$A$11:$A$202,0)))) -> 203 | C9: =IFERROR(INDEX('Annex 1 LV, HV and UMS charges'!$C$13:$C$44,MATCH($A9,'Annex 1 LV, HV and UMS charges'!$A$13:$A$44,0)),INDEX('Annex 4 LDNO charges'!$C$13:$C$202,MATCH($A9,'Annex 4 LDNO charges'!$A$13:$A$202,0))) -> 0, 3, 4, 5-8 | F9: 0.052226762
A10: Non-Domestic Aggregated Band 4 | B10: =IFERROR(INDEX('Annex 1 LV, HV and UMS charges'!$B$12:$B$44,MATCH($A10,'Annex 1 LV, HV and UMS charges'!$A$12:$A$44,0)),IF(INDEX('Annex 4 LDNO charges'!$B$11:$B$202,MATCH($A10,'Annex 4 LDNO charges'!$A$11:$A$202,0))=0,"",INDEX('Annex 4 LDNO charges'!$B$11:$B$202,MATCH($A10,'Annex 4 LDNO charges'!$A$11:$A$202,0)))) -> 204 | C10: =IFERROR(INDEX('Annex 1 LV, HV and UMS charges'!$C$13:$C$44,MATCH($A10,'Annex 1 LV, HV and UMS charges'!$A$13:$A$44,0)),INDEX('Annex 4 LDNO charges'!$C$13:$C$202,MATCH($A10,'Annex 4 LDNO charges'!$A$13:$A$202,0))) -> 0, 3, 4, 5-8 | F10: 0.052226762
A11: LV Site Specific No Residual | B11: =IFERROR(INDEX('Annex 1 LV, HV and UMS charges'!$B$12:$B$44,MATCH($A11,'Annex 1 LV, HV and UMS charges'!$A$12:$A$44,0)),IF(INDEX('Annex 4 LDNO charges'!$B$11:$B$202,MATCH($A11,'Annex 4 LDNO charges'!$A$11:$A$202,0))=0,"",INDEX('Annex 4 LDNO charges'!$B$11:$B$202,MATCH($A11,'Annex 4 LDNO charges'!$A$11:$A$202,0)))) -> 70 | C11: =IFERROR(INDEX('Annex 1 LV, HV and UMS charges'!$C$13:$C$44,MATCH($A11,'Annex 1 LV, HV and UMS charges'!$A$13:$A$44,0)),INDEX('Annex 4 LDNO charges'!$C$13:$C$202,MATCH($A11,'Annex 4 LDNO charges'!$A$13:$A$202,0))) -> 0 | F11: 0.052226762
A12: LV Site Specific Band 1 | B12: =IFERROR(INDEX('Annex 1 LV, HV and UMS charges'!$B$12:$B$44,MATCH($A12,'Annex 1 LV, HV and UMS charges'!$A$12:$A$44,0)),IF(INDEX('Annex 4 LDNO charges'!$B$11:$B$202,MATCH($A12,'Annex 4 LDNO charges'!$A$11:$A$202,0))=0,"",INDEX('Annex 4 LDNO charges'!$B$11:$B$202,MATCH($A12,'Annex 4 LDNO charges'!$A$11:$A$202,0)))) -> 71 | C12: =IFERROR(INDEX('Annex 1 LV, HV and UMS charges'!$C$13:$C$44,MATCH($A12,'Annex 1 LV, HV and UMS charges'!$A$13:$A$44,0)),INDEX('Annex 4 LDNO charges'!$C$13:$C$202,MATCH($A12,'Annex 4 LDNO charges'!$A$13:$A$202,0))) -> 0 | F12: 0.052226762
A13: LV Site Specific Band 2 | B13: =IFERROR(INDEX('Annex 1 LV, HV and UMS charges'!$B$12:$B$44,MATCH($A13,'Annex 1 LV, HV and UMS charges'!$A$12:$A$44,0)),IF(INDEX('Annex 4 LDNO charges'!$B$11:$B$202,MATCH($A13,'Annex 4 LDNO charges'!$A$11:$A$202,0))=0,"",INDEX('Annex 4 LDNO charges'!$B$11:$B$202,MATCH($A13,'Annex 4 LDNO charges'!$A$11:$A$202,0)))) -> 72 | C13: =IFERROR(INDEX('Annex 1 LV, HV and UMS charges'!$C$13:$C$44,MATCH($A13,'Annex 1 LV, HV and UMS charges'!$A$13:$A$44,0)),INDEX('Annex 4 LDNO charges'!$C$13:$C$202,MATCH($A13,'Annex 4 LDNO charges'!$A$13:$A$202,0))) -> 0 | F13: 0.052226762
A14: LV Site Specific Band 3 | B14: =IFERROR(INDEX('Annex 1 LV, HV and UMS charges'!$B$12:$B$44,MATCH($A14,'Annex 1 LV, HV and UMS charges'!$A$12:$A$44,0)),IF(INDEX('Annex 4 LDNO charges'!$B$11:$B$202,MATCH($A14,'Annex 4 LDNO charges'!$A$11:$A$202,0))=0,"",INDEX('Annex 4 LDNO charges'!$B$11:$B$202,MATCH($A14,'Annex 4 LDNO charges'!$A$11:$A$202,0)))) -> 73 | C14: =IFERROR(INDEX('Annex 1 LV, HV and UMS charges'!$C$13:$C$44,MATCH($A14,'Annex 1 LV, HV and UMS charges'!$A$13:$A$44,0)),INDEX('Annex 4 LDNO charges'!$C$13:$C$202,MATCH($A14,'Annex 4 LDNO charges'!$A$13:$A$202,0))) -> 0 | F14: 0.052226762
A15: LV Site Specific Band 4 | B15: =IFERROR(INDEX('Annex 1 LV, HV and UMS charges'!$B$12:$B$44,MATCH($A15,'Annex 1 LV, HV and UMS charges'!$A$12:$A$44,0)),IF(INDEX('Annex 4 LDNO charges'!$B$11:$B$202,MATCH($A15,'Annex 4 LDNO charges'!$A$11:$A$202,0))=0,"",INDEX('Annex 4 LDNO charges'!$B$11:$B$202,MATCH($A15,'Annex 4 LDNO charges'!$A$11:$A$202,0)))) -> 74 | C15: =IFERROR(INDEX('Annex 1 LV, HV and UMS charges'!$C$13:$C$44,MATCH($A15,'Annex 1 LV, HV and UMS charges'!$A$13:$A$44,0)),INDEX('Annex 4 LDNO charges'!$C$13:$C$202,MATCH($A15,'Annex 4 LDNO charges'!$A$13:$A$202,0))) -> 0 | F15: 0.052226762
A16: LV Sub Site Specific No Residual | B16: =IFERROR(INDEX('Annex 1 LV, HV and UMS charges'!$B$12:$B$44,MATCH($A16,'Annex 1 LV, HV and UMS charges'!$A$12:$A$44,0)),IF(INDEX('Annex 4 LDNO charges'!$B$11:$B$202,MATCH($A16,'Annex 4 LDNO charges'!$A$11:$A$202,0))=0,"",INDEX('Annex 4 LDNO charges'!$B$11:$B$202,MATCH($A16,'Annex 4 LDNO charges'!$A$11:$A$202,0)))) -> 80 | C16: =IFERROR(INDEX('Annex 1 LV, HV and UMS charges'!$C$13:$C$44,MATCH($A16,'Annex 1 LV, HV and UMS charges'!$A$13:$A$44,0)),INDEX('Annex 4 LDNO charges'!$C$13:$C$202,MATCH($A16,'Annex 4 LDNO charges'!$A$13:$A$202,0))) -> 0 | F16: 0.052226762
A17: LV Sub Site Specific Band 1 | B17: =IFERROR(INDEX('Annex 1 LV, HV and UMS charges'!$B$12:$B$44,MATCH($A17,'Annex 1 LV, HV and UMS charges'!$A$12:$A$44,0)),IF(INDEX('Annex 4 LDNO charges'!$B$11:$B$202,MATCH($A17,'Annex 4 LDNO charges'!$A$11:$A$202,0))=0,"",INDEX('Annex 4 LDNO charges'!$B$11:$B$202,MATCH($A17,'Annex 4 LDNO charges'!$A$11:$A$202,0)))) -> 81 | C17: =IFERROR(INDEX('Annex 1 LV, HV and UMS charges'!$C$13:$C$44,MATCH($A17,'Annex 1 LV, HV and UMS charges'!$A$13:$A$44,0)),INDEX('Annex 4 LDNO charges'!$C$13:$C$202,MATCH($A17,'Annex 4 LDNO charges'!$A$13:$A$202,0))) -> 0 | F17: 0.052226762
... A25: HV Site Specific Band 4 | B25: =IFERROR(INDEX('Annex 1 LV, HV and UMS charges'!$B$12:$B$44,MATCH($A25,'Annex 1 LV, HV and UMS charges'!$A$12:$A$44,0)),IF(INDEX('Annex 4 LDNO charges'!$B$11:$B$202,MATCH($A25,'Annex 4 LDNO charges'!$A$11:$A$202,0))=0,"",INDEX('Annex 4 LDNO charges'!$B$11:$B$202,MATCH($A25,'Annex 4 LDNO charges'!$A$11:$A$202,0)))) -> 94 | C25: =IFERROR(INDEX('Annex 1 LV, HV and UMS charges'!$C$13:$C$44,MATCH($A25,'Annex 1 LV, HV and UMS charges'!$A$13:$A$44,0)),INDEX('Annex 4 LDNO charges'!$C$13:$C$202,MATCH($A25,'Annex 4 LDNO charges'!$A$13:$A$202,0))) -> 0 | F25: 0.052226762
A26: LDNO LV: Domestic Aggregated with Residual | B26: =IFERROR(INDEX('Annex 1 LV, HV and UMS charges'!$B$12:$B$44,MATCH($A26,'Annex 1 LV, HV and UMS charges'!$A$12:$A$44,0)),IF(INDEX('Annex 4 LDNO charges'!$B$11:$B$202,MATCH($A26,'Annex 4 LDNO charges'!$A$11:$A$202,0))=0,"",INDEX('Annex 4 LDNO charges'!$B$11:$B$202,MATCH($A26,'Annex 4 LDNO charges'!$A$11:$A$202,0)))) -> A00 | C26: =IFERROR(INDEX('Annex 1 LV, HV and UMS charges'!$C$13:$C$44,MATCH($A26,'Annex 1 LV, HV and UMS charges'!$A$13:$A$44,0)),INDEX('Annex 4 LDNO charges'!$C$13:$C$202,MATCH($A26,'Annex 4 LDNO charges'!$A$13:$A$202,0))) -> 0, 1, 2 | D26: 0.05859276 | E26: 9.6543478 | F26: 0.052226762
A27: LDNO LV: Non-Domestic Aggregated No Residual | B27: =IFERROR(INDEX('Annex 1 LV, HV and UMS charges'!$B$12:$B$44,MATCH($A27,'Annex 1 LV, HV and UMS charges'!$A$12:$A$44,0)),IF(INDEX('Annex 4 LDNO charges'!$B$11:$B$202,MATCH($A27,'Annex 4 LDNO charges'!$A$11:$A$202,0))=0,"",INDEX('Annex 4 LDNO charges'!$B$11:$B$202,MATCH($A27,'Annex 4 LDNO charges'!$A$11:$A$202,0)))) -> C00 | C27: =IFERROR(INDEX('Annex 1 LV, HV and UMS charges'!$C$13:$C$44,MATCH($A27,'Annex 1 LV, HV and UMS charges'!$A$13:$A$44,0)),INDEX('Annex 4 LDNO charges'!$C$13:$C$202,MATCH($A27,'Annex 4 LDNO charges'!$A$13:$A$202,0))) -> 0, 3, 4, 5-8 | F27: 0.052226762
A28: LDNO LV: Non-Domestic Aggregated Band 1 | B28: =IFERROR(INDEX('Annex 1 LV, HV and UMS charges'!$B$12:$B$44,MATCH($A28,'Annex 1 LV, HV and UMS charges'!$A$12:$A$44,0)),IF(INDEX('Annex 4 LDNO charges'!$B$11:$B$202,MATCH($A28,'Annex 4 LDNO charges'!$A$11:$A$202,0))=0,"",INDEX('Annex 4 LDNO charges'!$B$11:$B$202,MATCH($A28,'Annex 4 LDNO charges'!$A$11:$A$202,0)))) -> C01 | C28: =IFERROR(INDEX('Annex 1 LV, HV and UMS charges'!$C$13:$C$44,MATCH($A28,'Annex 1 LV, HV and UMS charges'!$A$13:$A$44,0)),INDEX('Annex 4 LDNO charges'!$C$13:$C$202,MATCH($A28,'Annex 4 LDNO charges'!$A$13:$A$202,0))) -> 0, 3, 4, 5-8 | F28: 0.052226762
A29: LDNO LV: Non-Domestic Aggregated Band 2 | B29: =IFERROR(INDEX('Annex 1 LV, HV and UMS charges'!$B$12:$B$44,MATCH($A29,'Annex 1 LV, HV and UMS charges'!$A$12:$A$44,0)),IF(INDEX('Annex 4 LDNO charges'!$B$11:$B$202,MATCH($A29,'Annex 4 LDNO charges'!$A$11:$A$202,0))=0,"",INDEX('Annex 4 LDNO charges'!$B$11:$B$202,MATCH($A29,'Annex 4 LDNO charges'!$A$11:$A$202,0)))) -> C02 | C29: =IFERROR(INDEX('Annex 1 LV, HV and UMS charges'!$C$13:$C$44,MATCH($A29,'Annex 1 LV, HV and UMS charges'!$A$13:$A$44,0)),INDEX('Annex 4 LDNO charges'!$C$13:$C$202,MATCH($A29,'Annex 4 LDNO charges'!$A$13:$A$202,0))) -> 0, 3, 4, 5-8 | F29: 0.052226762
A30: LDNO LV: Non-Domestic Aggregated Band 3 | B30: =IFERROR(INDEX('Annex 1 LV, HV and UMS charges'!$B$12:$B$44,MATCH($A30,'Annex 1 LV, HV and UMS charges'!$A$12:$A$44,0)),IF(INDEX('Annex 4 LDNO charges'!$B$11:$B$202,MATCH($A30,'Annex 4 LDNO charges'!$A$11:$A$202,0))=0,"",INDEX('Annex 4 LDNO charges'!$B$11:$B$202,MATCH($A30,'Annex 4 LDNO charges'!$A$11:$A$202,0)))) -> C03 | C30: =IFERROR(INDEX('Annex 1 LV, HV and UMS charges'!$C$13:$C$44,MATCH($A30,'Annex 1 LV, HV and UMS charges'!$A$13:$A$44,0)),INDEX('Annex 4 LDNO charges'!$C$13:$C$202,MATCH($A30,'Annex 4 LDNO charges'!$A$13:$A$202,0))) -> 0, 3, 4, 5-8 | F30: 0.052226762
A31: LDNO LV: Non-Domestic Aggregated Band 4 | B31: =IFERROR(INDEX('Annex 1 LV, HV and UMS charges'!$B$12:$B$44,MATCH($A31,'Annex 1 LV, HV and UMS charges'!$A$12:$A$44,0)),IF(INDEX('Annex 4 LDNO charges'!$B$11:$B$202,MATCH($A31,'Annex 4 LDNO charges'!$A$11:$A$202,0))=0,"",INDEX('Annex 4 LDNO charges'!$B$11:$B$202,MATCH($A31,'Annex 4 LDNO charges'!$A$11:$A$202,0)))) -> C04 | C31: =IFERROR(INDEX('Annex 1 LV, HV and UMS charges'!$C$13:$C$44,MATCH($A31,'Annex 1 LV, HV and UMS charges'!$A$13:$A$44,0)),INDEX('Annex 4 LDNO charges'!$C$13:$C$202,MATCH($A31,'Annex 4 LDNO charges'!$A$13:$A$202,0))) -> 0, 3, 4, 5-8 | F31: 0.052226762
A32: LDNO LV: LV Site Specific No Residual | B32: =IFERROR(INDEX('Annex 1 LV, HV and UMS charges'!$B$12:$B$44,MATCH($A32,'Annex 1 LV, HV and UMS charges'!$A$12:$A$44,0)),IF(INDEX('Annex 4 LDNO charges'!$B$11:$B$202,MATCH($A32,'Annex 4 LDNO charges'!$A$11:$A$202,0))=0,"",INDEX('Annex 4 LDNO charges'!$B$11:$B$202,MATCH($A32,'Annex 4 LDNO charges'!$A$11:$A$202,0)))) -> E00 | C32: =IFERROR(INDEX('Annex 1 LV, HV and UMS charges'!$C$13:$C$44,MATCH($A32,'Annex 1 LV, HV and UMS charges'!$A$13:$A$44,0)),INDEX('Annex 4 LDNO charges'!$C$13:$C$202,MATCH($A32,'Annex 4 LDNO charges'!$A$13:$A$202,0))) -> 0 | F32: 0.052226762
A33: LDNO LV: LV Site Specific Band 1 | B33: =IFERROR(INDEX('Annex 1 LV, HV and UMS charges'!$B$12:$B$44,MATCH($A33,'Annex 1 LV, HV and UMS charges'!$A$12:$A$44,0)),IF(INDEX('Annex 4 LDNO charges'!$B$11:$B$202,MATCH($A33,'Annex 4 LDNO charges'!$A$11:$A$202,0))=0,"",INDEX('Annex 4 LDNO charges'!$B$11:$B$202,MATCH($A33,'Annex 4 LDNO charges'!$A$11:$A$202,0)))) -> E01 | C33: =IFERROR(INDEX('Annex 1 LV, HV and UMS charges'!$C$13:$C$44,MATCH($A33,'Annex 1 LV, HV and UMS charges'!$A$13:$A$44,0)),INDEX('Annex 4 LDNO charges'!$C$13:$C$202,MATCH($A33,'Annex 4 LDNO charges'!$A$13:$A$202,0))) -> 0 | F33: 0.052226762
A34: LDNO LV: LV Site Specific Band 2 | B34: =IFERROR(INDEX('Annex 1 LV, HV and UMS charges'!$B$12:$B$44,MATCH($A34,'Annex 1 LV, HV and UMS charges'!$A$12:$A$44,0)),IF(INDEX('Annex 4 LDNO charges'!$B$11:$B$202,MATCH($A34,'Annex 4 LDNO charges'!$A$11:$A$202,0))=0,"",INDEX('Annex 4 LDNO charges'!$B$11:$B$202,MATCH($A34,'Annex 4 LDNO charges'!$A$11:$A$202,0)))) -> E02 | C34: =IFERROR(INDEX('Annex 1 LV, HV and UMS charges'!$C$13:$C$44,MATCH($A34,'Annex 1 LV, HV and UMS charges'!$A$13:$A$44,0)),INDEX('Annex 4 LDNO charges'!$C$13:$C$202,MATCH($A34,'Annex 4 LDNO charges'!$A$13:$A$202,0))) -> 0 | F34: 0.052226762
A35: LDNO LV: LV Site Specific Band 3 | B35: =IFERROR(INDEX('Annex 1 LV, HV and UMS charges'!$B$12:$B$44,MATCH($A35,'Annex 1 LV, HV and UMS charges'!$A$12:$A$44,0)),IF(INDEX('Annex 4 LDNO charges'!$B$11:$B$202,MATCH($A35,'Annex 4 LDNO charges'!$A$11:$A$202,0))=0,"",INDEX('Annex 4 LDNO charges'!$B$11:$B$202,MATCH($A35,'Annex 4 LDNO charges'!$A$11:$A$202,0)))) -> E03 | C35: =IFERROR(INDEX('Annex 1 LV, HV and UMS charges'!$C$13:$C$44,MATCH($A35,'Annex 1 LV, HV and UMS charges'!$A$13:$A$44,0)),INDEX('Annex 4 LDNO charges'!$C$13:$C$202,MATCH($A35,'Annex 4 LDNO charges'!$A$13:$A$202,0))) -> 0 | F35: 0.052226762
A36: LDNO LV: LV Site Specific Band 4 | B36: =IFERROR(INDEX('Annex 1 LV, HV and UMS charges'!$B$12:$B$44,MATCH($A36,'Annex 1 LV, HV and UMS charges'!$A$12:$A$44,0)),IF(INDEX('Annex 4 LDNO charges'!$B$11:$B$202,MATCH($A36,'Annex 4 LDNO charges'!$A$11:$A$202,0))=0,"",INDEX('Annex 4 LDNO charges'!$B$11:$B$202,MATCH($A36,'Annex 4 LDNO charges'!$A$11:$A$202,0)))) -> E04 | C36: =IFERROR(INDEX('Annex 1 LV, HV and UMS charges'!$C$13:$C$44,MATCH($A36,'Annex 1 LV, HV and UMS charges'!$A$13:$A$44,0)),INDEX('Annex 4 LDNO charges'!$C$13:$C$202,MATCH($A36,'Annex 4 LDNO charges'!$A$13:$A$202,0))) -> 0 | F36: 0.052226762
A37: LDNO HV: Domestic Aggregated with Residual | B37: =IFERROR(INDEX('Annex 1 LV, HV and UMS charges'!$B$12:$B$44,MATCH($A37,'Annex 1 LV, HV and UMS charges'!$A$12:$A$44,0)),IF(INDEX('Annex 4 LDNO charges'!$B$11:$B$202,MATCH($A37,'Annex 4 LDNO charges'!$A$11:$A$202,0))=0,"",INDEX('Annex 4 LDNO charges'!$B$11:$B$202,MATCH($A37,'Annex 4 LDNO charges'!$A$11:$A$202,0)))) -> A10 | C37: =IFERROR(INDEX('Annex 1 LV, HV and UMS charges'!$C$13:$C$44,MATCH($A37,'Annex 1 LV, HV and UMS charges'!$A$13:$A$44,0)),INDEX('Annex 4 LDNO charges'!$C$13:$C$202,MATCH($A37,'Annex 4 LDNO charges'!$A$13:$A$202,0))) -> 0, 1, 2 | D37: 0.05859276 | E37: 9.6543478 | F37: 0.052226762
A38: LDNO HV: Non-Domestic Aggregated No Residual | B38: =IFERROR(INDEX('Annex 1 LV, HV and UMS charges'!$B$12:$B$44,MATCH($A38,'Annex 1 LV, HV and UMS charges'!$A$12:$A$44,0)),IF(INDEX('Annex 4 LDNO charges'!$B$11:$B$202,MATCH($A38,'Annex 4 LDNO charges'!$A$11:$A$202,0))=0,"",INDEX('Annex 4 LDNO charges'!$B$11:$B$202,MATCH($A38,'Annex 4 LDNO charges'!$A$11:$A$202,0)))) -> C10 | C38: =IFERROR(INDEX('Annex 1 LV, HV and UMS charges'!$C$13:$C$44,MATCH($A38,'Annex 1 LV, HV and UMS charges'!$A$13:$A$44,0)),INDEX('Annex 4 LDNO charges'!$C$13:$C$202,MATCH($A38,'Annex 4 LDNO charges'!$A$13:$A$202,0))) -> 0, 3, 4, 5-8 | F38: 0.052226762
A39: LDNO HV: Non-Domestic Aggregated Band 1 | B39: =IFERROR(INDEX('Annex 1 LV, HV and UMS charges'!$B$12:$B$44,MATCH($A39,'Annex 1 LV, HV and UMS charges'!$A$12:$A$44,0)),IF(INDEX('Annex 4 LDNO charges'!$B$11:$B$202,MATCH($A39,'Annex 4 LDNO charges'!$A$11:$A$202,0))=0,"",INDEX('Annex 4 LDNO charges'!$B$11:$B$202,MATCH($A39,'Annex 4 LDNO charges'!$A$11:$A$202,0)))) -> C11 | C39: =IFERROR(INDEX('Annex 1 LV, HV and UMS charges'!$C$13:$C$44,MATCH($A39,'Annex 1 LV, HV and UMS charges'!$A$13:$A$44,0)),INDEX('Annex 4 LDNO charges'!$C$13:$C$202,MATCH($A39,'Annex 4 LDNO charges'!$A$13:$A$202,0))) -> 0, 3, 4, 5-8 | F39: 0.052226762
A40: LDNO HV: Non-Domestic Aggregated Band 2 | B40: =IFERROR(INDEX('Annex 1 LV, HV and UMS charges'!$B$12:$B$44,MATCH($A40,'Annex 1 LV, HV and UMS charges'!$A$12:$A$44,0)),IF(INDEX('Annex 4 LDNO charges'!$B$11:$B$202,MATCH($A40,'Annex 4 LDNO charges'!$A$11:$A$202,0))=0,"",INDEX('Annex 4 LDNO charges'!$B$11:$B$202,MATCH($A40,'Annex 4 LDNO charges'!$A$11:$A$202,0)))) -> C12 | C40: =IFERROR(INDEX('Annex 1 LV, HV and UMS charges'!$C$13:$C$44,MATCH($A40,'Annex 1 LV, HV and UMS charges'!$A$13:$A$44,0)),INDEX('Annex 4 LDNO charges'!$C$13:$C$202,MATCH($A40,'Annex 4 LDNO charges'!$A$13:$A$202,0))) -> 0, 3, 4, 5-8 | F40: 0.052226762
A41: LDNO HV: Non-Domestic Aggregated Band 3 | B41: =IFERROR(INDEX('Annex 1 LV, HV and UMS charges'!$B$12:$B$44,MATCH($A41,'Annex 1 LV, HV and UMS charges'!$A$12:$A$44,0)),IF(INDEX('Annex 4 LDNO charges'!$B$11:$B$202,MATCH($A41,'Annex 4 LDNO charges'!$A$11:$A$202,0))=0,"",INDEX('Annex 4 LDNO charges'!$B$11:$B$202,MATCH($A41,'Annex 4 LDNO charges'!$A$11:$A$202,0)))) -> C13 | C41: =IFERROR(INDEX('Annex 1 LV, HV and UMS charges'!$C$13:$C$44,MATCH($A41,'Annex 1 LV, HV and UMS charges'!$A$13:$A$44,0)),INDEX('Annex 4 LDNO charges'!$C$13:$C$202,MATCH($A41,'Annex 4 LDNO charges'!$A$13:$A$202,0))) -> 0, 3, 4, 5-8 | F41: 0.052226762
A42: LDNO HV: Non-Domestic Aggregated Band 4 | B42: =IFERROR(INDEX('Annex 1 LV, HV and UMS charges'!$B$12:$B$44,MATCH($A42,'Annex 1 LV, HV and UMS charges'!$A$12:$A$44,0)),IF(INDEX('Annex 4 LDNO charges'!$B$11:$B$202,MATCH($A42,'Annex 4 LDNO charges'!$A$11:$A$202,0))=0,"",INDEX('Annex 4 LDNO charges'!$B$11:$B$202,MATCH($A42,'Annex 4 LDNO charges'!$A$11:$A$202,0)))) -> C14 | C42: =IFERROR(INDEX('Annex 1 LV, HV and UMS charges'!$C$13:$C$44,MATCH($A42,'Annex 1 LV, HV and UMS charges'!$A$13:$A$44,0)),INDEX('Annex 4 LDNO charges'!$C$13:$C$202,MATCH($A42,'Annex 4 LDNO charges'!$A$13:$A$202,0))) -> 0, 3, 4, 5-8 | F42: 0.052226762
A43: LDNO HV: LV Site Specific No Residual | B43: =IFERROR(INDEX('Annex 1 LV, HV and UMS charges'!$B$12:$B$44,MATCH($A43,'Annex 1 LV, HV and UMS charges'!$A$12:$A$44,0)),IF(INDEX('Annex 4 LDNO charges'!$B$11:$B$202,MATCH($A43,'Annex 4 LDNO charges'!$A$11:$A$202,0))=0,"",INDEX('Annex 4 LDNO charges'!$B$11:$B$202,MATCH($A43,'Annex 4 LDNO charges'!$A$11:$A$202,0)))) -> E10 | C43: =IFERROR(INDEX('Annex 1 LV, HV and UMS charges'!$C$13:$C$44,MATCH($A43,'Annex 1 LV, HV and UMS charges'!$A$13:$A$44,0)),INDEX('Annex 4 LDNO charges'!$C$13:$C$202,MATCH($A43,'Annex 4 LDNO charges'!$A$13:$A$202,0))) -> 0 | F43: 0.052226762
A44: LDNO HV: LV Site Specific Band 1 | B44: =IFERROR(INDEX('Annex 1 LV, HV and UMS charges'!$B$12:$B$44,MATCH($A44,'Annex 1 LV, HV and UMS charges'!$A$12:$A$44,0)),IF(INDEX('Annex 4 LDNO charges'!$B$11:$B$202,MATCH($A44,'Annex 4 LDNO charges'!$A$11:$A$202,0))=0,"",INDEX('Annex 4 LDNO charges'!$B$11:$B$202,MATCH($A44,'Annex 4 LDNO charges'!$A$11:$A$202,0)))) -> E11 | C44: =IFERROR(INDEX('Annex 1 LV, HV and UMS charges'!$C$13:$C$44,MATCH($A44,'Annex 1 LV, HV and UMS charges'!$A$13:$A$44,0)),INDEX('Annex 4 LDNO charges'!$C$13:$C$202,MATCH($A44,'Annex 4 LDNO charges'!$A$13:$A$202,0))) -> 0 | F44: 0.052226762
A45: LDNO HV: LV Site Specific Band 2 | B45: =IFERROR(INDEX('Annex 1 LV, HV and UMS charges'!$B$12:$B$44,MATCH($A45,'Annex 1 LV, HV and UMS charges'!$A$12:$A$44,0)),IF(INDEX('Annex 4 LDNO charges'!$B$11:$B$202,MATCH($A45,'Annex 4 LDNO charges'!$A$11:$A$202,0))=0,"",INDEX('Annex 4 LDNO charges'!$B$11:$B$202,MATCH($A45,'Annex 4 LDNO charges'!$A$11:$A$202,0)))) -> E12 | C45: =IFERROR(INDEX('Annex 1 LV, HV and UMS charges'!$C$13:$C$44,MATCH($A45,'Annex 1 LV, HV and UMS charges'!$A$13:$A$44,0)),INDEX('Annex 4 LDNO charges'!$C$13:$C$202,MATCH($A45,'Annex 4 LDNO charges'!$A$13:$A$202,0))) -> 0 | F45: 0.052226762
A46: LDNO HV: LV Site Specific Band 3 | B46: =IFERROR(INDEX('Annex 1 LV, HV and UMS charges'!$B$12:$B$44,MATCH($A46,'Annex 1 LV, HV and UMS charges'!$A$12:$A$44,0)),IF(INDEX('Annex 4 LDNO charges'!$B$11:$B$202,MATCH($A46,'Annex 4 LDNO charges'!$A$11:$A$202,0))=0,"",INDEX('Annex 4 LDNO charges'!$B$11:$B$202,MATCH($A46,'Annex 4 LDNO charges'!$A$11:$A$202,0)))) -> E13 | C46: =IFERROR(INDEX('Annex 1 LV, HV and UMS charges'!$C$13:$C$44,MATCH($A46,'Annex 1 LV, HV and UMS charges'!$A$13:$A$44,0)),INDEX('Annex 4 LDNO charges'!$C$13:$C$202,MATCH($A46,'Annex 4 LDNO charges'!$A$13:$A$202,0))) -> 0 | F46: 0.052226762
A47: LDNO HV: LV Site Specific Band 4 | B47: =IFERROR(INDEX('Annex 1 LV, HV and UMS charges'!$B$12:$B$44,MATCH($A47,'Annex 1 LV, HV and UMS charges'!$A$12:$A$44,0)),IF(INDEX('Annex 4 LDNO charges'!$B$11:$B$202,MATCH($A47,'Annex 4 LDNO charges'!$A$11:$A$202,0))=0,"",INDEX('Annex 4 LDNO charges'!$B$11:$B$202,MATCH($A47,'Annex 4 LDNO charges'!$A$11:$A$202,0)))) -> E14 | C47: =IFERROR(INDEX('Annex 1 LV, HV and UMS charges'!$C$13:$C$44,MATCH($A47,'Annex 1 LV, HV and UMS charges'!$A$13:$A$44,0)),INDEX('Annex 4 LDNO charges'!$C$13:$C$202,MATCH($A47,'Annex 4 LDNO charges'!$A$13:$A$202,0))) -> 0 | F47: 0.052226762
A48: LDNO HV: LV Sub Site Specific No Residual | B48: =IFERROR(INDEX('Annex 1 LV, HV and UMS charges'!$B$12:$B$44,MATCH($A48,'Annex 1 LV, HV and UMS charges'!$A$12:$A$44,0)),IF(INDEX('Annex 4 LDNO charges'!$B$11:$B$202,MATCH($A48,'Annex 4 LDNO charges'!$A$11:$A$202,0))=0,"",INDEX('Annex 4 LDNO charges'!$B$11:$B$202,MATCH($A48,'Annex 4 LDNO charges'!$A$11:$A$202,0)))) -> J10 | C48: =IFERROR(INDEX('Annex 1 LV, HV and UMS charges'!$C$13:$C$44,MATCH($A48,'Annex 1 LV, HV and UMS charges'!$A$13:$A$44,0)),INDEX('Annex 4 LDNO charges'!$C$13:$C$202,MATCH($A48,'Annex 4 LDNO charges'!$A$13:$A$202,0))) -> 0 | F48: 0.052226762
A49: LDNO HV: LV Sub Site Specific Band 1 | B49: =IFERROR(INDEX('Annex 1 LV, HV and UMS charges'!$B$12:$B$44,MATCH($A49,'Annex 1 LV, HV and UMS charges'!$A$12:$A$44,0)),IF(INDEX('Annex 4 LDNO charges'!$B$11:$B$202,MATCH($A49,'Annex 4 LDNO charges'!$A$11:$A$202,0))=0,"",INDEX('Annex 4 LDNO charges'!$B$11:$B$202,MATCH($A49,'Annex 4 LDNO charges'!$A$11:$A$202,0)))) -> J11 | C49: =IFERROR(INDEX('Annex 1 LV, HV and UMS charges'!$C$13:$C$44,MATCH($A49,'Annex 1 LV, HV and UMS charges'!$A$13:$A$44,0)),INDEX('Annex 4 LDNO charges'!$C$13:$C$202,MATCH($A49,'Annex 4 LDNO charges'!$A$13:$A$202,0))) -> 0 | F49: 0.052226762
... A57: LDNO HV: HV Site Specific Band 4 | B57: =IFERROR(INDEX('Annex 1 LV, HV and UMS charges'!$B$12:$B$44,MATCH($A57,'Annex 1 LV, HV and UMS charges'!$A$12:$A$44,0)),IF(INDEX('Annex 4 LDNO charges'!$B$11:$B$202,MATCH($A57,'Annex 4 LDNO charges'!$A$11:$A$202,0))=0,"",INDEX('Annex 4 LDNO charges'!$B$11:$B$202,MATCH($A57,'Annex 4 LDNO charges'!$A$11:$A$202,0)))) -> K14 | C57: =IFERROR(INDEX('Annex 1 LV, HV and UMS charges'!$C$13:$C$44,MATCH($A57,'Annex 1 LV, HV and UMS charges'!$A$13:$A$44,0)),INDEX('Annex 4 LDNO charges'!$C$13:$C$202,MATCH($A57,'Annex 4 LDNO charges'!$A$13:$A$202,0))) -> 0 | F57: 0.052226762
A58: LDNO HVplus: Domestic Aggregated with Residual | B58: =IFERROR(INDEX('Annex 1 LV, HV and UMS charges'!$B$12:$B$44,MATCH($A58,'Annex 1 LV, HV and UMS charges'!$A$12:$A$44,0)),IF(INDEX('Annex 4 LDNO charges'!$B$11:$B$202,MATCH($A58,'Annex 4 LDNO charges'!$A$11:$A$202,0))=0,"",INDEX('Annex 4 LDNO charges'!$B$11:$B$202,MATCH($A58,'Annex 4 LDNO charges'!$A$11:$A$202,0)))) -> A20 | C58: =IFERROR(INDEX('Annex 1 LV, HV and UMS charges'!$C$13:$C$44,MATCH($A58,'Annex 1 LV, HV and UMS charges'!$A$13:$A$44,0)),INDEX('Annex 4 LDNO charges'!$C$13:$C$202,MATCH($A58,'Annex 4 LDNO charges'!$A$13:$A$202,0))) -> 0, 1, 2 | D58: 0.05859276 | E58: 9.6543478 | F58: 0.052226762
A59: LDNO HVplus: Non-Domestic Aggregated No Residual | B59: =IFERROR(INDEX('Annex 1 LV, HV and UMS charges'!$B$12:$B$44,MATCH($A59,'Annex 1 LV, HV and UMS charges'!$A$12:$A$44,0)),IF(INDEX('Annex 4 LDNO charges'!$B$11:$B$202,MATCH($A59,'Annex 4 LDNO charges'!$A$11:$A$202,0))=0,"",INDEX('Annex 4 LDNO charges'!$B$11:$B$202,MATCH($A59,'Annex 4 LDNO charges'!$A$11:$A$202,0)))) -> C20 | C59: =IFERROR(INDEX('Annex 1 LV, HV and UMS charges'!$C$13:$C$44,MATCH($A59,'Annex 1 LV, HV and UMS charges'!$A$13:$A$44,0)),INDEX('Annex 4 LDNO charges'!$C$13:$C$202,MATCH($A59,'Annex 4 LDNO charges'!$A$13:$A$202,0))) -> 0, 3, 4, 5-8 | F59: 0.052226762
A60: LDNO HVplus: Non-Domestic Aggregated Band 1 | B60: =IFERROR(INDEX('Annex 1 LV, HV and UMS charges'!$B$12:$B$44,MATCH($A60,'Annex 1 LV, HV and UMS charges'!$A$12:$A$44,0)),IF(INDEX('Annex 4 LDNO charges'!$B$11:$B$202,MATCH($A60,'Annex 4 LDNO charges'!$A$11:$A$202,0))=0,"",INDEX('Annex 4 LDNO charges'!$B$11:$B$202,MATCH($A60,'Annex 4 LDNO charges'!$A$11:$A$202,0)))) -> C21 | C60: =IFERROR(INDEX('Annex 1 LV, HV and UMS charges'!$C$13:$C$44,MATCH($A60,'Annex 1 LV, HV and UMS charges'!$A$13:$A$44,0)),INDEX('Annex 4 LDNO charges'!$C$13:$C$202,MATCH($A60,'Annex 4 LDNO charges'!$A$13:$A$202,0))) -> 0, 3, 4, 5-8 | F60: 0.052226762
A61: LDNO HVplus: Non-Domestic Aggregated Band 2 | B61: =IFERROR(INDEX('Annex 1 LV, HV and UMS charges'!$B$12:$B$44,MATCH($A61,'Annex 1 LV, HV and UMS charges'!$A$12:$A$44,0)),IF(INDEX('Annex 4 LDNO charges'!$B$11:$B$202,MATCH($A61,'Annex 4 LDNO charges'!$A$11:$A$202,0))=0,"",INDEX('Annex 4 LDNO charges'!$B$11:$B$202,MATCH($A61,'Annex 4 LDNO charges'!$A$11:$A$202,0)))) -> C22 | C61: =IFERROR(INDEX('Annex 1 LV, HV and UMS charges'!$C$13:$C$44,MATCH($A61,'Annex 1 LV, HV and UMS charges'!$A$13:$A$44,0)),INDEX('Annex 4 LDNO charges'!$C$13:$C$202,MATCH($A61,'Annex 4 LDNO charges'!$A$13:$A$202,0))) -> 0, 3, 4, 5-8 | F61: 0.052226762
A62: LDNO HVplus: Non-Domestic Aggregated Band 3 | B62: =IFERROR(INDEX('Annex 1 LV, HV and UMS charges'!$B$12:$B$44,MATCH($A62,'Annex 1 LV, HV and UMS charges'!$A$12:$A$44,0)),IF(INDEX('Annex 4 LDNO charges'!$B$11:$B$202,MATCH($A62,'Annex 4 LDNO charges'!$A$11:$A$202,0))=0,"",INDEX('Annex 4 LDNO charges'!$B$11:$B$202,MATCH($A62,'Annex 4 LDNO charges'!$A$11:$A$202,0)))) -> C23 | C62: =IFERROR(INDEX('Annex 1 LV, HV and UMS charges'!$C$13:$C$44,MATCH($A62,'Annex 1 LV, HV and UMS charges'!$A$13:$A$44,0)),INDEX('Annex 4 LDNO charges'!$C$13:$C$202,MATCH($A62,'Annex 4 LDNO charges'!$A$13:$A$202,0))) -> 0, 3, 4, 5-8 | F62: 0.052226762
A63: LDNO HVplus: Non-Domestic Aggregated Band 4 | B63: =IFERROR(INDEX('Annex 1 LV, HV and UMS charges'!$B$12:$B$44,MATCH($A63,'Annex 1 LV, HV and UMS charges'!$A$12:$A$44,0)),IF(INDEX('Annex 4 LDNO charges'!$B$11:$B$202,MATCH($A63,'Annex 4 LDNO charges'!$A$11:$A$202,0))=0,"",INDEX('Annex 4 LDNO charges'!$B$11:$B$202,MATCH($A63,'Annex 4 LDNO charges'!$A$11:$A$202,0)))) -> C24 | C63: =IFERROR(INDEX('Annex 1 LV, HV and UMS charges'!$C$13:$C$44,MATCH($A63,'Annex 1 LV, HV and UMS charges'!$A$13:$A$44,0)),INDEX('Annex 4 LDNO charges'!$C$13:$C$202,MATCH($A63,'Annex 4 LDNO charges'!$A$13:$A$202,0))) -> 0, 3, 4, 5-8 | F63: 0.052226762
A64: LDNO HVplus: LV Site Specific No Residual | B64: =IFERROR(INDEX('Annex 1 LV, HV and UMS charges'!$B$12:$B$44,MATCH($A64,'Annex 1 LV, HV and UMS charges'!$A$12:$A$44,0)),IF(INDEX('Annex 4 LDNO charges'!$B$11:$B$202,MATCH($A64,'Annex 4 LDNO charges'!$A$11:$A$202,0))=0,"",INDEX('Annex 4 LDNO charges'!$B$11:$B$202,MATCH($A64,'Annex 4 LDNO charges'!$A$11:$A$202,0)))) -> E20 | C64: =IFERROR(INDEX('Annex 1 LV, HV and UMS charges'!$C$13:$C$44,MATCH($A64,'Annex 1 LV, HV and UMS charges'!$A$13:$A$44,0)),INDEX('Annex 4 LDNO charges'!$C$13:$C$202,MATCH($A64,'Annex 4 LDNO charges'!$A$13:$A$202,0))) -> 0 | F64: 0.052226762
A65: LDNO HVplus: LV Site Specific Band 1 | B65: =IFERROR(INDEX('Annex 1 LV, HV and UMS charges'!$B$12:$B$44,MATCH($A65,'Annex 1 LV, HV and UMS charges'!$A$12:$A$44,0)),IF(INDEX('Annex 4 LDNO charges'!$B$11:$B$202,MATCH($A65,'Annex 4 LDNO charges'!$A$11:$A$202,0))=0,"",INDEX('Annex 4 LDNO charges'!$B$11:$B$202,MATCH($A65,'Annex 4 LDNO charges'!$A$11:$A$202,0)))) -> E21 | C65: =IFERROR(INDEX('Annex 1 LV, HV and UMS charges'!$C$13:$C$44,MATCH($A65,'Annex 1 LV, HV and UMS charges'!$A$13:$A$44,0)),INDEX('Annex 4 LDNO charges'!$C$13:$C$202,MATCH($A65,'Annex 4 LDNO charges'!$A$13:$A$202,0))) -> 0 | F65: 0.052226762
A66: LDNO HVplus: LV Site Specific Band 2 | B66: =IFERROR(INDEX('Annex 1 LV, HV and UMS charges'!$B$12:$B$44,MATCH($A66,'Annex 1 LV, HV and UMS charges'!$A$12:$A$44,0)),IF(INDEX('Annex 4 LDNO charges'!$B$11:$B$202,MATCH($A66,'Annex 4 LDNO charges'!$A$11:$A$202,0))=0,"",INDEX('Annex 4 LDNO charges'!$B$11:$B$202,MATCH($A66,'Annex 4 LDNO charges'!$A$11:$A$202,0)))) -> E22 | C66: =IFERROR(INDEX('Annex 1 LV, HV and UMS charges'!$C$13:$C$44,MATCH($A66,'Annex 1 LV, HV and UMS charges'!$A$13:$A$44,0)),INDEX('Annex 4 LDNO charges'!$C$13:$C$202,MATCH($A66,'Annex 4 LDNO charges'!$A$13:$A$202,0))) -> 0 | F66: 0.052226762
A67: LDNO HVplus: LV Site Specific Band 3 | B67: =IFERROR(INDEX('Annex 1 LV, HV and UMS charges'!$B$12:$B$44,MATCH($A67,'Annex 1 LV, HV and UMS charges'!$A$12:$A$44,0)),IF(INDEX('Annex 4 LDNO charges'!$B$11:$B$202,MATCH($A67,'Annex 4 LDNO charges'!$A$11:$A$202,0))=0,"",INDEX('Annex 4 LDNO charges'!$B$11:$B$202,MATCH($A67,'Annex 4 LDNO charges'!$A$11:$A$202,0)))) -> E23 | C67: =IFERROR(INDEX('Annex 1 LV, HV and UMS charges'!$C$13:$C$44,MATCH($A67,'Annex 1 LV, HV and UMS charges'!$A$13:$A$44,0)),INDEX('Annex 4 LDNO charges'!$C$13:$C$202,MATCH($A67,'Annex 4 LDNO charges'!$A$13:$A$202,0))) -> 0 | F67: 0.052226762
A68: LDNO HVplus: LV Site Specific Band 4 | B68: =IFERROR(INDEX('Annex 1 LV, HV and UMS charges'!$B$12:$B$44,MATCH($A68,'Annex 1 LV, HV and UMS charges'!$A$12:$A$44,0)),IF(INDEX('Annex 4 LDNO charges'!$B$11:$B$202,MATCH($A68,'Annex 4 LDNO charges'!$A$11:$A$202,0))=0,"",INDEX('Annex 4 LDNO charges'!$B$11:$B$202,MATCH($A68,'Annex 4 LDNO charges'!$A$11:$A$202,0)))) -> E24 | C68: =IFERROR(INDEX('Annex 1 LV, HV and UMS charges'!$C$13:$C$44,MATCH($A68,'Annex 1 LV, HV and UMS charges'!$A$13:$A$44,0)),INDEX('Annex 4 LDNO charges'!$C$13:$C$202,MATCH($A68,'Annex 4 LDNO charges'!$A$13:$A$202,0))) -> 0 | F68: 0.052226762
A69: LDNO HVplus: LV Sub Site Specific No Residual | B69: =IFERROR(INDEX('Annex 1 LV, HV and UMS charges'!$B$12:$B$44,MATCH($A69,'Annex 1 LV, HV and UMS charges'!$A$12:$A$44,0)),IF(INDEX('Annex 4 LDNO charges'!$B$11:$B$202,MATCH($A69,'Annex 4 LDNO charges'!$A$11:$A$202,0))=0,"",INDEX('Annex 4 LDNO charges'!$B$11:$B$202,MATCH($A69,'Annex 4 LDNO charges'!$A$11:$A$202,0)))) -> J20 | C69: =IFERROR(INDEX('Annex 1 LV, HV and UMS charges'!$C$13:$C$44,MATCH($A69,'Annex 1 LV, HV and UMS charges'!$A$13:$A$44,0)),INDEX('Annex 4 LDNO charges'!$C$13:$C$202,MATCH($A69,'Annex 4 LDNO charges'!$A$13:$A$202,0))) -> 0 | F69: 0.052226762
A70: LDNO HVplus: LV Sub Site Specific Band 1 | B70: =IFERROR(INDEX('Annex 1 LV, HV and UMS charges'!$B$12:$B$44,MATCH($A70,'Annex 1 LV, HV and UMS charges'!$A$12:$A$44,0)),IF(INDEX('Annex 4 LDNO charges'!$B$11:$B$202,MATCH($A70,'Annex 4 LDNO charges'!$A$11:$A$202,0))=0,"",INDEX('Annex 4 LDNO charges'!$B$11:$B$202,MATCH($A70,'Annex 4 LDNO charges'!$A$11:$A$202,0)))) -> J21 | C70: =IFERROR(INDEX('Annex 1 LV, HV and UMS charges'!$C$13:$C$44,MATCH($A70,'Annex 1 LV, HV and UMS charges'!$A$13:$A$44,0)),INDEX('Annex 4 LDNO charges'!$C$13:$C$202,MATCH($A70,'Annex 4 LDNO charges'!$A$13:$A$202,0))) -> 0 | F70: 0.052226762
... A78: LDNO HVplus: HV Site Specific Band 4 | B78: =IFERROR(INDEX('Annex 1 LV, HV and UMS charges'!$B$12:$B$44,MATCH($A78,'Annex 1 LV, HV and UMS charges'!$A$12:$A$44,0)),IF(INDEX('Annex 4 LDNO charges'!$B$11:$B$202,MATCH($A78,'Annex 4 LDNO charges'!$A$11:$A$202,0))=0,"",INDEX('Annex 4 LDNO charges'!$B$11:$B$202,MATCH($A78,'Annex 4 LDNO charges'!$A$11:$A$202,0)))) -> K24 | C78: =IFERROR(INDEX('Annex 1 LV, HV and UMS charges'!$C$13:$C$44,MATCH($A78,'Annex 1 LV, HV and UMS charges'!$A$13:$A$44,0)),INDEX('Annex 4 LDNO charges'!$C$13:$C$202,MATCH($A78,'Annex 4 LDNO charges'!$A$13:$A$202,0))) -> 0 | F78: 0.052226762
A79: LDNO EHV: Domestic Aggregated with Residual | B79: =IFERROR(INDEX('Annex 1 LV, HV and UMS charges'!$B$12:$B$44,MATCH($A79,'Annex 1 LV, HV and UMS charges'!$A$12:$A$44,0)),IF(INDEX('Annex 4 LDNO charges'!$B$11:$B$202,MATCH($A79,'Annex 4 LDNO charges'!$A$11:$A$202,0))=0,"",INDEX('Annex 4 LDNO charges'!$B$11:$B$202,MATCH($A79,'Annex 4 LDNO charges'!$A$11:$A$202,0)))) -> A30 | C79: =IFERROR(INDEX('Annex 1 LV, HV and UMS charges'!$C$13:$C$44,MATCH($A79,'Annex 1 LV, HV and UMS charges'!$A$13:$A$44,0)),INDEX('Annex 4 LDNO charges'!$C$13:$C$202,MATCH($A79,'Annex 4 LDNO charges'!$A$13:$A$202,0))) -> 0, 1, 2 | D79: 0.05859276 | E79: 9.6543478 | F79: 0.052226762
A80: LDNO EHV: Non-Domestic Aggregated No Residual | B80: =IFERROR(INDEX('Annex 1 LV, HV and UMS charges'!$B$12:$B$44,MATCH($A80,'Annex 1 LV, HV and UMS charges'!$A$12:$A$44,0)),IF(INDEX('Annex 4 LDNO charges'!$B$11:$B$202,MATCH($A80,'Annex 4 LDNO charges'!$A$11:$A$202,0))=0,"",INDEX('Annex 4 LDNO charges'!$B$11:$B$202,MATCH($A80,'Annex 4 LDNO charges'!$A$11:$A$202,0)))) -> C30 | C80: =IFERROR(INDEX('Annex 1 LV, HV and UMS charges'!$C$13:$C$44,MATCH($A80,'Annex 1 LV, HV and UMS charges'!$A$13:$A$44,0)),INDEX('Annex 4 LDNO charges'!$C$13:$C$202,MATCH($A80,'Annex 4 LDNO charges'!$A$13:$A$202,0))) -> 0, 3, 4, 5-8 | F80: 0.052226762
A81: LDNO EHV: Non-Domestic Aggregated Band 1 | B81: =IFERROR(INDEX('Annex 1 LV, HV and UMS charges'!$B$12:$B$44,MATCH($A81,'Annex 1 LV, HV and UMS charges'!$A$12:$A$44,0)),IF(INDEX('Annex 4 LDNO charges'!$B$11:$B$202,MATCH($A81,'Annex 4 LDNO charges'!$A$11:$A$202,0))=0,"",INDEX('Annex 4 LDNO charges'!$B$11:$B$202,MATCH($A81,'Annex 4 LDNO charges'!$A$11:$A$202,0)))) -> C31 | C81: =IFERROR(INDEX('Annex 1 LV, HV and UMS charges'!$C$13:$C$44,MATCH($A81,'Annex 1 LV, HV and UMS charges'!$A$13:$A$44,0)),INDEX('Annex 4 LDNO charges'!$C$13:$C$202,MATCH($A81,'Annex 4 LDNO charges'!$A$13:$A$202,0))) -> 0, 3, 4, 5-8 | F81: 0.052226762
A82: LDNO EHV: Non-Domestic Aggregated Band 2 | B82: =IFERROR(INDEX('Annex 1 LV, HV and UMS charges'!$B$12:$B$44,MATCH($A82,'Annex 1 LV, HV and UMS charges'!$A$12:$A$44,0)),IF(INDEX('Annex 4 LDNO charges'!$B$11:$B$202,MATCH($A82,'Annex 4 LDNO charges'!$A$11:$A$202,0))=0,"",INDEX('Annex 4 LDNO charges'!$B$11:$B$202,MATCH($A82,'Annex 4 LDNO charges'!$A$11:$A$202,0)))) -> C32 | C82: =IFERROR(INDEX('Annex 1 LV, HV and UMS charges'!$C$13:$C$44,MATCH($A82,'Annex 1 LV, HV and UMS charges'!$A$13:$A$44,0)),INDEX('Annex 4 LDNO charges'!$C$13:$C$202,MATCH($A82,'Annex 4 LDNO charges'!$A$13:$A$202,0))) -> 0, 3, 4, 5-8 | F82: 0.052226762
A83: LDNO EHV: Non-Domestic Aggregated Band 3 | B83: =IFERROR(INDEX('Annex 1 LV, HV and UMS charges'!$B$12:$B$44,MATCH($A83,'Annex 1 LV, HV and UMS charges'!$A$12:$A$44,0)),IF(INDEX('Annex 4 LDNO charges'!$B$11:$B$202,MATCH($A83,'Annex 4 LDNO charges'!$A$11:$A$202,0))=0,"",INDEX('Annex 4 LDNO charges'!$B$11:$B$202,MATCH($A83,'Annex 4 LDNO charges'!$A$11:$A$202,0)))) -> C33 | C83: =IFERROR(INDEX('Annex 1 LV, HV and UMS charges'!$C$13:$C$44,MATCH($A83,'Annex 1 LV, HV and UMS charges'!$A$13:$A$44,0)),INDEX('Annex 4 LDNO charges'!$C$13:$C$202,MATCH($A83,'Annex 4 LDNO charges'!$A$13:$A$202,0))) -> 0, 3, 4, 5-8 | F83: 0.052226762
A84: LDNO EHV: Non-Domestic Aggregated Band 4 | B84: =IFERROR(INDEX('Annex 1 LV, HV and UMS charges'!$B$12:$B$44,MATCH($A84,'Annex 1 LV, HV and UMS charges'!$A$12:$A$44,0)),IF(INDEX('Annex 4 LDNO charges'!$B$11:$B$202,MATCH($A84,'Annex 4 LDNO charges'!$A$11:$A$202,0))=0,"",INDEX('Annex 4 LDNO charges'!$B$11:$B$202,MATCH($A84,'Annex 4 LDNO charges'!$A$11:$A$202,0)))) -> C34 | C84: =IFERROR(INDEX('Annex 1 LV, HV and UMS charges'!$C$13:$C$44,MATCH($A84,'Annex 1 LV, HV and UMS charges'!$A$13:$A$44,0)),INDEX('Annex 4 LDNO charges'!$C$13:$C$202,MATCH($A84,'Annex 4 LDNO charges'!$A$13:$A$202,0))) -> 0, 3, 4, 5-8 | F84: 0.052226762
A85: LDNO EHV: LV Site Specific No Residual | B85: =IFERROR(INDEX('Annex 1 LV, HV and UMS charges'!$B$12:$B$44,MATCH($A85,'Annex 1 LV, HV and UMS charges'!$A$12:$A$44,0)),IF(INDEX('Annex 4 LDNO charges'!$B$11:$B$202,MATCH($A85,'Annex 4 LDNO charges'!$A$11:$A$202,0))=0,"",INDEX('Annex 4 LDNO charges'!$B$11:$B$202,MATCH($A85,'Annex 4 LDNO charges'!$A$11:$A$202,0)))) -> E30 | C85: =IFERROR(INDEX('Annex 1 LV, HV and UMS charges'!$C$13:$C$44,MATCH($A85,'Annex 1 LV, HV and UMS charges'!$A$13:$A$44,0)),INDEX('Annex 4 LDNO charges'!$C$13:$C$202,MATCH($A85,'Annex 4 LDNO charges'!$A$13:$A$202,0))) -> 0 | F85: 0.052226762
A86: LDNO EHV: LV Site Specific Band 1 | B86: =IFERROR(INDEX('Annex 1 LV, HV and UMS charges'!$B$12:$B$44,MATCH($A86,'Annex 1 LV, HV and UMS charges'!$A$12:$A$44,0)),IF(INDEX('Annex 4 LDNO charges'!$B$11:$B$202,MATCH($A86,'Annex 4 LDNO charges'!$A$11:$A$202,0))=0,"",INDEX('Annex 4 LDNO charges'!$B$11:$B$202,MATCH($A86,'Annex 4 LDNO charges'!$A$11:$A$202,0)))) -> E31 | C86: =IFERROR(INDEX('Annex 1 LV, HV and UMS charges'!$C$13:$C$44,MATCH($A86,'Annex 1 LV, HV and UMS charges'!$A$13:$A$44,0)),INDEX('Annex 4 LDNO charges'!$C$13:$C$202,MATCH($A86,'Annex 4 LDNO charges'!$A$13:$A$202,0))) -> 0 | F86: 0.052226762
A87: LDNO EHV: LV Site Specific Band 2 | B87: =IFERROR(INDEX('Annex 1 LV, HV and UMS charges'!$B$12:$B$44,MATCH($A87,'Annex 1 LV, HV and UMS charges'!$A$12:$A$44,0)),IF(INDEX('Annex 4 LDNO charges'!$B$11:$B$202,MATCH($A87,'Annex 4 LDNO charges'!$A$11:$A$202,0))=0,"",INDEX('Annex 4 LDNO charges'!$B$11:$B$202,MATCH($A87,'Annex 4 LDNO charges'!$A$11:$A$202,0)))) -> E32 | C87: =IFERROR(INDEX('Annex 1 LV, HV and UMS charges'!$C$13:$C$44,MATCH($A87,'Annex 1 LV, HV and UMS charges'!$A$13:$A$44,0)),INDEX('Annex 4 LDNO charges'!$C$13:$C$202,MATCH($A87,'Annex 4 LDNO charges'!$A$13:$A$202,0))) -> 0 | F87: 0.052226762
A88: LDNO EHV: LV Site Specific Band 3 | B88: =IFERROR(INDEX('Annex 1 LV, HV and UMS charges'!$B$12:$B$44,MATCH($A88,'Annex 1 LV, HV and UMS charges'!$A$12:$A$44,0)),IF(INDEX('Annex 4 LDNO charges'!$B$11:$B$202,MATCH($A88,'Annex 4 LDNO charges'!$A$11:$A$202,0))=0,"",INDEX('Annex 4 LDNO charges'!$B$11:$B$202,MATCH($A88,'Annex 4 LDNO charges'!$A$11:$A$202,0)))) -> E33 | C88: =IFERROR(INDEX('Annex 1 LV, HV and UMS charges'!$C$13:$C$44,MATCH($A88,'Annex 1 LV, HV and UMS charges'!$A$13:$A$44,0)),INDEX('Annex 4 LDNO charges'!$C$13:$C$202,MATCH($A88,'Annex 4 LDNO charges'!$A$13:$A$202,0))) -> 0 | F88: 0.052226762
A89: LDNO EHV: LV Site Specific Band 4 | B89: =IFERROR(INDEX('Annex 1 LV, HV and UMS charges'!$B$12:$B$44,MATCH($A89,'Annex 1 LV, HV and UMS charges'!$A$12:$A$44,0)),IF(INDEX('Annex 4 LDNO charges'!$B$11:$B$202,MATCH($A89,'Annex 4 LDNO charges'!$A$11:$A$202,0))=0,"",INDEX('Annex 4 LDNO charges'!$B$11:$B$202,MATCH($A89,'Annex 4 LDNO charges'!$A$11:$A$202,0)))) -> E34 | C89: =IFERROR(INDEX('Annex 1 LV, HV and UMS charges'!$C$13:$C$44,MATCH($A89,'Annex 1 LV, HV and UMS charges'!$A$13:$A$44,0)),INDEX('Annex 4 LDNO charges'!$C$13:$C$202,MATCH($A89,'Annex 4 LDNO charges'!$A$13:$A$202,0))) -> 0 | F89: 0.052226762
A90: LDNO EHV: LV Sub Site Specific No Residual | B90: =IFERROR(INDEX('Annex 1 LV, HV and UMS charges'!$B$12:$B$44,MATCH($A90,'Annex 1 LV, HV and UMS charges'!$A$12:$A$44,0)),IF(INDEX('Annex 4 LDNO charges'!$B$11:$B$202,MATCH($A90,'Annex 4 LDNO charges'!$A$11:$A$202,0))=0,"",INDEX('Annex 4 LDNO charges'!$B$11:$B$202,MATCH($A90,'Annex 4 LDNO charges'!$A$11:$A$202,0)))) -> J30 | C90: =IFERROR(INDEX('Annex 1 LV, HV and UMS charges'!$C$13:$C$44,MATCH($A90,'Annex 1 LV, HV and UMS charges'!$A$13:$A$44,0)),INDEX('Annex 4 LDNO charges'!$C$13:$C$202,MATCH($A90,'Annex 4 LDNO charges'!$A$13:$A$202,0))) -> 0 | F90: 0.052226762
A91: LDNO EHV: LV Sub Site Specific Band 1 | B91: =IFERROR(INDEX('Annex 1 LV, HV and UMS charges'!$B$12:$B$44,MATCH($A91,'Annex 1 LV, HV and UMS charges'!$A$12:$A$44,0)),IF(INDEX('Annex 4 LDNO charges'!$B$11:$B$202,MATCH($A91,'Annex 4 LDNO charges'!$A$11:$A$202,0))=0,"",INDEX('Annex 4 LDNO charges'!$B$11:$B$202,MATCH($A91,'Annex 4 LDNO charges'!$A$11:$A$202,0)))) -> J31 | C91: =IFERROR(INDEX('Annex 1 LV, HV and UMS charges'!$C$13:$C$44,MATCH($A91,'Annex 1 LV, HV and UMS charges'!$A$13:$A$44,0)),INDEX('Annex 4 LDNO charges'!$C$13:$C$202,MATCH($A91,'Annex 4 LDNO charges'!$A$13:$A$202,0))) -> 0 | F91: 0.052226762
... A99: LDNO EHV: HV Site Specific Band 4 | B99: =IFERROR(INDEX('Annex 1 LV, HV and UMS charges'!$B$12:$B$44,MATCH($A99,'Annex 1 LV, HV and UMS charges'!$A$12:$A$44,0)),IF(INDEX('Annex 4 LDNO charges'!$B$11:$B$202,MATCH($A99,'Annex 4 LDNO charges'!$A$11:$A$202,0))=0,"",INDEX('Annex 4 LDNO charges'!$B$11:$B$202,MATCH($A99,'Annex 4 LDNO charges'!$A$11:$A$202,0)))) -> K34 | C99: =IFERROR(INDEX('Annex 1 LV, HV and UMS charges'!$C$13:$C$44,MATCH($A99,'Annex 1 LV, HV and UMS charges'!$A$13:$A$44,0)),INDEX('Annex 4 LDNO charges'!$C$13:$C$202,MATCH($A99,'Annex 4 LDNO charges'!$A$13:$A$202,0))) -> 0 | F99: 0.052226762
A100: LDNO 132kV/EHV: Domestic Aggregated with Residual | B100: =IFERROR(INDEX('Annex 1 LV, HV and UMS charges'!$B$12:$B$44,MATCH($A100,'Annex 1 LV, HV and UMS charges'!$A$12:$A$44,0)),IF(INDEX('Annex 4 LDNO charges'!$B$11:$B$202,MATCH($A100,'Annex 4 LDNO charges'!$A$11:$A$202,0))=0,"",INDEX('Annex 4 LDNO charges'!$B$11:$B$202,MATCH($A100,'Annex 4 LDNO charges'!$A$11:$A$202,0)))) -> A40 | C100: =IFERROR(INDEX('Annex 1 LV, HV and UMS charges'!$C$13:$C$44,MATCH($A100,'Annex 1 LV, HV and UMS charges'!$A$13:$A$44,0)),INDEX('Annex 4 LDNO charges'!$C$13:$C$202,MATCH($A100,'Annex 4 LDNO charges'!$A$13:$A$202,0))) -> 0, 1, 2 | D100: 0.05859276 | E100: 9.6543478 | F100: 0.052226762
A101: LDNO 132kV/EHV: Non-Domestic Aggregated No Residual | B101: =IFERROR(INDEX('Annex 1 LV, HV and UMS charges'!$B$12:$B$44,MATCH($A101,'Annex 1 LV, HV and UMS charges'!$A$12:$A$44,0)),IF(INDEX('Annex 4 LDNO charges'!$B$11:$B$202,MATCH($A101,'Annex 4 LDNO charges'!$A$11:$A$202,0))=0,"",INDEX('Annex 4 LDNO charges'!$B$11:$B$202,MATCH($A101,'Annex 4 LDNO charges'!$A$11:$A$202,0)))) -> C40 | C101: =IFERROR(INDEX('Annex 1 LV, HV and UMS charges'!$C$13:$C$44,MATCH($A101,'Annex 1 LV, HV and UMS charges'!$A$13:$A$44,0)),INDEX('Annex 4 LDNO charges'!$C$13:$C$202,MATCH($A101,'Annex 4 LDNO charges'!$A$13:$A$202,0))) -> 0, 3, 4, 5-8 | F101: 0.052226762
A102: LDNO 132kV/EHV: Non-Domestic Aggregated Band 1 | B102: =IFERROR(INDEX('Annex 1 LV, HV and UMS charges'!$B$12:$B$44,MATCH($A102,'Annex 1 LV, HV and UMS charges'!$A$12:$A$44,0)),IF(INDEX('Annex 4 LDNO charges'!$B$11:$B$202,MATCH($A102,'Annex 4 LDNO charges'!$A$11:$A$202,0))=0,"",INDEX('Annex 4 LDNO charges'!$B$11:$B$202,MATCH($A102,'Annex 4 LDNO charges'!$A$11:$A$202,0)))) -> C41 | C102: =IFERROR(INDEX('Annex 1 LV, HV and UMS charges'!$C$13:$C$44,MATCH($A102,'Annex 1 LV, HV and UMS charges'!$A$13:$A$44,0)),INDEX('Annex 4 LDNO charges'!$C$13:$C$202,MATCH($A102,'Annex 4 LDNO charges'!$A$13:$A$202,0))) -> 0, 3, 4, 5-8 | F102: 0.052226762
A103: LDNO 132kV/EHV: Non-Domestic Aggregated Band 2 | B103: =IFERROR(INDEX('Annex 1 LV, HV and UMS charges'!$B$12:$B$44,MATCH($A103,'Annex 1 LV, HV and UMS charges'!$A$12:$A$44,0)),IF(INDEX('Annex 4 LDNO charges'!$B$11:$B$202,MATCH($A103,'Annex 4 LDNO charges'!$A$11:$A$202,0))=0,"",INDEX('Annex 4 LDNO charges'!$B$11:$B$202,MATCH($A103,'Annex 4 LDNO charges'!$A$11:$A$202,0)))) -> C42 | C103: =IFERROR(INDEX('Annex 1 LV, HV and UMS charges'!$C$13:$C$44,MATCH($A103,'Annex 1 LV, HV and UMS charges'!$A$13:$A$44,0)),INDEX('Annex 4 LDNO charges'!$C$13:$C$202,MATCH($A103,'Annex 4 LDNO charges'!$A$13:$A$202,0))) -> 0, 3, 4, 5-8 | F103: 0.052226762
A104: LDNO 132kV/EHV: Non-Domestic Aggregated Band 3 | B104: =IFERROR(INDEX('Annex 1 LV, HV and UMS charges'!$B$12:$B$44,MATCH($A104,'Annex 1 LV, HV and UMS charges'!$A$12:$A$44,0)),IF(INDEX('Annex 4 LDNO charges'!$B$11:$B$202,MATCH($A104,'Annex 4 LDNO charges'!$A$11:$A$202,0))=0,"",INDEX('Annex 4 LDNO charges'!$B$11:$B$202,MATCH($A104,'Annex 4 LDNO charges'!$A$11:$A$202,0)))) -> C43 | C104: =IFERROR(INDEX('Annex 1 LV, HV and UMS charges'!$C$13:$C$44,MATCH($A104,'Annex 1 LV, HV and UMS charges'!$A$13:$A$44,0)),INDEX('Annex 4 LDNO charges'!$C$13:$C$202,MATCH($A104,'Annex 4 LDNO charges'!$A$13:$A$202,0))) -> 0, 3, 4, 5-8 | F104: 0.052226762
A105: LDNO 132kV/EHV: Non-Domestic Aggregated Band 4 | B105: =IFERROR(INDEX('Annex 1 LV, HV and UMS charges'!$B$12:$B$44,MATCH($A105,'Annex 1 LV, HV and UMS charges'!$A$12:$A$44,0)),IF(INDEX('Annex 4 LDNO charges'!$B$11:$B$202,MATCH($A105,'Annex 4 LDNO charges'!$A$11:$A$202,0))=0,"",INDEX('Annex 4 LDNO charges'!$B$11:$B$202,MATCH($A105,'Annex 4 LDNO charges'!$A$11:$A$202,0)))) -> C44 | C105: =IFERROR(INDEX('Annex 1 LV, HV and UMS charges'!$C$13:$C$44,MATCH($A105,'Annex 1 LV, HV and UMS charges'!$A$13:$A$44,0)),INDEX('Annex 4 LDNO charges'!$C$13:$C$202,MATCH($A105,'Annex 4 LDNO charges'!$A$13:$A$202,0))) -> 0, 3, 4, 5-8 | F105: 0.052226762
A106: LDNO 132kV/EHV: LV Site Specific No Residual | B106: =IFERROR(INDEX('Annex 1 LV, HV and UMS charges'!$B$12:$B$44,MATCH($A106,'Annex 1 LV, HV and UMS charges'!$A$12:$A$44,0)),IF(INDEX('Annex 4 LDNO charges'!$B$11:$B$202,MATCH($A106,'Annex 4 LDNO charges'!$A$11:$A$202,0))=0,"",INDEX('Annex 4 LDNO charges'!$B$11:$B$202,MATCH($A106,'Annex 4 LDNO charges'!$A$11:$A$202,0)))) -> E40 | C106: =IFERROR(INDEX('Annex 1 LV, HV and UMS charges'!$C$13:$C$44,MATCH($A106,'Annex 1 LV, HV and UMS charges'!$A$13:$A$44,0)),INDEX('Annex 4 LDNO charges'!$C$13:$C$202,MATCH($A106,'Annex 4 LDNO charges'!$A$13:$A$202,0))) -> 0 | F106: 0.052226762
A107: LDNO 132kV/EHV: LV Site Specific Band 1 | B107: =IFERROR(INDEX('Annex 1 LV, HV and UMS charges'!$B$12:$B$44,MATCH($A107,'Annex 1 LV, HV and UMS charges'!$A$12:$A$44,0)),IF(INDEX('Annex 4 LDNO charges'!$B$11:$B$202,MATCH($A107,'Annex 4 LDNO charges'!$A$11:$A$202,0))=0,"",INDEX('Annex 4 LDNO charges'!$B$11:$B$202,MATCH($A107,'Annex 4 LDNO charges'!$A$11:$A$202,0)))) -> E41 | C107: =IFERROR(INDEX('Annex 1 LV, HV and UMS charges'!$C$13:$C$44,MATCH($A107,'Annex 1 LV, HV and UMS charges'!$A$13:$A$44,0)),INDEX('Annex 4 LDNO charges'!$C$13:$C$202,MATCH($A107,'Annex 4 LDNO charges'!$A$13:$A$202,0))) -> 0 | F107: 0.052226762
A108: LDNO 132kV/EHV: LV Site Specific Band 2 | B108: =IFERROR(INDEX('Annex 1 LV, HV and UMS charges'!$B$12:$B$44,MATCH($A108,'Annex 1 LV, HV and UMS charges'!$A$12:$A$44,0)),IF(INDEX('Annex 4 LDNO charges'!$B$11:$B$202,MATCH($A108,'Annex 4 LDNO charges'!$A$11:$A$202,0))=0,"",INDEX('Annex 4 LDNO charges'!$B$11:$B$202,MATCH($A108,'Annex 4 LDNO charges'!$A$11:$A$202,0)))) -> E42 | C108: =IFERROR(INDEX('Annex 1 LV, HV and UMS charges'!$C$13:$C$44,MATCH($A108,'Annex 1 LV, HV and UMS charges'!$A$13:$A$44,0)),INDEX('Annex 4 LDNO charges'!$C$13:$C$202,MATCH($A108,'Annex 4 LDNO charges'!$A$13:$A$202,0))) -> 0 | F108: 0.052226762
A109: LDNO 132kV/EHV: LV Site Specific Band 3 | B109: =IFERROR(INDEX('Annex 1 LV, HV and UMS charges'!$B$12:$B$44,MATCH($A109,'Annex 1 LV, HV and UMS charges'!$A$12:$A$44,0)),IF(INDEX('Annex 4 LDNO charges'!$B$11:$B$202,MATCH($A109,'Annex 4 LDNO charges'!$A$11:$A$202,0))=0,"",INDEX('Annex 4 LDNO charges'!$B$11:$B$202,MATCH($A109,'Annex 4 LDNO charges'!$A$11:$A$202,0)))) -> E43 | C109: =IFERROR(INDEX('Annex 1 LV, HV and UMS charges'!$C$13:$C$44,MATCH($A109,'Annex 1 LV, HV and UMS charges'!$A$13:$A$44,0)),INDEX('Annex 4 LDNO charges'!$C$13:$C$202,MATCH($A109,'Annex 4 LDNO charges'!$A$13:$A$202,0))) -> 0 | F109: 0.052226762
A110: LDNO 132kV/EHV: LV Site Specific Band 4 | B110: =IFERROR(INDEX('Annex 1 LV, HV and UMS charges'!$B$12:$B$44,MATCH($A110,'Annex 1 LV, HV and UMS charges'!$A$12:$A$44,0)),IF(INDEX('Annex 4 LDNO charges'!$B$11:$B$202,MATCH($A110,'Annex 4 LDNO charges'!$A$11:$A$202,0))=0,"",INDEX('Annex 4 LDNO charges'!$B$11:$B$202,MATCH($A110,'Annex 4 LDNO charges'!$A$11:$A$202,0)))) -> E44 | C110: =IFERROR(INDEX('Annex 1 LV, HV and UMS charges'!$C$13:$C$44,MATCH($A110,'Annex 1 LV, HV and UMS charges'!$A$13:$A$44,0)),INDEX('Annex 4 LDNO charges'!$C$13:$C$202,MATCH($A110,'Annex 4 LDNO charges'!$A$13:$A$202,0))) -> 0 | F110: 0.052226762
A111: LDNO 132kV/EHV: LV Sub Site Specific No Residual | B111: =IFERROR(INDEX('Annex 1 LV, HV and UMS charges'!$B$12:$B$44,MATCH($A111,'Annex 1 LV, HV and UMS charges'!$A$12:$A$44,0)),IF(INDEX('Annex 4 LDNO charges'!$B$11:$B$202,MATCH($A111,'Annex 4 LDNO charges'!$A$11:$A$202,0))=0,"",INDEX('Annex 4 LDNO charges'!$B$11:$B$202,MATCH($A111,'Annex 4 LDNO charges'!$A$11:$A$202,0)))) -> J40 | C111: =IFERROR(INDEX('Annex 1 LV, HV and UMS charges'!$C$13:$C$44,MATCH($A111,'Annex 1 LV, HV and UMS charges'!$A$13:$A$44,0)),INDEX('Annex 4 LDNO charges'!$C$13:$C$202,MATCH($A111,'Annex 4 LDNO charges'!$A$13:$A$202,0))) -> 0 | F111: 0.052226762
A112: LDNO 132kV/EHV: LV Sub Site Specific Band 1 | B112: =IFERROR(INDEX('Annex 1 LV, HV and UMS charges'!$B$12:$B$44,MATCH($A112,'Annex 1 LV, HV and UMS charges'!$A$12:$A$44,0)),IF(INDEX('Annex 4 LDNO charges'!$B$11:$B$202,MATCH($A112,'Annex 4 LDNO charges'!$A$11:$A$202,0))=0,"",INDEX('Annex 4 LDNO charges'!$B$11:$B$202,MATCH($A112,'Annex 4 LDNO charges'!$A$11:$A$202,0)))) -> J41 | C112: =IFERROR(INDEX('Annex 1 LV, HV and UMS charges'!$C$13:$C$44,MATCH($A112,'Annex 1 LV, HV and UMS charges'!$A$13:$A$44,0)),INDEX('Annex 4 LDNO charges'!$C$13:$C$202,MATCH($A112,'Annex 4 LDNO charges'!$A$13:$A$202,0))) -> 0 | F112: 0.052226762
... A120: LDNO 132kV/EHV: HV Site Specific Band 4 | B120: =IFERROR(INDEX('Annex 1 LV, HV and UMS charges'!$B$12:$B$44,MATCH($A120,'Annex 1 LV, HV and UMS charges'!$A$12:$A$44,0)),IF(INDEX('Annex 4 LDNO charges'!$B$11:$B$202,MATCH($A120,'Annex 4 LDNO charges'!$A$11:$A$202,0))=0,"",INDEX('Annex 4 LDNO charges'!$B$11:$B$202,MATCH($A120,'Annex 4 LDNO charges'!$A$11:$A$202,0)))) -> K44 | C120: =IFERROR(INDEX('Annex 1 LV, HV and UMS charges'!$C$13:$C$44,MATCH($A120,'Annex 1 LV, HV and UMS charges'!$A$13:$A$44,0)),INDEX('Annex 4 LDNO charges'!$C$13:$C$202,MATCH($A120,'Annex 4 LDNO charges'!$A$13:$A$202,0))) -> 0 | F120: 0.052226762
A121: LDNO 132kV: Domestic Aggregated with Residual | B121: =IFERROR(INDEX('Annex 1 LV, HV and UMS charges'!$B$12:$B$44,MATCH($A121,'Annex 1 LV, HV and UMS charges'!$A$12:$A$44,0)),IF(INDEX('Annex 4 LDNO charges'!$B$11:$B$202,MATCH($A121,'Annex 4 LDNO charges'!$A$11:$A$202,0))=0,"",INDEX('Annex 4 LDNO charges'!$B$11:$B$202,MATCH($A121,'Annex 4 LDNO charges'!$A$11:$A$202,0)))) -> A50 | C121: =IFERROR(INDEX('Annex 1 LV, HV and UMS charges'!$C$13:$C$44,MATCH($A121,'Annex 1 LV, HV and UMS charges'!$A$13:$A$44,0)),INDEX('Annex 4 LDNO charges'!$C$13:$C$202,MATCH($A121,'Annex 4 LDNO charges'!$A$13:$A$202,0))) -> 0, 1, 2 | D121: 0.05859276 | E121: 9.6543478 | F121: 0.052226762
A122: LDNO 132kV: Non-Domestic Aggregated No Residual | B122: =IFERROR(INDEX('Annex 1 LV, HV and UMS charges'!$B$12:$B$44,MATCH($A122,'Annex 1 LV, HV and UMS charges'!$A$12:$A$44,0)),IF(INDEX('Annex 4 LDNO charges'!$B$11:$B$202,MATCH($A122,'Annex 4 LDNO charges'!$A$11:$A$202,0))=0,"",INDEX('Annex 4 LDNO charges'!$B$11:$B$202,MATCH($A122,'Annex 4 LDNO charges'!$A$11:$A$202,0)))) -> C50 | C122: =IFERROR(INDEX('Annex 1 LV, HV and UMS charges'!$C$13:$C$44,MATCH($A122,'Annex 1 LV, HV and UMS charges'!$A$13:$A$44,0)),INDEX('Annex 4 LDNO charges'!$C$13:$C$202,MATCH($A122,'Annex 4 LDNO charges'!$A$13:$A$202,0))) -> 0, 3, 4, 5-8 | F122: 0.052226762
A123: LDNO 132kV: Non-Domestic Aggregated Band 1 | B123: =IFERROR(INDEX('Annex 1 LV, HV and UMS charges'!$B$12:$B$44,MATCH($A123,'Annex 1 LV, HV and UMS charges'!$A$12:$A$44,0)),IF(INDEX('Annex 4 LDNO charges'!$B$11:$B$202,MATCH($A123,'Annex 4 LDNO charges'!$A$11:$A$202,0))=0,"",INDEX('Annex 4 LDNO charges'!$B$11:$B$202,MATCH($A123,'Annex 4 LDNO charges'!$A$11:$A$202,0)))) -> C51 | C123: =IFERROR(INDEX('Annex 1 LV, HV and UMS charges'!$C$13:$C$44,MATCH($A123,'Annex 1 LV, HV and UMS charges'!$A$13:$A$44,0)),INDEX('Annex 4 LDNO charges'!$C$13:$C$202,MATCH($A123,'Annex 4 LDNO charges'!$A$13:$A$202,0))) -> 0, 3, 4, 5-8 | F123: 0.052226762
A124: LDNO 132kV: Non-Domestic Aggregated Band 2 | B124: =IFERROR(INDEX('Annex 1 LV, HV and UMS charges'!$B$12:$B$44,MATCH($A124,'Annex 1 LV, HV and UMS charges'!$A$12:$A$44,0)),IF(INDEX('Annex 4 LDNO charges'!$B$11:$B$202,MATCH($A124,'Annex 4 LDNO charges'!$A$11:$A$202,0))=0,"",INDEX('Annex 4 LDNO charges'!$B$11:$B$202,MATCH($A124,'Annex 4 LDNO charges'!$A$11:$A$202,0)))) -> C52 | C124: =IFERROR(INDEX('Annex 1 LV, HV and UMS charges'!$C$13:$C$44,MATCH($A124,'Annex 1 LV, HV and UMS charges'!$A$13:$A$44,0)),INDEX('Annex 4 LDNO charges'!$C$13:$C$202,MATCH($A124,'Annex 4 LDNO charges'!$A$13:$A$202,0))) -> 0, 3, 4, 5-8 | F124: 0.052226762
A125: LDNO 132kV: Non-Domestic Aggregated Band 3 | B125: =IFERROR(INDEX('Annex 1 LV, HV and UMS charges'!$B$12:$B$44,MATCH($A125,'Annex 1 LV, HV and UMS charges'!$A$12:$A$44,0)),IF(INDEX('Annex 4 LDNO charges'!$B$11:$B$202,MATCH($A125,'Annex 4 LDNO charges'!$A$11:$A$202,0))=0,"",INDEX('Annex 4 LDNO charges'!$B$11:$B$202,MATCH($A125,'Annex 4 LDNO charges'!$A$11:$A$202,0)))) -> C53 | C125: =IFERROR(INDEX('Annex 1 LV, HV and UMS charges'!$C$13:$C$44,MATCH($A125,'Annex 1 LV, HV and UMS charges'!$A$13:$A$44,0)),INDEX('Annex 4 LDNO charges'!$C$13:$C$202,MATCH($A125,'Annex 4 LDNO charges'!$A$13:$A$202,0))) -> 0, 3, 4, 5-8 | F125: 0.052226762
A126: LDNO 132kV: Non-Domestic Aggregated Band 4 | B126: =IFERROR(INDEX('Annex 1 LV, HV and UMS charges'!$B$12:$B$44,MATCH($A126,'Annex 1 LV, HV and UMS charges'!$A$12:$A$44,0)),IF(INDEX('Annex 4 LDNO charges'!$B$11:$B$202,MATCH($A126,'Annex 4 LDNO charges'!$A$11:$A$202,0))=0,"",INDEX('Annex 4 LDNO charges'!$B$11:$B$202,MATCH($A126,'Annex 4 LDNO charges'!$A$11:$A$202,0)))) -> C54 | C126: =IFERROR(INDEX('Annex 1 LV, HV and UMS charges'!$C$13:$C$44,MATCH($A126,'Annex 1 LV, HV and UMS charges'!$A$13:$A$44,0)),INDEX('Annex 4 LDNO charges'!$C$13:$C$202,MATCH($A126,'Annex 4 LDNO charges'!$A$13:$A$202,0))) -> 0, 3, 4, 5-8 | F126: 0.052226762
A127: LDNO 132kV: LV Site Specific No Residual | B127: =IFERROR(INDEX('Annex 1 LV, HV and UMS charges'!$B$12:$B$44,MATCH($A127,'Annex 1 LV, HV and UMS charges'!$A$12:$A$44,0)),IF(INDEX('Annex 4 LDNO charges'!$B$11:$B$202,MATCH($A127,'Annex 4 LDNO charges'!$A$11:$A$202,0))=0,"",INDEX('Annex 4 LDNO charges'!$B$11:$B$202,MATCH($A127,'Annex 4 LDNO charges'!$A$11:$A$202,0)))) -> E50 | C127: =IFERROR(INDEX('Annex 1 LV, HV and UMS charges'!$C$13:$C$44,MATCH($A127,'Annex 1 LV, HV and UMS charges'!$A$13:$A$44,0)),INDEX('Annex 4 LDNO charges'!$C$13:$C$202,MATCH($A127,'Annex 4 LDNO charges'!$A$13:$A$202,0))) -> 0 | F127: 0.052226762
A128: LDNO 132kV: LV Site Specific Band 1 | B128: =IFERROR(INDEX('Annex 1 LV, HV and UMS charges'!$B$12:$B$44,MATCH($A128,'Annex 1 LV, HV and UMS charges'!$A$12:$A$44,0)),IF(INDEX('Annex 4 LDNO charges'!$B$11:$B$202,MATCH($A128,'Annex 4 LDNO charges'!$A$11:$A$202,0))=0,"",INDEX('Annex 4 LDNO charges'!$B$11:$B$202,MATCH($A128,'Annex 4 LDNO charges'!$A$11:$A$202,0)))) -> E51 | C128: =IFERROR(INDEX('Annex 1 LV, HV and UMS charges'!$C$13:$C$44,MATCH($A128,'Annex 1 LV, HV and UMS charges'!$A$13:$A$44,0)),INDEX('Annex 4 LDNO charges'!$C$13:$C$202,MATCH($A128,'Annex 4 LDNO charges'!$A$13:$A$202,0))) -> 0 | F128: 0.052226762
A129: LDNO 132kV: LV Site Specific Band 2 | B129: =IFERROR(INDEX('Annex 1 LV, HV and UMS charges'!$B$12:$B$44,MATCH($A129,'Annex 1 LV, HV and UMS charges'!$A$12:$A$44,0)),IF(INDEX('Annex 4 LDNO charges'!$B$11:$B$202,MATCH($A129,'Annex 4 LDNO charges'!$A$11:$A$202,0))=0,"",INDEX('Annex 4 LDNO charges'!$B$11:$B$202,MATCH($A129,'Annex 4 LDNO charges'!$A$11:$A$202,0)))) -> E52 | C129: =IFERROR(INDEX('Annex 1 LV, HV and UMS charges'!$C$13:$C$44,MATCH($A129,'Annex 1 LV, HV and UMS charges'!$A$13:$A$44,0)),INDEX('Annex 4 LDNO charges'!$C$13:$C$202,MATCH($A129,'Annex 4 LDNO charges'!$A$13:$A$202,0))) -> 0 | F129: 0.052226762
A130: LDNO 132kV: LV Site Specific Band 3 | B130: =IFERROR(INDEX('Annex 1 LV, HV and UMS charges'!$B$12:$B$44,MATCH($A130,'Annex 1 LV, HV and UMS charges'!$A$12:$A$44,0)),IF(INDEX('Annex 4 LDNO charges'!$B$11:$B$202,MATCH($A130,'Annex 4 LDNO charges'!$A$11:$A$202,0))=0,"",INDEX('Annex 4 LDNO charges'!$B$11:$B$202,MATCH($A130,'Annex 4 LDNO charges'!$A$11:$A$202,0)))) -> E53 | C130: =IFERROR(INDEX('Annex 1 LV, HV and UMS charges'!$C$13:$C$44,MATCH($A130,'Annex 1 LV, HV and UMS charges'!$A$13:$A$44,0)),INDEX('Annex 4 LDNO charges'!$C$13:$C$202,MATCH($A130,'Annex 4 LDNO charges'!$A$13:$A$202,0))) -> 0 | F130: 0.052226762
A131: LDNO 132kV: LV Site Specific Band 4 | B131: =IFERROR(INDEX('Annex 1 LV, HV and UMS charges'!$B$12:$B$44,MATCH($A131,'Annex 1 LV, HV and UMS charges'!$A$12:$A$44,0)),IF(INDEX('Annex 4 LDNO charges'!$B$11:$B$202,MATCH($A131,'Annex 4 LDNO charges'!$A$11:$A$202,0))=0,"",INDEX('Annex 4 LDNO charges'!$B$11:$B$202,MATCH($A131,'Annex 4 LDNO charges'!$A$11:$A$202,0)))) -> E54 | C131: =IFERROR(INDEX('Annex 1 LV, HV and UMS charges'!$C$13:$C$44,MATCH($A131,'Annex 1 LV, HV and UMS charges'!$A$13:$A$44,0)),INDEX('Annex 4 LDNO charges'!$C$13:$C$202,MATCH($A131,'Annex 4 LDNO charges'!$A$13:$A$202,0))) -> 0 | F131: 0.052226762
A132: LDNO 132kV: LV Sub Site Specific No Residual | B132: =IFERROR(INDEX('Annex 1 LV, HV and UMS charges'!$B$12:$B$44,MATCH($A132,'Annex 1 LV, HV and UMS charges'!$A$12:$A$44,0)),IF(INDEX('Annex 4 LDNO charges'!$B$11:$B$202,MATCH($A132,'Annex 4 LDNO charges'!$A$11:$A$202,0))=0,"",INDEX('Annex 4 LDNO charges'!$B$11:$B$202,MATCH($A132,'Annex 4 LDNO charges'!$A$11:$A$202,0)))) -> J50 | C132: =IFERROR(INDEX('Annex 1 LV, HV and UMS charges'!$C$13:$C$44,MATCH($A132,'Annex 1 LV, HV and UMS charges'!$A$13:$A$44,0)),INDEX('Annex 4 LDNO charges'!$C$13:$C$202,MATCH($A132,'Annex 4 LDNO charges'!$A$13:$A$202,0))) -> 0 | F132: 0.052226762
A133: LDNO 132kV: LV Sub Site Specific Band 1 | B133: =IFERROR(INDEX('Annex 1 LV, HV and UMS charges'!$B$12:$B$44,MATCH($A133,'Annex 1 LV, HV and UMS charges'!$A$12:$A$44,0)),IF(INDEX('Annex 4 LDNO charges'!$B$11:$B$202,MATCH($A133,'Annex 4 LDNO charges'!$A$11:$A$202,0))=0,"",INDEX('Annex 4 LDNO charges'!$B$11:$B$202,MATCH($A133,'Annex 4 LDNO charges'!$A$11:$A$202,0)))) -> J51 | C133: =IFERROR(INDEX('Annex 1 LV, HV and UMS charges'!$C$13:$C$44,MATCH($A133,'Annex 1 LV, HV and UMS charges'!$A$13:$A$44,0)),INDEX('Annex 4 LDNO charges'!$C$13:$C$202,MATCH($A133,'Annex 4 LDNO charges'!$A$13:$A$202,0))) -> 0 | F133: 0.052226762
... A141: LDNO 132kV: HV Site Specific Band 4 | B141: =IFERROR(INDEX('Annex 1 LV, HV and UMS charges'!$B$12:$B$44,MATCH($A141,'Annex 1 LV, HV and UMS charges'!$A$12:$A$44,0)),IF(INDEX('Annex 4 LDNO charges'!$B$11:$B$202,MATCH($A141,'Annex 4 LDNO charges'!$A$11:$A$202,0))=0,"",INDEX('Annex 4 LDNO charges'!$B$11:$B$202,MATCH($A141,'Annex 4 LDNO charges'!$A$11:$A$202,0)))) -> K54 | C141: =IFERROR(INDEX('Annex 1 LV, HV and UMS charges'!$C$13:$C$44,MATCH($A141,'Annex 1 LV, HV and UMS charges'!$A$13:$A$44,0)),INDEX('Annex 4 LDNO charges'!$C$13:$C$202,MATCH($A141,'Annex 4 LDNO charges'!$A$13:$A$202,0))) -> 0 | F141: 0.052226762
A142: LDNO 0000: Domestic Aggregated with Residual | B142: =IFERROR(INDEX('Annex 1 LV, HV and UMS charges'!$B$12:$B$44,MATCH($A142,'Annex 1 LV, HV and UMS charges'!$A$12:$A$44,0)),IF(INDEX('Annex 4 LDNO charges'!$B$11:$B$202,MATCH($A142,'Annex 4 LDNO charges'!$A$11:$A$202,0))=0,"",INDEX('Annex 4 LDNO charges'!$B$11:$B$202,MATCH($A142,'Annex 4 LDNO charges'!$A$11:$A$202,0)))) -> A60 | C142: =IFERROR(INDEX('Annex 1 LV, HV and UMS charges'!$C$13:$C$44,MATCH($A142,'Annex 1 LV, HV and UMS charges'!$A$13:$A$44,0)),INDEX('Annex 4 LDNO charges'!$C$13:$C$202,MATCH($A142,'Annex 4 LDNO charges'!$A$13:$A$202,0))) -> 0, 1, 2 | D142: 0.05859276 | E142: 9.6543478 | F142: 0.052226762
A143: LDNO 0000: Non-Domestic Aggregated No Residual | B143: =IFERROR(INDEX('Annex 1 LV, HV and UMS charges'!$B$12:$B$44,MATCH($A143,'Annex 1 LV, HV and UMS charges'!$A$12:$A$44,0)),IF(INDEX('Annex 4 LDNO charges'!$B$11:$B$202,MATCH($A143,'Annex 4 LDNO charges'!$A$11:$A$202,0))=0,"",INDEX('Annex 4 LDNO charges'!$B$11:$B$202,MATCH($A143,'Annex 4 LDNO charges'!$A$11:$A$202,0)))) -> C60 | C143: =IFERROR(INDEX('Annex 1 LV, HV and UMS charges'!$C$13:$C$44,MATCH($A143,'Annex 1 LV, HV and UMS charges'!$A$13:$A$44,0)),INDEX('Annex 4 LDNO charges'!$C$13:$C$202,MATCH($A143,'Annex 4 LDNO charges'!$A$13:$A$202,0))) -> 0, 3, 4, 5-8 | F143: 0.052226762
...

Sheet Nodal prices
A1: Back to Overview
A2: =Overview!B4& " - Effective from "&Overview!D4&" - "&Overview!E4&" Nodal/Zonal charges" -> London Power Networks - Effective from 1 April 2022 - Final Nodal/Zonal charges
A3: Node/Zone ID | B3: Geographical name | C3: Local charge 1 £/kVA | D3: Remote charge 1 £/kVA
A4: ABPA51 | B4: Aberdeen Place | C4: 3.7029388 | D4: 0.10505079
A5: ABPA52 | B5: Aberdeen Place | C5: 1.152449 | D5: 0.080983892
A6: ABPB51 | B6: Aberdeen Place | C6: 5.5308652 | D6: 0.094810606
A7: ACTL81 | B7: Acton Lane | C7: 0 | D7: 0
A8: AMBL51 | B8: Amberley Rd | C8: 0 | D8: 0.10410807
A9: AMBL52 | B9: Amberley Rd | C9: 0 | D9: 0
A10: ASWN91 | B10: APCM Swanscombe | C10: 0 | D10: 0
A11: AXES51 | B11: Axe St | C11: 2.2082683 | D11: 8.9831447
A12: AXES52 | B12: Axe St | C12: 1.4660907 | D12: 4.8624602
A13: BACA51 | B13: Back Hill | C13: 5.0312393 | D13: 0.35841098
A14: BACA52 | B14: Back Hill | C14: 0.68093341 | D14: 0
A15: BANC51 | B15: Bankside | C15: 0 | D15: 0
... A258: WDGR51 | B258: Woodgrange Park | C258: 1.431653 | D258: 6.3559599

Sheet SSC unit rate lookup
A1: Back to Overview
A28: Standard Settlement Configuration Id | B28: Standard Settlement Configuration Desc | C28: Common Decode | F28: Change implemented | G28: Date | H28: Comments
A29: 3 | B29: 10-hour OP | C29: A/R | F29: Notes updated | G29: 43626 | H29: Updated to reflect DCP 268 which delinks all tariffs from the TPR bands
A30: 4 | B30: 10-hour OP | C30: A/R | F30: Code 1 & 2 changed to A | G30: 43626 | H30: Updated to reflect DCP 268 which delinks all tariffs from the TPR bands
A31: 5 | B31: 10-hour OP + w/e | C31: A/R | F31: Code O changed to A/R | G31: 43626 | H31: Updated to reflect DCP 268 which delinks all tariffs from the TPR bands
A32: 6 | B32: 10.5-hour OP | C32: A/R | F32: Removed TPR | G32: 43626 | H32: Removed TPR lookup element as this no longer effects which rate to apply
A33: 7 | B33: 10.5-hour OP | C33: A/R
A34: 8 | B34: 10.5-hour OP | C34: A/R
A35: 9 | B35: 10.5-hour OP | C35: A/R
A36: 10 | B36: 10.5-hour OP | C36: A/R
A37: 11 | B37: 10.5-hour OP | C37: A/R
A38: 12 | B38: 10.5-hour OP | C38: A/R
A39: 13 | B39: 11 Hour OP | C39: A/R
A40: 15 | B40: 11 Hour OP | C40: A/R
A41: 16 | B41: 11.5-hour OP | C41: A/R
A42: 17 | B42: 11.5-hour OP | C42: A/R
A43: 18 | B43: 11.5-hour OP | C43: A/R
A44: 19 | B44: 11.5-hour OP | C44: A/R
... A764: 997 | B764: Evening/Weekend - BST | C764: A

Sheet Residual Charging Bands
A1: Back to Overview
A2: =Overview!B4& " - Effective from "&Overview!C4&" - "&Overview!E4&" Residual Charging Bands" -> London Power Networks - Effective from 2022/23 - Final Residual Charging Bands
A4: Voltage of Connection | B4: Band | C4: Units | D4: Lower Threshold* | E4: Upper Threshold* | F4: Residual Charge per Fixed Charge** (p/day) | G4: Residual Charge per Unit rate 1** (p/kWh) | H4: Residual Charge per Unit rate 2** (p/kWh) | I4: Residual Charge per Unit rate 3** (p/kWh)
A5: Domestic Aggregated | B5: Single band | C5: - | D5: - | E5: - | F5: -1.9750804
A6: Designated Properties connected at LV, billing with no MIC | B6: 1 | C6: kWh | D6: 0 | E6: 3571 | F6: -0.77548884
B7: 2 | C7: kWh | D7: 3571 | E7: 12553 | F7: -3.2009281 | G7: -0.12510535 | H7: -0.12510535 | I7: -0.035050624
B8: 3 | C8: kWh | D8: 12553 | E8: 25279 | F8: -3.2009281 | G8: -0.27387446 | H8: -0.27387446 | I8: -0.035050624
B9: 4 | C9: kWh | D9: 25279 | E9: ∞ | F9: -3.2009281 | G9: -0.34815666 | H9: -0.34815666 | I9: -0.035050624
A10: Designated Properties connected at LV, billing with MIC | B10: 1 | C10: kVA | D10: 0 | E10: 80 | F10: -5.8566104 | G10: -0.37678979 | H10: -0.37678979 | I10: -0.024141973
B11: 2 | C11: kVA | D11: 80 | E11: 150 | F11: -5.8566104 | G11: -0.38711404 | H11: -0.38711404 | I11: -0.024141973
B12: 3 | C12: kVA | D12: 150 | E12: 231 | F12: -5.8566104 | G12: -0.396551 | H12: -0.396551 | I12: -0.024141973
B13: 4 | C13: kVA | D13: 231 | E13: ∞ | F13: -5.8566104 | G13: -0.4041872 | H13: -0.4041872 | I13: -0.024141973
A14: Designated Properties connected at HV | B14: 1 | C14: kVA | D14: 0 | E14: 422 | F14: -78.569805 | G14: -0.35119911 | H14: -0.35119911 | I14: -0.016837749
B15: 2 | C15: kVA | D15: 422 | E15: 1000 | F15: -78.569805 | G15: -0.39731306 | H15: -0.39731306 | I15: -0.016837749
B16: 3 | C16: kVA | D16: 1000 | E16: 1800 | F16: -78.569805 | G16: -0.40898001 | H16: -0.40898001 | I16: -0.016837749
B17: 4 | C17: kVA | D17: 1800 | E17: ∞ | F17: -78.569805 | G17: -0.42047139 | H17: -0.42047139 | I17: -0.016837749
A18: Designated EHV Properties | B18: 1 | C18: kVA | D18: 0 | E18: 5000 | F18: 870.46144
B19: 2 | C19: kVA | D19: 5000 | E19: 12000 | F19: 5754.8515
B20: 3 | C20: kVA | D20: 12000 | E20: 21500 | F20: 17523.641
B21: 4 | C21: kVA | D21: 21500 | E21: ∞ | F21: 43861.687
A22: * All boundaries are inclusive of the upper threshold and exclusive of the lower threshold i.e. Lower < x ≤ Upper.
A23: **Residual charge element in London Power Networks CDCM model is negative and therefore the application of the residual reduces the calculated fixed charge. If the fixed charge reaches zero then the remaining reduction is applied to the unit rates.

Sheet Charge Calculator
B1: Back to Overview
B2: =Overview!B4& " - Effective from "&Overview!D4&" - "&Overview!E4 -> London Power Networks - Effective from 1 April 2022 - Final | AC2: Red/black unit charge p/kWh | AD2: Amber/yellow unit charge p/kWh | AE2: Green unit charge p/kWh | AF2: Fixed charge p/MPAN/day | AG2: Capacity charge p/kVA/day | AH2: Exceeded capacity charge p/kVA/day | AI2: Reactive power charge p/kVArh
AB3: Domestic Aggregated | AC3: Red unit charge p/kWh | AD3: Amber unit charge p/kWh | AE3: Green unit charge p/kWh | AF3: Fixed charge p/MPAN/day | AG3: n/a | AH3: n/a | AI3: n/a
B4: LV and HV designated properties and Unmetered Supplies tariff calculator | L4: EHV designated property calculator | AB4: Domestic Aggregated (related MPAN) | AC4: Red unit charge p/kWh | AD4: Amber unit charge p/kWh | AE4: Green unit charge p/kWh | AF4: n/a | AG4: n/a | AH4: n/a | AI4: n/a
B5: Step 1, Choose your tariff using the drop down list in cell B10 | L5: Step 1, Choose your tariff using the drop down list in cell L10 | AB5: Non-Domestic Aggregated | AC5: Red unit charge p/kWh | AD5: Amber unit charge p/kWh | AE5: Green unit charge p/kWh | AF5: Fixed charge p/MPAN/day | AG5: n/a | AH5: n/a | AI5: n/a
B6: Step 2, After selecting a tariff in step 1, Cells C12-I12 will generate headings, please enter your consumption in cells C13:I13 underneath each heading generated (if no heading leave cell blank) | L6: Step 2, After selecting a tariff in step 1, Cells M12-T12 will generate headings, please enter your consumption in cells M13:T13 underneath each heading generated (if no heading leave cell blank) | AB6: Non-Domestic Aggregated (related MPAN) | AC6: Red unit charge p/kWh | AD6: Amber unit charge p/kWh | AE6: Green unit charge p/kWh | AF6: n/a | AG6: n/a | AH6: n/a | AI6: n/a
B7: Step 3, Enter a forecast of consumption if required in cells C14:I14 | L7: Step 3, Enter a forecast of consumption if required in cells M14:T14 | AB7: LV Site Specific | AC7: Red unit charge p/kWh | AD7: Amber unit charge p/kWh | AE7: Green unit charge p/kWh | AF7: Fixed charge p/MPAN/day | AG7: Capacity charge p/kVA/day | AH7: Exceeded Capacity charge p/kVA/day | AI7: Reactive power charge p/kVArh
AB8: LV Sub Site Specific | AC8: Red unit charge p/kWh | AD8: Amber unit charge p/kWh | AE8: Green unit charge p/kWh | AF8: Fixed charge p/MPAN/day | AG8: Capacity charge p/kVA/day | AH8: Exceeded Capacity charge p/kVA/day | AI8: Reactive power charge p/kVArh
B9: Tariff details Choose tariff name from drop down box below | C9: =IFERROR(VLOOKUP($B$10,$AB$2:$AI$18,2,FALSE),AC2) -> Red/black unit charge p/kWh | D9: =IFERROR(VLOOKUP($B$10,$AB$2:$AI$18,3,FALSE),AD2) -> Amber/yellow unit charge p/kWh | E9: =IFERROR(VLOOKUP($B$10,$AB$2:$AI$18,4,FALSE),AE2) -> Green unit charge p/kWh | F9: =IFERROR(VLOOKUP($B$10,$AB$2:$AI$18,5,FALSE),AF2) -> Fixed charge p/MPAN/day | G9: =IFERROR(VLOOKUP($B$10,$AB$2:$AI$18,6,FALSE),AG2) -> Capacity charge p/kVA/day | H9: =IFERROR(VLOOKUP($B$10,$AB$2:$AI$18,7,FALSE),AH2) -> Exceeded capacity charge p/kVA/day | I9: =IFERROR(VLOOKUP($B$10,$AB$2:$AI$18,8,FALSE),AI2) -> Reactive power charge p/kVArh | L9: Site details Choose the site name from the drop down box below | M9: ='Annex 2 EHV charges'!H10 -> Import Super Red unit charge (p/kWh) | N9: ='Annex 2 EHV charges'!I10 -> Import fixed charge (p/day) | O9: ='Annex 2 EHV charges'!J10 -> Import capacity charge (p/kVA/day) | P9: ='Annex 2 EHV charges'!K10 -> Import exceeded capacity charge (p/kVA/day) | Q9: ='Annex 2 EHV charges'!L10 -> Export Super Red unit charge (p/kWh) | R9: ='Annex 2 EHV charges'!M10 -> Export fixed charge (p/day) | S9: ='Annex 2 EHV charges'!N10 -> Export capacity charge (p/kVA/day) | T9: ='Annex 2 EHV charges'!O10 -> Export exceeded capacity charge (p/kVA/day) | AB9: HV Site Specific | AC9: Red unit charge p/kWh | AD9: Amber unit charge p/kWh | AE9: Green unit charge p/kWh | AF9: Fixed charge p/MPAN/day | AG9: Capacity charge p/kVA/day | AH9: Exceeded Capacity charge p/kVA/day | AI9: Reactive power charge p/kVArh
C10: =IFERROR(VLOOKUP($B$10,'Annex 1 LV, HV and UMS charges'!$A:$K,4,FALSE),"") | D10: =IFERROR(VLOOKUP($B$10,'Annex 1 LV, HV and UMS charges'!$A:$K,5,FALSE),"") | E10: =IFERROR(VLOOKUP($B$10,'Annex 1 LV, HV and UMS charges'!$A:$K,6,FALSE),"") | F10: =IFERROR(VLOOKUP($B$10,'Annex 1 LV, HV and UMS charges'!$A:$K,7,FALSE),"") | G10: =IFERROR(VLOOKUP($B$10,'Annex 1 LV, HV and UMS charges'!$A:$K,8,FALSE),"") | H10: =IFERROR(VLOOKUP($B$10,'Annex 1 LV, HV and UMS charges'!$A:$K,9,FALSE),"") | I10: =IFERROR(VLOOKUP($B$10,'Annex 1 LV, HV and UMS charges'!$A:$K,10,FALSE),"") | M10: =IFERROR(VLOOKUP($L$10,'Annex 2 EHV charges'!$G:$O,2,FALSE),"") | N10: =IFERROR(VLOOKUP($L$10,'Annex 2 EHV charges'!$G:$O,3,FALSE),"") | O10: =IFERROR(VLOOKUP($L$10,'Annex 2 EHV charges'!$G:$O,4,FALSE),"") | P10: =IFERROR(VLOOKUP($L$10,'Annex 2 EHV charges'!$G:$O,5,FALSE),"") | Q10: =IFERROR(VLOOKUP($L$10,'Annex 2 EHV charges'!$G:$O,6,FALSE),"") | R10: =IFERROR(VLOOKUP($L$10,'Annex 2 EHV charges'!$G:$O,7,FALSE),"") | S10: =IFERROR(VLOOKUP($L$10,'Annex 2 EHV charges'!$G:$O,8,FALSE),"") | T10: =IFERROR(VLOOKUP($L$10,'Annex 2 EHV charges'!$G:$O,9,FALSE),"") | AB10: Unmetered Supplies | AC10: Black unit charge p/kWh | AD10: Yellow unit charge p/kWh | AE10: Green unit charge p/kWh | AF10: n/a | AG10: n/a | AH10: n/a | AI10: n/a
AB11: LV Generation Aggregated | AC11: Red unit charge p/kWh | AD11: Amber unit charge p/kWh | AE11: Green unit charge p/kWh | AF11: Fixed charge p/MPAN/day | AG11: n/a | AH11: n/a | AI11: n/a
B12: Tariff components | C12: =C9 -> Red/black unit charge p/kWh | D12: =D9 -> Amber/yellow unit charge p/kWh | E12: =E9 -> Green unit charge p/kWh | F12: Number of days in consumption period i.e. 365 if one year | G12: Maximum import or export capacity kVA | H12: Average daily exceeded capacity kVA | I12: Excess reactive units kVArh | L12: Tariff components | M12: Import super red kWh | N12: Number of days in consumption period i.e. 365 if one year | O12: Maximum import capacity kVA | P12: Average daily exceeded capacity kVA | Q12: Export Super Red kWh | R12: Number of days in consumption period i.e. 365 if one year | S12: Maximum export capacity kVA | T12: Average daily exceeded capacity kVA | AB12: LV Sub Generation Aggregated | AC12: Red unit charge p/kWh | AD12: Amber unit charge p/kWh | AE12: Green unit charge p/kWh | AF12: Fixed charge p/MPAN/day | AG12: n/a | AH12: n/a | AI12: n/a
B13: Enter current consumption details | L13: Enter current consumption details | R13: =N13 -> 0 | AB13: LV Generation Site Specific | AC13: Red unit charge p/kWh | AD13: Amber unit charge p/kWh | AE13: Green unit charge p/kWh | AF13: Fixed charge p/MPAN/day | AG13: n/a | AH13: n/a | AI13: Reactive power charge p/kVArh
B14: Enter forecast consumption details (if different) | C14: =C13 -> 0 | D14: =D13 -> 0 | E14: =E13 -> 0 | F14: =F13 -> 0 | G14: =G13 -> 0 | H14: =H13 -> 0 | I14: =I13 -> 0 | L14: Enter forecast consumption details (if different) | M14: =M13 -> 0 | N14: =N13 -> 0 | O14: =O13 -> 0 | P14: =P13 -> 0 | Q14: =Q13 -> 0 | R14: =R13 -> 0 | S14: =S13 -> 0 | T14: =T13 -> 0 | AB14: LV Generation Site Specific no RP charge | AC14: Red unit charge p/kWh | AD14: Amber unit charge p/kWh | AE14: Green unit charge p/kWh | AF14: Fixed charge p/MPAN/day | AG14: n/a | AH14: n/a | AI14: n/a
AB15: LV Sub Generation Site Specific | AC15: Red unit charge p/kWh | AD15: Amber unit charge p/kWh | AE15: Green unit charge p/kWh | AF15: Fixed charge p/MPAN/day | AG15: n/a | AH15: n/a | AI15: Reactive power charge p/kVArh
B16: Charge components | C16: Unit 1 £ | D16: Unit 2 £ | E16: Unit 3 £ | F16: Fixed charge £ | G16: Capacity charge £ | H16: Exceeded capacity charge £ | I16: Reactive power charge £ | L16: Charge components | M16: Import super red charge £ | N16: Import fixed charge £ | O16: Import capacity charge £ | P16: Import exceeded capacity charge £ | Q16: Export super red charge £ | R16: Export fixed charge £ | S16: Export capacity charge £ | T16: Export exceeded capacity charge £ | AB16: LV Sub Generation Site Specific no RP charge | AC16: Red unit charge p/kWh | AD16: Amber unit charge p/kWh | AE16: Green unit charge p/kWh | AF16: Fixed charge p/MPAN/day | AG16: n/a | AH16: n/a | AI16: n/a
B17: Current consumption period charges | C17: =IFERROR(C10*C13/100,"") | D17: =IFERROR(D10*D13/100,"") | E17: =IFERROR(E10*E13/100,"") | F17: =IFERROR(F10*F13/100,"") | G17: =IFERROR(G10*G13*F13/100,"") | H17: =IFERROR(H10*H13*F13/100,"") | I17: =IFERROR(I10*I13/100,"") | L17: Current consumption period charges | M17: =IFERROR(M10*M13/100,"") | N17: =IFERROR(N10*N13/100,"") | O17: =IFERROR(O10*O13*N13/100,"") | P17: =IFERROR(P10*P13*N13/100,"") | Q17: =IFERROR(Q10*Q13/100,"") | R17: =IFERROR(R10*R13/100,"") | S17: =IFERROR(S10*S13*R13/100,"") | T17: =IFERROR(T10*T13*R13/100,"") | AB17: HV Generation Site Specific | AC17: Red unit charge p/kWh | AD17: Amber unit charge p/kWh | AE17: Green unit charge p/kWh | AF17: Fixed charge p/MPAN/day | AG17: n/a | AH17: n/a | AI17: Reactive power charge p/kVArh
B18: Forecast consumption period charges | C18: =IFERROR(C10*C14/100,"") | D18: =IFERROR(D10*D14/100,"") | E18: =IFERROR(E10*E14/100,"") | F18: =IFERROR(F10*F14/100,"") | G18: =IFERROR(G10*G14*F14/100,"") | H18: =IFERROR(H10*H14*F14/100,"") | I18: =IFERROR(I10*I14/100,"") | L18: Forecast consumption period charges | M18: =IFERROR(M10*M14/100,"") | N18: =IFERROR(N10*N14/100,"") | O18: =IFERROR(O10*O14*N14/100,"") | P18: =IFERROR(P10*P14*N14/100,"") | Q18: =IFERROR(Q10*Q14/100,"") | R18: =IFERROR(R10*R14/100,"") | S18: =IFERROR(S10*S14*R14/100,"") | T18: =IFERROR(T10*T14*R14/100,"") | AB18: HV Generation Site Specific no RP charge | AC18: Red unit charge p/kWh | AD18: Amber unit charge p/kWh | AE18: Green unit charge p/kWh | AF18: Fixed charge p/MPAN/day | AG18: n/a | AH18: n/a | AI18: n/a
C20: Total charge £ | M20: Import total charge £ | N20: Export total charge £
B21: Current consumption period charges | C21: =SUM(C17:I17) -> 0 | L21: Current consumption period charges | M21: =SUM(M17:P17) -> 0 | N21: =SUM(Q17:T17) -> 0
B22: Forecast consumption period charges | C22: =SUM(C18:I18) -> 0 | L22: Forecast consumption period charges | M22: =SUM(M18:P18) -> 0 | N22: =SUM(Q18:T18) -> 0
B24: These charges are estimates based on tariff selected and consumption values entered. | L24: These charges are estimates based on site selected and consumption values entered.
