Workbook
Name OLE_LINK1: 'Annex 3 Preserved charges'!#REF!

Sheet Overview
A2: Company and Licence name, charging year, effective from, status
B3: Company and Licence name | C3: Year | D3: Effective From | E3: Status
A4: Company and Licence name, charging year, effective from, status | B4: South Eastern Power Networks | C4: 2024/25 | D4: 1 April 2024 | E4: Final
A6: List of data tables in this workbook
A7: Worksheet | B7: Information
A8: Annex 1 LV, HV and Unmetered Supplies charges | B8: Annex 1 contains the charges to LV and HV Designated Properties and Unmetered Supplies.
A9: Annex 2 EHV charges | B9: ="Annex 2 contains the charges to Designated EHV Properties and charges applied to LDNOs with Designated EHV Properties/end-users embedded in networks within the " &B4 &" Licence area." -> Annex 2 contains the charges to Designated EHV Properties and charges applied to LDNOs with Designated EHV Properties/end-users embedded in networks within the South Eastern Power Networks Licence area.
A10: Annex 3 Preserved charges | B10: Annex 3 contains details of any preserved and additional charges that are valid at this time.
A11: Annex 4 LDNO charges | B11: ="Annex 4 contains charges that are levied on the owner of an embedded network within the "&B4&" Licence area. "&"Electricity suppliers and consumers who have properties connected to an embedded network should contact the embedded network owner to determine their distribution charges."&" The charges listed in this table are not payable by domestic consumers, business consumers or electricity suppliers." -> Annex 4 contains charges that are levied on the owner of an embedded network within the South Eastern Power Networks Licence area. Electricity suppliers and consumers who have properties connected to an embedded network should contact the embedded network owner to determine their distribution charges. The charges listed in this table are not payable by domestic consumers, business consumers or electricity suppliers.
A12: Annex 5 LLFs | B12: Annex 5 has been intentionally left blank as this charging statement is published a complete year before the LLFs have been audited. The line loss factors that are approved by the BSC Panel for the applicable year and consequently published on the Elexon website will take precedence and be used in Settlement. This annex will be re-published with these values once they are available.
A13: Annex 6 Charges for New or Amended Designated EHV Properties | B13: ="Annex 6 contains the charges for new or amended Designated EHV Properties and charges applied to LDNOs with new or amended Designated EHV Properties/end-users embedded in networks within the " &B4 &" Licence area." -> Annex 6 contains the charges for new or amended Designated EHV Properties and charges applied to LDNOs with new or amended Designated EHV Properties/end-users embedded in networks within the South Eastern Power Networks Licence area.
A14: Annex 7 Fixed adders for Supplier of Last Resort and Eligible Bad Debt pass-through costs | B14: Annex 7 contains the fixed adders to recover Supplier of Last Resort and Eligible Bad Debt pass-through costs. The Excess Supplier of Last Resort fixed adder relates to an increase to previously published charges only.
A15: Nodal prices | B15: Contains the underlying nodal group costs used to calculate the current EDCM charges.
A16: Residual Charging Bandings | B16: Contains the four Residual charging band allocation for Customers
A17: Charge calculator | B17: Charge calculator is a tool to help you estimate your distribution charges using current consumption data and forecast consumption data.
A19: Notes to users of this spreadsheet
A21: Please use this spreadsheet with reference to the LC14 use of system charging statement.
A23: Notes to DNOs populating this spreadsheet
A25: DNOs must endeavour to maintain consistency in the structure of this spreadsheet. Any changes to the structure must be noted in the 'Notes to users of this spreadsheet'
A26: The drop down list on the charge calculator can be expanded by unprotecting the charge calculator sheet and selecting 'data', 'data validation...' and then expanding the 'source' data range. The sheet can then be protected.

Sheet Annex 1 LV, HV and UMS charges
A1: Back to Overview | B1: 'DNOs paste value cells A15:J47 from CDCM 3701 into cells A14:J46
A2: =Overview!B4& " - Effective from "&Overview!D4&" - "&Overview!E4&" LV and HV charges" -> South Eastern Power Networks - Effective from 1 April 2024 - Final LV and HV charges
A4: Time Bands for LV and HV Designated Properties | G4: Time Bands for Unmetered Properties
A5: Time periods | B5: Red Time Band | C5: Amber Time Band | E5: Green Time Band | I5: Black Time Band | J5: Yellow Time Band | K5: Green Time Band
A6: Monday to Friday (Including Bank Holidays) All Year | B6: 16:00 - 19:00 | C6: 07:00 - 16:00 19:00 - 23:00 | E6: 00:00 - 07:00 23:00 - 24:00 | G6: Monday to Friday (Including Bank Holidays) November to February Inclusive | I6: 16:00 - 19:00 | J6: 07:00 - 16:00 19:00 - 23:00 | K6: 00:00 - 07:00 23:00 - 24:00
A7: Saturday and Sunday All Year | E7: 00:00 - 24:00 | G7: Monday to Friday (Including Bank Holidays) March to October Inclusive | J7: 07:00 - 23:00 | K7: 00:00 - 07:00 23:00 - 24:00
A8: Notes | B8: All the above times are in UK Clock time | G8: Saturday and Sunday All Year | K8: 00:00 - 24:00
G9: Notes | I9: All the above times are in UK Clock time
A11: Tariff name | B11: Open LLFCs | C11: PCs | D11: Red/black unit charge p/kWh | E11: Amber/yellow unit charge p/kWh | F11: Green unit charge p/kWh | G11: Fixed charge p/MPAN/day | H11: Capacity charge p/kVA/day | I11: Exceeded capacity charge p/kVA/day | J11: Reactive power charge p/kVArh | K11: Closed LLFCs
A12: Domestic Aggregated or CT with Residual | B12: 1 | C12: 0, 1, 2 | D12: 17.48 | E12: 0.656 | F12: 0.224 | G12: 20 | K12: 100, 300
A13: Domestic Aggregated (Related MPAN) | B13: 2 | C13: 2 | D13: 17.48 | E13: 0.656 | F13: 0.224 | K13: 251
A14: Non-Domestic Aggregated or CT No Residual | B14: 199 | C14: 0, 3, 4, 5-8 | D14: 11.894 | E14: 0.446 | F14: 0.152 | G14: 6.1
A15: Non-Domestic Aggregated or CT Band 1 | B15: 201 | C15: 0, 3, 4, 5-8 | D15: 11.894 | E15: 0.446 | F15: 0.152 | G15: 11.78 | K15: 200, 320
A16: Non-Domestic Aggregated or CT Band 2 | B16: 202 | C16: 0, 3, 4, 5-8 | D16: 11.894 | E16: 0.446 | F16: 0.152 | G16: 37.16
A17: Non-Domestic Aggregated or CT Band 3 | B17: 203 | C17: 0, 3, 4, 5-8 | D17: 11.894 | E17: 0.446 | F17: 0.152 | G17: 78.22
A18: Non-Domestic Aggregated or CT Band 4 | B18: 204 | C18: 0, 3, 4, 5-8 | D18: 11.894 | E18: 0.446 | F18: 0.152 | G18: 229.77
A19: Non-Domestic Aggregated (related MPAN) | B19: 200 | C19: 4 | D19: 11.894 | E19: 0.446 | F19: 0.152 | K19: 287
A20: LV Site Specific No Residual | B20: 70 | C20: 0 | D20: 9.862 | E20: 0.358 | F20: 0.12 | G20: 18.94 | H20: 4.34 | I20: 7.73 | J20: 0.32
A21: LV Site Specific Band 1 | B21: 71 | C21: 0 | D21: 9.862 | E21: 0.358 | F21: 0.12 | G21: 439.77 | H21: 4.34 | I21: 7.73 | J21: 0.32
A22: LV Site Specific Band 2 | B22: 72 | C22: 0 | D22: 9.862 | E22: 0.358 | F22: 0.12 | G22: 728.02 | H22: 4.34 | I22: 7.73 | J22: 0.32
A23: LV Site Specific Band 3 | B23: 73 | C23: 0 | D23: 9.862 | E23: 0.358 | F23: 0.12 | G23: 1176.88 | H23: 4.34 | I23: 7.73 | J23: 0.32
A24: LV Site Specific Band 4 | B24: 74 | C24: 0 | D24: 9.862 | E24: 0.358 | F24: 0.12 | G24: 2596.04 | H24: 4.34 | I24: 7.73 | J24: 0.32
A25: LV Sub Site Specific No Residual | B25: 80 | C25: 0 | D25: 6.35 | E25: 0.215 | F25: 0.069 | G25: 16.01 | H25: 6.32 | I25: 8.03 | J25: 0.201
A26: LV Sub Site Specific Band 1 | B26: 81 | C26: 0 | D26: 6.35 | E26: 0.215 | F26: 0.069 | G26: 436.84 | H26: 6.32 | I26: 8.03 | J26: 0.201
A27: LV Sub Site Specific Band 2 | B27: 82 | C27: 0 | D27: 6.35 | E27: 0.215 | F27: 0.069 | G27: 725.09 | H27: 6.32 | I27: 8.03 | J27: 0.201
A28: LV Sub Site Specific Band 3 | B28: 83 | C28: 0 | D28: 6.35 | E28: 0.215 | F28: 0.069 | G28: 1173.95 | H28: 6.32 | I28: 8.03 | J28: 0.201
A29: LV Sub Site Specific Band 4 | B29: 84 | C29: 0 | D29: 6.35 | E29: 0.215 | F29: 0.069 | G29: 2593.11 | H29: 6.32 | I29: 8.03 | J29: 0.201
A30: HV Site Specific No Residual | B30: 90 | C30: 0 | D30: 5.569 | E30: 0.181 | F30: 0.054 | G30: 180.95 | H30: 4.86 | I30: 7.2 | J30: 0.174
A31: HV Site Specific Band 1 | B31: 91 | C31: 0 | D31: 5.569 | E31: 0.181 | F31: 0.054 | G31: 1874.44 | H31: 4.86 | I31: 7.2 | J31: 0.174
... A34: HV Site Specific Band 4 | B34: 94 | C34: 0 | D34: 5.569 | E34: 0.181 | F34: 0.054 | G34: 21672.59 | H34: 4.86 | I34: 7.2 | J34: 0.174
A35: Unmetered Supplies | B35: 350, 351, 352, 353, 354 | C35: 0, 1 or 8 | D35: 46.082 | E35: 3.234 | F35: 2.919 | K35: 355, 356, 357, 358, 359, 360, 361, 362, 363, 364, 365, 366
A36: LV Generation Aggregated | B36: 932 | C36: 0 | D36: -10.397 | E36: -0.39 | F36: -0.133 | G36: 0
A37: LV Sub Generation Aggregated | C37: 0 | D37: -8.979 | E37: -0.33 | F37: -0.111 | G37: 0
A38: LV Generation Site Specific | B38: 980 | C38: 0 | D38: -10.397 | E38: -0.39 | F38: -0.133 | G38: 0 | J38: 0.311 | K38: 982
A39: LV Generation Site Specific no RP charge | B39: 981 | C39: 0 | D39: -10.397 | E39: -0.39 | F39: -0.133 | G39: 0 | K39: 983
A40: LV Sub Generation Site Specific | B40: 984 | C40: 0 | D40: -8.979 | E40: -0.33 | F40: -0.111 | G40: 0 | J40: 0.272 | K40: 986
A41: LV Sub Generation Site Specific no RP charge | B41: 985 | C41: 0 | D41: -8.979 | E41: -0.33 | F41: -0.111 | G41: 0 | K41: 987
A42: HV Generation Site Specific | B42: 988 | C42: 0 | D42: -6.173 | E42: -0.207 | F42: -0.065 | G42: 13.66 | J42: 0.22 | K42: 990
A43: HV Generation Site Specific no RP charge | B43: 989 | C43: 0 | D43: -6.173 | E43: -0.207 | F43: -0.065 | G43: 13.66 | K43: 991

Sheet Annex 2 EHV charges
A1: Back to Overview | C1: Copy EDCM table 5001 range starting B101 and paste into G11. Extend or reduce print area as required. | F1: Note: The DNO reserves the right to apply the listed charges to any other MPANs/MSIDs associated with the site. This includes reallocating charges to a traded MPAN at the same site where another MPAN has been disconnected or de-energised.
A2: =Overview!B4& " - Effective from "&Overview!D4&" - "&Overview!E4&" EDCM charges" -> South Eastern Power Networks - Effective from 1 April 2024 - Final EDCM charges
A4: Time Periods for Designated EHV Properties
A5: Time periods | D5: Super Red Time Band
A6: Monday to Friday (Including Bank Holidays) November to February Inclusive | D6: 16:00 - 19:00
A7: Notes | D7: All the above times are in UK Clock time
A9: Import Unique Identifier | B9: LLFC | C9: Import MPANs/MSIDs | D9: Export Unique Identifier | E9: LLFC | F9: Export MPANs/MSIDs | G9: Name | H9: Residual Charging Band | I9: Import Super Red unit charge (p/kWh) | J9: Import fixed charge (p/day) | K9: Import capacity charge (p/kVA/day) | L9: Import exceeded capacity charge (p/kVA/day) | M9: Export Super Red unit charge (p/kWh) | N9: Export fixed charge (p/day) | O9: Export capacity charge (p/kVA/day) | P9: Export exceeded capacity charge (p/kVA/day)
A10: B&RLTD | B10: 834 | C10: 1900035000482;1900035425153 | G10: B&RLTD | H10: 1 | I10: 1.862 | J10: 2865.31 | K10: 2.97 | L10: 2.97 | M10: 0 | N10: 0 | O10: 0 | P10: 0
A11: BEDDIN | B11: 889 | C11: 1900070745640;1900070745650;1900070745669;1900070745678 | G11: BEDDIN | H11: 2 | I11: 0.005 | J11: 16076.25 | K11: 1.45 | L11: 1.45 | M11: 0 | N11: 0 | O11: 0 | P11: 0
A12: BP_OIL | B12: 835 | C12: 1900017426438;1900017426447 | G12: BP_OIL | H12: 1 | I12: 0.312 | J12: 2865.31 | K12: 1.43 | L12: 1.43 | M12: 0 | N12: 0 | O12: 0 | P12: 0
A13: CHESDC | C13: ENET | G13: CHESDC | H13: 3 | I13: 0.004 | J13: 33041.98 | K13: 0.99 | L13: 0.99 | M13: 0 | N13: 0 | O13: 0 | P13: 0
A14: DIGREA | B14: 833 | C14: 1900091200323;1900091200332 | G14: DIGREA | H14: 4 | I14: 0 | J14: 69548.53 | K14: 1.86 | L14: 1.86 | M14: 0 | N14: 0 | O14: 0 | P14: 0
A15: EUROTU | B15: 874 | C15: 1900060219605 | G15: EUROTU | H15: 4 | I15: 0 | J15: 220981.93 | K15: 0.74 | L15: 0.74 | M15: 0 | N15: 0 | O15: 0 | P15: 0
A16: GAT_AF | B16: 869 | C16: 1900017427938;1900017427947;1900060576620 | G16: GAT_AF | H16: 3 | I16: 0.746 | J16: 39690.72 | K16: 1.78 | L16: 1.78 | M16: 0 | N16: 0 | O16: 0 | P16: 0
A17: GAT_BF | B17: 870 | C17: 1900060690231;1900060690240 | G17: GAT_BF | H17: 3 | I17: 0.776 | J17: 36594.39 | K17: 1.91 | L17: 1.91 | M17: 0 | N17: 0 | O17: 0 | P17: 0
A18: KNGSPN | C18: MSID: 1027 | G18: KNGSPN | H18: 4 | I18: 0.13 | J18: 66928.99 | K18: 2.16 | L18: 2.16 | M18: 0 | N18: 0 | O18: 0 | P18: 0
A19: NP_LAB | B19: 837 | C19: 1900047386380 | G19: NP_LAB | H19: 1 | I19: 1.888 | J19: 3238.38 | K19: 3.07 | L19: 3.07 | M19: 0 | N19: 0 | O19: 0 | P19: 0
A20: NR_3BR | B20: 866 | C20: 1900060219145 | G20: NR_3BR | H20: 4 | I20: 0.815 | J20: 68534.37 | K20: 2.73 | L20: 2.73 | M20: 0 | N20: 0 | O20: 0 | P20: 0
A21: NR_AFD | B21: 851 | C21: 1900060219377 | G21: NR_AFD | H21: 3 | I21: 1.802 | J21: 36594.39 | K21: 2.42 | L21: 2.42 | M21: 0 | N21: 0 | O21: 0 | P21: 0
A22: NR_ASH | B22: 879 | C22: 1900070068129 | G22: NR_ASH | H22: 3 | I22: 0.341 | J22: 36594.39 | K22: 2.78 | L22: 2.78 | M22: 0 | N22: 0 | O22: 0 | P22: 0
A23: NR_BRI | B23: 852 | C23: 1900060218675 | G23: NR_BRI | H23: 4 | I23: 0.405 | J23: 68534.37 | K23: 2.22 | L23: 2.22 | M23: 0 | N23: 0 | O23: 0 | P23: 0
A24: NR_BYF | B24: 853 | C24: 1900060218727 | G24: NR_BYF | H24: 4 | I24: 0.364 | J24: 68534.37 | K24: 1.95 | L24: 1.95 | M24: 0 | N24: 0 | O24: 0 | P24: 0
A25: NR_CAN | B25: 854 | C25: 1900060218790 | G25: NR_CAN | H25: 2 | I25: 0.015 | J25: 16959.97 | K25: 2.56 | L25: 2.56 | M25: 0 | N25: 0 | O25: 0 | P25: 0
A26: NR_CRO | B26: 855 | C26: 1900060218815 | G26: NR_CRO | H26: 4 | I26: 0.021 | J26: 67999.24 | K26: 2.11 | L26: 2.11 | M26: 0 | N26: 0 | O26: 0 | P26: 0
A27: NR_DOR | B27: 856 | C27: 1900060219303 | G27: NR_DOR | H27: 2 | I27: 4.623 | J27: 16959.97 | K27: 2.3 | L27: 2.3 | M27: 0 | N27: 0 | O27: 0 | P27: 0
A28: NR_EAS | B28: 857 | C28: 1900060218912 | G28: NR_EAS | H28: 2 | I28: 1.26 | J28: 16959.97 | K28: 3.08 | L28: 3.08 | M28: 0 | N28: 0 | O28: 0 | P28: 0
A29: NR_FOK | B29: 858 | C29: 1900060218959 | G29: NR_FOK | H29: 2 | I29: 1.451 | J29: 16959.97 | K29: 1.97 | L29: 1.97 | M29: 0 | N29: 0 | O29: 0 | P29: 0
A30: NR_HAS | B30: 859 | C30: 1900060218986 | G30: NR_HAS | H30: 2 | I30: 0 | J30: 22539.41 | K30: 2.92 | L30: 2.92 | M30: 0 | N30: 0 | O30: 0 | P30: 0
... A34: NR_QUE | B34: 863 | C34: 1900060219084 | G34: NR_QUE | H34: 1 | I34: 0 | J34: 3054.42 | K34: 1.33 | L34: 1.33 | M34: 0 | N34: 0 | O34: 0 | P34: 0
A35: NR_SIT | B35: 864 | C35: 1900060219819;1900060219855 | G35: NR_SIT | H35: 3 | I35: 0 | J35: 36594.39 | K35: 1.82 | L35: 1.82 | M35: 0 | N35: 0 | O35: 0 | P35: 0
A36: NR_THA | B36: 865 | C36: 1900060219720;1900060219794 | G36: NR_THA | H36: 2 | I36: 1.788 | J36: 16959.97 | K36: 2.43 | L36: 2.43 | M36: 0 | N36: 0 | O36: 0 | P36: 0
A37: NR_TUN | B37: 867 | C37: 1900060219206 | G37: NR_TUN | H37: 3 | I37: 7.341 | J37: 36594.39 | K37: 2.9 | L37: 2.9 | M37: 0 | N37: 0 | O37: 0 | P37: 0
A38: PFIZER | B38: 881 | C38: 1900060219544 | F38: 1900060858356 | G38: PFIZER | H38: 2 | I38: 0 | J38: 19440.83 | K38: 1.14 | L38: 1.14 | M38: 0 | N38: 0 | O38: 0 | P38: 0
A39: SENTIV | B39: 888 | C39: 1900090497281;1900090497290;1900090497306;1900090497315 | G39: SENTIV | H39: 4 | I39: 0.05 | J39: 183985.57 | K39: 1.39 | L39: 1.39 | M39: 0 | N39: 0 | O39: 0 | P39: 0
A40: THAMEM | B40: 838 | C40: 1900090872672;1900090872681 | D40: THAMEM | E40: 691 | F40: 1900090876979;1900090876988 | G40: THAMEM | H40: 4 | I40: 0 | J40: 73474.95 | K40: 1.6 | L40: 1.6 | M40: 0 | N40: 4909.47 | O40: 0.05 | P40: 0.05
A41: THAMES | B41: 884 | C41: 1900016424857 | D41: THAMES | E41: 732 | F41: 1900060576611 | G41: THAMES | H41: 2 | I41: 0.756 | J41: 20906.49 | K41: 3.14 | L41: 3.14 | M41: -0.482 | N41: 2943.17 | O41: 0.05 | P41: 0.05
A42: TWHK66 | B42: 839 | C42: 1900091206176 | D42: TWHK66 | E42: 692 | F42: 1900091206194 | G42: TWHK66 | H42: 2 | I42: 7.429 | J42: 16211.32 | K42: 2.34 | L42: 2.34 | M42: -8.002 | N42: 51.46 | O42: 0.05 | P42: 0.05
A43: ANMSTR | B43: 873 | C43: 1900091919588 | D43: ANMSTR | E43: 780 | F43: 1900091919597 | G43: ANMSTR | H43: 0 | I43: 2.153 | J43: 58.21 | K43: 1.02 | L43: 1.02 | M43: -2.153 | N43: 1633.73 | O43: 0.05 | P43: 0.05
A44: ASHBYS | B44: 809 | C44: 1900091216963 | D44: ASHBYS | E44: 741 | F44: 1900091216972 | G44: ASHBYS | H44: 0 | I44: 5.143 | J44: 16.42 | K44: 1.9 | L44: 1.9 | M44: 0 | N44: 1674.86 | O44: 0.05 | P44: 0.05
A45: AYLESF | B45: 868 | C45: 1900060216613 | D45: AYLESF | E45: 725 | F45: 1900060436880 | G45: AYLESF | H45: 4 | I45: 0.045 | J45: 67518.21 | K45: 0.8 | L45: 0.8 | M45: 0 | N45: 0 | O45: 0 | P45: 0
A46: BEDERF | B46: 840 | C46: 1900091482588 | D46: BEDERF | E46: 693 | F46: 1900091482597 | G46: BEDERF | H46: 0 | I46: 0.201 | J46: 577.83 | K46: 1 | L46: 1 | M46: -0.317 | N46: 4105.64 | O46: 0.05 | P46: 0.05
A47: BESAYL | B47: 841 | C47: 1900091632775 | D47: BESAYL | E47: 694 | F47: 1900091632784 | G47: BESAYL | H47: 0 | I47: 0.045 | J47: 589.22 | K47: 0.9 | L47: 0.9 | M47: -0.087 | N47: 589.22 | O47: 0.05 | P47: 0.05
A48: BNTLEY | B48: 890 | C48: 1900091343778 | D48: BNTLEY | E48: 713 | F48: 1900091343787 | G48: BNTLEY | H48: 0 | I48: 6.286 | J48: 14.77 | K48: 1.3 | L48: 1.3 | M48: 0 | N48: 1477.43 | O48: 0.05 | P48: 0.05
A49: BNTLY2 | B49: 830 | C49: 1900091463646 | D49: BNTLY2 | E49: 712 | F49: 1900091463655 | G49: BNTLY2 | H49: 0 | I49: 6.286 | J49: 11.26 | K49: 1.58 | L49: 1.58 | M49: 0 | N49: 945.82 | O49: 0.05 | P49: 0.05
A50: BOBBNG | B50: 891 | C50: 1900091395508 | D50: BOBBNG | E50: 705 | F50: 1900091395517 | G50: BOBBNG | H50: 0 | I50: 0 | J50: 8.02 | K50: 2.63 | L50: 2.63 | M50: 0 | N50: 1603.2 | O50: 0.05 | P50: 0.05
A51: BRAMBS | B51: 842 | C51: 1900091566810 | D51: BRAMBS | E51: 695 | F51: 1900091566820 | G51: BRAMBS | H51: 0 | I51: 0.289 | J51: 589.22 | K51: 1.26 | L51: 1.26 | M51: -0.6 | N51: 589.22 | O51: 0.05 | P51: 0.05
A52: BRELLE | B52: 843 | C52: 1900091523116 | D52: BRELLE | E52: 696 | F52: 1900091523125 | G52: BRELLE | H52: 1 | I52: 0 | J52: 2549.85 | K52: 1.34 | L52: 1.34 | M52: 0 | N52: 1229.03 | O52: 0.05 | P52: 0.05
A53: BRETSH | B53: 871 | C53: 1900061003393;1900090466576 | D53: BRETSH | E53: 726 | F53: 1900060866064;1900060866082 | G53: BRETSH | H53: 0 | I53: 0.014 | J53: 38.36 | K53: 1.18 | L53: 1.18 | M53: 0 | N53: 0 | O53: 0 | P53: 0
A54: BRKHST | B54: 802 | C54: 1900090834409 | D54: BRKHST | E54: 738 | F54: 1900090834418 | G54: BRKHST | H54: 2 | I54: 1.52 | J54: 18665.83 | K54: 3.84 | L54: 3.84 | M54: -4.734 | N54: 8247.87 | O54: 0.05 | P54: 0.05
A55: BTBRKS | B55: 810 | C55: 1900091199350 | D55: BTBRKS | E55: 742 | F55: 1900091199379 | G55: BTBRKS | H55: 1 | I55: 0.499 | J55: 2575.35 | K55: 1.51 | L55: 1.51 | M55: 0 | N55: 1846.86 | O55: 0.05 | P55: 0.05
A56: CAPELG | B56: 893 | C56: 1900091353298 | D56: CAPELG | E56: 706 | F56: 1900091353303 | G56: CAPELG | H56: 0 | I56: 7.592 | J56: 1.47 | K56: 4.72 | L56: 4.72 | M56: 0 | N56: 1198.62 | O56: 0.05 | P56: 0.05
A57: CLYHLL | B57: 894 | C57: 1900091343750 | D57: CLYHLL | E57: 716 | F57: 1900091343769 | G57: CLYHLL | H57: 0 | I57: 1.368 | J57: 11.13 | K57: 3.46 | L57: 3.46 | M57: 0 | N57: 1113.22 | O57: 0.05 | P57: 0.05
A58: CRYENG | C58: MSID: 7441 | D58: CRYENG | F58: MSID: 7442 | G58: CRYENG | H58: 0 | I58: 0 | J58: 191.17 | K58: 0.92 | L58: 0.92 | M58: -0.002 | N58: 509.79 | O58: 0.05 | P58: 0.05
A59: CWSTBS | C59: ENET | D59: CWSTBS | F59: ENET | G59: CWSTBS | H59: 0 | I59: 0 | J59: 28.81 | K59: 0.59 | L59: 0.59 | M59: 0 | N59: 28.81 | O59: 0.05 | P59: 0.05
A60: DARENT | B60: 836 | C60: 1900091057568 | D60: DARENT | E60: 767 | F60: 1900091057559 | G60: DARENT | H60: 1 | I60: 0 | J60: 2712.53 | K60: 0.97 | L60: 0.97 | M60: 0 | N60: 3392.49 | O60: 0.05 | P60: 0.05
A61: DSCPRK | B61: 804 | C61: 1900091637072 | D61: DSCPRK | E61: 704 | F61: 1900091637081 | G61: DSCPRK | H61: 3 | I61: 0 | J61: 37070.63 | K61: 0.79 | L61: 0.79 | M61: 0 | N61: 2071.7 | O61: 0.05 | P61: 0.05
A62: FORDSF | B62: 895 | C62: 1900091361962 | D62: FORDSF | E62: 707 | F62: 1900091361971 | G62: FORDSF | H62: 0 | I62: 0.275 | J62: 19.34 | K62: 1.92 | L62: 1.92 | M62: 0 | N62: 1105.02 | O62: 0.05 | P62: 0.05
A63: FRWOOD | B63: 811 | C63: 1900091200388 | D63: FRWOOD | E63: 743 | F63: 1900091200397 | G63: FRWOOD | H63: 0 | I63: 0 | J63: 30.53 | K63: 1.38 | L63: 1.38 | M63: 0 | N63: 1526.59 | O63: 0.05 | P63: 0.05
A64: GLASSN | B64: 844 | C64: 1900091523301;1900092049178 | D64: GLASSN | E64: 697 | F64: 1900091523310;1900092037980 | G64: GLASSN | H64: 0 | I64: 0 | J64: 654.88 | K64: 1.6 | L64: 1.6 | M64: -1.034 | N64: 654.88 | O64: 0.05 | P64: 0.05
A65: GROVEH | B65: 875 | C65: 1900060225185 | D65: GROVEH | E65: 727 | F65: 1900060225194 | G65: GROVEH | H65: 4 | I65: 0 | J65: 67630.79 | K65: 1.27 | L65: 1.27 | M65: 0 | N65: 0 | O65: 0 | P65: 0
A66: GUSTON | B66: 831 | C66: 1900091338040 | D66: GUSTON | E66: 708 | F66: 1900091338059 | G66: GUSTON | H66: 0 | I66: 5.225 | J66: 25.83 | K66: 1.45 | L66: 1.45 | M66: 0 | N66: 2582.93 | O66: 0.05 | P66: 0.05
A67: HADLOW | B67: 812 | C67: 1900091217043 | D67: HADLOW | E67: 744 | F67: 1900091217052 | G67: HADLOW | H67: 0 | I67: 4.106 | J67: 3.11 | K67: 3.5 | L67: 3.5 | M67: 0 | N67: 1175.34 | O67: 0.05 | P67: 0.05
A68: HANSTA | B68: 876 | C68: 1900004383769;1900031426056 | D68: HANSTA | E68: 728 | F68: 1900060442174;1900060512032 | G68: HANSTA | H68: 0 | I68: 4.446 | J68: 3.08 | K68: 0.92 | L68: 0.92 | M68: 0 | N68: 0 | O68: 0 | P68: 0
A69: HLLMBY | B69: 813 | C69: 1900091217070 | D69: HLLMBY | E69: 745 | F69: 1900091217080 | G69: HLLMBY | H69: 0 | I69: 0 | J69: 16.05 | K69: 1.27 | L69: 1.27 | M69: 0 | N69: 1293.72 | O69: 0.05 | P69: 0.05
A70: HORAMS | B70: 824 | C70: 1900091200068 | D70: HORAMS | E70: 701 | F70: 1900091200077 | G70: HORAMS | H70: 0 | I70: 0 | J70: 22.46 | K70: 3.79 | L70: 3.79 | M70: 0 | N70: 2919.53 | O70: 0.05 | P70: 0.05
A71: KENTI2 | B71: 814 | C71: 1900091199519 | D71: KENTI2 | E71: 746 | F71: 1900091199528 | G71: KENTI2 | H71: 1 | I71: 0 | J71: 2506.35 | K71: 0.87 | L71: 0.87 | M71: 0 | N71: 521.02 | O71: 0.05 | P71: 0.05
A72: KENTIS | B72: 877 | C72: 1900070122273 | D72: KENTIS | E72: 722 | F72: 1900070122343 | G72: KENTIS | H72: 1 | I72: 0 | J72: 2518.19 | K72: 0.87 | L72: 0.87 | M72: 0 | N72: 0 | O72: 0 | P72: 0
A73: KM3CHP | B73: 846 | C73: 1900091669720 | D73: KM3CHP | E73: 699 | F73: 1900091669739 | G73: KM3CHP | H73: 2 | I73: 0 | J73: 16333.77 | K73: 0.89 | L73: 0.89 | M73: 0 | N73: 4207.52 | O73: 0.05 | P73: 0.05
A74: KNTSFM | C74: MSID: 7435 | D74: KNTSFM | F74: MSID: 7436 | G74: KNTSFM | H74: 0 | I74: 0.828 | J74: 1259.15 | K74: 0.8 | L74: 0.8 | M74: -0.796 | N74: 1325.81 | O74: 0.05 | P74: 0.05
A75: KNWLTN | B75: 803 | C75: 1900091091930 | D75: KNWLTN | E75: 735 | F75: 1900091091940 | G75: KNWLTN | H75: 0 | I75: 0 | J75: 23.1 | K75: 5.05 | L75: 5.05 | M75: 0 | N75: 2183.18 | O75: 0.05 | P75: 0.05
A76: LBOURN | B76: 815 | C76: 1900091171267 | D76: LBOURN | E76: 747 | F76: 1900091171276 | G76: LBOURN | H76: 0 | I76: 0 | J76: 13.41 | K76: 3.41 | L76: 3.41 | M76: 0 | N76: 1257.01 | O76: 0.05 | P76: 0.05
A77: LCHEYI | B77: 878 | C77: 1900090194653 | D77: LCHEYI | E77: 721 | F77: 1900090194644 | G77: LCHEYI | H77: 0 | I77: 0.15 | J77: 10.01 | K77: 2.93 | L77: 2.93 | M77: 0 | N77: 1299.75 | O77: 0.05 | P77: 0.05
A78: LENHAM | B78: 808 | C78: 1900091081560 | D78: LENHAM | E78: 736 | F78: 1900091081570 | G78: LENHAM | H78: 0 | I78: 6.39 | J78: 21.84 | K78: 1.83 | L78: 1.83 | M78: 0 | N78: 2184.44 | O78: 0.05 | P78: 0.05
A79: LGHTON | B79: 816 | C79: 1900091200138 | D79: LGHTON | E79: 748 | F79: 1900091200147 | G79: LGHTON | H79: 0 | I79: 3.834 | J79: 18.73 | K79: 3.78 | L79: 3.78 | M79: 0 | N79: 1311.19 | O79: 0.05 | P79: 0.05
A80: MARSHB | B80: 896 | C80: 1900091310596 | D80: MARSHB | E80: 709 | F80: 1900091310601 | G80: MARSHB | H80: 0 | I80: 0 | J80: 34.15 | K80: 1.19 | L80: 1.19 | M80: 0 | N80: 1393.15 | O80: 0.05 | P80: 0.05
A81: MLEHLL | B81: 819 | C81: 1900091183402 | D81: MLEHLL | E81: 751 | F81: 1900091183411 | G81: MLEHLL | H81: 0 | I81: 0.002 | J81: 4.25 | K81: 1.71 | L81: 1.71 | M81: 0 | N81: 530.88 | O81: 0.05 | P81: 0.05
A82: MLMAYN | B82: 817 | C82: 1900091079241 | D82: MLMAYN | E82: 749 | F82: 1900091079232 | G82: MLMAYN | H82: 0 | I82: 0 | J82: 2.34 | K82: 2.85 | L82: 2.85 | M82: 0 | N82: 1122.02 | O82: 0.05 | P82: 0.05
A83: MVVRID | B83: 897 | C83: 1900091199138 | D83: MVVRID | E83: 710 | F83: 1900091199147 | G83: MVVRID | H83: 0 | I83: 0 | J83: 2815.57 | K83: 0.71 | L83: 0.71 | M83: 0 | N83: 14809.91 | O83: 0.05 | P83: 0.05
A84: NEWHVN | B84: 800 | C84: 1900090585014 | D84: NEWHVN | E84: 700 | F84: 1900090585005 | G84: NEWHVN | H84: 0 | I84: 1.53 | J84: 66.89 | K84: 1.05 | L84: 1.05 | M84: -1.668 | N84: 468.24 | O84: 0.05 | P84: 0.05
A85: NEWRID | B85: 845 | C85: 1900091718313;1900092210410 | D85: NEWRID | E85: 698 | F85: 1900091718322 | G85: NEWRID | H85: 1 | I85: 0.018 | J85: 2498.23 | K85: 1.59 | L85: 1.59 | M85: 0 | N85: 2395.04 | O85: 0.05 | P85: 0.05
A86: OAKLND | B86: 820 | C86: 1900091197414 | D86: OAKLND | E86: 752 | F86: 1900091197423 | G86: OAKLND | H86: 0 | I86: 1.744 | J86: 9.75 | K86: 3.77 | L86: 3.77 | M86: 0 | N86: 1071.33 | O86: 0.05 | P86: 0.05
A87: OLDRSF | B87: 805 | C87: 1900091024517 | D87: OLDRSF | E87: 739 | F87: 1900091024526 | G87: OLDRSF | H87: 0 | I87: 0 | J87: 7.05 | K87: 2.04 | L87: 2.04 | M87: 0 | N87: 1409.43 | O87: 0.05 | P87: 0.05
A88: ORCHRD | B88: 898 | C88: 1900091085120;1900091349715;1900091349706 | D88: ORCHRD | E88: 753 | F88: 1900091085110;1900091349724;1900091349733 | G88: ORCHRD | H88: 0 | I88: 0 | J88: 8.84 | K88: 2.43 | L88: 2.43 | M88: 0 | N88: 1591.56 | O88: 0.05 | P88: 0.05
A89: PADWSF | B89: 822 | C89: 1900091216634 | D89: PADWSF | E89: 754 | F89: 1900091216643 | G89: PADWSF | H89: 0 | I89: 12.693 | J89: 7.39 | K89: 1.51 | L89: 1.51 | M89: 0 | N89: 1171.06 | O89: 0.05 | P89: 0.05
A90: POSHWF | B90: 827 | C90: 1900091227307 | D90: POSHWF | E90: 719 | F90: 1900091227316 | G90: POSHWF | H90: 0 | I90: 0 | J90: 10.49 | K90: 0.95 | L90: 0.95 | M90: 0 | N90: 524.64 | O90: 0.05 | P90: 0.05
A91: PRIORS | B91: 899 | C91: 1900091319942 | D91: PRIORS | E91: 717 | F91: 1900091320006 | G91: PRIORS | H91: 0 | I91: 1.734 | J91: 7.35 | K91: 1.53 | L91: 1.53 | M91: 0 | N91: 1106.18 | O91: 0.05 | P91: 0.05
A92: PSHLEY | B92: 826 | C92: 1900091178954 | D92: PSHLEY | E92: 703 | F92: 1900091178963 | G92: PSHLEY | H92: 0 | I92: 0 | J92: 19.97 | K92: 1.89 | L92: 1.89 | M92: 0 | N92: 1996.97 | O92: 0.05 | P92: 0.05
A93: SELLSF | B93: 900 | C93: 1900091360950 | D93: SELLSF | E93: 720 | F93: 1900091360969 | G93: SELLSF | H93: 0 | I93: 0.449 | J93: 6.32 | K93: 1.57 | L93: 1.57 | M93: 0 | N93: 1226.22 | O93: 0.05 | P93: 0.05
A94: SEVIND | C94: MSID: 7160 | D94: SEVIND | F94: MSID: 7160 | G94: SEVIND | H94: 0 | I94: 3.749 | J94: 2.3 | K94: 2.84 | L94: 2.84 | M94: -3.749 | N94: 184.23 | O94: 0.05 | P94: 0.05
A95: SHEPHM | B95: 832 | C95: 1900091420128 | D95: SHEPHM | E95: 718 | F95: 1900091420137 | G95: SHEPHM | H95: 0 | I95: 2.366 | J95: 78.23 | K95: 1.4 | L95: 1.4 | M95: 0 | N95: 2933.66 | O95: 0.05 | P95: 0.05
A96: SHORHM | C96: MSID: 7104 | D96: SHORHM | F96: MSID: 7104 | G96: SHORHM | H96: 2 | I96: 0.005 | J96: 16376.02 | K96: 1.42 | L96: 1.42 | M96: 0 | N96: 0 | O96: 0 | P96: 0
A97: SOLEES | B97: 823 | C97: 1900091121257;1900091121275 | D97: SOLEES | E97: 755 | F97: 1900091121266;1900091121284 | G97: SOLEES | H97: 0 | I97: 0.009 | J97: 64.88 | K97: 1.26 | L97: 1.26 | M97: 0 | N97: 2724.79 | O97: 0.05 | P97: 0.05
A98: STAREN | B98: 883 | C98: 1900060830217 | D98: STAREN | E98: 729 | F98: 1900060830226 | G98: STAREN | H98: 1 | I98: 4.093 | J98: 4707.27 | K98: 1.27 | L98: 1.27 | M98: 0 | N98: 0 | O98: 0 | P98: 0
A99: SYCAMR | B99: 807 | C99: 1900091090096 | D99: SYCAMR | E99: 737 | F99: 1900091090101 | G99: SYCAMR | H99: 0 | I99: 1.518 | J99: 98.37 | K99: 2.75 | L99: 2.75 | M99: 0 | N99: 3541.46 | O99: 0.05 | P99: 0.05
A100: THAEAR | B100: 850 | C100: 1900090417081;1900090417106;1900090417133;1900090417142;1900090417151 | D100: THAEAR | E100: 733 | F100: 1900090417160;1900090417189;1900090417212;1900090417221;1900090417230 | G100: THAEAR | H100: 4 | I100: 0 | J100: 72404.61 | K100: 1.74 | L100: 1.74 | M100: -1.229 | N100: 5475.62 | O100: 0.05 | P100: 0.05
A101: THANET | C101: MSID: 7246 | D101: THANET | F101: MSID: 7246 | G101: THANET | H101: 1 | I101: 0.086 | J101: 2516.87 | K101: 1.75 | L101: 1.75 | M101: 0 | N101: 2594.9 | O101: 0.05 | P101: 0.05
A102: THORNE | B102: 818 | C102: 1900091171364 | D102: THORNE | E102: 750 | F102: 1900091171373 | G102: THORNE | H102: 0 | I102: 0 | J102: 33.33 | K102: 1.61 | L102: 1.61 | M102: 0 | N102: 3465.86 | O102: 0.05 | P102: 0.05
A103: TONGSF | B103: 828 | C103: 1900091363000 | D103: TONGSF | E103: 711 | F103: 1900091363019 | G103: TONGSF | H103: 1 | I103: 0.682 | J103: 2542.91 | K103: 1.3 | L103: 1.3 | M103: 0 | N103: 3940.79 | O103: 0.05 | P103: 0.05
A104: WDLNDS | B104: 825 | C104: 1900091207124 | D104: WDLNDS | E104: 702 | F104: 1900091207133 | G104: WDLNDS | H104: 0 | I104: 0.015 | J104: 37.46 | K104: 1.7 | L104: 1.7 | M104: 0 | N104: 4494.97 | O104: 0.05 | P104: 0.05
A105: WIDHFM | B105: 821 | C105: 1900091478493 | D105: WIDHFM | E105: 714 | F105: 1900091478509 | G105: WIDHFM | H105: 0 | I105: 4.885 | J105: 29.24 | K105: 1.7 | L105: 1.7 | M105: 0 | N105: 2339.33 | O105: 0.05 | P105: 0.05
...

Sheet Annex 2a Import
A1: Note: The list of MPANs / MSIDs provided may be incomplete; the DNO reserves the right to apply the listed charges to any other MPANs / MSIDs associated with the site. Note: This table is automatically populated based on the content of the tab entitled 'Annex 2 EHV Charges'. The timebands are as shown in Annex 2.
A2: =Overview!B4& " - Effective from "&Overview!D4&" - "&Overview!E4&" EDCM import charges" -> South Eastern Power Networks - Effective from 1 April 2024 - Final EDCM import charges
A4: Import Unique Identifier | B4: LLFC | C4: Import MPANs/MSIDs | D4: Name | E4: ='Annex 2 EHV charges'!I9 -> Import Super Red unit charge (p/kWh) | F4: ='Annex 2 EHV charges'!J9 -> Import fixed charge (p/day) | G4: ='Annex 2 EHV charges'!K9 -> Import capacity charge (p/kVA/day) | H4: ='Annex 2 EHV charges'!L9 -> Import exceeded capacity charge (p/kVA/day)
A5: {=IFERROR(INDEX('Annex 2 EHV charges'!$A$10:$A$108, MATCH(0, IF(ISBLANK('Annex 2 EHV charges'!$A$10:$A$108),1, COUNTIF(A$4:$A4, 'Annex 2 EHV charges'!$A$10:$A$108)), 0)),"")} -> B&RLTD | B5: =IF($A5="","",VLOOKUP($A5,'Annex 2 EHV charges'!$A:$O,2,0)) -> 834 | C5: =IF($A5="","",VLOOKUP($A5,'Annex 2 EHV charges'!$A:$O,3,0)) -> 1900035000482;1900035425153 | D5: =IF($A5="","",VLOOKUP($A5,'Annex 2 EHV charges'!$A:$O,7,0)) -> B&RLTD | E5: =IFERROR(IF(VLOOKUP($A5,'Annex 2 EHV charges'!$A:$O,9,FALSE)=0,"",VLOOKUP($A5,'Annex 2 EHV charges'!$A:$O,9,FALSE)),"") -> 1.862 | F5: =IFERROR(IF(VLOOKUP($A5,'Annex 2 EHV charges'!$A:$O,10,FALSE)=0,"",VLOOKUP($A5,'Annex 2 EHV charges'!$A:$O,10,FALSE)),"") -> 2865.31 | G5: =IFERROR(IF(VLOOKUP($A5,'Annex 2 EHV charges'!$A:$O,11,FALSE)=0,"",VLOOKUP($A5,'Annex 2 EHV charges'!$A:$O,11,FALSE)),"") -> 2.97 | H5: =IFERROR(IF(VLOOKUP($A5,'Annex 2 EHV charges'!$A:$O,12,FALSE)=0,"",VLOOKUP($A5,'Annex 2 EHV charges'!$A:$O,12,FALSE)),"") -> 2.97
A6: {=IFERROR(INDEX('Annex 2 EHV charges'!$A$10:$A$108, MATCH(0, IF(ISBLANK('Annex 2 EHV charges'!$A$10:$A$108),1, COUNTIF(A$4:$A5, 'Annex 2 EHV charges'!$A$10:$A$108)), 0)),"")} -> BEDDIN | B6: =IF($A6="","",VLOOKUP($A6,'Annex 2 EHV charges'!$A:$O,2,0)) -> 889 | C6: =IF($A6="","",VLOOKUP($A6,'Annex 2 EHV charges'!$A:$O,3,0)) -> 1900070745640;1900070745650;1900070745669;1900070745678 | D6: =IF($A6="","",VLOOKUP($A6,'Annex 2 EHV charges'!$A:$O,7,0)) -> BEDDIN | E6: =IFERROR(IF(VLOOKUP($A6,'Annex 2 EHV charges'!$A:$O,9,FALSE)=0,"",VLOOKUP($A6,'Annex 2 EHV charges'!$A:$O,9,FALSE)),"") -> 0.005 | F6: =IFERROR(IF(VLOOKUP($A6,'Annex 2 EHV charges'!$A:$O,10,FALSE)=0,"",VLOOKUP($A6,'Annex 2 EHV charges'!$A:$O,10,FALSE)),"") -> 16076.25 | G6: =IFERROR(IF(VLOOKUP($A6,'Annex 2 EHV charges'!$A:$O,11,FALSE)=0,"",VLOOKUP($A6,'Annex 2 EHV charges'!$A:$O,11,FALSE)),"") -> 1.45 | H6: =IFERROR(IF(VLOOKUP($A6,'Annex 2 EHV charges'!$A:$O,12,FALSE)=0,"",VLOOKUP($A6,'Annex 2 EHV charges'!$A:$O,12,FALSE)),"") -> 1.45
A7: {=IFERROR(INDEX('Annex 2 EHV charges'!$A$10:$A$108, MATCH(0, IF(ISBLANK('Annex 2 EHV charges'!$A$10:$A$108),1, COUNTIF(A$4:$A6, 'Annex 2 EHV charges'!$A$10:$A$108)), 0)),"")} -> BP_OIL | B7: =IF($A7="","",VLOOKUP($A7,'Annex 2 EHV charges'!$A:$O,2,0)) -> 835 | C7: =IF($A7="","",VLOOKUP($A7,'Annex 2 EHV charges'!$A:$O,3,0)) -> 1900017426438;1900017426447 | D7: =IF($A7="","",VLOOKUP($A7,'Annex 2 EHV charges'!$A:$O,7,0)) -> BP_OIL | E7: =IFERROR(IF(VLOOKUP($A7,'Annex 2 EHV charges'!$A:$O,9,FALSE)=0,"",VLOOKUP($A7,'Annex 2 EHV charges'!$A:$O,9,FALSE)),"") -> 0.312 | F7: =IFERROR(IF(VLOOKUP($A7,'Annex 2 EHV charges'!$A:$O,10,FALSE)=0,"",VLOOKUP($A7,'Annex 2 EHV charges'!$A:$O,10,FALSE)),"") -> 2865.31 | G7: =IFERROR(IF(VLOOKUP($A7,'Annex 2 EHV charges'!$A:$O,11,FALSE)=0,"",VLOOKUP($A7,'Annex 2 EHV charges'!$A:$O,11,FALSE)),"") -> 1.43 | H7: =IFERROR(IF(VLOOKUP($A7,'Annex 2 EHV charges'!$A:$O,12,FALSE)=0,"",VLOOKUP($A7,'Annex 2 EHV charges'!$A:$O,12,FALSE)),"") -> 1.43
A8: {=IFERROR(INDEX('Annex 2 EHV charges'!$A$10:$A$108, MATCH(0, IF(ISBLANK('Annex 2 EHV charges'!$A$10:$A$108),1, COUNTIF(A$4:$A7, 'Annex 2 EHV charges'!$A$10:$A$108)), 0)),"")} -> CHESDC | B8: =IF($A8="","",VLOOKUP($A8,'Annex 2 EHV charges'!$A:$O,2,0)) -> 0 | C8: =IF($A8="","",VLOOKUP($A8,'Annex 2 EHV charges'!$A:$O,3,0)) -> ENET | D8: =IF($A8="","",VLOOKUP($A8,'Annex 2 EHV charges'!$A:$O,7,0)) -> CHESDC | E8: =IFERROR(IF(VLOOKUP($A8,'Annex 2 EHV charges'!$A:$O,9,FALSE)=0,"",VLOOKUP($A8,'Annex 2 EHV charges'!$A:$O,9,FALSE)),"") -> 0.004 | F8: =IFERROR(IF(VLOOKUP($A8,'Annex 2 EHV charges'!$A:$O,10,FALSE)=0,"",VLOOKUP($A8,'Annex 2 EHV charges'!$A:$O,10,FALSE)),"") -> 33041.98 | G8: =IFERROR(IF(VLOOKUP($A8,'Annex 2 EHV charges'!$A:$O,11,FALSE)=0,"",VLOOKUP($A8,'Annex 2 EHV charges'!$A:$O,11,FALSE)),"") -> 0.99 | H8: =IFERROR(IF(VLOOKUP($A8,'Annex 2 EHV charges'!$A:$O,12,FALSE)=0,"",VLOOKUP($A8,'Annex 2 EHV charges'!$A:$O,12,FALSE)),"") -> 0.99
A9: {=IFERROR(INDEX('Annex 2 EHV charges'!$A$10:$A$108, MATCH(0, IF(ISBLANK('Annex 2 EHV charges'!$A$10:$A$108),1, COUNTIF(A$4:$A8, 'Annex 2 EHV charges'!$A$10:$A$108)), 0)),"")} -> DIGREA | B9: =IF($A9="","",VLOOKUP($A9,'Annex 2 EHV charges'!$A:$O,2,0)) -> 833 | C9: =IF($A9="","",VLOOKUP($A9,'Annex 2 EHV charges'!$A:$O,3,0)) -> 1900091200323;1900091200332 | D9: =IF($A9="","",VLOOKUP($A9,'Annex 2 EHV charges'!$A:$O,7,0)) -> DIGREA | E9: =IFERROR(IF(VLOOKUP($A9,'Annex 2 EHV charges'!$A:$O,9,FALSE)=0,"",VLOOKUP($A9,'Annex 2 EHV charges'!$A:$O,9,FALSE)),"") | F9: =IFERROR(IF(VLOOKUP($A9,'Annex 2 EHV charges'!$A:$O,10,FALSE)=0,"",VLOOKUP($A9,'Annex 2 EHV charges'!$A:$O,10,FALSE)),"") -> 69548.53 | G9: =IFERROR(IF(VLOOKUP($A9,'Annex 2 EHV charges'!$A:$O,11,FALSE)=0,"",VLOOKUP($A9,'Annex 2 EHV charges'!$A:$O,11,FALSE)),"") -> 1.86 | H9: =IFERROR(IF(VLOOKUP($A9,'Annex 2 EHV charges'!$A:$O,12,FALSE)=0,"",VLOOKUP($A9,'Annex 2 EHV charges'!$A:$O,12,FALSE)),"") -> 1.86
A10: {=IFERROR(INDEX('Annex 2 EHV charges'!$A$10:$A$108, MATCH(0, IF(ISBLANK('Annex 2 EHV charges'!$A$10:$A$108),1, COUNTIF(A$4:$A9, 'Annex 2 EHV charges'!$A$10:$A$108)), 0)),"")} -> EUROTU | B10: =IF($A10="","",VLOOKUP($A10,'Annex 2 EHV charges'!$A:$O,2,0)) -> 874 | C10: =IF($A10="","",VLOOKUP($A10,'Annex 2 EHV charges'!$A:$O,3,0)) -> 1900060219605 | D10: =IF($A10="","",VLOOKUP($A10,'Annex 2 EHV charges'!$A:$O,7,0)) -> EUROTU | E10: =IFERROR(IF(VLOOKUP($A10,'Annex 2 EHV charges'!$A:$O,9,FALSE)=0,"",VLOOKUP($A10,'Annex 2 EHV charges'!$A:$O,9,FALSE)),"") | F10: =IFERROR(IF(VLOOKUP($A10,'Annex 2 EHV charges'!$A:$O,10,FALSE)=0,"",VLOOKUP($A10,'Annex 2 EHV charges'!$A:$O,10,FALSE)),"") -> 220981.93 | G10: =IFERROR(IF(VLOOKUP($A10,'Annex 2 EHV charges'!$A:$O,11,FALSE)=0,"",VLOOKUP($A10,'Annex 2 EHV charges'!$A:$O,11,FALSE)),"") -> 0.74 | H10: =IFERROR(IF(VLOOKUP($A10,'Annex 2 EHV charges'!$A:$O,12,FALSE)=0,"",VLOOKUP($A10,'Annex 2 EHV charges'!$A:$O,12,FALSE)),"") -> 0.74
A11: {=IFERROR(INDEX('Annex 2 EHV charges'!$A$10:$A$108, MATCH(0, IF(ISBLANK('Annex 2 EHV charges'!$A$10:$A$108),1, COUNTIF(A$4:$A10, 'Annex 2 EHV charges'!$A$10:$A$108)), 0)),"")} -> GAT_AF | B11: =IF($A11="","",VLOOKUP($A11,'Annex 2 EHV charges'!$A:$O,2,0)) -> 869 | C11: =IF($A11="","",VLOOKUP($A11,'Annex 2 EHV charges'!$A:$O,3,0)) -> 1900017427938;1900017427947;1900060576620 | D11: =IF($A11="","",VLOOKUP($A11,'Annex 2 EHV charges'!$A:$O,7,0)) -> GAT_AF | E11: =IFERROR(IF(VLOOKUP($A11,'Annex 2 EHV charges'!$A:$O,9,FALSE)=0,"",VLOOKUP($A11,'Annex 2 EHV charges'!$A:$O,9,FALSE)),"") -> 0.746 | F11: =IFERROR(IF(VLOOKUP($A11,'Annex 2 EHV charges'!$A:$O,10,FALSE)=0,"",VLOOKUP($A11,'Annex 2 EHV charges'!$A:$O,10,FALSE)),"") -> 39690.72 | G11: =IFERROR(IF(VLOOKUP($A11,'Annex 2 EHV charges'!$A:$O,11,FALSE)=0,"",VLOOKUP($A11,'Annex 2 EHV charges'!$A:$O,11,FALSE)),"") -> 1.78 | H11: =IFERROR(IF(VLOOKUP($A11,'Annex 2 EHV charges'!$A:$O,12,FALSE)=0,"",VLOOKUP($A11,'Annex 2 EHV charges'!$A:$O,12,FALSE)),"") -> 1.78
A12: {=IFERROR(INDEX('Annex 2 EHV charges'!$A$10:$A$108, MATCH(0, IF(ISBLANK('Annex 2 EHV charges'!$A$10:$A$108),1, COUNTIF(A$4:$A11, 'Annex 2 EHV charges'!$A$10:$A$108)), 0)),"")} -> GAT_BF | B12: =IF($A12="","",VLOOKUP($A12,'Annex 2 EHV charges'!$A:$O,2,0)) -> 870 | C12: =IF($A12="","",VLOOKUP($A12,'Annex 2 EHV charges'!$A:$O,3,0)) -> 1900060690231;1900060690240 | D12: =IF($A12="","",VLOOKUP($A12,'Annex 2 EHV charges'!$A:$O,7,0)) -> GAT_BF | E12: =IFERROR(IF(VLOOKUP($A12,'Annex 2 EHV charges'!$A:$O,9,FALSE)=0,"",VLOOKUP($A12,'Annex 2 EHV charges'!$A:$O,9,FALSE)),"") -> 0.776 | F12: =IFERROR(IF(VLOOKUP($A12,'Annex 2 EHV charges'!$A:$O,10,FALSE)=0,"",VLOOKUP($A12,'Annex 2 EHV charges'!$A:$O,10,FALSE)),"") -> 36594.39 | G12: =IFERROR(IF(VLOOKUP($A12,'Annex 2 EHV charges'!$A:$O,11,FALSE)=0,"",VLOOKUP($A12,'Annex 2 EHV charges'!$A:$O,11,FALSE)),"") -> 1.91 | H12: =IFERROR(IF(VLOOKUP($A12,'Annex 2 EHV charges'!$A:$O,12,FALSE)=0,"",VLOOKUP($A12,'Annex 2 EHV charges'!$A:$O,12,FALSE)),"") -> 1.91
A13: {=IFERROR(INDEX('Annex 2 EHV charges'!$A$10:$A$108, MATCH(0, IF(ISBLANK('Annex 2 EHV charges'!$A$10:$A$108),1, COUNTIF(A$4:$A12, 'Annex 2 EHV charges'!$A$10:$A$108)), 0)),"")} -> KNGSPN | B13: =IF($A13="","",VLOOKUP($A13,'Annex 2 EHV charges'!$A:$O,2,0)) -> 0 | C13: =IF($A13="","",VLOOKUP($A13,'Annex 2 EHV charges'!$A:$O,3,0)) -> MSID: 1027 | D13: =IF($A13="","",VLOOKUP($A13,'Annex 2 EHV charges'!$A:$O,7,0)) -> KNGSPN | E13: =IFERROR(IF(VLOOKUP($A13,'Annex 2 EHV charges'!$A:$O,9,FALSE)=0,"",VLOOKUP($A13,'Annex 2 EHV charges'!$A:$O,9,FALSE)),"") -> 0.13 | F13: =IFERROR(IF(VLOOKUP($A13,'Annex 2 EHV charges'!$A:$O,10,FALSE)=0,"",VLOOKUP($A13,'Annex 2 EHV charges'!$A:$O,10,FALSE)),"") -> 66928.99 | G13: =IFERROR(IF(VLOOKUP($A13,'Annex 2 EHV charges'!$A:$O,11,FALSE)=0,"",VLOOKUP($A13,'Annex 2 EHV charges'!$A:$O,11,FALSE)),"") -> 2.16 | H13: =IFERROR(IF(VLOOKUP($A13,'Annex 2 EHV charges'!$A:$O,12,FALSE)=0,"",VLOOKUP($A13,'Annex 2 EHV charges'!$A:$O,12,FALSE)),"") -> 2.16
A14: {=IFERROR(INDEX('Annex 2 EHV charges'!$A$10:$A$108, MATCH(0, IF(ISBLANK('Annex 2 EHV charges'!$A$10:$A$108),1, COUNTIF(A$4:$A13, 'Annex 2 EHV charges'!$A$10:$A$108)), 0)),"")} -> NP_LAB | B14: =IF($A14="","",VLOOKUP($A14,'Annex 2 EHV charges'!$A:$O,2,0)) -> 837 | C14: =IF($A14="","",VLOOKUP($A14,'Annex 2 EHV charges'!$A:$O,3,0)) -> 1900047386380 | D14: =IF($A14="","",VLOOKUP($A14,'Annex 2 EHV charges'!$A:$O,7,0)) -> NP_LAB | E14: =IFERROR(IF(VLOOKUP($A14,'Annex 2 EHV charges'!$A:$O,9,FALSE)=0,"",VLOOKUP($A14,'Annex 2 EHV charges'!$A:$O,9,FALSE)),"") -> 1.888 | F14: =IFERROR(IF(VLOOKUP($A14,'Annex 2 EHV charges'!$A:$O,10,FALSE)=0,"",VLOOKUP($A14,'Annex 2 EHV charges'!$A:$O,10,FALSE)),"") -> 3238.38 | G14: =IFERROR(IF(VLOOKUP($A14,'Annex 2 EHV charges'!$A:$O,11,FALSE)=0,"",VLOOKUP($A14,'Annex 2 EHV charges'!$A:$O,11,FALSE)),"") -> 3.07 | H14: =IFERROR(IF(VLOOKUP($A14,'Annex 2 EHV charges'!$A:$O,12,FALSE)=0,"",VLOOKUP($A14,'Annex 2 EHV charges'!$A:$O,12,FALSE)),"") -> 3.07
A15: {=IFERROR(INDEX('Annex 2 EHV charges'!$A$10:$A$108, MATCH(0, IF(ISBLANK('Annex 2 EHV charges'!$A$10:$A$108),1, COUNTIF(A$4:$A14, 'Annex 2 EHV charges'!$A$10:$A$108)), 0)),"")} -> NR_3BR | B15: =IF($A15="","",VLOOKUP($A15,'Annex 2 EHV charges'!$A:$O,2,0)) -> 866 | C15: =IF($A15="","",VLOOKUP($A15,'Annex 2 EHV charges'!$A:$O,3,0)) -> 1900060219145 | D15: =IF($A15="","",VLOOKUP($A15,'Annex 2 EHV charges'!$A:$O,7,0)) -> NR_3BR | E15: =IFERROR(IF(VLOOKUP($A15,'Annex 2 EHV charges'!$A:$O,9,FALSE)=0,"",VLOOKUP($A15,'Annex 2 EHV charges'!$A:$O,9,FALSE)),"") -> 0.815 | F15: =IFERROR(IF(VLOOKUP($A15,'Annex 2 EHV charges'!$A:$O,10,FALSE)=0,"",VLOOKUP($A15,'Annex 2 EHV charges'!$A:$O,10,FALSE)),"") -> 68534.37 | G15: =IFERROR(IF(VLOOKUP($A15,'Annex 2 EHV charges'!$A:$O,11,FALSE)=0,"",VLOOKUP($A15,'Annex 2 EHV charges'!$A:$O,11,FALSE)),"") -> 2.73 | H15: =IFERROR(IF(VLOOKUP($A15,'Annex 2 EHV charges'!$A:$O,12,FALSE)=0,"",VLOOKUP($A15,'Annex 2 EHV charges'!$A:$O,12,FALSE)),"") -> 2.73
A16: {=IFERROR(INDEX('Annex 2 EHV charges'!$A$10:$A$108, MATCH(0, IF(ISBLANK('Annex 2 EHV charges'!$A$10:$A$108),1, COUNTIF(A$4:$A15, 'Annex 2 EHV charges'!$A$10:$A$108)), 0)),"")} -> NR_AFD | B16: =IF($A16="","",VLOOKUP($A16,'Annex 2 EHV charges'!$A:$O,2,0)) -> 851 | C16: =IF($A16="","",VLOOKUP($A16,'Annex 2 EHV charges'!$A:$O,3,0)) -> 1900060219377 | D16: =IF($A16="","",VLOOKUP($A16,'Annex 2 EHV charges'!$A:$O,7,0)) -> NR_AFD | E16: =IFERROR(IF(VLOOKUP($A16,'Annex 2 EHV charges'!$A:$O,9,FALSE)=0,"",VLOOKUP($A16,'Annex 2 EHV charges'!$A:$O,9,FALSE)),"") -> 1.802 | F16: =IFERROR(IF(VLOOKUP($A16,'Annex 2 EHV charges'!$A:$O,10,FALSE)=0,"",VLOOKUP($A16,'Annex 2 EHV charges'!$A:$O,10,FALSE)),"") -> 36594.39 | G16: =IFERROR(IF(VLOOKUP($A16,'Annex 2 EHV charges'!$A:$O,11,FALSE)=0,"",VLOOKUP($A16,'Annex 2 EHV charges'!$A:$O,11,FALSE)),"") -> 2.42 | H16: =IFERROR(IF(VLOOKUP($A16,'Annex 2 EHV charges'!$A:$O,12,FALSE)=0,"",VLOOKUP($A16,'Annex 2 EHV charges'!$A:$O,12,FALSE)),"") -> 2.42
... A254: {=IFERROR(INDEX('Annex 2 EHV charges'!$A$10:$A$108, MATCH(0, IF(ISBLANK('Annex 2 EHV charges'!$A$10:$A$108),1, COUNTIF(A$4:$A253, 'Annex 2 EHV charges'!$A$10:$A$108)), 0)),"")} | B254: =IF($A254="","",VLOOKUP($A254,'Annex 2 EHV charges'!$A:$O,2,0)) | C254: =IF($A254="","",VLOOKUP($A254,'Annex 2 EHV charges'!$A:$O,3,0)) | D254: =IF($A254="","",VLOOKUP($A254,'Annex 2 EHV charges'!$A:$O,7,0)) | E254: =IFERROR(IF(VLOOKUP($A254,'Annex 2 EHV charges'!$A:$O,9,FALSE)=0,"",VLOOKUP($A254,'Annex 2 EHV charges'!$A:$O,9,FALSE)),"") | F254: =IFERROR(IF(VLOOKUP($A254,'Annex 2 EHV charges'!$A:$O,10,FALSE)=0,"",VLOOKUP($A254,'Annex 2 EHV charges'!$A:$O,10,FALSE)),"") | G254: =IFERROR(IF(VLOOKUP($A254,'Annex 2 EHV charges'!$A:$O,11,FALSE)=0,"",VLOOKUP($A254,'Annex 2 EHV charges'!$A:$O,11,FALSE)),"") | H254: =IFERROR(IF(VLOOKUP($A254,'Annex 2 EHV charges'!$A:$O,12,FALSE)=0,"",VLOOKUP($A254,'Annex 2 EHV charges'!$A:$O,12,FALSE)),"")

Sheet Annex 2b Export
A1: Note: The list of MPANs / MSIDs provided may be incomplete; the DNO reserves the right to apply the listed charges to any other MPANs / MSIDs associated with the site. Note: This table is automatically populated based on the content of the tab entitled 'Annex 2 EHV Charges'. The timebands are as shown in Annex 2.
A2: =Overview!B4& " - Effective from "&Overview!D4&" - "&Overview!E4&" EDCM export charges" -> South Eastern Power Networks - Effective from 1 April 2024 - Final EDCM export charges
A4: Export Unique Identifier | B4: LLFC | C4: Export MPANs/MSIDs | D4: Name | E4: ='Annex 2 EHV charges'!M9 -> Export Super Red unit charge (p/kWh) | F4: ='Annex 2 EHV charges'!N9 -> Export fixed charge (p/day) | G4: ='Annex 2 EHV charges'!O9 -> Export capacity charge (p/kVA/day) | H4: ='Annex 2 EHV charges'!P9 -> Export exceeded capacity charge (p/kVA/day)
A5: {=IFERROR(INDEX('Annex 2 EHV charges'!$D$10:$D$108, MATCH(0, IF(ISBLANK('Annex 2 EHV charges'!$D$10:$D$108),1, COUNTIF(A$4:$A4, 'Annex 2 EHV charges'!$D$10:$D$108)), 0)),"")} -> THAMEM | B5: =IF($A5="","",VLOOKUP($A5,'Annex 2 EHV charges'!$D:$O,2,0)) -> 691 | C5: =IF($A5="","",VLOOKUP($A5,'Annex 2 EHV charges'!$D:$O,3,0)) -> 1900090876979;1900090876988 | D5: =IF($A5="","",VLOOKUP($A5,'Annex 2 EHV charges'!$D:$O,4,0)) -> THAMEM | E5: =IFERROR(IF(VLOOKUP($A5,'Annex 2 EHV charges'!$D:$O,10,FALSE)=0,"",VLOOKUP($A5,'Annex 2 EHV charges'!$D:$O,10,FALSE)),"") | F5: =IFERROR(IF(VLOOKUP($A5,'Annex 2 EHV charges'!$D:$O,11,FALSE)=0,"",VLOOKUP($A5,'Annex 2 EHV charges'!$D:$O,11,FALSE)),"") -> 4909.47 | G5: =IFERROR(IF(VLOOKUP($A5,'Annex 2 EHV charges'!$D:$O,12,FALSE)=0,"",VLOOKUP($A5,'Annex 2 EHV charges'!$D:$O,12,FALSE)),"") -> 0.05 | H5: =IFERROR(IF(VLOOKUP($A5,'Annex 2 EHV charges'!$D:$P,13,FALSE)=0,"",VLOOKUP($A5,'Annex 2 EHV charges'!$D:$P,13,FALSE)),"") -> 0.05
A6: {=IFERROR(INDEX('Annex 2 EHV charges'!$D$10:$D$108, MATCH(0, IF(ISBLANK('Annex 2 EHV charges'!$D$10:$D$108),1, COUNTIF(A$4:$A5, 'Annex 2 EHV charges'!$D$10:$D$108)), 0)),"")} -> THAMES | B6: =IF($A6="","",VLOOKUP($A6,'Annex 2 EHV charges'!$D:$O,2,0)) -> 732 | C6: =IF($A6="","",VLOOKUP($A6,'Annex 2 EHV charges'!$D:$O,3,0)) -> 1900060576611 | D6: =IF($A6="","",VLOOKUP($A6,'Annex 2 EHV charges'!$D:$O,4,0)) -> THAMES | E6: =IFERROR(IF(VLOOKUP($A6,'Annex 2 EHV charges'!$D:$O,10,FALSE)=0,"",VLOOKUP($A6,'Annex 2 EHV charges'!$D:$O,10,FALSE)),"") -> -0.482 | F6: =IFERROR(IF(VLOOKUP($A6,'Annex 2 EHV charges'!$D:$O,11,FALSE)=0,"",VLOOKUP($A6,'Annex 2 EHV charges'!$D:$O,11,FALSE)),"") -> 2943.17 | G6: =IFERROR(IF(VLOOKUP($A6,'Annex 2 EHV charges'!$D:$O,12,FALSE)=0,"",VLOOKUP($A6,'Annex 2 EHV charges'!$D:$O,12,FALSE)),"") -> 0.05 | H6: =IFERROR(IF(VLOOKUP($A6,'Annex 2 EHV charges'!$D:$P,13,FALSE)=0,"",VLOOKUP($A6,'Annex 2 EHV charges'!$D:$P,13,FALSE)),"") -> 0.05
A7: {=IFERROR(INDEX('Annex 2 EHV charges'!$D$10:$D$108, MATCH(0, IF(ISBLANK('Annex 2 EHV charges'!$D$10:$D$108),1, COUNTIF(A$4:$A6, 'Annex 2 EHV charges'!$D$10:$D$108)), 0)),"")} -> TWHK66 | B7: =IF($A7="","",VLOOKUP($A7,'Annex 2 EHV charges'!$D:$O,2,0)) -> 692 | C7: =IF($A7="","",VLOOKUP($A7,'Annex 2 EHV charges'!$D:$O,3,0)) -> 1900091206194 | D7: =IF($A7="","",VLOOKUP($A7,'Annex 2 EHV charges'!$D:$O,4,0)) -> TWHK66 | E7: =IFERROR(IF(VLOOKUP($A7,'Annex 2 EHV charges'!$D:$O,10,FALSE)=0,"",VLOOKUP($A7,'Annex 2 EHV charges'!$D:$O,10,FALSE)),"") -> -8.002 | F7: =IFERROR(IF(VLOOKUP($A7,'Annex 2 EHV charges'!$D:$O,11,FALSE)=0,"",VLOOKUP($A7,'Annex 2 EHV charges'!$D:$O,11,FALSE)),"") -> 51.46 | G7: =IFERROR(IF(VLOOKUP($A7,'Annex 2 EHV charges'!$D:$O,12,FALSE)=0,"",VLOOKUP($A7,'Annex 2 EHV charges'!$D:$O,12,FALSE)),"") -> 0.05 | H7: =IFERROR(IF(VLOOKUP($A7,'Annex 2 EHV charges'!$D:$P,13,FALSE)=0,"",VLOOKUP($A7,'Annex 2 EHV charges'!$D:$P,13,FALSE)),"") -> 0.05
A8: {=IFERROR(INDEX('Annex 2 EHV charges'!$D$10:$D$108, MATCH(0, IF(ISBLANK('Annex 2 EHV charges'!$D$10:$D$108),1, COUNTIF(A$4:$A7, 'Annex 2 EHV charges'!$D$10:$D$108)), 0)),"")} -> ANMSTR | B8: =IF($A8="","",VLOOKUP($A8,'Annex 2 EHV charges'!$D:$O,2,0)) -> 780 | C8: =IF($A8="","",VLOOKUP($A8,'Annex 2 EHV charges'!$D:$O,3,0)) -> 1900091919597 | D8: =IF($A8="","",VLOOKUP($A8,'Annex 2 EHV charges'!$D:$O,4,0)) -> ANMSTR | E8: =IFERROR(IF(VLOOKUP($A8,'Annex 2 EHV charges'!$D:$O,10,FALSE)=0,"",VLOOKUP($A8,'Annex 2 EHV charges'!$D:$O,10,FALSE)),"") -> -2.153 | F8: =IFERROR(IF(VLOOKUP($A8,'Annex 2 EHV charges'!$D:$O,11,FALSE)=0,"",VLOOKUP($A8,'Annex 2 EHV charges'!$D:$O,11,FALSE)),"") -> 1633.73 | G8: =IFERROR(IF(VLOOKUP($A8,'Annex 2 EHV charges'!$D:$O,12,FALSE)=0,"",VLOOKUP($A8,'Annex 2 EHV charges'!$D:$O,12,FALSE)),"") -> 0.05 | H8: =IFERROR(IF(VLOOKUP($A8,'Annex 2 EHV charges'!$D:$P,13,FALSE)=0,"",VLOOKUP($A8,'Annex 2 EHV charges'!$D:$P,13,FALSE)),"") -> 0.05
A9: {=IFERROR(INDEX('Annex 2 EHV charges'!$D$10:$D$108, MATCH(0, IF(ISBLANK('Annex 2 EHV charges'!$D$10:$D$108),1, COUNTIF(A$4:$A8, 'Annex 2 EHV charges'!$D$10:$D$108)), 0)),"")} -> ASHBYS | B9: =IF($A9="","",VLOOKUP($A9,'Annex 2 EHV charges'!$D:$O,2,0)) -> 741 | C9: =IF($A9="","",VLOOKUP($A9,'Annex 2 EHV charges'!$D:$O,3,0)) -> 1900091216972 | D9: =IF($A9="","",VLOOKUP($A9,'Annex 2 EHV charges'!$D:$O,4,0)) -> ASHBYS | E9: =IFERROR(IF(VLOOKUP($A9,'Annex 2 EHV charges'!$D:$O,10,FALSE)=0,"",VLOOKUP($A9,'Annex 2 EHV charges'!$D:$O,10,FALSE)),"") | F9: =IFERROR(IF(VLOOKUP($A9,'Annex 2 EHV charges'!$D:$O,11,FALSE)=0,"",VLOOKUP($A9,'Annex 2 EHV charges'!$D:$O,11,FALSE)),"") -> 1674.86 | G9: =IFERROR(IF(VLOOKUP($A9,'Annex 2 EHV charges'!$D:$O,12,FALSE)=0,"",VLOOKUP($A9,'Annex 2 EHV charges'!$D:$O,12,FALSE)),"") -> 0.05 | H9: =IFERROR(IF(VLOOKUP($A9,'Annex 2 EHV charges'!$D:$P,13,FALSE)=0,"",VLOOKUP($A9,'Annex 2 EHV charges'!$D:$P,13,FALSE)),"") -> 0.05
A10: {=IFERROR(INDEX('Annex 2 EHV charges'!$D$10:$D$108, MATCH(0, IF(ISBLANK('Annex 2 EHV charges'!$D$10:$D$108),1, COUNTIF(A$4:$A9, 'Annex 2 EHV charges'!$D$10:$D$108)), 0)),"")} -> AYLESF | B10: =IF($A10="","",VLOOKUP($A10,'Annex 2 EHV charges'!$D:$O,2,0)) -> 725 | C10: =IF($A10="","",VLOOKUP($A10,'Annex 2 EHV charges'!$D:$O,3,0)) -> 1900060436880 | D10: =IF($A10="","",VLOOKUP($A10,'Annex 2 EHV charges'!$D:$O,4,0)) -> AYLESF | E10: =IFERROR(IF(VLOOKUP($A10,'Annex 2 EHV charges'!$D:$O,10,FALSE)=0,"",VLOOKUP($A10,'Annex 2 EHV charges'!$D:$O,10,FALSE)),"") | F10: =IFERROR(IF(VLOOKUP($A10,'Annex 2 EHV charges'!$D:$O,11,FALSE)=0,"",VLOOKUP($A10,'Annex 2 EHV charges'!$D:$O,11,FALSE)),"") | G10: =IFERROR(IF(VLOOKUP($A10,'Annex 2 EHV charges'!$D:$O,12,FALSE)=0,"",VLOOKUP($A10,'Annex 2 EHV charges'!$D:$O,12,FALSE)),"") | H10: =IFERROR(IF(VLOOKUP($A10,'Annex 2 EHV charges'!$D:$P,13,FALSE)=0,"",VLOOKUP($A10,'Annex 2 EHV charges'!$D:$P,13,FALSE)),"")
A11: {=IFERROR(INDEX('Annex 2 EHV charges'!$D$10:$D$108, MATCH(0, IF(ISBLANK('Annex 2 EHV charges'!$D$10:$D$108),1, COUNTIF(A$4:$A10, 'Annex 2 EHV charges'!$D$10:$D$108)), 0)),"")} -> BEDERF | B11: =IF($A11="","",VLOOKUP($A11,'Annex 2 EHV charges'!$D:$O,2,0)) -> 693 | C11: =IF($A11="","",VLOOKUP($A11,'Annex 2 EHV charges'!$D:$O,3,0)) -> 1900091482597 | D11: =IF($A11="","",VLOOKUP($A11,'Annex 2 EHV charges'!$D:$O,4,0)) -> BEDERF | E11: =IFERROR(IF(VLOOKUP($A11,'Annex 2 EHV charges'!$D:$O,10,FALSE)=0,"",VLOOKUP($A11,'Annex 2 EHV charges'!$D:$O,10,FALSE)),"") -> -0.317 | F11: =IFERROR(IF(VLOOKUP($A11,'Annex 2 EHV charges'!$D:$O,11,FALSE)=0,"",VLOOKUP($A11,'Annex 2 EHV charges'!$D:$O,11,FALSE)),"") -> 4105.64 | G11: =IFERROR(IF(VLOOKUP($A11,'Annex 2 EHV charges'!$D:$O,12,FALSE)=0,"",VLOOKUP($A11,'Annex 2 EHV charges'!$D:$O,12,FALSE)),"") -> 0.05 | H11: =IFERROR(IF(VLOOKUP($A11,'Annex 2 EHV charges'!$D:$P,13,FALSE)=0,"",VLOOKUP($A11,'Annex 2 EHV charges'!$D:$P,13,FALSE)),"") -> 0.05
A12: {=IFERROR(INDEX('Annex 2 EHV charges'!$D$10:$D$108, MATCH(0, IF(ISBLANK('Annex 2 EHV charges'!$D$10:$D$108),1, COUNTIF(A$4:$A11, 'Annex 2 EHV charges'!$D$10:$D$108)), 0)),"")} -> BESAYL | B12: =IF($A12="","",VLOOKUP($A12,'Annex 2 EHV charges'!$D:$O,2,0)) -> 694 | C12: =IF($A12="","",VLOOKUP($A12,'Annex 2 EHV charges'!$D:$O,3,0)) -> 1900091632784 | D12: =IF($A12="","",VLOOKUP($A12,'Annex 2 EHV charges'!$D:$O,4,0)) -> BESAYL | E12: =IFERROR(IF(VLOOKUP($A12,'Annex 2 EHV charges'!$D:$O,10,FALSE)=0,"",VLOOKUP($A12,'Annex 2 EHV charges'!$D:$O,10,FALSE)),"") -> -0.087 | F12: =IFERROR(IF(VLOOKUP($A12,'Annex 2 EHV charges'!$D:$O,11,FALSE)=0,"",VLOOKUP($A12,'Annex 2 EHV charges'!$D:$O,11,FALSE)),"") -> 589.22 | G12: =IFERROR(IF(VLOOKUP($A12,'Annex 2 EHV charges'!$D:$O,12,FALSE)=0,"",VLOOKUP($A12,'Annex 2 EHV charges'!$D:$O,12,FALSE)),"") -> 0.05 | H12: =IFERROR(IF(VLOOKUP($A12,'Annex 2 EHV charges'!$D:$P,13,FALSE)=0,"",VLOOKUP($A12,'Annex 2 EHV charges'!$D:$P,13,FALSE)),"") -> 0.05
A13: {=IFERROR(INDEX('Annex 2 EHV charges'!$D$10:$D$108, MATCH(0, IF(ISBLANK('Annex 2 EHV charges'!$D$10:$D$108),1, COUNTIF(A$4:$A12, 'Annex 2 EHV charges'!$D$10:$D$108)), 0)),"")} -> BNTLEY | B13: =IF($A13="","",VLOOKUP($A13,'Annex 2 EHV charges'!$D:$O,2,0)) -> 713 | C13: =IF($A13="","",VLOOKUP($A13,'Annex 2 EHV charges'!$D:$O,3,0)) -> 1900091343787 | D13: =IF($A13="","",VLOOKUP($A13,'Annex 2 EHV charges'!$D:$O,4,0)) -> BNTLEY | E13: =IFERROR(IF(VLOOKUP($A13,'Annex 2 EHV charges'!$D:$O,10,FALSE)=0,"",VLOOKUP($A13,'Annex 2 EHV charges'!$D:$O,10,FALSE)),"") | F13: =IFERROR(IF(VLOOKUP($A13,'Annex 2 EHV charges'!$D:$O,11,FALSE)=0,"",VLOOKUP($A13,'Annex 2 EHV charges'!$D:$O,11,FALSE)),"") -> 1477.43 | G13: =IFERROR(IF(VLOOKUP($A13,'Annex 2 EHV charges'!$D:$O,12,FALSE)=0,"",VLOOKUP($A13,'Annex 2 EHV charges'!$D:$O,12,FALSE)),"") -> 0.05 | H13: =IFERROR(IF(VLOOKUP($A13,'Annex 2 EHV charges'!$D:$P,13,FALSE)=0,"",VLOOKUP($A13,'Annex 2 EHV charges'!$D:$P,13,FALSE)),"") -> 0.05
A14: {=IFERROR(INDEX('Annex 2 EHV charges'!$D$10:$D$108, MATCH(0, IF(ISBLANK('Annex 2 EHV charges'!$D$10:$D$108),1, COUNTIF(A$4:$A13, 'Annex 2 EHV charges'!$D$10:$D$108)), 0)),"")} -> BNTLY2 | B14: =IF($A14="","",VLOOKUP($A14,'Annex 2 EHV charges'!$D:$O,2,0)) -> 712 | C14: =IF($A14="","",VLOOKUP($A14,'Annex 2 EHV charges'!$D:$O,3,0)) -> 1900091463655 | D14: =IF($A14="","",VLOOKUP($A14,'Annex 2 EHV charges'!$D:$O,4,0)) -> BNTLY2 | E14: =IFERROR(IF(VLOOKUP($A14,'Annex 2 EHV charges'!$D:$O,10,FALSE)=0,"",VLOOKUP($A14,'Annex 2 EHV charges'!$D:$O,10,FALSE)),"") | F14: =IFERROR(IF(VLOOKUP($A14,'Annex 2 EHV charges'!$D:$O,11,FALSE)=0,"",VLOOKUP($A14,'Annex 2 EHV charges'!$D:$O,11,FALSE)),"") -> 945.82 | G14: =IFERROR(IF(VLOOKUP($A14,'Annex 2 EHV charges'!$D:$O,12,FALSE)=0,"",VLOOKUP($A14,'Annex 2 EHV charges'!$D:$O,12,FALSE)),"") -> 0.05 | H14: =IFERROR(IF(VLOOKUP($A14,'Annex 2 EHV charges'!$D:$P,13,FALSE)=0,"",VLOOKUP($A14,'Annex 2 EHV charges'!$D:$P,13,FALSE)),"") -> 0.05
A15: {=IFERROR(INDEX('Annex 2 EHV charges'!$D$10:$D$108, MATCH(0, IF(ISBLANK('Annex 2 EHV charges'!$D$10:$D$108),1, COUNTIF(A$4:$A14, 'Annex 2 EHV charges'!$D$10:$D$108)), 0)),"")} -> BOBBNG | B15: =IF($A15="","",VLOOKUP($A15,'Annex 2 EHV charges'!$D:$O,2,0)) -> 705 | C15: =IF($A15="","",VLOOKUP($A15,'Annex 2 EHV charges'!$D:$O,3,0)) -> 1900091395517 | D15: =IF($A15="","",VLOOKUP($A15,'Annex 2 EHV charges'!$D:$O,4,0)) -> BOBBNG | E15: =IFERROR(IF(VLOOKUP($A15,'Annex 2 EHV charges'!$D:$O,10,FALSE)=0,"",VLOOKUP($A15,'Annex 2 EHV charges'!$D:$O,10,FALSE)),"") | F15: =IFERROR(IF(VLOOKUP($A15,'Annex 2 EHV charges'!$D:$O,11,FALSE)=0,"",VLOOKUP($A15,'Annex 2 EHV charges'!$D:$O,11,FALSE)),"") -> 1603.2 | G15: =IFERROR(IF(VLOOKUP($A15,'Annex 2 EHV charges'!$D:$O,12,FALSE)=0,"",VLOOKUP($A15,'Annex 2 EHV charges'!$D:$O,12,FALSE)),"") -> 0.05 | H15: =IFERROR(IF(VLOOKUP($A15,'Annex 2 EHV charges'!$D:$P,13,FALSE)=0,"",VLOOKUP($A15,'Annex 2 EHV charges'!$D:$P,13,FALSE)),"") -> 0.05
A16: {=IFERROR(INDEX('Annex 2 EHV charges'!$D$10:$D$108, MATCH(0, IF(ISBLANK('Annex 2 EHV charges'!$D$10:$D$108),1, COUNTIF(A$4:$A15, 'Annex 2 EHV charges'!$D$10:$D$108)), 0)),"")} -> BRAMBS | B16: =IF($A16="","",VLOOKUP($A16,'Annex 2 EHV charges'!$D:$O,2,0)) -> 695 | C16: =IF($A16="","",VLOOKUP($A16,'Annex 2 EHV charges'!$D:$O,3,0)) -> 1900091566820 | D16: =IF($A16="","",VLOOKUP($A16,'Annex 2 EHV charges'!$D:$O,4,0)) -> BRAMBS | E16: =IFERROR(IF(VLOOKUP($A16,'Annex 2 EHV charges'!$D:$O,10,FALSE)=0,"",VLOOKUP($A16,'Annex 2 EHV charges'!$D:$O,10,FALSE)),"") -> -0.6 | F16: =IFERROR(IF(VLOOKUP($A16,'Annex 2 EHV charges'!$D:$O,11,FALSE)=0,"",VLOOKUP($A16,'Annex 2 EHV charges'!$D:$O,11,FALSE)),"") -> 589.22 | G16: =IFERROR(IF(VLOOKUP($A16,'Annex 2 EHV charges'!$D:$O,12,FALSE)=0,"",VLOOKUP($A16,'Annex 2 EHV charges'!$D:$O,12,FALSE)),"") -> 0.05 | H16: =IFERROR(IF(VLOOKUP($A16,'Annex 2 EHV charges'!$D:$P,13,FALSE)=0,"",VLOOKUP($A16,'Annex 2 EHV charges'!$D:$P,13,FALSE)),"") -> 0.05
... A254: {=IFERROR(INDEX('Annex 2 EHV charges'!$D$10:$D$108, MATCH(0, IF(ISBLANK('Annex 2 EHV charges'!$D$10:$D$108),1, COUNTIF(A$4:$A253, 'Annex 2 EHV charges'!$D$10:$D$108)), 0)),"")} | B254: =IF($A254="","",VLOOKUP($A254,'Annex 2 EHV charges'!$D:$O,2,0)) | C254: =IF($A254="","",VLOOKUP($A254,'Annex 2 EHV charges'!$D:$O,3,0)) | D254: =IF($A254="","",VLOOKUP($A254,'Annex 2 EHV charges'!$D:$O,4,0)) | E254: =IFERROR(IF(VLOOKUP($A254,'Annex 2 EHV charges'!$D:$O,10,FALSE)=0,"",VLOOKUP($A254,'Annex 2 EHV charges'!$D:$O,10,FALSE)),"") | F254: =IFERROR(IF(VLOOKUP($A254,'Annex 2 EHV charges'!$D:$O,11,FALSE)=0,"",VLOOKUP($A254,'Annex 2 EHV charges'!$D:$O,11,FALSE)),"") | G254: =IFERROR(IF(VLOOKUP($A254,'Annex 2 EHV charges'!$D:$O,12,FALSE)=0,"",VLOOKUP($A254,'Annex 2 EHV charges'!$D:$O,12,FALSE)),"") | H254: =IFERROR(IF(VLOOKUP($A254,'Annex 2 EHV charges'!$D:$P,13,FALSE)=0,"",VLOOKUP($A254,'Annex 2 EHV charges'!$D:$P,13,FALSE)),"")

Sheet Annex 3 Preserved charges
A1: Back to Overview
A2: =Overview!B4& " - Effective from "&Overview!D4&" - "&Overview!E4&" LV and HV tariffs" -> South Eastern Power Networks - Effective from 1 April 2024 - Final LV and HV tariffs
A3: Supercustomer preserved charges/additional LLFCs
B4: Closed LLFCs | C4: PCs | D4: Red/black unit charge p/kWh | E4: Amber/yellow unit charge p/kWh | F4: Green unit charge p/kWh | G4: Fixed charge p/MPAN/day
A6: Notes: | B6: South Eastern Power Networks has no Preserved NHH Tariffs/Additional LLFC classes
A11: Site Specific preserved charges/additional LLFCs
B12: Closed LLFCs | C12: PCs | D12: Red/black unit charge p/kWh | E12: Amber/yellow unit charge p/kWh | F12: Green unit charge p/kWh | G12: Fixed charge p/MPAN/day | H12: Capacity charge p/kVA/day | I12: Exceeded capacity charge p/kVA/day | J12: Reactive power charge p/kVArh
A14: Notes: | B14: South Eastern Power Networks has no Preserved HH Tariffs/Additional LLFC classes

Sheet Annex 4 LDNO charges
A1: Back to Overview | B1: Copy from CDCM table 3701 "Tariffs!A42:I84" and paste values into A14 | F1: Copy from EDCM table 6005 "LDNORev!B549:G683" and paste values into D57
A2: =Overview!B4& " - Effective from "&Overview!D4&" - "&Overview!E4&" LDNO tariffs" -> South Eastern Power Networks - Effective from 1 April 2024 - Final LDNO tariffs
A4: Time Bands for LV and HV Designated Properties | F4: Time Bands for Unmetered Properties
A5: Time periods | B5: Red Time Band | C5: Amber Time Band | D5: Green Time Band | H5: Black Time Band | I5: Yellow Time Band | J5: Green Time Band
A6: Monday to Friday (Including Bank Holidays) All Year | B6: 16:00 - 19:00 | C6: 07:00 - 16:00 19:00 - 23:00 | D6: 00:00 - 07:00 23:00 - 24:00 | F6: Monday to Friday (Including Bank Holidays) November to February Inclusive | H6: 16:00 - 19:00 | I6: 07:00 - 16:00 19:00 - 23:00 | J6: 00:00 - 07:00 23:00 - 24:00
A7: Saturday and Sunday All Year | D7: 00:00 - 24:00 | F7: Monday to Friday (Including Bank Holidays) March to October Inclusive | I7: 07:00 - 23:00 | J7: 00:00 - 07:00 23:00 - 24:00
A8: Notes | B8: All the above times are in UK Clock time | F8: Saturday and Sunday All Year | J8: 00:00 - 24:00
F9: Notes | H9: All the above times are in UK Clock time
A11: Tariff name | B11: Unique billing identifier | C11: PCs | D11: Red/black unit charge p/kWh | E11: Amber/yellow unit charge p/kWh | F11: Green unit charge p/kWh | G11: Fixed charge p/MPAN/day | H11: Capacity charge p/kVA/day | I11: Exceeded capacity charge p/kVA/day | J11: Reactive power charge p/kVArh
A12: LDNO LV: Domestic Aggregated or CT with Residual | B12: A00 | C12: 0, 1, 2 | D12: 11.554 | E12: 0.433 | F12: 0.148 | G12: 13.56
A13: LDNO LV: Domestic Aggregated (related MPAN) | B13: B00 | C13: 2 | D13: 11.554 | E13: 0.433 | F13: 0.148
A14: LDNO LV: Non-Domestic Aggregated or CT No Residual | B14: C00 | C14: 0, 3, 4, 5-8 | D14: 7.862 | E14: 0.295 | F14: 0.101 | G14: 4.31
A15: LDNO LV: Non-Domestic Aggregated or CT Band 1 | B15: C01 | C15: 0, 3, 4, 5-8 | D15: 7.862 | E15: 0.295 | F15: 0.101 | G15: 8.06
A16: LDNO LV: Non-Domestic Aggregated or CT Band 2 | B16: C02 | C16: 0, 3, 4, 5-8 | D16: 7.862 | E16: 0.295 | F16: 0.101 | G16: 24.84
A17: LDNO LV: Non-Domestic Aggregated or CT Band 3 | B17: C03 | C17: 0, 3, 4, 5-8 | D17: 7.862 | E17: 0.295 | F17: 0.101 | G17: 51.97
A18: LDNO LV: Non-Domestic Aggregated or CT Band 4 | B18: C04 | C18: 0, 3, 4, 5-8 | D18: 7.862 | E18: 0.295 | F18: 0.101 | G18: 152.15
A19: LDNO LV: Non-Domestic Aggregated (related MPAN) | B19: D00 | C19: 4 | D19: 7.862 | E19: 0.295 | F19: 0.101
A20: LDNO LV: LV Site Specific No Residual | B20: E00 | C20: 0 | D20: 6.519 | E20: 0.237 | F20: 0.079 | G20: 12.79 | H20: 2.87 | I20: 5.11 | J20: 0.212
A21: LDNO LV: LV Site Specific Band 1 | B21: E01 | C21: 0 | D21: 6.519 | E21: 0.237 | F21: 0.079 | G21: 290.94 | H21: 2.87 | I21: 5.11 | J21: 0.212
A22: LDNO LV: LV Site Specific Band 2 | B22: E02 | C22: 0 | D22: 6.519 | E22: 0.237 | F22: 0.079 | G22: 481.47 | H22: 2.87 | I22: 5.11 | J22: 0.212
A23: LDNO LV: LV Site Specific Band 3 | B23: E03 | C23: 0 | D23: 6.519 | E23: 0.237 | F23: 0.079 | G23: 778.14 | H23: 2.87 | I23: 5.11 | J23: 0.212
A24: LDNO LV: LV Site Specific Band 4 | B24: E04 | C24: 0 | D24: 6.519 | E24: 0.237 | F24: 0.079 | G24: 1716.15 | H24: 2.87 | I24: 5.11 | J24: 0.212
A25: LDNO LV: Unmetered Supplies | B25: U00 | C25: 0, 1 or 8 | D25: 30.458 | E25: 2.138 | F25: 1.929
A26: LDNO LV: LV Generation Aggregated | B26: F00 | C26: 0 | D26: -10.397 | E26: -0.39 | F26: -0.133 | G26: 0
A27: LDNO LV: LV Generation Site Specific | B27: G00 | C27: 0 | D27: -10.397 | E27: -0.39 | F27: -0.133 | G27: 0 | J27: 0.311
A28: LDNO HV: Domestic Aggregated or CT with Residual | B28: A10 | C28: 0, 1, 2 | D28: 8.911 | E28: 0.334 | F28: 0.114 | G28: 10.68
A29: LDNO HV: Domestic Aggregated (Related MPAN) | B29: B10 | C29: 2 | D29: 8.911 | E29: 0.334 | F29: 0.114
A30: LDNO HV: Non-Domestic Aggregated or CT No Residual | B30: C10 | C30: 0, 3, 4, 5-8 | D30: 6.063 | E30: 0.227 | F30: 0.078 | G30: 3.51
A31: LDNO HV: Non-Domestic Aggregated or CT Band 1 | B31: C11 | C31: 0, 3, 4, 5-8 | D31: 6.063 | E31: 0.227 | F31: 0.078 | G31: 6.4
A32: LDNO HV: Non-Domestic Aggregated or CT Band 2 | B32: C12 | C32: 0, 3, 4, 5-8 | D32: 6.063 | E32: 0.227 | F32: 0.078 | G32: 19.34
A33: LDNO HV: Non-Domestic Aggregated or CT Band 3 | B33: C13 | C33: 0, 3, 4, 5-8 | D33: 6.063 | E33: 0.227 | F33: 0.078 | G33: 40.27
A34: LDNO HV: Non-Domestic Aggregated or CT Band 4 | B34: C14 | C34: 0, 3, 4, 5-8 | D34: 6.063 | E34: 0.227 | F34: 0.078 | G34: 117.53
A35: LDNO HV: Non-Domestic Aggregated (related MPAN) | B35: D10 | C35: 4 | D35: 6.063 | E35: 0.227 | F35: 0.078
A36: LDNO HV: LV Site Specific No Residual | B36: E10 | C36: 0 | D36: 5.027 | E36: 0.183 | F36: 0.061 | G36: 10.05 | H36: 2.21 | I36: 3.94 | J36: 0.163
A37: LDNO HV: LV Site Specific Band 1 | B37: E11 | C37: 0 | D37: 5.027 | E37: 0.183 | F37: 0.061 | G37: 224.58 | H37: 2.21 | I37: 3.94 | J37: 0.163
A38: LDNO HV: LV Site Specific Band 2 | B38: E12 | C38: 0 | D38: 5.027 | E38: 0.183 | F38: 0.061 | G38: 371.52 | H38: 2.21 | I38: 3.94 | J38: 0.163
A39: LDNO HV: LV Site Specific Band 3 | B39: E13 | C39: 0 | D39: 5.027 | E39: 0.183 | F39: 0.061 | G39: 600.33 | H39: 2.21 | I39: 3.94 | J39: 0.163
A40: LDNO HV: LV Site Specific Band 4 | B40: E14 | C40: 0 | D40: 5.027 | E40: 0.183 | F40: 0.061 | G40: 1323.77 | H40: 2.21 | I40: 3.94 | J40: 0.163
A41: LDNO HV: LV Sub Site Specific No Residual | B41: J10 | C41: 0 | D41: 4.973 | E41: 0.169 | F41: 0.054 | G41: 12.71 | H41: 4.95 | I41: 6.29 | J41: 0.157
A42: LDNO HV: LV Sub Site Specific Band 1 | B42: J11 | C42: 0 | D42: 4.973 | E42: 0.169 | F42: 0.054 | G42: 342.29 | H42: 4.95 | I42: 6.29 | J42: 0.157
A43: LDNO HV: LV Sub Site Specific Band 2 | B43: J12 | C43: 0 | D43: 4.973 | E43: 0.169 | F43: 0.054 | G43: 568.03 | H43: 4.95 | I43: 6.29 | J43: 0.157
A44: LDNO HV: LV Sub Site Specific Band 3 | B44: J13 | C44: 0 | D44: 4.973 | E44: 0.169 | F44: 0.054 | G44: 919.56 | H44: 4.95 | I44: 6.29 | J44: 0.157
A45: LDNO HV: LV Sub Site Specific Band 4 | B45: J14 | C45: 0 | D45: 4.973 | E45: 0.169 | F45: 0.054 | G45: 2030.97 | H45: 4.95 | I45: 6.29 | J45: 0.157
A46: LDNO HV: HV Site Specific No Residual | B46: K10 | C46: 0 | D46: 4.87 | E46: 0.158 | F46: 0.047 | G46: 158.32 | H46: 4.25 | I46: 6.29 | J46: 0.152
A47: LDNO HV: HV Site Specific Band 1 | B47: K11 | C47: 0 | D47: 4.87 | E47: 0.158 | F47: 0.047 | G47: 1639.1 | H47: 4.25 | I47: 6.29 | J47: 0.152
... A50: LDNO HV: HV Site Specific Band 4 | B50: K14 | C50: 0 | D50: 4.87 | E50: 0.158 | F50: 0.047 | G50: 18950.48 | H50: 4.25 | I50: 6.29 | J50: 0.152
A51: LDNO HV: Unmetered Supplies | B51: U10 | C51: 0, 1 or 8 | D51: 23.491 | E51: 1.649 | F51: 1.488
A52: LDNO HV: LV Generation Aggregated | B52: F10 | C52: 0 | D52: -10.397 | E52: -0.39 | F52: -0.133 | G52: 0
A53: LDNO HV: LV Sub Generation Aggregated | B53: H10 | C53: 0 | D53: -8.979 | E53: -0.33 | F53: -0.111 | G53: 0
A54: LDNO HV: LV Generation Site Specific | B54: G10 | C54: 0 | D54: -10.397 | E54: -0.39 | F54: -0.133 | G54: 0 | J54: 0.311
A55: LDNO HV: LV Sub Generation Site Specific | B55: L10 | C55: 0 | D55: -8.979 | E55: -0.33 | F55: -0.111 | G55: 0 | J55: 0.272
A56: LDNO HV: HV Generation Site Specific | B56: M10 | C56: 0 | D56: -6.173 | E56: -0.207 | F56: -0.065 | G56: 0 | J56: 0.22
A57: LDNO HVplus: Domestic Aggregated or CT with Residual | B57: A20 | C57: 0, 1, 2 | D57: 6.465 | E57: 0.242 | F57: 0.083 | G57: 8.02
A58: LDNO HVplus: Domestic Aggregated (related MPAN) | B58: B20 | C58: 2 | D58: 6.465 | E58: 0.242 | F58: 0.083
A59: LDNO HVplus: Non-Domestic Aggregated or CT No Residual | B59: C20 | C59: 0, 3, 4, 5-8 | D59: 4.399 | E59: 0.165 | F59: 0.056 | G59: 2.77
A60: LDNO HVplus: Non-Domestic Aggregated or CT Band 1 | B60: C21 | C60: 0, 3, 4, 5-8 | D60: 4.399 | E60: 0.165 | F60: 0.056 | G60: 4.87
A61: LDNO HVplus: Non-Domestic Aggregated or CT Band 2 | B61: C22 | C61: 0, 3, 4, 5-8 | D61: 4.399 | E61: 0.165 | F61: 0.056 | G61: 14.25
A62: LDNO HVplus: Non-Domestic Aggregated or CT Band 3 | B62: C23 | C62: 0, 3, 4, 5-8 | D62: 4.399 | E62: 0.165 | F62: 0.056 | G62: 29.44
A63: LDNO HVplus: Non-Domestic Aggregated or CT Band 4 | B63: C24 | C63: 0, 3, 4, 5-8 | D63: 4.399 | E63: 0.165 | F63: 0.056 | G63: 85.49
A64: LDNO HVplus: Non-Domestic Aggregated (related MPAN) | B64: D20 | C64: 4 | D64: 4.399 | E64: 0.165 | F64: 0.056
A65: LDNO HVplus: LV Site Specific No Residual | B65: E20 | C65: 0 | D65: 3.648 | E65: 0.133 | F65: 0.044 | G65: 7.51 | H65: 1.61 | I65: 2.86 | J65: 0.119
A66: LDNO HVplus: LV Site Specific Band 1 | B66: E21 | C66: 0 | D66: 3.648 | E66: 0.133 | F66: 0.044 | G66: 163.15 | H66: 1.61 | I66: 2.86 | J66: 0.119
A67: LDNO HVplus: LV Site Specific Band 2 | B67: E22 | C67: 0 | D67: 3.648 | E67: 0.133 | F67: 0.044 | G67: 269.76 | H67: 1.61 | I67: 2.86 | J67: 0.119
A68: LDNO HVplus: LV Site Specific Band 3 | B68: E23 | C68: 0 | D68: 3.648 | E68: 0.133 | F68: 0.044 | G68: 435.77 | H68: 1.61 | I68: 2.86 | J68: 0.119
A69: LDNO HVplus: LV Site Specific Band 4 | B69: E24 | C69: 0 | D69: 3.648 | E69: 0.133 | F69: 0.044 | G69: 960.63 | H69: 1.61 | I69: 2.86 | J69: 0.119
A70: LDNO HVplus: LV Sub Site Specific No Residual | B70: J20 | C70: 0 | D70: 3.563 | E70: 0.121 | F70: 0.039 | G70: 9.34 | H70: 3.55 | I70: 4.5 | J70: 0.113
A71: LDNO HVplus: LV Sub Site Specific Band 1 | B71: J21 | C71: 0 | D71: 3.563 | E71: 0.121 | F71: 0.039 | G71: 245.47 | H71: 3.55 | I71: 4.5 | J71: 0.113
A72: LDNO HVplus: LV Sub Site Specific Band 2 | B72: J22 | C72: 0 | D72: 3.563 | E72: 0.121 | F72: 0.039 | G72: 407.21 | H72: 3.55 | I72: 4.5 | J72: 0.113
A73: LDNO HVplus: LV Sub Site Specific Band 3 | B73: J23 | C73: 0 | D73: 3.563 | E73: 0.121 | F73: 0.039 | G73: 659.06 | H73: 3.55 | I73: 4.5 | J73: 0.113
A74: LDNO HVplus: LV Sub Site Specific Band 4 | B74: J24 | C74: 0 | D74: 3.563 | E74: 0.121 | F74: 0.039 | G74: 1455.36 | H74: 3.55 | I74: 4.5 | J74: 0.113
A75: LDNO HVplus: HV Site Specific No Residual | B75: K20 | C75: 0 | D75: 3.473 | E75: 0.113 | F75: 0.034 | G75: 113.15 | H75: 3.03 | I75: 4.49 | J75: 0.109
A76: LDNO HVplus: HV Site Specific Band 1 | B76: K21 | C76: 0 | D76: 3.473 | E76: 0.113 | F76: 0.034 | G76: 1169.25 | H76: 3.03 | I76: 4.49 | J76: 0.109
... A79: LDNO HVplus: HV Site Specific Band 4 | B79: K24 | C79: 0 | D79: 3.473 | E79: 0.113 | F79: 0.034 | G79: 13515.82 | H79: 3.03 | I79: 4.49 | J79: 0.109
A80: LDNO HVplus: Unmetered Supplies | B80: U20 | C80: 0, 1 or 8 | D80: 17.043 | E80: 1.196 | F80: 1.08
A81: LDNO HVplus: LV Generation Aggregated | B81: F20 | C81: 0 | D81: -5.834 | E81: -0.219 | F81: -0.075 | G81: 0
A82: LDNO HVplus: LV Sub Generation Aggregated | B82: H20 | C82: 0 | D82: -5.6 | E82: -0.206 | F82: -0.07 | G82: 0
A83: LDNO HVplus: LV Generation Site Specific | B83: G20 | C83: 0 | D83: -5.834 | E83: -0.219 | F83: -0.075 | G83: 0 | J83: 0.174
A84: LDNO HVplus: LV Sub Generation Site Specific | B84: L20 | C84: 0 | D84: -5.6 | E84: -0.206 | F84: -0.07 | G84: 0 | J84: 0.17
A85: LDNO HVplus: HV Generation Site Specific | B85: M20 | C85: 0 | D85: -6.173 | E85: -0.207 | F85: -0.065 | G85: 13.66 | J85: 0.22
A86: LDNO EHV: Domestic Aggregated or CT with Residual | B86: A30 | C86: 0, 1, 2 | D86: 5.226 | E86: 0.196 | F86: 0.067 | G86: 6.67
A87: LDNO EHV: Domestic Aggregated (related MPAN) | B87: B30 | C87: 2 | D87: 5.226 | E87: 0.196 | F87: 0.067
A88: LDNO EHV: Non-Domestic Aggregated or CT No Residual | B88: C30 | C88: 0, 3, 4, 5-8 | D88: 3.556 | E88: 0.133 | F88: 0.046 | G88: 2.39
A89: LDNO EHV: Non-Domestic Aggregated or CT Band 1 | B89: C31 | C89: 0, 3, 4, 5-8 | D89: 3.556 | E89: 0.133 | F89: 0.046 | G89: 4.09
A90: LDNO EHV: Non-Domestic Aggregated or CT Band 2 | B90: C32 | C90: 0, 3, 4, 5-8 | D90: 3.556 | E90: 0.133 | F90: 0.046 | G90: 11.68
A91: LDNO EHV: Non-Domestic Aggregated or CT Band 3 | B91: C33 | C91: 0, 3, 4, 5-8 | D91: 3.556 | E91: 0.133 | F91: 0.046 | G91: 23.95
A92: LDNO EHV: Non-Domestic Aggregated or CT Band 4 | B92: C34 | C92: 0, 3, 4, 5-8 | D92: 3.556 | E92: 0.133 | F92: 0.046 | G92: 69.26
A93: LDNO EHV: Non-Domestic Aggregated (related MPAN) | B93: D30 | C93: 4 | D93: 3.556 | E93: 0.133 | F93: 0.046
A94: LDNO EHV: LV Site Specific No Residual | B94: E30 | C94: 0 | D94: 2.948 | E94: 0.107 | F94: 0.036 | G94: 6.23 | H94: 1.3 | I94: 2.31 | J94: 0.096
A95: LDNO EHV: LV Site Specific Band 1 | B95: E31 | C95: 0 | D95: 2.948 | E95: 0.107 | F95: 0.036 | G95: 132.04 | H95: 1.3 | I95: 2.31 | J95: 0.096
A96: LDNO EHV: LV Site Specific Band 2 | B96: E32 | C96: 0 | D96: 2.948 | E96: 0.107 | F96: 0.036 | G96: 218.21 | H96: 1.3 | I96: 2.31 | J96: 0.096
A97: LDNO EHV: LV Site Specific Band 3 | B97: E33 | C97: 0 | D97: 2.948 | E97: 0.107 | F97: 0.036 | G97: 352.4 | H97: 1.3 | I97: 2.31 | J97: 0.096
A98: LDNO EHV: LV Site Specific Band 4 | B98: E34 | C98: 0 | D98: 2.948 | E98: 0.107 | F98: 0.036 | G98: 776.67 | H98: 1.3 | I98: 2.31 | J98: 0.096
A99: LDNO EHV: LV Sub Site Specific No Residual | B99: J30 | C99: 0 | D99: 2.88 | E99: 0.098 | F99: 0.031 | G99: 7.7 | H99: 2.87 | I99: 3.64 | J99: 0.091
A100: LDNO EHV: LV Sub Site Specific Band 1 | B100: J31 | C100: 0 | D100: 2.88 | E100: 0.098 | F100: 0.031 | G100: 198.57 | H100: 2.87 | I100: 3.64 | J100: 0.091
A101: LDNO EHV: LV Sub Site Specific Band 2 | B101: J32 | C101: 0 | D101: 2.88 | E101: 0.098 | F101: 0.031 | G101: 329.31 | H101: 2.87 | I101: 3.64 | J101: 0.091
A102: LDNO EHV: LV Sub Site Specific Band 3 | B102: J33 | C102: 0 | D102: 2.88 | E102: 0.098 | F102: 0.031 | G102: 532.9 | H102: 2.87 | I102: 3.64 | J102: 0.091
A103: LDNO EHV: LV Sub Site Specific Band 4 | B103: J34 | C103: 0 | D103: 2.88 | E103: 0.098 | F103: 0.031 | G103: 1176.57 | H103: 2.87 | I103: 3.64 | J103: 0.091
A104: LDNO EHV: HV Site Specific No Residual | B104: K30 | C104: 0 | D104: 2.807 | E104: 0.091 | F104: 0.027 | G104: 91.61 | H104: 2.45 | I104: 3.63 | J104: 0.088
A105: LDNO EHV: HV Site Specific Band 1 | B105: K31 | C105: 0 | D105: 2.807 | E105: 0.091 | F105: 0.027 | G105: 945.3 | H105: 2.45 | I105: 3.63 | J105: 0.088
... A108: LDNO EHV: HV Site Specific Band 4 | B108: K34 | C108: 0 | D108: 2.807 | E108: 0.091 | F108: 0.027 | G108: 10925.43 | H108: 2.45 | I108: 3.63 | J108: 0.088
...

Sheet Annex 5 LLFs
A1: Back to Overview
A2: These line loss factors are illustrative based on the latest calculated values and are published in good faith. However, the line loss factors that are approved by the BSC Panel for the applicable year and consequently published on the Elexon website will take precedence and will be used in Settlement if they differ from these values.
A3: =Overview!B4& " - Illustrative LLFs for year beginning "&Overview!D4 -> South Eastern Power Networks - Illustrative LLFs for year beginning 1 April 2024
A4: Time periods | C4: Period 1 | D4: Period 2 | E4: Period 3 | F4: Period 4 | G4: Period 5
C5: Winter Peak | D5: Summer Peak | E5: Winter Shoulder | F5: Night | G5: Other
A6: Monday to Friday November to February | C6: 16:00 - 20:00 | E6: 07:00 - 16:00
A7: Monday to Friday June to August | D7: 07:00 - 20:00
A8: Monday to Friday March | E8: 07:00 - 20:00
A9: All Year | F9: 00:00 - 07:00 | G9: All Other Times
A10: Notes | C10: All the above times are in UK Clock time
A12: Generic demand and generation LLFs
A13: Metered voltage, respective periods and associated LLFCs
A14: Metered voltage | B14: Period 1 | C14: Period 2 | D14: Period 3 | E14: Period 4 | F14: Period 5 | G14: Associated LLFC
A15: Low-voltage network | B15: 1.106 | C15: 1.078 | D15: 1.093 | E15: 1.07 | F15: 1.083 | G15: 1, 2, 70, 71, 72, 73, 74, 100, 199, 200, 201, 202, 203, 204, 300, 350, 351, 352, 353, 354, 355, 356, 357, 358, 359, 360, 361, 362, 363, 364, 365, 366, 932, 980, 981
A16: Low-voltage substation | B16: 1.047 | C16: 1.039 | D16: 1.043 | E16: 1.039 | F16: 1.041 | G16: 80, 81, 82, 83, 84, 984, 985
A17: High-voltage network | B17: 1.036 | C17: 1.028 | D17: 1.032 | E17: 1.025 | F17: 1.029 | G17: 90, 91, 92, 93, 94, 988, 989
A18: High-voltage substation | B18: 1.03 | C18: 1.024 | D18: 1.027 | E18: 1.022 | F18: 1.025 | G18: 771, 791, 792
A19: 33kV generic | B19: 1.017 | C19: 1.013 | D19: 1.015 | E19: 1.012 | F19: 1.014 | G19: 796, 797
A20: 132kV generic | B20: 1.006 | C20: 1.005 | D20: 1.006 | E20: 1.004 | F20: 1.005 | G20: 798, 799
A22: EHV site specific LLFs
A23: Demand
A24: Site | B24: Period 1 | C24: Period 2 | D24: Period 3 | E24: Period 4 | F24: Period 5 | G24: Associated LLFC
A25: NEWHVN - Import | B25: 1.035 | C25: 1.05 | D25: 1.049 | E25: 1.046 | F25: 1.048 | G25: 800
A26: BRKHST - Import | B26: 1.047 | C26: 1.016 | D26: 1.048 | E26: 1.03 | F26: 1.032 | G26: 802
A27: KNWLTN - Import | B27: 1.017 | C27: 1.013 | D27: 1.015 | E27: 1.012 | F27: 1.014 | G27: 803
A28: DSCPRK - Import | B28: 1.023 | C28: 1.017 | D28: 1.022 | E28: 1.011 | F28: 1.015 | G28: 804
A29: OLDRSF - Import | B29: 1.017 | C29: 1.013 | D29: 1.015 | E29: 1.012 | F29: 1.014 | G29: 805
A30: WSTWDX - Import | B30: 1.017 | C30: 1.013 | D30: 1.015 | E30: 1.012 | F30: 1.014 | G30: 806
A31: SYCAMR - Import | B31: 1.017 | C31: 1.013 | D31: 1.015 | E31: 1.012 | F31: 1.014 | G31: 807
A32: LENHAM - Import | B32: 1.017 | C32: 1.013 | D32: 1.015 | E32: 1.012 | F32: 1.014 | G32: 808
A33: ASHBYS - Import | B33: 1.017 | C33: 1.013 | D33: 1.015 | E33: 1.012 | F33: 1.014 | G33: 809
A34: BTBRKS - Import | B34: 1.017 | C34: 1.013 | D34: 1.015 | E34: 1.012 | F34: 1.014 | G34: 810
A35: FRWOOD - Import | B35: 1.017 | C35: 1.013 | D35: 1.015 | E35: 1.012 | F35: 1.014 | G35: 811
A36: HADLOW - Import | B36: 1.017 | C36: 1.013 | D36: 1.015 | E36: 1.012 | F36: 1.014 | G36: 812
... A116: POTMBS - Import | B116: 1.006 | C116: 1.005 | D116: 1.006 | E116: 1.004 | F116: 1.005 | G116: 925
A118: EHV site specific LLFs
A119: Generation
A120: Site | B120: Period 1 | C120: Period 2 | D120: Period 3 | E120: Period 4 | F120: Period 5 | G120: Associated LLFC
A121: THAMEM - Export | B121: 1.03 | C121: 1.024 | D121: 1.027 | E121: 1.022 | F121: 1.025 | G121: 691
A122: TWHK66 - Export | B122: 1.03 | C122: 1.024 | D122: 1.027 | E122: 1.022 | F122: 1.025 | G122: 692
A123: BEDERF - Export | B123: 1.001 | C123: 0.998 | D123: 1 | E123: 0.998 | F123: 0.999 | G123: 693
A124: BESAYL - Export | B124: 1 | C124: 1 | D124: 1 | E124: 1 | F124: 1 | G124: 694
A125: BRAMBS - Export | B125: 1 | C125: 1 | D125: 1 | E125: 1 | F125: 1 | G125: 695
A126: BRELLE - Export | B126: 1 | C126: 0.999 | D126: 1 | E126: 1 | F126: 1 | G126: 696
A127: GLASSN - Export | B127: 1.004 | C127: 1.002 | D127: 1.003 | E127: 1.001 | F127: 1.002 | G127: 697
A128: NEWRID - Export | B128: 1 | C128: 0.999 | D128: 1 | E128: 1 | F128: 1 | G128: 698
A129: KM3CHP - Export | B129: 1 | C129: 1 | D129: 1 | E129: 1 | F129: 1 | G129: 699
A130: NEWHVN - Export | B130: 1.014 | C130: 1.009 | D130: 1.013 | E130: 1.009 | F130: 1.011 | G130: 700
A131: HORAMS - Export | B131: 1.056 | C131: 1.037 | D131: 1.037 | E131: 1.03 | F131: 1.045 | G131: 701
A132: WDLNDS - Export | B132: 1 | C132: 0.994 | D132: 0.996 | E132: 0.999 | F132: 0.995 | G132: 702
... A185: POTMBS - Export | B185: 1.006 | C185: 1.005 | D185: 1.006 | E185: 1.004 | F185: 1.005 | G185: 785
A187: CVA site specific LLFs
A188: Site | B188: Period 1 | C188: Period 2 | D188: Period 3 | E188: Period 4 | F188: Period 5 | G188: MSID
A189: Dartford _J DSCP | B189: 1.018 | C189: 1.014 | D189: 1.017 | E189: 1.013 | F189: 1.015 | G189: 1032
A190: Bromley DSCP | B190: 1.006 | C190: 1.005 | D190: 1.006 | E190: 1.005 | F190: 1.006 | G190: 1630
A191: Shoreham Power Station - Export | B191: 1.002 | C191: 0.999 | D191: 1.001 | E191: 0.999 | F191: 1.002 | G191: 7104
A192: Shoreham Power Station - Import | B192: 1.036 | C192: 1.028 | D192: 1.032 | E192: 1.025 | F192: 1.029 | G192: 7105
A193: Sevington District Energy | B193: 1.03 | C193: 1.024 | D193: 1.027 | E193: 1.022 | F193: 1.025 | G193: 7160
A194: Kents Farm Battery Storage - Import | B194: 1.016 | C194: 1.016 | D194: 1.018 | E194: 1.017 | F194: 1.017 | G194: 7435
A195: Kents Farm Battery Storage - Export | B195: 1.004 | C195: 1.001 | D195: 1.001 | E195: 1 | F195: 1.002 | G195: 7436
A196: Croydon Energy Limited - Factory Lane - Import | B196: 1 | C196: 1 | D196: 1 | E196: 1 | F196: 1 | G196: 7441
A197: Croydon Energy Limited - Factory Lane - Export | B197: 0.999 | C197: 0.999 | D197: 0.999 | E197: 1 | F197: 1 | G197: 7442
A198: Broadditch Energy Storage - Import | B198: 1.017 | C198: 1.013 | D198: 1.015 | E198: 1.012 | F198: 1.014 | G198: 7478
A199: Broadditch Energy Storage - Export | B199: 1.017 | C199: 1.013 | D199: 1.015 | E199: 1.012 | F199: 1.014 | G199: 7479

Sheet Annex 6 New or Amended EHV
A1: Back to Overview | G1: Note: The DNO reserves the right to apply the listed charges to any other MPANs/MSIDs associated with the site. This includes reallocating charges to a traded MPAN at the same site where another MPAN has been disconnected or de-energised. If sites appear in both Annex 2 and Annex 6, the charges in Annex 6 take precedence. Where an existing Designated EHV Property is modified and energised in the charging year, we may revise the EDCM charges for the modified Designated EHV Property.
A2: Annex 6 - Charges for New or Amended Designated EHV Properties
A4: =Overview!B4& " - Effective from "&Overview!D4&" - "&Overview!E4&" new designated EHV charges" -> South Eastern Power Networks - Effective from 1 April 2024 - Final new designated EHV charges
A5: Effective from date | B5: Import Unique Identifier | C5: LLFC | D5: Import MPANs/MSIDs | E5: Export Unique Identifier | F5: LLFC | G5: Export MPANs/MSIDs | H5: Name | I5: Residual Charging Band | J5: ='Annex 2 EHV charges'!I9 -> Import Super Red unit charge (p/kWh) | K5: ='Annex 2 EHV charges'!J9 -> Import fixed charge (p/day) | L5: ='Annex 2 EHV charges'!K9 -> Import capacity charge (p/kVA/day) | M5: ='Annex 2 EHV charges'!L9 -> Import exceeded capacity charge (p/kVA/day) | N5: ='Annex 2 EHV charges'!M9 -> Export Super Red unit charge (p/kWh) | O5: ='Annex 2 EHV charges'!N9 -> Export fixed charge (p/day) | P5: ='Annex 2 EHV charges'!O9 -> Export capacity charge (p/kVA/day) | Q5: ='Annex 2 EHV charges'!P9 -> Export exceeded capacity charge (p/kVA/day)
A6: 45383 | B6: BRELLE | C6: 843 | D6: 1900091523116 | E6: BRELLE | F6: 696 | G6: 1900091523125 | H6: BRELLE | J6: 0 | K6: 57.61 | L6: 1.34 | M6: 1.34 | N6: 0 | O6: 1229.03 | P6: 0.05 | Q6: 0.05
A7: 45383 | B7: BROABS | D7: MSID: 7478 | E7: BROABS | G7: MSID: 7479 | H7: BROABS | J7: 0 | K7: 589.13 | L7: 1.08 | M7: 1.08 | N7: -0.074 | O7: 589.13 | P7: 0.05 | Q7: 0.05
A8: 01/04/2024 | B8: POTMBS | C8: 925 | D8: 1900092272791 | E8: POTMBS | F8: 785 | G8: 1900092272807 | H8: POTMBS | J8: 0 | K8: 1028.78 | L8: 0.95 | M8: 0.95 | N8: 0 | O8: 1028.78 | P8: 0.05 | Q8: 0.05
A9: 01/04/2024 | B9: BTBRKS | C9: 810 | D9: 1900091199350 | E9: BTBRKS | F9: 742 | G9: 1900091199379 | H9: BTBRKS | J9: 0.499 | K9: 83.11 | L9: 1.51 | M9: 1.51 | N9: 0 | O9: 1846.86 | P9: 0.05 | Q9: 0.05
A10: 01/04/2024 | B10: GATWEV | C10: 924 | D10: 1900092421070 | H10: GATWEV | I10: 1 | J10: 0.746 | K10: 3358.19 | L10: 1.81 | M10: 1.81
A11: 01/04/2024 | B11: GATWBS | C11: 907 | D11: 1900092421061 | E11: GATWBS | F11: 768 | G11: 1900092421113 | H11: GATWBS | I11: 1 | J11: 0.746 | K11: 3339.31 | L11: 1.08 | M11: 1.08 | N11: -0.793 | O11: 660.95 | P11: 0.05 | Q11: 0.05
A12: 01/04/2024 | B12: THAER1 | C12: 850 | D12: 1900090417081 | E12: THAER1 | F12: 733 | G12: 1900090417160 | H12: THAER1 | I12: 2 | J12: 0 | K12: 15767.52 | L12: 1.72 | M12: 1.72 | N12: -1.229 | O12: 1526.56 | P12: 0.05 | Q12: 0.05
A13: 01/04/2024 | B13: THAER2 | C13: 850 | D13: 1900090417106 | E13: THAER2 | F13: 733 | G13: 1900090417189 | H13: THAER2 | I13: 2 | J13: 0 | K13: 15452.22 | L13: 1.72 | M13: 1.72 | N13: -1.229 | O13: 1211.26 | P13: 0.05 | Q13: 0.05
A14: 01/04/2024 | B14: THAER3 | C14: 850 | D14: 1900090417133 | E14: THAER3 | F14: 733 | G14: 1900090417212 | H14: THAER3 | I14: 2 | J14: 0 | K14: 16319.29 | L14: 1.72 | M14: 1.72 | N14: -1.229 | O14: 2078.33 | P14: 0.05 | Q14: 0.05
A15: 01/04/2024 | B15: THAER4 | C15: 850 | D15: 1900090417151 | E15: THAER4 | F15: 733 | G15: 1900090417230 | H15: THAER4 | I15: 1 | J15: 0 | K15: 3132.12 | L15: 1.92 | M15: 1.92 | N15: -1.229 | O15: 659.48 | P15: 0.05 | Q15: 0.05
A16: 01/04/2024 | B16: THAER2 | C16: 850 | D16: 1900090417106 | E16: THAER2 | F16: 733 | G16: 1900090417189 | H16: THAER2 | I16: 2 | J16: 0 | K16: 15767.52 | L16: 1.72 | M16: 1.72 | N16: -1.229 | O16: 1526.56 | P16: 0.05 | Q16: 0.05
A17: 01/04/2024 | B17: THAER4 | C17: 850 | D17: 1900090417151 | E17: THAER4 | F17: 733 | G17: 1900090417230 | H17: THAER4 | I17: 1 | J17: 0 | K17: 2816.82 | L17: 2.33 | M17: 2.33 | N17: -1.229 | O17: 344.18 | P17: 0.05 | Q17: 0.05
A18: 01/04/2024 | B18: GATWBS | C18: 907 | D18: 1900092421061 | E18: GATWBS | F18: 768 | G18: 1900092421113 | H18: GATWBS | J18: 0.746 | K18: 462.67 | L18: 1.08 | M18: 1.08 | N18: -0.793 | O18: 660.95 | P18: 0.05 | Q18: 0.05
A19: 01/04/2024 | B19: LONGDC | D19: ENET | H19: LONGDC | I19: 2 | K19: 15575.58 | L19: 1.35 | M19: 1.35
A20: 01/04/2024 | B20: DSCPRK | C20: 804 | D20: 1900091637072;1900091057568;1900060219544 | E20: DSCPRK | F20: 704 | G20: 1900091637081;1900091057559 | H20: DSCPRK | I20: 3 | J20: 0 | K20: 40266.8 | L20: 0.96 | M20: 0.96 | N20: 0 | O20: 6634.06 | P20: 0.05 | Q20: 0.05
A22: =Overview!B4& " - Effective from "&Overview!D4&" - "&Overview!E4&" new designated EHV line loss factors" -> South Eastern Power Networks - Effective from 1 April 2024 - Final new designated EHV line loss factors
A23: Effective from date | B23: Import Unique Identifier | C23: LLFC | D23: Import MPANs/MSIDs | E23: Export Unique Identifier | F23: LLFC | G23: Export MPANs/MSIDs | H23: Name | I23: Residual Charging Band | J23: Import LLF period 1 | K23: Import LLF period 2 | L23: Import LLF period 3 | M23: Import LLF period 4 | N23: Import LLF period 5 | O23: Export LLF period 1 | P23: Export LLF period 2 | Q23: Export LLF period 3 | R23: Export LLF period 4 | S23: Export LLF period 5
A24: 01/04/2024 | B24: GATWEV | C24: 924 | D24: 1900092421070 | H24: GATWEV | I24: 1 | J24: 1.017 | K24: 1.013 | L24: 1.015 | M24: 1.012 | N24: 1.014
A25: 01/04/2024 | B25: GATWBS | C25: 907 | D25: 1900092421061 | E25: GATWBS | F25: 768 | G25: 1900092421113 | H25: GATWBS | I25: 1 | J25: 1.017 | K25: 1.013 | L25: 1.015 | M25: 1.012 | N25: 1.014 | O25: 1.017 | P25: 1.013 | Q25: 1.015 | R25: 1.012 | S25: 1.014

Sheet Annex 7 Pass-Through Costs
A1: Back to Overview
A2: =Overview!B4& " - Effective from "&Overview!D4&" - "&Overview!E4&" Supplier of Last Resort and Eligible Bad Debt Pass-Through Costs" -> South Eastern Power Networks - Effective from 1 April 2024 - Final Supplier of Last Resort and Eligible Bad Debt Pass-Through Costs
A4: Tariff name | B4: Open LLFCs / LDNO unique billing identifier | C4: PCs | D4: Supplier of Last Resort Fixed charge adder* p/MPAN/day | E4: Excess Supplier of Last Resort Fixed charge adder** p/MPAN/day | F4: Eligible Bad Debt Fixed charge adder*** p/MPAN/day
A5: Domestic Aggregated or CT with Residual | B5: =IFERROR(INDEX('Annex 1 LV, HV and UMS charges'!$B$12:$B$43,MATCH($A5,'Annex 1 LV, HV and UMS charges'!$A$12:$A$43,0)),IF(INDEX('Annex 4 LDNO charges'!$B$11:$B$201,MATCH($A5,'Annex 4 LDNO charges'!$A$11:$A$201,0))=0,"",INDEX('Annex 4 LDNO charges'!$B$11:$B$201,MATCH($A5,'Annex 4 LDNO charges'!$A$11:$A$201,0)))) -> 1 | C5: =IFERROR(INDEX('Annex 1 LV, HV and UMS charges'!$C$12:$C$43,MATCH($A5,'Annex 1 LV, HV and UMS charges'!$A$12:$A$43,0)),INDEX('Annex 4 LDNO charges'!$C$11:$C$201,MATCH($A5,'Annex 4 LDNO charges'!$A$11:$A$201,0))) -> 0, 1, 2 | D5: 0.18118202 | F5: 0.80732906
A6: Non-Domestic Aggregated or CT No Residual | B6: =IFERROR(INDEX('Annex 1 LV, HV and UMS charges'!$B$12:$B$43,MATCH($A6,'Annex 1 LV, HV and UMS charges'!$A$12:$A$43,0)),IF(INDEX('Annex 4 LDNO charges'!$B$11:$B$201,MATCH($A6,'Annex 4 LDNO charges'!$A$11:$A$201,0))=0,"",INDEX('Annex 4 LDNO charges'!$B$11:$B$201,MATCH($A6,'Annex 4 LDNO charges'!$A$11:$A$201,0)))) -> 199 | C6: =IFERROR(INDEX('Annex 1 LV, HV and UMS charges'!$C$12:$C$43,MATCH($A6,'Annex 1 LV, HV and UMS charges'!$A$12:$A$43,0)),INDEX('Annex 4 LDNO charges'!$C$11:$C$201,MATCH($A6,'Annex 4 LDNO charges'!$A$11:$A$201,0))) -> 0, 3, 4, 5-8 | F6: 0.80732906
A7: Non-Domestic Aggregated or CT Band 1 | B7: =IFERROR(INDEX('Annex 1 LV, HV and UMS charges'!$B$12:$B$43,MATCH($A7,'Annex 1 LV, HV and UMS charges'!$A$12:$A$43,0)),IF(INDEX('Annex 4 LDNO charges'!$B$11:$B$201,MATCH($A7,'Annex 4 LDNO charges'!$A$11:$A$201,0))=0,"",INDEX('Annex 4 LDNO charges'!$B$11:$B$201,MATCH($A7,'Annex 4 LDNO charges'!$A$11:$A$201,0)))) -> 201 | C7: =IFERROR(INDEX('Annex 1 LV, HV and UMS charges'!$C$12:$C$43,MATCH($A7,'Annex 1 LV, HV and UMS charges'!$A$12:$A$43,0)),INDEX('Annex 4 LDNO charges'!$C$11:$C$201,MATCH($A7,'Annex 4 LDNO charges'!$A$11:$A$201,0))) -> 0, 3, 4, 5-8 | F7: 0.80732906
A8: Non-Domestic Aggregated or CT Band 2 | B8: =IFERROR(INDEX('Annex 1 LV, HV and UMS charges'!$B$12:$B$43,MATCH($A8,'Annex 1 LV, HV and UMS charges'!$A$12:$A$43,0)),IF(INDEX('Annex 4 LDNO charges'!$B$11:$B$201,MATCH($A8,'Annex 4 LDNO charges'!$A$11:$A$201,0))=0,"",INDEX('Annex 4 LDNO charges'!$B$11:$B$201,MATCH($A8,'Annex 4 LDNO charges'!$A$11:$A$201,0)))) -> 202 | C8: =IFERROR(INDEX('Annex 1 LV, HV and UMS charges'!$C$12:$C$43,MATCH($A8,'Annex 1 LV, HV and UMS charges'!$A$12:$A$43,0)),INDEX('Annex 4 LDNO charges'!$C$11:$C$201,MATCH($A8,'Annex 4 LDNO charges'!$A$11:$A$201,0))) -> 0, 3, 4, 5-8 | F8: 0.80732906
A9: Non-Domestic Aggregated or CT Band 3 | B9: =IFERROR(INDEX('Annex 1 LV, HV and UMS charges'!$B$12:$B$43,MATCH($A9,'Annex 1 LV, HV and UMS charges'!$A$12:$A$43,0)),IF(INDEX('Annex 4 LDNO charges'!$B$11:$B$201,MATCH($A9,'Annex 4 LDNO charges'!$A$11:$A$201,0))=0,"",INDEX('Annex 4 LDNO charges'!$B$11:$B$201,MATCH($A9,'Annex 4 LDNO charges'!$A$11:$A$201,0)))) -> 203 | C9: =IFERROR(INDEX('Annex 1 LV, HV and UMS charges'!$C$12:$C$43,MATCH($A9,'Annex 1 LV, HV and UMS charges'!$A$12:$A$43,0)),INDEX('Annex 4 LDNO charges'!$C$11:$C$201,MATCH($A9,'Annex 4 LDNO charges'!$A$11:$A$201,0))) -> 0, 3, 4, 5-8 | F9: 0.80732906
A10: Non-Domestic Aggregated or CT Band 4 | B10: =IFERROR(INDEX('Annex 1 LV, HV and UMS charges'!$B$12:$B$43,MATCH($A10,'Annex 1 LV, HV and UMS charges'!$A$12:$A$43,0)),IF(INDEX('Annex 4 LDNO charges'!$B$11:$B$201,MATCH($A10,'Annex 4 LDNO charges'!$A$11:$A$201,0))=0,"",INDEX('Annex 4 LDNO charges'!$B$11:$B$201,MATCH($A10,'Annex 4 LDNO charges'!$A$11:$A$201,0)))) -> 204 | C10: =IFERROR(INDEX('Annex 1 LV, HV and UMS charges'!$C$12:$C$43,MATCH($A10,'Annex 1 LV, HV and UMS charges'!$A$12:$A$43,0)),INDEX('Annex 4 LDNO charges'!$C$11:$C$201,MATCH($A10,'Annex 4 LDNO charges'!$A$11:$A$201,0))) -> 0, 3, 4, 5-8 | F10: 0.80732906
A11: LV Site Specific No Residual | B11: =IFERROR(INDEX('Annex 1 LV, HV and UMS charges'!$B$12:$B$43,MATCH($A11,'Annex 1 LV, HV and UMS charges'!$A$12:$A$43,0)),IF(INDEX('Annex 4 LDNO charges'!$B$11:$B$201,MATCH($A11,'Annex 4 LDNO charges'!$A$11:$A$201,0))=0,"",INDEX('Annex 4 LDNO charges'!$B$11:$B$201,MATCH($A11,'Annex 4 LDNO charges'!$A$11:$A$201,0)))) -> 70 | C11: =IFERROR(INDEX('Annex 1 LV, HV and UMS charges'!$C$12:$C$43,MATCH($A11,'Annex 1 LV, HV and UMS charges'!$A$12:$A$43,0)),INDEX('Annex 4 LDNO charges'!$C$11:$C$201,MATCH($A11,'Annex 4 LDNO charges'!$A$11:$A$201,0))) -> 0 | F11: 0.80732906
A12: LV Site Specific Band 1 | B12: =IFERROR(INDEX('Annex 1 LV, HV and UMS charges'!$B$12:$B$43,MATCH($A12,'Annex 1 LV, HV and UMS charges'!$A$12:$A$43,0)),IF(INDEX('Annex 4 LDNO charges'!$B$11:$B$201,MATCH($A12,'Annex 4 LDNO charges'!$A$11:$A$201,0))=0,"",INDEX('Annex 4 LDNO charges'!$B$11:$B$201,MATCH($A12,'Annex 4 LDNO charges'!$A$11:$A$201,0)))) -> 71 | C12: =IFERROR(INDEX('Annex 1 LV, HV and UMS charges'!$C$12:$C$43,MATCH($A12,'Annex 1 LV, HV and UMS charges'!$A$12:$A$43,0)),INDEX('Annex 4 LDNO charges'!$C$11:$C$201,MATCH($A12,'Annex 4 LDNO charges'!$A$11:$A$201,0))) -> 0 | F12: 0.80732906
A13: LV Site Specific Band 2 | B13: =IFERROR(INDEX('Annex 1 LV, HV and UMS charges'!$B$12:$B$43,MATCH($A13,'Annex 1 LV, HV and UMS charges'!$A$12:$A$43,0)),IF(INDEX('Annex 4 LDNO charges'!$B$11:$B$201,MATCH($A13,'Annex 4 LDNO charges'!$A$11:$A$201,0))=0,"",INDEX('Annex 4 LDNO charges'!$B$11:$B$201,MATCH($A13,'Annex 4 LDNO charges'!$A$11:$A$201,0)))) -> 72 | C13: =IFERROR(INDEX('Annex 1 LV, HV and UMS charges'!$C$12:$C$43,MATCH($A13,'Annex 1 LV, HV and UMS charges'!$A$12:$A$43,0)),INDEX('Annex 4 LDNO charges'!$C$11:$C$201,MATCH($A13,'Annex 4 LDNO charges'!$A$11:$A$201,0))) -> 0 | F13: 0.80732906
A14: LV Site Specific Band 3 | B14: =IFERROR(INDEX('Annex 1 LV, HV and UMS charges'!$B$12:$B$43,MATCH($A14,'Annex 1 LV, HV and UMS charges'!$A$12:$A$43,0)),IF(INDEX('Annex 4 LDNO charges'!$B$11:$B$201,MATCH($A14,'Annex 4 LDNO charges'!$A$11:$A$201,0))=0,"",INDEX('Annex 4 LDNO charges'!$B$11:$B$201,MATCH($A14,'Annex 4 LDNO charges'!$A$11:$A$201,0)))) -> 73 | C14: =IFERROR(INDEX('Annex 1 LV, HV and UMS charges'!$C$12:$C$43,MATCH($A14,'Annex 1 LV, HV and UMS charges'!$A$12:$A$43,0)),INDEX('Annex 4 LDNO charges'!$C$11:$C$201,MATCH($A14,'Annex 4 LDNO charges'!$A$11:$A$201,0))) -> 0 | F14: 0.80732906
A15: LV Site Specific Band 4 | B15: =IFERROR(INDEX('Annex 1 LV, HV and UMS charges'!$B$12:$B$43,MATCH($A15,'Annex 1 LV, HV and UMS charges'!$A$12:$A$43,0)),IF(INDEX('Annex 4 LDNO charges'!$B$11:$B$201,MATCH($A15,'Annex 4 LDNO charges'!$A$11:$A$201,0))=0,"",INDEX('Annex 4 LDNO charges'!$B$11:$B$201,MATCH($A15,'Annex 4 LDNO charges'!$A$11:$A$201,0)))) -> 74 | C15: =IFERROR(INDEX('Annex 1 LV, HV and UMS charges'!$C$12:$C$43,MATCH($A15,'Annex 1 LV, HV and UMS charges'!$A$12:$A$43,0)),INDEX('Annex 4 LDNO charges'!$C$11:$C$201,MATCH($A15,'Annex 4 LDNO charges'!$A$11:$A$201,0))) -> 0 | F15: 0.80732906
A16: LV Sub Site Specific No Residual | B16: =IFERROR(INDEX('Annex 1 LV, HV and UMS charges'!$B$12:$B$43,MATCH($A16,'Annex 1 LV, HV and UMS charges'!$A$12:$A$43,0)),IF(INDEX('Annex 4 LDNO charges'!$B$11:$B$201,MATCH($A16,'Annex 4 LDNO charges'!$A$11:$A$201,0))=0,"",INDEX('Annex 4 LDNO charges'!$B$11:$B$201,MATCH($A16,'Annex 4 LDNO charges'!$A$11:$A$201,0)))) -> 80 | C16: =IFERROR(INDEX('Annex 1 LV, HV and UMS charges'!$C$12:$C$43,MATCH($A16,'Annex 1 LV, HV and UMS charges'!$A$12:$A$43,0)),INDEX('Annex 4 LDNO charges'!$C$11:$C$201,MATCH($A16,'Annex 4 LDNO charges'!$A$11:$A$201,0))) -> 0 | F16: 0.80732906
A17: LV Sub Site Specific Band 1 | B17: =IFERROR(INDEX('Annex 1 LV, HV and UMS charges'!$B$12:$B$43,MATCH($A17,'Annex 1 LV, HV and UMS charges'!$A$12:$A$43,0)),IF(INDEX('Annex 4 LDNO charges'!$B$11:$B$201,MATCH($A17,'Annex 4 LDNO charges'!$A$11:$A$201,0))=0,"",INDEX('Annex 4 LDNO charges'!$B$11:$B$201,MATCH($A17,'Annex 4 LDNO charges'!$A$11:$A$201,0)))) -> 81 | C17: =IFERROR(INDEX('Annex 1 LV, HV and UMS charges'!$C$12:$C$43,MATCH($A17,'Annex 1 LV, HV and UMS charges'!$A$12:$A$43,0)),INDEX('Annex 4 LDNO charges'!$C$11:$C$201,MATCH($A17,'Annex 4 LDNO charges'!$A$11:$A$201,0))) -> 0 | F17: 0.80732906
... A25: HV Site Specific Band 4 | B25: =IFERROR(INDEX('Annex 1 LV, HV and UMS charges'!$B$12:$B$43,MATCH($A25,'Annex 1 LV, HV and UMS charges'!$A$12:$A$43,0)),IF(INDEX('Annex 4 LDNO charges'!$B$11:$B$201,MATCH($A25,'Annex 4 LDNO charges'!$A$11:$A$201,0))=0,"",INDEX('Annex 4 LDNO charges'!$B$11:$B$201,MATCH($A25,'Annex 4 LDNO charges'!$A$11:$A$201,0)))) -> 94 | C25: =IFERROR(INDEX('Annex 1 LV, HV and UMS charges'!$C$12:$C$43,MATCH($A25,'Annex 1 LV, HV and UMS charges'!$A$12:$A$43,0)),INDEX('Annex 4 LDNO charges'!$C$11:$C$201,MATCH($A25,'Annex 4 LDNO charges'!$A$11:$A$201,0))) -> 0 | F25: 0.80732906
A26: LDNO LV: Domestic Aggregated or CT with Residual | B26: =IFERROR(INDEX('Annex 1 LV, HV and UMS charges'!$B$12:$B$43,MATCH($A26,'Annex 1 LV, HV and UMS charges'!$A$12:$A$43,0)),IF(INDEX('Annex 4 LDNO charges'!$B$11:$B$201,MATCH($A26,'Annex 4 LDNO charges'!$A$11:$A$201,0))=0,"",INDEX('Annex 4 LDNO charges'!$B$11:$B$201,MATCH($A26,'Annex 4 LDNO charges'!$A$11:$A$201,0)))) -> A00 | C26: =IFERROR(INDEX('Annex 1 LV, HV and UMS charges'!$C$12:$C$43,MATCH($A26,'Annex 1 LV, HV and UMS charges'!$A$12:$A$43,0)),INDEX('Annex 4 LDNO charges'!$C$11:$C$201,MATCH($A26,'Annex 4 LDNO charges'!$A$11:$A$201,0))) -> 0, 1, 2 | D26: 0.18118202 | F26: 0.80732906
A27: LDNO LV: Non-Domestic Aggregated or CT No Residual | B27: =IFERROR(INDEX('Annex 1 LV, HV and UMS charges'!$B$12:$B$43,MATCH($A27,'Annex 1 LV, HV and UMS charges'!$A$12:$A$43,0)),IF(INDEX('Annex 4 LDNO charges'!$B$11:$B$201,MATCH($A27,'Annex 4 LDNO charges'!$A$11:$A$201,0))=0,"",INDEX('Annex 4 LDNO charges'!$B$11:$B$201,MATCH($A27,'Annex 4 LDNO charges'!$A$11:$A$201,0)))) -> C00 | C27: =IFERROR(INDEX('Annex 1 LV, HV and UMS charges'!$C$12:$C$43,MATCH($A27,'Annex 1 LV, HV and UMS charges'!$A$12:$A$43,0)),INDEX('Annex 4 LDNO charges'!$C$11:$C$201,MATCH($A27,'Annex 4 LDNO charges'!$A$11:$A$201,0))) -> 0, 3, 4, 5-8 | F27: 0.80732906
A28: LDNO LV: Non-Domestic Aggregated or CT Band 1 | B28: =IFERROR(INDEX('Annex 1 LV, HV and UMS charges'!$B$12:$B$43,MATCH($A28,'Annex 1 LV, HV and UMS charges'!$A$12:$A$43,0)),IF(INDEX('Annex 4 LDNO charges'!$B$11:$B$201,MATCH($A28,'Annex 4 LDNO charges'!$A$11:$A$201,0))=0,"",INDEX('Annex 4 LDNO charges'!$B$11:$B$201,MATCH($A28,'Annex 4 LDNO charges'!$A$11:$A$201,0)))) -> C01 | C28: =IFERROR(INDEX('Annex 1 LV, HV and UMS charges'!$C$12:$C$43,MATCH($A28,'Annex 1 LV, HV and UMS charges'!$A$12:$A$43,0)),INDEX('Annex 4 LDNO charges'!$C$11:$C$201,MATCH($A28,'Annex 4 LDNO charges'!$A$11:$A$201,0))) -> 0, 3, 4, 5-8 | F28: 0.80732906
A29: LDNO LV: Non-Domestic Aggregated or CT Band 2 | B29: =IFERROR(INDEX('Annex 1 LV, HV and UMS charges'!$B$12:$B$43,MATCH($A29,'Annex 1 LV, HV and UMS charges'!$A$12:$A$43,0)),IF(INDEX('Annex 4 LDNO charges'!$B$11:$B$201,MATCH($A29,'Annex 4 LDNO charges'!$A$11:$A$201,0))=0,"",INDEX('Annex 4 LDNO charges'!$B$11:$B$201,MATCH($A29,'Annex 4 LDNO charges'!$A$11:$A$201,0)))) -> C02 | C29: =IFERROR(INDEX('Annex 1 LV, HV and UMS charges'!$C$12:$C$43,MATCH($A29,'Annex 1 LV, HV and UMS charges'!$A$12:$A$43,0)),INDEX('Annex 4 LDNO charges'!$C$11:$C$201,MATCH($A29,'Annex 4 LDNO charges'!$A$11:$A$201,0))) -> 0, 3, 4, 5-8 | F29: 0.80732906
A30: LDNO LV: Non-Domestic Aggregated or CT Band 3 | B30: =IFERROR(INDEX('Annex 1 LV, HV and UMS charges'!$B$12:$B$43,MATCH($A30,'Annex 1 LV, HV and UMS charges'!$A$12:$A$43,0)),IF(INDEX('Annex 4 LDNO charges'!$B$11:$B$201,MATCH($A30,'Annex 4 LDNO charges'!$A$11:$A$201,0))=0,"",INDEX('Annex 4 LDNO charges'!$B$11:$B$201,MATCH($A30,'Annex 4 LDNO charges'!$A$11:$A$201,0)))) -> C03 | C30: =IFERROR(INDEX('Annex 1 LV, HV and UMS charges'!$C$12:$C$43,MATCH($A30,'Annex 1 LV, HV and UMS charges'!$A$12:$A$43,0)),INDEX('Annex 4 LDNO charges'!$C$11:$C$201,MATCH($A30,'Annex 4 LDNO charges'!$A$11:$A$201,0))) -> 0, 3, 4, 5-8 | F30: 0.80732906
A31: LDNO LV: Non-Domestic Aggregated or CT Band 4 | B31: =IFERROR(INDEX('Annex 1 LV, HV and UMS charges'!$B$12:$B$43,MATCH($A31,'Annex 1 LV, HV and UMS charges'!$A$12:$A$43,0)),IF(INDEX('Annex 4 LDNO charges'!$B$11:$B$201,MATCH($A31,'Annex 4 LDNO charges'!$A$11:$A$201,0))=0,"",INDEX('Annex 4 LDNO charges'!$B$11:$B$201,MATCH($A31,'Annex 4 LDNO charges'!$A$11:$A$201,0)))) -> C04 | C31: =IFERROR(INDEX('Annex 1 LV, HV and UMS charges'!$C$12:$C$43,MATCH($A31,'Annex 1 LV, HV and UMS charges'!$A$12:$A$43,0)),INDEX('Annex 4 LDNO charges'!$C$11:$C$201,MATCH($A31,'Annex 4 LDNO charges'!$A$11:$A$201,0))) -> 0, 3, 4, 5-8 | F31: 0.80732906
A32: LDNO LV: LV Site Specific No Residual | B32: =IFERROR(INDEX('Annex 1 LV, HV and UMS charges'!$B$12:$B$43,MATCH($A32,'Annex 1 LV, HV and UMS charges'!$A$12:$A$43,0)),IF(INDEX('Annex 4 LDNO charges'!$B$11:$B$201,MATCH($A32,'Annex 4 LDNO charges'!$A$11:$A$201,0))=0,"",INDEX('Annex 4 LDNO charges'!$B$11:$B$201,MATCH($A32,'Annex 4 LDNO charges'!$A$11:$A$201,0)))) -> E00 | C32: =IFERROR(INDEX('Annex 1 LV, HV and UMS charges'!$C$12:$C$43,MATCH($A32,'Annex 1 LV, HV and UMS charges'!$A$12:$A$43,0)),INDEX('Annex 4 LDNO charges'!$C$11:$C$201,MATCH($A32,'Annex 4 LDNO charges'!$A$11:$A$201,0))) -> 0 | F32: 0.80732906
A33: LDNO LV: LV Site Specific Band 1 | B33: =IFERROR(INDEX('Annex 1 LV, HV and UMS charges'!$B$12:$B$43,MATCH($A33,'Annex 1 LV, HV and UMS charges'!$A$12:$A$43,0)),IF(INDEX('Annex 4 LDNO charges'!$B$11:$B$201,MATCH($A33,'Annex 4 LDNO charges'!$A$11:$A$201,0))=0,"",INDEX('Annex 4 LDNO charges'!$B$11:$B$201,MATCH($A33,'Annex 4 LDNO charges'!$A$11:$A$201,0)))) -> E01 | C33: =IFERROR(INDEX('Annex 1 LV, HV and UMS charges'!$C$12:$C$43,MATCH($A33,'Annex 1 LV, HV and UMS charges'!$A$12:$A$43,0)),INDEX('Annex 4 LDNO charges'!$C$11:$C$201,MATCH($A33,'Annex 4 LDNO charges'!$A$11:$A$201,0))) -> 0 | F33: 0.80732906
A34: LDNO LV: LV Site Specific Band 2 | B34: =IFERROR(INDEX('Annex 1 LV, HV and UMS charges'!$B$12:$B$43,MATCH($A34,'Annex 1 LV, HV and UMS charges'!$A$12:$A$43,0)),IF(INDEX('Annex 4 LDNO charges'!$B$11:$B$201,MATCH($A34,'Annex 4 LDNO charges'!$A$11:$A$201,0))=0,"",INDEX('Annex 4 LDNO charges'!$B$11:$B$201,MATCH($A34,'Annex 4 LDNO charges'!$A$11:$A$201,0)))) -> E02 | C34: =IFERROR(INDEX('Annex 1 LV, HV and UMS charges'!$C$12:$C$43,MATCH($A34,'Annex 1 LV, HV and UMS charges'!$A$12:$A$43,0)),INDEX('Annex 4 LDNO charges'!$C$11:$C$201,MATCH($A34,'Annex 4 LDNO charges'!$A$11:$A$201,0))) -> 0 | F34: 0.80732906
A35: LDNO LV: LV Site Specific Band 3 | B35: =IFERROR(INDEX('Annex 1 LV, HV and UMS charges'!$B$12:$B$43,MATCH($A35,'Annex 1 LV, HV and UMS charges'!$A$12:$A$43,0)),IF(INDEX('Annex 4 LDNO charges'!$B$11:$B$201,MATCH($A35,'Annex 4 LDNO charges'!$A$11:$A$201,0))=0,"",INDEX('Annex 4 LDNO charges'!$B$11:$B$201,MATCH($A35,'Annex 4 LDNO charges'!$A$11:$A$201,0)))) -> E03 | C35: =IFERROR(INDEX('Annex 1 LV, HV and UMS charges'!$C$12:$C$43,MATCH($A35,'Annex 1 LV, HV and UMS charges'!$A$12:$A$43,0)),INDEX('Annex 4 LDNO charges'!$C$11:$C$201,MATCH($A35,'Annex 4 LDNO charges'!$A$11:$A$201,0))) -> 0 | F35: 0.80732906
A36: LDNO LV: LV Site Specific Band 4 | B36: =IFERROR(INDEX('Annex 1 LV, HV and UMS charges'!$B$12:$B$43,MATCH($A36,'Annex 1 LV, HV and UMS charges'!$A$12:$A$43,0)),IF(INDEX('Annex 4 LDNO charges'!$B$11:$B$201,MATCH($A36,'Annex 4 LDNO charges'!$A$11:$A$201,0))=0,"",INDEX('Annex 4 LDNO charges'!$B$11:$B$201,MATCH($A36,'Annex 4 LDNO charges'!$A$11:$A$201,0)))) -> E04 | C36: =IFERROR(INDEX('Annex 1 LV, HV and UMS charges'!$C$12:$C$43,MATCH($A36,'Annex 1 LV, HV and UMS charges'!$A$12:$A$43,0)),INDEX('Annex 4 LDNO charges'!$C$11:$C$201,MATCH($A36,'Annex 4 LDNO charges'!$A$11:$A$201,0))) -> 0 | F36: 0.80732906
A37: LDNO HV: Domestic Aggregated or CT with Residual | B37: =IFERROR(INDEX('Annex 1 LV, HV and UMS charges'!$B$12:$B$43,MATCH($A37,'Annex 1 LV, HV and UMS charges'!$A$12:$A$43,0)),IF(INDEX('Annex 4 LDNO charges'!$B$11:$B$201,MATCH($A37,'Annex 4 LDNO charges'!$A$11:$A$201,0))=0,"",INDEX('Annex 4 LDNO charges'!$B$11:$B$201,MATCH($A37,'Annex 4 LDNO charges'!$A$11:$A$201,0)))) -> A10 | C37: =IFERROR(INDEX('Annex 1 LV, HV and UMS charges'!$C$12:$C$43,MATCH($A37,'Annex 1 LV, HV and UMS charges'!$A$12:$A$43,0)),INDEX('Annex 4 LDNO charges'!$C$11:$C$201,MATCH($A37,'Annex 4 LDNO charges'!$A$11:$A$201,0))) -> 0, 1, 2 | D37: 0.18118202 | F37: 0.80732906
A38: LDNO HV: Non-Domestic Aggregated or CT No Residual | B38: =IFERROR(INDEX('Annex 1 LV, HV and UMS charges'!$B$12:$B$43,MATCH($A38,'Annex 1 LV, HV and UMS charges'!$A$12:$A$43,0)),IF(INDEX('Annex 4 LDNO charges'!$B$11:$B$201,MATCH($A38,'Annex 4 LDNO charges'!$A$11:$A$201,0))=0,"",INDEX('Annex 4 LDNO charges'!$B$11:$B$201,MATCH($A38,'Annex 4 LDNO charges'!$A$11:$A$201,0)))) -> C10 | C38: =IFERROR(INDEX('Annex 1 LV, HV and UMS charges'!$C$12:$C$43,MATCH($A38,'Annex 1 LV, HV and UMS charges'!$A$12:$A$43,0)),INDEX('Annex 4 LDNO charges'!$C$11:$C$201,MATCH($A38,'Annex 4 LDNO charges'!$A$11:$A$201,0))) -> 0, 3, 4, 5-8 | F38: 0.80732906
A39: LDNO HV: Non-Domestic Aggregated or CT Band 1 | B39: =IFERROR(INDEX('Annex 1 LV, HV and UMS charges'!$B$12:$B$43,MATCH($A39,'Annex 1 LV, HV and UMS charges'!$A$12:$A$43,0)),IF(INDEX('Annex 4 LDNO charges'!$B$11:$B$201,MATCH($A39,'Annex 4 LDNO charges'!$A$11:$A$201,0))=0,"",INDEX('Annex 4 LDNO charges'!$B$11:$B$201,MATCH($A39,'Annex 4 LDNO charges'!$A$11:$A$201,0)))) -> C11 | C39: =IFERROR(INDEX('Annex 1 LV, HV and UMS charges'!$C$12:$C$43,MATCH($A39,'Annex 1 LV, HV and UMS charges'!$A$12:$A$43,0)),INDEX('Annex 4 LDNO charges'!$C$11:$C$201,MATCH($A39,'Annex 4 LDNO charges'!$A$11:$A$201,0))) -> 0, 3, 4, 5-8 | F39: 0.80732906
A40: LDNO HV: Non-Domestic Aggregated or CT Band 2 | B40: =IFERROR(INDEX('Annex 1 LV, HV and UMS charges'!$B$12:$B$43,MATCH($A40,'Annex 1 LV, HV and UMS charges'!$A$12:$A$43,0)),IF(INDEX('Annex 4 LDNO charges'!$B$11:$B$201,MATCH($A40,'Annex 4 LDNO charges'!$A$11:$A$201,0))=0,"",INDEX('Annex 4 LDNO charges'!$B$11:$B$201,MATCH($A40,'Annex 4 LDNO charges'!$A$11:$A$201,0)))) -> C12 | C40: =IFERROR(INDEX('Annex 1 LV, HV and UMS charges'!$C$12:$C$43,MATCH($A40,'Annex 1 LV, HV and UMS charges'!$A$12:$A$43,0)),INDEX('Annex 4 LDNO charges'!$C$11:$C$201,MATCH($A40,'Annex 4 LDNO charges'!$A$11:$A$201,0))) -> 0, 3, 4, 5-8 | F40: 0.80732906
A41: LDNO HV: Non-Domestic Aggregated or CT Band 3 | B41: =IFERROR(INDEX('Annex 1 LV, HV and UMS charges'!$B$12:$B$43,MATCH($A41,'Annex 1 LV, HV and UMS charges'!$A$12:$A$43,0)),IF(INDEX('Annex 4 LDNO charges'!$B$11:$B$201,MATCH($A41,'Annex 4 LDNO charges'!$A$11:$A$201,0))=0,"",INDEX('Annex 4 LDNO charges'!$B$11:$B$201,MATCH($A41,'Annex 4 LDNO charges'!$A$11:$A$201,0)))) -> C13 | C41: =IFERROR(INDEX('Annex 1 LV, HV and UMS charges'!$C$12:$C$43,MATCH($A41,'Annex 1 LV, HV and UMS charges'!$A$12:$A$43,0)),INDEX('Annex 4 LDNO charges'!$C$11:$C$201,MATCH($A41,'Annex 4 LDNO charges'!$A$11:$A$201,0))) -> 0, 3, 4, 5-8 | F41: 0.80732906
A42: LDNO HV: Non-Domestic Aggregated or CT Band 4 | B42: =IFERROR(INDEX('Annex 1 LV, HV and UMS charges'!$B$12:$B$43,MATCH($A42,'Annex 1 LV, HV and UMS charges'!$A$12:$A$43,0)),IF(INDEX('Annex 4 LDNO charges'!$B$11:$B$201,MATCH($A42,'Annex 4 LDNO charges'!$A$11:$A$201,0))=0,"",INDEX('Annex 4 LDNO charges'!$B$11:$B$201,MATCH($A42,'Annex 4 LDNO charges'!$A$11:$A$201,0)))) -> C14 | C42: =IFERROR(INDEX('Annex 1 LV, HV and UMS charges'!$C$12:$C$43,MATCH($A42,'Annex 1 LV, HV and UMS charges'!$A$12:$A$43,0)),INDEX('Annex 4 LDNO charges'!$C$11:$C$201,MATCH($A42,'Annex 4 LDNO charges'!$A$11:$A$201,0))) -> 0, 3, 4, 5-8 | F42: 0.80732906
A43: LDNO HV: LV Site Specific No Residual | B43: =IFERROR(INDEX('Annex 1 LV, HV and UMS charges'!$B$12:$B$43,MATCH($A43,'Annex 1 LV, HV and UMS charges'!$A$12:$A$43,0)),IF(INDEX('Annex 4 LDNO charges'!$B$11:$B$201,MATCH($A43,'Annex 4 LDNO charges'!$A$11:$A$201,0))=0,"",INDEX('Annex 4 LDNO charges'!$B$11:$B$201,MATCH($A43,'Annex 4 LDNO charges'!$A$11:$A$201,0)))) -> E10 | C43: =IFERROR(INDEX('Annex 1 LV, HV and UMS charges'!$C$12:$C$43,MATCH($A43,'Annex 1 LV, HV and UMS charges'!$A$12:$A$43,0)),INDEX('Annex 4 LDNO charges'!$C$11:$C$201,MATCH($A43,'Annex 4 LDNO charges'!$A$11:$A$201,0))) -> 0 | F43: 0.80732906
A44: LDNO HV: LV Site Specific Band 1 | B44: =IFERROR(INDEX('Annex 1 LV, HV and UMS charges'!$B$12:$B$43,MATCH($A44,'Annex 1 LV, HV and UMS charges'!$A$12:$A$43,0)),IF(INDEX('Annex 4 LDNO charges'!$B$11:$B$201,MATCH($A44,'Annex 4 LDNO charges'!$A$11:$A$201,0))=0,"",INDEX('Annex 4 LDNO charges'!$B$11:$B$201,MATCH($A44,'Annex 4 LDNO charges'!$A$11:$A$201,0)))) -> E11 | C44: =IFERROR(INDEX('Annex 1 LV, HV and UMS charges'!$C$12:$C$43,MATCH($A44,'Annex 1 LV, HV and UMS charges'!$A$12:$A$43,0)),INDEX('Annex 4 LDNO charges'!$C$11:$C$201,MATCH($A44,'Annex 4 LDNO charges'!$A$11:$A$201,0))) -> 0 | F44: 0.80732906
A45: LDNO HV: LV Site Specific Band 2 | B45: =IFERROR(INDEX('Annex 1 LV, HV and UMS charges'!$B$12:$B$43,MATCH($A45,'Annex 1 LV, HV and UMS charges'!$A$12:$A$43,0)),IF(INDEX('Annex 4 LDNO charges'!$B$11:$B$201,MATCH($A45,'Annex 4 LDNO charges'!$A$11:$A$201,0))=0,"",INDEX('Annex 4 LDNO charges'!$B$11:$B$201,MATCH($A45,'Annex 4 LDNO charges'!$A$11:$A$201,0)))) -> E12 | C45: =IFERROR(INDEX('Annex 1 LV, HV and UMS charges'!$C$12:$C$43,MATCH($A45,'Annex 1 LV, HV and UMS charges'!$A$12:$A$43,0)),INDEX('Annex 4 LDNO charges'!$C$11:$C$201,MATCH($A45,'Annex 4 LDNO charges'!$A$11:$A$201,0))) -> 0 | F45: 0.80732906
A46: LDNO HV: LV Site Specific Band 3 | B46: =IFERROR(INDEX('Annex 1 LV, HV and UMS charges'!$B$12:$B$43,MATCH($A46,'Annex 1 LV, HV and UMS charges'!$A$12:$A$43,0)),IF(INDEX('Annex 4 LDNO charges'!$B$11:$B$201,MATCH($A46,'Annex 4 LDNO charges'!$A$11:$A$201,0))=0,"",INDEX('Annex 4 LDNO charges'!$B$11:$B$201,MATCH($A46,'Annex 4 LDNO charges'!$A$11:$A$201,0)))) -> E13 | C46: =IFERROR(INDEX('Annex 1 LV, HV and UMS charges'!$C$12:$C$43,MATCH($A46,'Annex 1 LV, HV and UMS charges'!$A$12:$A$43,0)),INDEX('Annex 4 LDNO charges'!$C$11:$C$201,MATCH($A46,'Annex 4 LDNO charges'!$A$11:$A$201,0))) -> 0 | F46: 0.80732906
A47: LDNO HV: LV Site Specific Band 4 | B47: =IFERROR(INDEX('Annex 1 LV, HV and UMS charges'!$B$12:$B$43,MATCH($A47,'Annex 1 LV, HV and UMS charges'!$A$12:$A$43,0)),IF(INDEX('Annex 4 LDNO charges'!$B$11:$B$201,MATCH($A47,'Annex 4 LDNO charges'!$A$11:$A$201,0))=0,"",INDEX('Annex 4 LDNO charges'!$B$11:$B$201,MATCH($A47,'Annex 4 LDNO charges'!$A$11:$A$201,0)))) -> E14 | C47: =IFERROR(INDEX('Annex 1 LV, HV and UMS charges'!$C$12:$C$43,MATCH($A47,'Annex 1 LV, HV and UMS charges'!$A$12:$A$43,0)),INDEX('Annex 4 LDNO charges'!$C$11:$C$201,MATCH($A47,'Annex 4 LDNO charges'!$A$11:$A$201,0))) -> 0 | F47: 0.80732906
A48: LDNO HV: LV Sub Site Specific No Residual | B48: =IFERROR(INDEX('Annex 1 LV, HV and UMS charges'!$B$12:$B$43,MATCH($A48,'Annex 1 LV, HV and UMS charges'!$A$12:$A$43,0)),IF(INDEX('Annex 4 LDNO charges'!$B$11:$B$201,MATCH($A48,'Annex 4 LDNO charges'!$A$11:$A$201,0))=0,"",INDEX('Annex 4 LDNO charges'!$B$11:$B$201,MATCH($A48,'Annex 4 LDNO charges'!$A$11:$A$201,0)))) -> J10 | C48: =IFERROR(INDEX('Annex 1 LV, HV and UMS charges'!$C$12:$C$43,MATCH($A48,'Annex 1 LV, HV and UMS charges'!$A$12:$A$43,0)),INDEX('Annex 4 LDNO charges'!$C$11:$C$201,MATCH($A48,'Annex 4 LDNO charges'!$A$11:$A$201,0))) -> 0 | F48: 0.80732906
A49: LDNO HV: LV Sub Site Specific Band 1 | B49: =IFERROR(INDEX('Annex 1 LV, HV and UMS charges'!$B$12:$B$43,MATCH($A49,'Annex 1 LV, HV and UMS charges'!$A$12:$A$43,0)),IF(INDEX('Annex 4 LDNO charges'!$B$11:$B$201,MATCH($A49,'Annex 4 LDNO charges'!$A$11:$A$201,0))=0,"",INDEX('Annex 4 LDNO charges'!$B$11:$B$201,MATCH($A49,'Annex 4 LDNO charges'!$A$11:$A$201,0)))) -> J11 | C49: =IFERROR(INDEX('Annex 1 LV, HV and UMS charges'!$C$12:$C$43,MATCH($A49,'Annex 1 LV, HV and UMS charges'!$A$12:$A$43,0)),INDEX('Annex 4 LDNO charges'!$C$11:$C$201,MATCH($A49,'Annex 4 LDNO charges'!$A$11:$A$201,0))) -> 0 | F49: 0.80732906
... A57: LDNO HV: HV Site Specific Band 4 | B57: =IFERROR(INDEX('Annex 1 LV, HV and UMS charges'!$B$12:$B$43,MATCH($A57,'Annex 1 LV, HV and UMS charges'!$A$12:$A$43,0)),IF(INDEX('Annex 4 LDNO charges'!$B$11:$B$201,MATCH($A57,'Annex 4 LDNO charges'!$A$11:$A$201,0))=0,"",INDEX('Annex 4 LDNO charges'!$B$11:$B$201,MATCH($A57,'Annex 4 LDNO charges'!$A$11:$A$201,0)))) -> K14 | C57: =IFERROR(INDEX('Annex 1 LV, HV and UMS charges'!$C$12:$C$43,MATCH($A57,'Annex 1 LV, HV and UMS charges'!$A$12:$A$43,0)),INDEX('Annex 4 LDNO charges'!$C$11:$C$201,MATCH($A57,'Annex 4 LDNO charges'!$A$11:$A$201,0))) -> 0 | F57: 0.80732906
A58: LDNO HVplus: Domestic Aggregated or CT with Residual | B58: =IFERROR(INDEX('Annex 1 LV, HV and UMS charges'!$B$12:$B$43,MATCH($A58,'Annex 1 LV, HV and UMS charges'!$A$12:$A$43,0)),IF(INDEX('Annex 4 LDNO charges'!$B$11:$B$201,MATCH($A58,'Annex 4 LDNO charges'!$A$11:$A$201,0))=0,"",INDEX('Annex 4 LDNO charges'!$B$11:$B$201,MATCH($A58,'Annex 4 LDNO charges'!$A$11:$A$201,0)))) -> A20 | C58: =IFERROR(INDEX('Annex 1 LV, HV and UMS charges'!$C$12:$C$43,MATCH($A58,'Annex 1 LV, HV and UMS charges'!$A$12:$A$43,0)),INDEX('Annex 4 LDNO charges'!$C$11:$C$201,MATCH($A58,'Annex 4 LDNO charges'!$A$11:$A$201,0))) -> 0, 1, 2 | D58: 0.18118202 | F58: 0.80732906
A59: LDNO HVplus: Non-Domestic Aggregated or CT No Residual | B59: =IFERROR(INDEX('Annex 1 LV, HV and UMS charges'!$B$12:$B$43,MATCH($A59,'Annex 1 LV, HV and UMS charges'!$A$12:$A$43,0)),IF(INDEX('Annex 4 LDNO charges'!$B$11:$B$201,MATCH($A59,'Annex 4 LDNO charges'!$A$11:$A$201,0))=0,"",INDEX('Annex 4 LDNO charges'!$B$11:$B$201,MATCH($A59,'Annex 4 LDNO charges'!$A$11:$A$201,0)))) -> C20 | C59: =IFERROR(INDEX('Annex 1 LV, HV and UMS charges'!$C$12:$C$43,MATCH($A59,'Annex 1 LV, HV and UMS charges'!$A$12:$A$43,0)),INDEX('Annex 4 LDNO charges'!$C$11:$C$201,MATCH($A59,'Annex 4 LDNO charges'!$A$11:$A$201,0))) -> 0, 3, 4, 5-8 | F59: 0.80732906
A60: LDNO HVplus: Non-Domestic Aggregated or CT Band 1 | B60: =IFERROR(INDEX('Annex 1 LV, HV and UMS charges'!$B$12:$B$43,MATCH($A60,'Annex 1 LV, HV and UMS charges'!$A$12:$A$43,0)),IF(INDEX('Annex 4 LDNO charges'!$B$11:$B$201,MATCH($A60,'Annex 4 LDNO charges'!$A$11:$A$201,0))=0,"",INDEX('Annex 4 LDNO charges'!$B$11:$B$201,MATCH($A60,'Annex 4 LDNO charges'!$A$11:$A$201,0)))) -> C21 | C60: =IFERROR(INDEX('Annex 1 LV, HV and UMS charges'!$C$12:$C$43,MATCH($A60,'Annex 1 LV, HV and UMS charges'!$A$12:$A$43,0)),INDEX('Annex 4 LDNO charges'!$C$11:$C$201,MATCH($A60,'Annex 4 LDNO charges'!$A$11:$A$201,0))) -> 0, 3, 4, 5-8 | F60: 0.80732906
A61: LDNO HVplus: Non-Domestic Aggregated or CT Band 2 | B61: =IFERROR(INDEX('Annex 1 LV, HV and UMS charges'!$B$12:$B$43,MATCH($A61,'Annex 1 LV, HV and UMS charges'!$A$12:$A$43,0)),IF(INDEX('Annex 4 LDNO charges'!$B$11:$B$201,MATCH($A61,'Annex 4 LDNO charges'!$A$11:$A$201,0))=0,"",INDEX('Annex 4 LDNO charges'!$B$11:$B$201,MATCH($A61,'Annex 4 LDNO charges'!$A$11:$A$201,0)))) -> C22 | C61: =IFERROR(INDEX('Annex 1 LV, HV and UMS charges'!$C$12:$C$43,MATCH($A61,'Annex 1 LV, HV and UMS charges'!$A$12:$A$43,0)),INDEX('Annex 4 LDNO charges'!$C$11:$C$201,MATCH($A61,'Annex 4 LDNO charges'!$A$11:$A$201,0))) -> 0, 3, 4, 5-8 | F61: 0.80732906
A62: LDNO HVplus: Non-Domestic Aggregated or CT Band 3 | B62: =IFERROR(INDEX('Annex 1 LV, HV and UMS charges'!$B$12:$B$43,MATCH($A62,'Annex 1 LV, HV and UMS charges'!$A$12:$A$43,0)),IF(INDEX('Annex 4 LDNO charges'!$B$11:$B$201,MATCH($A62,'Annex 4 LDNO charges'!$A$11:$A$201,0))=0,"",INDEX('Annex 4 LDNO charges'!$B$11:$B$201,MATCH($A62,'Annex 4 LDNO charges'!$A$11:$A$201,0)))) -> C23 | C62: =IFERROR(INDEX('Annex 1 LV, HV and UMS charges'!$C$12:$C$43,MATCH($A62,'Annex 1 LV, HV and UMS charges'!$A$12:$A$43,0)),INDEX('Annex 4 LDNO charges'!$C$11:$C$201,MATCH($A62,'Annex 4 LDNO charges'!$A$11:$A$201,0))) -> 0, 3, 4, 5-8 | F62: 0.80732906
A63: LDNO HVplus: Non-Domestic Aggregated or CT Band 4 | B63: =IFERROR(INDEX('Annex 1 LV, HV and UMS charges'!$B$12:$B$43,MATCH($A63,'Annex 1 LV, HV and UMS charges'!$A$12:$A$43,0)),IF(INDEX('Annex 4 LDNO charges'!$B$11:$B$201,MATCH($A63,'Annex 4 LDNO charges'!$A$11:$A$201,0))=0,"",INDEX('Annex 4 LDNO charges'!$B$11:$B$201,MATCH($A63,'Annex 4 LDNO charges'!$A$11:$A$201,0)))) -> C24 | C63: =IFERROR(INDEX('Annex 1 LV, HV and UMS charges'!$C$12:$C$43,MATCH($A63,'Annex 1 LV, HV and UMS charges'!$A$12:$A$43,0)),INDEX('Annex 4 LDNO charges'!$C$11:$C$201,MATCH($A63,'Annex 4 LDNO charges'!$A$11:$A$201,0))) -> 0, 3, 4, 5-8 | F63: 0.80732906
A64: LDNO HVplus: LV Site Specific No Residual | B64: =IFERROR(INDEX('Annex 1 LV, HV and UMS charges'!$B$12:$B$43,MATCH($A64,'Annex 1 LV, HV and UMS charges'!$A$12:$A$43,0)),IF(INDEX('Annex 4 LDNO charges'!$B$11:$B$201,MATCH($A64,'Annex 4 LDNO charges'!$A$11:$A$201,0))=0,"",INDEX('Annex 4 LDNO charges'!$B$11:$B$201,MATCH($A64,'Annex 4 LDNO charges'!$A$11:$A$201,0)))) -> E20 | C64: =IFERROR(INDEX('Annex 1 LV, HV and UMS charges'!$C$12:$C$43,MATCH($A64,'Annex 1 LV, HV and UMS charges'!$A$12:$A$43,0)),INDEX('Annex 4 LDNO charges'!$C$11:$C$201,MATCH($A64,'Annex 4 LDNO charges'!$A$11:$A$201,0))) -> 0 | F64: 0.80732906
A65: LDNO HVplus: LV Site Specific Band 1 | B65: =IFERROR(INDEX('Annex 1 LV, HV and UMS charges'!$B$12:$B$43,MATCH($A65,'Annex 1 LV, HV and UMS charges'!$A$12:$A$43,0)),IF(INDEX('Annex 4 LDNO charges'!$B$11:$B$201,MATCH($A65,'Annex 4 LDNO charges'!$A$11:$A$201,0))=0,"",INDEX('Annex 4 LDNO charges'!$B$11:$B$201,MATCH($A65,'Annex 4 LDNO charges'!$A$11:$A$201,0)))) -> E21 | C65: =IFERROR(INDEX('Annex 1 LV, HV and UMS charges'!$C$12:$C$43,MATCH($A65,'Annex 1 LV, HV and UMS charges'!$A$12:$A$43,0)),INDEX('Annex 4 LDNO charges'!$C$11:$C$201,MATCH($A65,'Annex 4 LDNO charges'!$A$11:$A$201,0))) -> 0 | F65: 0.80732906
A66: LDNO HVplus: LV Site Specific Band 2 | B66: =IFERROR(INDEX('Annex 1 LV, HV and UMS charges'!$B$12:$B$43,MATCH($A66,'Annex 1 LV, HV and UMS charges'!$A$12:$A$43,0)),IF(INDEX('Annex 4 LDNO charges'!$B$11:$B$201,MATCH($A66,'Annex 4 LDNO charges'!$A$11:$A$201,0))=0,"",INDEX('Annex 4 LDNO charges'!$B$11:$B$201,MATCH($A66,'Annex 4 LDNO charges'!$A$11:$A$201,0)))) -> E22 | C66: =IFERROR(INDEX('Annex 1 LV, HV and UMS charges'!$C$12:$C$43,MATCH($A66,'Annex 1 LV, HV and UMS charges'!$A$12:$A$43,0)),INDEX('Annex 4 LDNO charges'!$C$11:$C$201,MATCH($A66,'Annex 4 LDNO charges'!$A$11:$A$201,0))) -> 0 | F66: 0.80732906
A67: LDNO HVplus: LV Site Specific Band 3 | B67: =IFERROR(INDEX('Annex 1 LV, HV and UMS charges'!$B$12:$B$43,MATCH($A67,'Annex 1 LV, HV and UMS charges'!$A$12:$A$43,0)),IF(INDEX('Annex 4 LDNO charges'!$B$11:$B$201,MATCH($A67,'Annex 4 LDNO charges'!$A$11:$A$201,0))=0,"",INDEX('Annex 4 LDNO charges'!$B$11:$B$201,MATCH($A67,'Annex 4 LDNO charges'!$A$11:$A$201,0)))) -> E23 | C67: =IFERROR(INDEX('Annex 1 LV, HV and UMS charges'!$C$12:$C$43,MATCH($A67,'Annex 1 LV, HV and UMS charges'!$A$12:$A$43,0)),INDEX('Annex 4 LDNO charges'!$C$11:$C$201,MATCH($A67,'Annex 4 LDNO charges'!$A$11:$A$201,0))) -> 0 | F67: 0.80732906
A68: LDNO HVplus: LV Site Specific Band 4 | B68: =IFERROR(INDEX('Annex 1 LV, HV and UMS charges'!$B$12:$B$43,MATCH($A68,'Annex 1 LV, HV and UMS charges'!$A$12:$A$43,0)),IF(INDEX('Annex 4 LDNO charges'!$B$11:$B$201,MATCH($A68,'Annex 4 LDNO charges'!$A$11:$A$201,0))=0,"",INDEX('Annex 4 LDNO charges'!$B$11:$B$201,MATCH($A68,'Annex 4 LDNO charges'!$A$11:$A$201,0)))) -> E24 | C68: =IFERROR(INDEX('Annex 1 LV, HV and UMS charges'!$C$12:$C$43,MATCH($A68,'Annex 1 LV, HV and UMS charges'!$A$12:$A$43,0)),INDEX('Annex 4 LDNO charges'!$C$11:$C$201,MATCH($A68,'Annex 4 LDNO charges'!$A$11:$A$201,0))) -> 0 | F68: 0.80732906
A69: LDNO HVplus: LV Sub Site Specific No Residual | B69: =IFERROR(INDEX('Annex 1 LV, HV and UMS charges'!$B$12:$B$43,MATCH($A69,'Annex 1 LV, HV and UMS charges'!$A$12:$A$43,0)),IF(INDEX('Annex 4 LDNO charges'!$B$11:$B$201,MATCH($A69,'Annex 4 LDNO charges'!$A$11:$A$201,0))=0,"",INDEX('Annex 4 LDNO charges'!$B$11:$B$201,MATCH($A69,'Annex 4 LDNO charges'!$A$11:$A$201,0)))) -> J20 | C69: =IFERROR(INDEX('Annex 1 LV, HV and UMS charges'!$C$12:$C$43,MATCH($A69,'Annex 1 LV, HV and UMS charges'!$A$12:$A$43,0)),INDEX('Annex 4 LDNO charges'!$C$11:$C$201,MATCH($A69,'Annex 4 LDNO charges'!$A$11:$A$201,0))) -> 0 | F69: 0.80732906
A70: LDNO HVplus: LV Sub Site Specific Band 1 | B70: =IFERROR(INDEX('Annex 1 LV, HV and UMS charges'!$B$12:$B$43,MATCH($A70,'Annex 1 LV, HV and UMS charges'!$A$12:$A$43,0)),IF(INDEX('Annex 4 LDNO charges'!$B$11:$B$201,MATCH($A70,'Annex 4 LDNO charges'!$A$11:$A$201,0))=0,"",INDEX('Annex 4 LDNO charges'!$B$11:$B$201,MATCH($A70,'Annex 4 LDNO charges'!$A$11:$A$201,0)))) -> J21 | C70: =IFERROR(INDEX('Annex 1 LV, HV and UMS charges'!$C$12:$C$43,MATCH($A70,'Annex 1 LV, HV and UMS charges'!$A$12:$A$43,0)),INDEX('Annex 4 LDNO charges'!$C$11:$C$201,MATCH($A70,'Annex 4 LDNO charges'!$A$11:$A$201,0))) -> 0 | F70: 0.80732906
... A78: LDNO HVplus: HV Site Specific Band 4 | B78: =IFERROR(INDEX('Annex 1 LV, HV and UMS charges'!$B$12:$B$43,MATCH($A78,'Annex 1 LV, HV and UMS charges'!$A$12:$A$43,0)),IF(INDEX('Annex 4 LDNO charges'!$B$11:$B$201,MATCH($A78,'Annex 4 LDNO charges'!$A$11:$A$201,0))=0,"",INDEX('Annex 4 LDNO charges'!$B$11:$B$201,MATCH($A78,'Annex 4 LDNO charges'!$A$11:$A$201,0)))) -> K24 | C78: =IFERROR(INDEX('Annex 1 LV, HV and UMS charges'!$C$12:$C$43,MATCH($A78,'Annex 1 LV, HV and UMS charges'!$A$12:$A$43,0)),INDEX('Annex 4 LDNO charges'!$C$11:$C$201,MATCH($A78,'Annex 4 LDNO charges'!$A$11:$A$201,0))) -> 0 | F78: 0.80732906
A79: LDNO EHV: Domestic Aggregated or CT with Residual | B79: =IFERROR(INDEX('Annex 1 LV, HV and UMS charges'!$B$12:$B$43,MATCH($A79,'Annex 1 LV, HV and UMS charges'!$A$12:$A$43,0)),IF(INDEX('Annex 4 LDNO charges'!$B$11:$B$201,MATCH($A79,'Annex 4 LDNO charges'!$A$11:$A$201,0))=0,"",INDEX('Annex 4 LDNO charges'!$B$11:$B$201,MATCH($A79,'Annex 4 LDNO charges'!$A$11:$A$201,0)))) -> A30 | C79: =IFERROR(INDEX('Annex 1 LV, HV and UMS charges'!$C$12:$C$43,MATCH($A79,'Annex 1 LV, HV and UMS charges'!$A$12:$A$43,0)),INDEX('Annex 4 LDNO charges'!$C$11:$C$201,MATCH($A79,'Annex 4 LDNO charges'!$A$11:$A$201,0))) -> 0, 1, 2 | D79: 0.18118202 | F79: 0.80732906
A80: LDNO EHV: Non-Domestic Aggregated or CT No Residual | B80: =IFERROR(INDEX('Annex 1 LV, HV and UMS charges'!$B$12:$B$43,MATCH($A80,'Annex 1 LV, HV and UMS charges'!$A$12:$A$43,0)),IF(INDEX('Annex 4 LDNO charges'!$B$11:$B$201,MATCH($A80,'Annex 4 LDNO charges'!$A$11:$A$201,0))=0,"",INDEX('Annex 4 LDNO charges'!$B$11:$B$201,MATCH($A80,'Annex 4 LDNO charges'!$A$11:$A$201,0)))) -> C30 | C80: =IFERROR(INDEX('Annex 1 LV, HV and UMS charges'!$C$12:$C$43,MATCH($A80,'Annex 1 LV, HV and UMS charges'!$A$12:$A$43,0)),INDEX('Annex 4 LDNO charges'!$C$11:$C$201,MATCH($A80,'Annex 4 LDNO charges'!$A$11:$A$201,0))) -> 0, 3, 4, 5-8 | F80: 0.80732906
A81: LDNO EHV: Non-Domestic Aggregated or CT Band 1 | B81: =IFERROR(INDEX('Annex 1 LV, HV and UMS charges'!$B$12:$B$43,MATCH($A81,'Annex 1 LV, HV and UMS charges'!$A$12:$A$43,0)),IF(INDEX('Annex 4 LDNO charges'!$B$11:$B$201,MATCH($A81,'Annex 4 LDNO charges'!$A$11:$A$201,0))=0,"",INDEX('Annex 4 LDNO charges'!$B$11:$B$201,MATCH($A81,'Annex 4 LDNO charges'!$A$11:$A$201,0)))) -> C31 | C81: =IFERROR(INDEX('Annex 1 LV, HV and UMS charges'!$C$12:$C$43,MATCH($A81,'Annex 1 LV, HV and UMS charges'!$A$12:$A$43,0)),INDEX('Annex 4 LDNO charges'!$C$11:$C$201,MATCH($A81,'Annex 4 LDNO charges'!$A$11:$A$201,0))) -> 0, 3, 4, 5-8 | F81: 0.80732906
A82: LDNO EHV: Non-Domestic Aggregated or CT Band 2 | B82: =IFERROR(INDEX('Annex 1 LV, HV and UMS charges'!$B$12:$B$43,MATCH($A82,'Annex 1 LV, HV and UMS charges'!$A$12:$A$43,0)),IF(INDEX('Annex 4 LDNO charges'!$B$11:$B$201,MATCH($A82,'Annex 4 LDNO charges'!$A$11:$A$201,0))=0,"",INDEX('Annex 4 LDNO charges'!$B$11:$B$201,MATCH($A82,'Annex 4 LDNO charges'!$A$11:$A$201,0)))) -> C32 | C82: =IFERROR(INDEX('Annex 1 LV, HV and UMS charges'!$C$12:$C$43,MATCH($A82,'Annex 1 LV, HV and UMS charges'!$A$12:$A$43,0)),INDEX('Annex 4 LDNO charges'!$C$11:$C$201,MATCH($A82,'Annex 4 LDNO charges'!$A$11:$A$201,0))) -> 0, 3, 4, 5-8 | F82: 0.80732906
A83: LDNO EHV: Non-Domestic Aggregated or CT Band 3 | B83: =IFERROR(INDEX('Annex 1 LV, HV and UMS charges'!$B$12:$B$43,MATCH($A83,'Annex 1 LV, HV and UMS charges'!$A$12:$A$43,0)),IF(INDEX('Annex 4 LDNO charges'!$B$11:$B$201,MATCH($A83,'Annex 4 LDNO charges'!$A$11:$A$201,0))=0,"",INDEX('Annex 4 LDNO charges'!$B$11:$B$201,MATCH($A83,'Annex 4 LDNO charges'!$A$11:$A$201,0)))) -> C33 | C83: =IFERROR(INDEX('Annex 1 LV, HV and UMS charges'!$C$12:$C$43,MATCH($A83,'Annex 1 LV, HV and UMS charges'!$A$12:$A$43,0)),INDEX('Annex 4 LDNO charges'!$C$11:$C$201,MATCH($A83,'Annex 4 LDNO charges'!$A$11:$A$201,0))) -> 0, 3, 4, 5-8 | F83: 0.80732906
A84: LDNO EHV: Non-Domestic Aggregated or CT Band 4 | B84: =IFERROR(INDEX('Annex 1 LV, HV and UMS charges'!$B$12:$B$43,MATCH($A84,'Annex 1 LV, HV and UMS charges'!$A$12:$A$43,0)),IF(INDEX('Annex 4 LDNO charges'!$B$11:$B$201,MATCH($A84,'Annex 4 LDNO charges'!$A$11:$A$201,0))=0,"",INDEX('Annex 4 LDNO charges'!$B$11:$B$201,MATCH($A84,'Annex 4 LDNO charges'!$A$11:$A$201,0)))) -> C34 | C84: =IFERROR(INDEX('Annex 1 LV, HV and UMS charges'!$C$12:$C$43,MATCH($A84,'Annex 1 LV, HV and UMS charges'!$A$12:$A$43,0)),INDEX('Annex 4 LDNO charges'!$C$11:$C$201,MATCH($A84,'Annex 4 LDNO charges'!$A$11:$A$201,0))) -> 0, 3, 4, 5-8 | F84: 0.80732906
A85: LDNO EHV: LV Site Specific No Residual | B85: =IFERROR(INDEX('Annex 1 LV, HV and UMS charges'!$B$12:$B$43,MATCH($A85,'Annex 1 LV, HV and UMS charges'!$A$12:$A$43,0)),IF(INDEX('Annex 4 LDNO charges'!$B$11:$B$201,MATCH($A85,'Annex 4 LDNO charges'!$A$11:$A$201,0))=0,"",INDEX('Annex 4 LDNO charges'!$B$11:$B$201,MATCH($A85,'Annex 4 LDNO charges'!$A$11:$A$201,0)))) -> E30 | C85: =IFERROR(INDEX('Annex 1 LV, HV and UMS charges'!$C$12:$C$43,MATCH($A85,'Annex 1 LV, HV and UMS charges'!$A$12:$A$43,0)),INDEX('Annex 4 LDNO charges'!$C$11:$C$201,MATCH($A85,'Annex 4 LDNO charges'!$A$11:$A$201,0))) -> 0 | F85: 0.80732906
A86: LDNO EHV: LV Site Specific Band 1 | B86: =IFERROR(INDEX('Annex 1 LV, HV and UMS charges'!$B$12:$B$43,MATCH($A86,'Annex 1 LV, HV and UMS charges'!$A$12:$A$43,0)),IF(INDEX('Annex 4 LDNO charges'!$B$11:$B$201,MATCH($A86,'Annex 4 LDNO charges'!$A$11:$A$201,0))=0,"",INDEX('Annex 4 LDNO charges'!$B$11:$B$201,MATCH($A86,'Annex 4 LDNO charges'!$A$11:$A$201,0)))) -> E31 | C86: =IFERROR(INDEX('Annex 1 LV, HV and UMS charges'!$C$12:$C$43,MATCH($A86,'Annex 1 LV, HV and UMS charges'!$A$12:$A$43,0)),INDEX('Annex 4 LDNO charges'!$C$11:$C$201,MATCH($A86,'Annex 4 LDNO charges'!$A$11:$A$201,0))) -> 0 | F86: 0.80732906
A87: LDNO EHV: LV Site Specific Band 2 | B87: =IFERROR(INDEX('Annex 1 LV, HV and UMS charges'!$B$12:$B$43,MATCH($A87,'Annex 1 LV, HV and UMS charges'!$A$12:$A$43,0)),IF(INDEX('Annex 4 LDNO charges'!$B$11:$B$201,MATCH($A87,'Annex 4 LDNO charges'!$A$11:$A$201,0))=0,"",INDEX('Annex 4 LDNO charges'!$B$11:$B$201,MATCH($A87,'Annex 4 LDNO charges'!$A$11:$A$201,0)))) -> E32 | C87: =IFERROR(INDEX('Annex 1 LV, HV and UMS charges'!$C$12:$C$43,MATCH($A87,'Annex 1 LV, HV and UMS charges'!$A$12:$A$43,0)),INDEX('Annex 4 LDNO charges'!$C$11:$C$201,MATCH($A87,'Annex 4 LDNO charges'!$A$11:$A$201,0))) -> 0 | F87: 0.80732906
A88: LDNO EHV: LV Site Specific Band 3 | B88: =IFERROR(INDEX('Annex 1 LV, HV and UMS charges'!$B$12:$B$43,MATCH($A88,'Annex 1 LV, HV and UMS charges'!$A$12:$A$43,0)),IF(INDEX('Annex 4 LDNO charges'!$B$11:$B$201,MATCH($A88,'Annex 4 LDNO charges'!$A$11:$A$201,0))=0,"",INDEX('Annex 4 LDNO charges'!$B$11:$B$201,MATCH($A88,'Annex 4 LDNO charges'!$A$11:$A$201,0)))) -> E33 | C88: =IFERROR(INDEX('Annex 1 LV, HV and UMS charges'!$C$12:$C$43,MATCH($A88,'Annex 1 LV, HV and UMS charges'!$A$12:$A$43,0)),INDEX('Annex 4 LDNO charges'!$C$11:$C$201,MATCH($A88,'Annex 4 LDNO charges'!$A$11:$A$201,0))) -> 0 | F88: 0.80732906
A89: LDNO EHV: LV Site Specific Band 4 | B89: =IFERROR(INDEX('Annex 1 LV, HV and UMS charges'!$B$12:$B$43,MATCH($A89,'Annex 1 LV, HV and UMS charges'!$A$12:$A$43,0)),IF(INDEX('Annex 4 LDNO charges'!$B$11:$B$201,MATCH($A89,'Annex 4 LDNO charges'!$A$11:$A$201,0))=0,"",INDEX('Annex 4 LDNO charges'!$B$11:$B$201,MATCH($A89,'Annex 4 LDNO charges'!$A$11:$A$201,0)))) -> E34 | C89: =IFERROR(INDEX('Annex 1 LV, HV and UMS charges'!$C$12:$C$43,MATCH($A89,'Annex 1 LV, HV and UMS charges'!$A$12:$A$43,0)),INDEX('Annex 4 LDNO charges'!$C$11:$C$201,MATCH($A89,'Annex 4 LDNO charges'!$A$11:$A$201,0))) -> 0 | F89: 0.80732906
A90: LDNO EHV: LV Sub Site Specific No Residual | B90: =IFERROR(INDEX('Annex 1 LV, HV and UMS charges'!$B$12:$B$43,MATCH($A90,'Annex 1 LV, HV and UMS charges'!$A$12:$A$43,0)),IF(INDEX('Annex 4 LDNO charges'!$B$11:$B$201,MATCH($A90,'Annex 4 LDNO charges'!$A$11:$A$201,0))=0,"",INDEX('Annex 4 LDNO charges'!$B$11:$B$201,MATCH($A90,'Annex 4 LDNO charges'!$A$11:$A$201,0)))) -> J30 | C90: =IFERROR(INDEX('Annex 1 LV, HV and UMS charges'!$C$12:$C$43,MATCH($A90,'Annex 1 LV, HV and UMS charges'!$A$12:$A$43,0)),INDEX('Annex 4 LDNO charges'!$C$11:$C$201,MATCH($A90,'Annex 4 LDNO charges'!$A$11:$A$201,0))) -> 0 | F90: 0.80732906
A91: LDNO EHV: LV Sub Site Specific Band 1 | B91: =IFERROR(INDEX('Annex 1 LV, HV and UMS charges'!$B$12:$B$43,MATCH($A91,'Annex 1 LV, HV and UMS charges'!$A$12:$A$43,0)),IF(INDEX('Annex 4 LDNO charges'!$B$11:$B$201,MATCH($A91,'Annex 4 LDNO charges'!$A$11:$A$201,0))=0,"",INDEX('Annex 4 LDNO charges'!$B$11:$B$201,MATCH($A91,'Annex 4 LDNO charges'!$A$11:$A$201,0)))) -> J31 | C91: =IFERROR(INDEX('Annex 1 LV, HV and UMS charges'!$C$12:$C$43,MATCH($A91,'Annex 1 LV, HV and UMS charges'!$A$12:$A$43,0)),INDEX('Annex 4 LDNO charges'!$C$11:$C$201,MATCH($A91,'Annex 4 LDNO charges'!$A$11:$A$201,0))) -> 0 | F91: 0.80732906
... A99: LDNO EHV: HV Site Specific Band 4 | B99: =IFERROR(INDEX('Annex 1 LV, HV and UMS charges'!$B$12:$B$43,MATCH($A99,'Annex 1 LV, HV and UMS charges'!$A$12:$A$43,0)),IF(INDEX('Annex 4 LDNO charges'!$B$11:$B$201,MATCH($A99,'Annex 4 LDNO charges'!$A$11:$A$201,0))=0,"",INDEX('Annex 4 LDNO charges'!$B$11:$B$201,MATCH($A99,'Annex 4 LDNO charges'!$A$11:$A$201,0)))) -> K34 | C99: =IFERROR(INDEX('Annex 1 LV, HV and UMS charges'!$C$12:$C$43,MATCH($A99,'Annex 1 LV, HV and UMS charges'!$A$12:$A$43,0)),INDEX('Annex 4 LDNO charges'!$C$11:$C$201,MATCH($A99,'Annex 4 LDNO charges'!$A$11:$A$201,0))) -> 0 | F99: 0.80732906
A100: LDNO 132kV/EHV: Domestic Aggregated or CT with Residual | B100: =IFERROR(INDEX('Annex 1 LV, HV and UMS charges'!$B$12:$B$43,MATCH($A100,'Annex 1 LV, HV and UMS charges'!$A$12:$A$43,0)),IF(INDEX('Annex 4 LDNO charges'!$B$11:$B$201,MATCH($A100,'Annex 4 LDNO charges'!$A$11:$A$201,0))=0,"",INDEX('Annex 4 LDNO charges'!$B$11:$B$201,MATCH($A100,'Annex 4 LDNO charges'!$A$11:$A$201,0)))) -> A40 | C100: =IFERROR(INDEX('Annex 1 LV, HV and UMS charges'!$C$12:$C$43,MATCH($A100,'Annex 1 LV, HV and UMS charges'!$A$12:$A$43,0)),INDEX('Annex 4 LDNO charges'!$C$11:$C$201,MATCH($A100,'Annex 4 LDNO charges'!$A$11:$A$201,0))) -> 0, 1, 2 | D100: 0.18118202 | F100: 0.80732906
A101: LDNO 132kV/EHV: Non-Domestic Aggregated or CT No Residual | B101: =IFERROR(INDEX('Annex 1 LV, HV and UMS charges'!$B$12:$B$43,MATCH($A101,'Annex 1 LV, HV and UMS charges'!$A$12:$A$43,0)),IF(INDEX('Annex 4 LDNO charges'!$B$11:$B$201,MATCH($A101,'Annex 4 LDNO charges'!$A$11:$A$201,0))=0,"",INDEX('Annex 4 LDNO charges'!$B$11:$B$201,MATCH($A101,'Annex 4 LDNO charges'!$A$11:$A$201,0)))) -> C40 | C101: =IFERROR(INDEX('Annex 1 LV, HV and UMS charges'!$C$12:$C$43,MATCH($A101,'Annex 1 LV, HV and UMS charges'!$A$12:$A$43,0)),INDEX('Annex 4 LDNO charges'!$C$11:$C$201,MATCH($A101,'Annex 4 LDNO charges'!$A$11:$A$201,0))) -> 0, 3, 4, 5-8 | F101: 0.80732906
A102: LDNO 132kV/EHV: Non-Domestic Aggregated or CT Band 1 | B102: =IFERROR(INDEX('Annex 1 LV, HV and UMS charges'!$B$12:$B$43,MATCH($A102,'Annex 1 LV, HV and UMS charges'!$A$12:$A$43,0)),IF(INDEX('Annex 4 LDNO charges'!$B$11:$B$201,MATCH($A102,'Annex 4 LDNO charges'!$A$11:$A$201,0))=0,"",INDEX('Annex 4 LDNO charges'!$B$11:$B$201,MATCH($A102,'Annex 4 LDNO charges'!$A$11:$A$201,0)))) -> C41 | C102: =IFERROR(INDEX('Annex 1 LV, HV and UMS charges'!$C$12:$C$43,MATCH($A102,'Annex 1 LV, HV and UMS charges'!$A$12:$A$43,0)),INDEX('Annex 4 LDNO charges'!$C$11:$C$201,MATCH($A102,'Annex 4 LDNO charges'!$A$11:$A$201,0))) -> 0, 3, 4, 5-8 | F102: 0.80732906
A103: LDNO 132kV/EHV: Non-Domestic Aggregated or CT Band 2 | B103: =IFERROR(INDEX('Annex 1 LV, HV and UMS charges'!$B$12:$B$43,MATCH($A103,'Annex 1 LV, HV and UMS charges'!$A$12:$A$43,0)),IF(INDEX('Annex 4 LDNO charges'!$B$11:$B$201,MATCH($A103,'Annex 4 LDNO charges'!$A$11:$A$201,0))=0,"",INDEX('Annex 4 LDNO charges'!$B$11:$B$201,MATCH($A103,'Annex 4 LDNO charges'!$A$11:$A$201,0)))) -> C42 | C103: =IFERROR(INDEX('Annex 1 LV, HV and UMS charges'!$C$12:$C$43,MATCH($A103,'Annex 1 LV, HV and UMS charges'!$A$12:$A$43,0)),INDEX('Annex 4 LDNO charges'!$C$11:$C$201,MATCH($A103,'Annex 4 LDNO charges'!$A$11:$A$201,0))) -> 0, 3, 4, 5-8 | F103: 0.80732906
A104: LDNO 132kV/EHV: Non-Domestic Aggregated or CT Band 3 | B104: =IFERROR(INDEX('Annex 1 LV, HV and UMS charges'!$B$12:$B$43,MATCH($A104,'Annex 1 LV, HV and UMS charges'!$A$12:$A$43,0)),IF(INDEX('Annex 4 LDNO charges'!$B$11:$B$201,MATCH($A104,'Annex 4 LDNO charges'!$A$11:$A$201,0))=0,"",INDEX('Annex 4 LDNO charges'!$B$11:$B$201,MATCH($A104,'Annex 4 LDNO charges'!$A$11:$A$201,0)))) -> C43 | C104: =IFERROR(INDEX('Annex 1 LV, HV and UMS charges'!$C$12:$C$43,MATCH($A104,'Annex 1 LV, HV and UMS charges'!$A$12:$A$43,0)),INDEX('Annex 4 LDNO charges'!$C$11:$C$201,MATCH($A104,'Annex 4 LDNO charges'!$A$11:$A$201,0))) -> 0, 3, 4, 5-8 | F104: 0.80732906
A105: LDNO 132kV/EHV: Non-Domestic Aggregated or CT Band 4 | B105: =IFERROR(INDEX('Annex 1 LV, HV and UMS charges'!$B$12:$B$43,MATCH($A105,'Annex 1 LV, HV and UMS charges'!$A$12:$A$43,0)),IF(INDEX('Annex 4 LDNO charges'!$B$11:$B$201,MATCH($A105,'Annex 4 LDNO charges'!$A$11:$A$201,0))=0,"",INDEX('Annex 4 LDNO charges'!$B$11:$B$201,MATCH($A105,'Annex 4 LDNO charges'!$A$11:$A$201,0)))) -> C44 | C105: =IFERROR(INDEX('Annex 1 LV, HV and UMS charges'!$C$12:$C$43,MATCH($A105,'Annex 1 LV, HV and UMS charges'!$A$12:$A$43,0)),INDEX('Annex 4 LDNO charges'!$C$11:$C$201,MATCH($A105,'Annex 4 LDNO charges'!$A$11:$A$201,0))) -> 0, 3, 4, 5-8 | F105: 0.80732906
A106: LDNO 132kV/EHV: LV Site Specific No Residual | B106: =IFERROR(INDEX('Annex 1 LV, HV and UMS charges'!$B$12:$B$43,MATCH($A106,'Annex 1 LV, HV and UMS charges'!$A$12:$A$43,0)),IF(INDEX('Annex 4 LDNO charges'!$B$11:$B$201,MATCH($A106,'Annex 4 LDNO charges'!$A$11:$A$201,0))=0,"",INDEX('Annex 4 LDNO charges'!$B$11:$B$201,MATCH($A106,'Annex 4 LDNO charges'!$A$11:$A$201,0)))) -> E40 | C106: =IFERROR(INDEX('Annex 1 LV, HV and UMS charges'!$C$12:$C$43,MATCH($A106,'Annex 1 LV, HV and UMS charges'!$A$12:$A$43,0)),INDEX('Annex 4 LDNO charges'!$C$11:$C$201,MATCH($A106,'Annex 4 LDNO charges'!$A$11:$A$201,0))) -> 0 | F106: 0.80732906
A107: LDNO 132kV/EHV: LV Site Specific Band 1 | B107: =IFERROR(INDEX('Annex 1 LV, HV and UMS charges'!$B$12:$B$43,MATCH($A107,'Annex 1 LV, HV and UMS charges'!$A$12:$A$43,0)),IF(INDEX('Annex 4 LDNO charges'!$B$11:$B$201,MATCH($A107,'Annex 4 LDNO charges'!$A$11:$A$201,0))=0,"",INDEX('Annex 4 LDNO charges'!$B$11:$B$201,MATCH($A107,'Annex 4 LDNO charges'!$A$11:$A$201,0)))) -> E41 | C107: =IFERROR(INDEX('Annex 1 LV, HV and UMS charges'!$C$12:$C$43,MATCH($A107,'Annex 1 LV, HV and UMS charges'!$A$12:$A$43,0)),INDEX('Annex 4 LDNO charges'!$C$11:$C$201,MATCH($A107,'Annex 4 LDNO charges'!$A$11:$A$201,0))) -> 0 | F107: 0.80732906
A108: LDNO 132kV/EHV: LV Site Specific Band 2 | B108: =IFERROR(INDEX('Annex 1 LV, HV and UMS charges'!$B$12:$B$43,MATCH($A108,'Annex 1 LV, HV and UMS charges'!$A$12:$A$43,0)),IF(INDEX('Annex 4 LDNO charges'!$B$11:$B$201,MATCH($A108,'Annex 4 LDNO charges'!$A$11:$A$201,0))=0,"",INDEX('Annex 4 LDNO charges'!$B$11:$B$201,MATCH($A108,'Annex 4 LDNO charges'!$A$11:$A$201,0)))) -> E42 | C108: =IFERROR(INDEX('Annex 1 LV, HV and UMS charges'!$C$12:$C$43,MATCH($A108,'Annex 1 LV, HV and UMS charges'!$A$12:$A$43,0)),INDEX('Annex 4 LDNO charges'!$C$11:$C$201,MATCH($A108,'Annex 4 LDNO charges'!$A$11:$A$201,0))) -> 0 | F108: 0.80732906
A109: LDNO 132kV/EHV: LV Site Specific Band 3 | B109: =IFERROR(INDEX('Annex 1 LV, HV and UMS charges'!$B$12:$B$43,MATCH($A109,'Annex 1 LV, HV and UMS charges'!$A$12:$A$43,0)),IF(INDEX('Annex 4 LDNO charges'!$B$11:$B$201,MATCH($A109,'Annex 4 LDNO charges'!$A$11:$A$201,0))=0,"",INDEX('Annex 4 LDNO charges'!$B$11:$B$201,MATCH($A109,'Annex 4 LDNO charges'!$A$11:$A$201,0)))) -> E43 | C109: =IFERROR(INDEX('Annex 1 LV, HV and UMS charges'!$C$12:$C$43,MATCH($A109,'Annex 1 LV, HV and UMS charges'!$A$12:$A$43,0)),INDEX('Annex 4 LDNO charges'!$C$11:$C$201,MATCH($A109,'Annex 4 LDNO charges'!$A$11:$A$201,0))) -> 0 | F109: 0.80732906
A110: LDNO 132kV/EHV: LV Site Specific Band 4 | B110: =IFERROR(INDEX('Annex 1 LV, HV and UMS charges'!$B$12:$B$43,MATCH($A110,'Annex 1 LV, HV and UMS charges'!$A$12:$A$43,0)),IF(INDEX('Annex 4 LDNO charges'!$B$11:$B$201,MATCH($A110,'Annex 4 LDNO charges'!$A$11:$A$201,0))=0,"",INDEX('Annex 4 LDNO charges'!$B$11:$B$201,MATCH($A110,'Annex 4 LDNO charges'!$A$11:$A$201,0)))) -> E44 | C110: =IFERROR(INDEX('Annex 1 LV, HV and UMS charges'!$C$12:$C$43,MATCH($A110,'Annex 1 LV, HV and UMS charges'!$A$12:$A$43,0)),INDEX('Annex 4 LDNO charges'!$C$11:$C$201,MATCH($A110,'Annex 4 LDNO charges'!$A$11:$A$201,0))) -> 0 | F110: 0.80732906
A111: LDNO 132kV/EHV: LV Sub Site Specific No Residual | B111: =IFERROR(INDEX('Annex 1 LV, HV and UMS charges'!$B$12:$B$43,MATCH($A111,'Annex 1 LV, HV and UMS charges'!$A$12:$A$43,0)),IF(INDEX('Annex 4 LDNO charges'!$B$11:$B$201,MATCH($A111,'Annex 4 LDNO charges'!$A$11:$A$201,0))=0,"",INDEX('Annex 4 LDNO charges'!$B$11:$B$201,MATCH($A111,'Annex 4 LDNO charges'!$A$11:$A$201,0)))) -> J40 | C111: =IFERROR(INDEX('Annex 1 LV, HV and UMS charges'!$C$12:$C$43,MATCH($A111,'Annex 1 LV, HV and UMS charges'!$A$12:$A$43,0)),INDEX('Annex 4 LDNO charges'!$C$11:$C$201,MATCH($A111,'Annex 4 LDNO charges'!$A$11:$A$201,0))) -> 0 | F111: 0.80732906
A112: LDNO 132kV/EHV: LV Sub Site Specific Band 1 | B112: =IFERROR(INDEX('Annex 1 LV, HV and UMS charges'!$B$12:$B$43,MATCH($A112,'Annex 1 LV, HV and UMS charges'!$A$12:$A$43,0)),IF(INDEX('Annex 4 LDNO charges'!$B$11:$B$201,MATCH($A112,'Annex 4 LDNO charges'!$A$11:$A$201,0))=0,"",INDEX('Annex 4 LDNO charges'!$B$11:$B$201,MATCH($A112,'Annex 4 LDNO charges'!$A$11:$A$201,0)))) -> J41 | C112: =IFERROR(INDEX('Annex 1 LV, HV and UMS charges'!$C$12:$C$43,MATCH($A112,'Annex 1 LV, HV and UMS charges'!$A$12:$A$43,0)),INDEX('Annex 4 LDNO charges'!$C$11:$C$201,MATCH($A112,'Annex 4 LDNO charges'!$A$11:$A$201,0))) -> 0 | F112: 0.80732906
... A120: LDNO 132kV/EHV: HV Site Specific Band 4 | B120: =IFERROR(INDEX('Annex 1 LV, HV and UMS charges'!$B$12:$B$43,MATCH($A120,'Annex 1 LV, HV and UMS charges'!$A$12:$A$43,0)),IF(INDEX('Annex 4 LDNO charges'!$B$11:$B$201,MATCH($A120,'Annex 4 LDNO charges'!$A$11:$A$201,0))=0,"",INDEX('Annex 4 LDNO charges'!$B$11:$B$201,MATCH($A120,'Annex 4 LDNO charges'!$A$11:$A$201,0)))) -> K44 | C120: =IFERROR(INDEX('Annex 1 LV, HV and UMS charges'!$C$12:$C$43,MATCH($A120,'Annex 1 LV, HV and UMS charges'!$A$12:$A$43,0)),INDEX('Annex 4 LDNO charges'!$C$11:$C$201,MATCH($A120,'Annex 4 LDNO charges'!$A$11:$A$201,0))) -> 0 | F120: 0.80732906
A121: LDNO 132kV: Domestic Aggregated or CT with Residual | B121: =IFERROR(INDEX('Annex 1 LV, HV and UMS charges'!$B$12:$B$43,MATCH($A121,'Annex 1 LV, HV and UMS charges'!$A$12:$A$43,0)),IF(INDEX('Annex 4 LDNO charges'!$B$11:$B$201,MATCH($A121,'Annex 4 LDNO charges'!$A$11:$A$201,0))=0,"",INDEX('Annex 4 LDNO charges'!$B$11:$B$201,MATCH($A121,'Annex 4 LDNO charges'!$A$11:$A$201,0)))) -> A50 | C121: =IFERROR(INDEX('Annex 1 LV, HV and UMS charges'!$C$12:$C$43,MATCH($A121,'Annex 1 LV, HV and UMS charges'!$A$12:$A$43,0)),INDEX('Annex 4 LDNO charges'!$C$11:$C$201,MATCH($A121,'Annex 4 LDNO charges'!$A$11:$A$201,0))) -> 0, 1, 2 | D121: 0.18118202 | F121: 0.80732906
A122: LDNO 132kV: Non-Domestic Aggregated or CT No Residual | B122: =IFERROR(INDEX('Annex 1 LV, HV and UMS charges'!$B$12:$B$43,MATCH($A122,'Annex 1 LV, HV and UMS charges'!$A$12:$A$43,0)),IF(INDEX('Annex 4 LDNO charges'!$B$11:$B$201,MATCH($A122,'Annex 4 LDNO charges'!$A$11:$A$201,0))=0,"",INDEX('Annex 4 LDNO charges'!$B$11:$B$201,MATCH($A122,'Annex 4 LDNO charges'!$A$11:$A$201,0)))) -> C50 | C122: =IFERROR(INDEX('Annex 1 LV, HV and UMS charges'!$C$12:$C$43,MATCH($A122,'Annex 1 LV, HV and UMS charges'!$A$12:$A$43,0)),INDEX('Annex 4 LDNO charges'!$C$11:$C$201,MATCH($A122,'Annex 4 LDNO charges'!$A$11:$A$201,0))) -> 0, 3, 4, 5-8 | F122: 0.80732906
A123: LDNO 132kV: Non-Domestic Aggregated or CT Band 1 | B123: =IFERROR(INDEX('Annex 1 LV, HV and UMS charges'!$B$12:$B$43,MATCH($A123,'Annex 1 LV, HV and UMS charges'!$A$12:$A$43,0)),IF(INDEX('Annex 4 LDNO charges'!$B$11:$B$201,MATCH($A123,'Annex 4 LDNO charges'!$A$11:$A$201,0))=0,"",INDEX('Annex 4 LDNO charges'!$B$11:$B$201,MATCH($A123,'Annex 4 LDNO charges'!$A$11:$A$201,0)))) -> C51 | C123: =IFERROR(INDEX('Annex 1 LV, HV and UMS charges'!$C$12:$C$43,MATCH($A123,'Annex 1 LV, HV and UMS charges'!$A$12:$A$43,0)),INDEX('Annex 4 LDNO charges'!$C$11:$C$201,MATCH($A123,'Annex 4 LDNO charges'!$A$11:$A$201,0))) -> 0, 3, 4, 5-8 | F123: 0.80732906
A124: LDNO 132kV: Non-Domestic Aggregated or CT Band 2 | B124: =IFERROR(INDEX('Annex 1 LV, HV and UMS charges'!$B$12:$B$43,MATCH($A124,'Annex 1 LV, HV and UMS charges'!$A$12:$A$43,0)),IF(INDEX('Annex 4 LDNO charges'!$B$11:$B$201,MATCH($A124,'Annex 4 LDNO charges'!$A$11:$A$201,0))=0,"",INDEX('Annex 4 LDNO charges'!$B$11:$B$201,MATCH($A124,'Annex 4 LDNO charges'!$A$11:$A$201,0)))) -> C52 | C124: =IFERROR(INDEX('Annex 1 LV, HV and UMS charges'!$C$12:$C$43,MATCH($A124,'Annex 1 LV, HV and UMS charges'!$A$12:$A$43,0)),INDEX('Annex 4 LDNO charges'!$C$11:$C$201,MATCH($A124,'Annex 4 LDNO charges'!$A$11:$A$201,0))) -> 0, 3, 4, 5-8 | F124: 0.80732906
A125: LDNO 132kV: Non-Domestic Aggregated or CT Band 3 | B125: =IFERROR(INDEX('Annex 1 LV, HV and UMS charges'!$B$12:$B$43,MATCH($A125,'Annex 1 LV, HV and UMS charges'!$A$12:$A$43,0)),IF(INDEX('Annex 4 LDNO charges'!$B$11:$B$201,MATCH($A125,'Annex 4 LDNO charges'!$A$11:$A$201,0))=0,"",INDEX('Annex 4 LDNO charges'!$B$11:$B$201,MATCH($A125,'Annex 4 LDNO charges'!$A$11:$A$201,0)))) -> C53 | C125: =IFERROR(INDEX('Annex 1 LV, HV and UMS charges'!$C$12:$C$43,MATCH($A125,'Annex 1 LV, HV and UMS charges'!$A$12:$A$43,0)),INDEX('Annex 4 LDNO charges'!$C$11:$C$201,MATCH($A125,'Annex 4 LDNO charges'!$A$11:$A$201,0))) -> 0, 3, 4, 5-8 | F125: 0.80732906
A126: LDNO 132kV: Non-Domestic Aggregated or CT Band 4 | B126: =IFERROR(INDEX('Annex 1 LV, HV and UMS charges'!$B$12:$B$43,MATCH($A126,'Annex 1 LV, HV and UMS charges'!$A$12:$A$43,0)),IF(INDEX('Annex 4 LDNO charges'!$B$11:$B$201,MATCH($A126,'Annex 4 LDNO charges'!$A$11:$A$201,0))=0,"",INDEX('Annex 4 LDNO charges'!$B$11:$B$201,MATCH($A126,'Annex 4 LDNO charges'!$A$11:$A$201,0)))) -> C54 | C126: =IFERROR(INDEX('Annex 1 LV, HV and UMS charges'!$C$12:$C$43,MATCH($A126,'Annex 1 LV, HV and UMS charges'!$A$12:$A$43,0)),INDEX('Annex 4 LDNO charges'!$C$11:$C$201,MATCH($A126,'Annex 4 LDNO charges'!$A$11:$A$201,0))) -> 0, 3, 4, 5-8 | F126: 0.80732906
A127: LDNO 132kV: LV Site Specific No Residual | B127: =IFERROR(INDEX('Annex 1 LV, HV and UMS charges'!$B$12:$B$43,MATCH($A127,'Annex 1 LV, HV and UMS charges'!$A$12:$A$43,0)),IF(INDEX('Annex 4 LDNO charges'!$B$11:$B$201,MATCH($A127,'Annex 4 LDNO charges'!$A$11:$A$201,0))=0,"",INDEX('Annex 4 LDNO charges'!$B$11:$B$201,MATCH($A127,'Annex 4 LDNO charges'!$A$11:$A$201,0)))) -> E50 | C127: =IFERROR(INDEX('Annex 1 LV, HV and UMS charges'!$C$12:$C$43,MATCH($A127,'Annex 1 LV, HV and UMS charges'!$A$12:$A$43,0)),INDEX('Annex 4 LDNO charges'!$C$11:$C$201,MATCH($A127,'Annex 4 LDNO charges'!$A$11:$A$201,0))) -> 0 | F127: 0.80732906
A128: LDNO 132kV: LV Site Specific Band 1 | B128: =IFERROR(INDEX('Annex 1 LV, HV and UMS charges'!$B$12:$B$43,MATCH($A128,'Annex 1 LV, HV and UMS charges'!$A$12:$A$43,0)),IF(INDEX('Annex 4 LDNO charges'!$B$11:$B$201,MATCH($A128,'Annex 4 LDNO charges'!$A$11:$A$201,0))=0,"",INDEX('Annex 4 LDNO charges'!$B$11:$B$201,MATCH($A128,'Annex 4 LDNO charges'!$A$11:$A$201,0)))) -> E51 | C128: =IFERROR(INDEX('Annex 1 LV, HV and UMS charges'!$C$12:$C$43,MATCH($A128,'Annex 1 LV, HV and UMS charges'!$A$12:$A$43,0)),INDEX('Annex 4 LDNO charges'!$C$11:$C$201,MATCH($A128,'Annex 4 LDNO charges'!$A$11:$A$201,0))) -> 0 | F128: 0.80732906
A129: LDNO 132kV: LV Site Specific Band 2 | B129: =IFERROR(INDEX('Annex 1 LV, HV and UMS charges'!$B$12:$B$43,MATCH($A129,'Annex 1 LV, HV and UMS charges'!$A$12:$A$43,0)),IF(INDEX('Annex 4 LDNO charges'!$B$11:$B$201,MATCH($A129,'Annex 4 LDNO charges'!$A$11:$A$201,0))=0,"",INDEX('Annex 4 LDNO charges'!$B$11:$B$201,MATCH($A129,'Annex 4 LDNO charges'!$A$11:$A$201,0)))) -> E52 | C129: =IFERROR(INDEX('Annex 1 LV, HV and UMS charges'!$C$12:$C$43,MATCH($A129,'Annex 1 LV, HV and UMS charges'!$A$12:$A$43,0)),INDEX('Annex 4 LDNO charges'!$C$11:$C$201,MATCH($A129,'Annex 4 LDNO charges'!$A$11:$A$201,0))) -> 0 | F129: 0.80732906
A130: LDNO 132kV: LV Site Specific Band 3 | B130: =IFERROR(INDEX('Annex 1 LV, HV and UMS charges'!$B$12:$B$43,MATCH($A130,'Annex 1 LV, HV and UMS charges'!$A$12:$A$43,0)),IF(INDEX('Annex 4 LDNO charges'!$B$11:$B$201,MATCH($A130,'Annex 4 LDNO charges'!$A$11:$A$201,0))=0,"",INDEX('Annex 4 LDNO charges'!$B$11:$B$201,MATCH($A130,'Annex 4 LDNO charges'!$A$11:$A$201,0)))) -> E53 | C130: =IFERROR(INDEX('Annex 1 LV, HV and UMS charges'!$C$12:$C$43,MATCH($A130,'Annex 1 LV, HV and UMS charges'!$A$12:$A$43,0)),INDEX('Annex 4 LDNO charges'!$C$11:$C$201,MATCH($A130,'Annex 4 LDNO charges'!$A$11:$A$201,0))) -> 0 | F130: 0.80732906
A131: LDNO 132kV: LV Site Specific Band 4 | B131: =IFERROR(INDEX('Annex 1 LV, HV and UMS charges'!$B$12:$B$43,MATCH($A131,'Annex 1 LV, HV and UMS charges'!$A$12:$A$43,0)),IF(INDEX('Annex 4 LDNO charges'!$B$11:$B$201,MATCH($A131,'Annex 4 LDNO charges'!$A$11:$A$201,0))=0,"",INDEX('Annex 4 LDNO charges'!$B$11:$B$201,MATCH($A131,'Annex 4 LDNO charges'!$A$11:$A$201,0)))) -> E54 | C131: =IFERROR(INDEX('Annex 1 LV, HV and UMS charges'!$C$12:$C$43,MATCH($A131,'Annex 1 LV, HV and UMS charges'!$A$12:$A$43,0)),INDEX('Annex 4 LDNO charges'!$C$11:$C$201,MATCH($A131,'Annex 4 LDNO charges'!$A$11:$A$201,0))) -> 0 | F131: 0.80732906
A132: LDNO 132kV: LV Sub Site Specific No Residual | B132: =IFERROR(INDEX('Annex 1 LV, HV and UMS charges'!$B$12:$B$43,MATCH($A132,'Annex 1 LV, HV and UMS charges'!$A$12:$A$43,0)),IF(INDEX('Annex 4 LDNO charges'!$B$11:$B$201,MATCH($A132,'Annex 4 LDNO charges'!$A$11:$A$201,0))=0,"",INDEX('Annex 4 LDNO charges'!$B$11:$B$201,MATCH($A132,'Annex 4 LDNO charges'!$A$11:$A$201,0)))) -> J50 | C132: =IFERROR(INDEX('Annex 1 LV, HV and UMS charges'!$C$12:$C$43,MATCH($A132,'Annex 1 LV, HV and UMS charges'!$A$12:$A$43,0)),INDEX('Annex 4 LDNO charges'!$C$11:$C$201,MATCH($A132,'Annex 4 LDNO charges'!$A$11:$A$201,0))) -> 0 | F132: 0.80732906
A133: LDNO 132kV: LV Sub Site Specific Band 1 | B133: =IFERROR(INDEX('Annex 1 LV, HV and UMS charges'!$B$12:$B$43,MATCH($A133,'Annex 1 LV, HV and UMS charges'!$A$12:$A$43,0)),IF(INDEX('Annex 4 LDNO charges'!$B$11:$B$201,MATCH($A133,'Annex 4 LDNO charges'!$A$11:$A$201,0))=0,"",INDEX('Annex 4 LDNO charges'!$B$11:$B$201,MATCH($A133,'Annex 4 LDNO charges'!$A$11:$A$201,0)))) -> J51 | C133: =IFERROR(INDEX('Annex 1 LV, HV and UMS charges'!$C$12:$C$43,MATCH($A133,'Annex 1 LV, HV and UMS charges'!$A$12:$A$43,0)),INDEX('Annex 4 LDNO charges'!$C$11:$C$201,MATCH($A133,'Annex 4 LDNO charges'!$A$11:$A$201,0))) -> 0 | F133: 0.80732906
... A141: LDNO 132kV: HV Site Specific Band 4 | B141: =IFERROR(INDEX('Annex 1 LV, HV and UMS charges'!$B$12:$B$43,MATCH($A141,'Annex 1 LV, HV and UMS charges'!$A$12:$A$43,0)),IF(INDEX('Annex 4 LDNO charges'!$B$11:$B$201,MATCH($A141,'Annex 4 LDNO charges'!$A$11:$A$201,0))=0,"",INDEX('Annex 4 LDNO charges'!$B$11:$B$201,MATCH($A141,'Annex 4 LDNO charges'!$A$11:$A$201,0)))) -> K54 | C141: =IFERROR(INDEX('Annex 1 LV, HV and UMS charges'!$C$12:$C$43,MATCH($A141,'Annex 1 LV, HV and UMS charges'!$A$12:$A$43,0)),INDEX('Annex 4 LDNO charges'!$C$11:$C$201,MATCH($A141,'Annex 4 LDNO charges'!$A$11:$A$201,0))) -> 0 | F141: 0.80732906
A142: LDNO 0000: Domestic Aggregated or CT with Residual | B142: =IFERROR(INDEX('Annex 1 LV, HV and UMS charges'!$B$12:$B$43,MATCH($A142,'Annex 1 LV, HV and UMS charges'!$A$12:$A$43,0)),IF(INDEX('Annex 4 LDNO charges'!$B$11:$B$201,MATCH($A142,'Annex 4 LDNO charges'!$A$11:$A$201,0))=0,"",INDEX('Annex 4 LDNO charges'!$B$11:$B$201,MATCH($A142,'Annex 4 LDNO charges'!$A$11:$A$201,0)))) -> A60 | C142: =IFERROR(INDEX('Annex 1 LV, HV and UMS charges'!$C$12:$C$43,MATCH($A142,'Annex 1 LV, HV and UMS charges'!$A$12:$A$43,0)),INDEX('Annex 4 LDNO charges'!$C$11:$C$201,MATCH($A142,'Annex 4 LDNO charges'!$A$11:$A$201,0))) -> 0, 1, 2 | D142: 0.18118202 | F142: 0.80732906
A143: LDNO 0000: Non-Domestic Aggregated or CT No Residual | B143: =IFERROR(INDEX('Annex 1 LV, HV and UMS charges'!$B$12:$B$43,MATCH($A143,'Annex 1 LV, HV and UMS charges'!$A$12:$A$43,0)),IF(INDEX('Annex 4 LDNO charges'!$B$11:$B$201,MATCH($A143,'Annex 4 LDNO charges'!$A$11:$A$201,0))=0,"",INDEX('Annex 4 LDNO charges'!$B$11:$B$201,MATCH($A143,'Annex 4 LDNO charges'!$A$11:$A$201,0)))) -> C60 | C143: =IFERROR(INDEX('Annex 1 LV, HV and UMS charges'!$C$12:$C$43,MATCH($A143,'Annex 1 LV, HV and UMS charges'!$A$12:$A$43,0)),INDEX('Annex 4 LDNO charges'!$C$11:$C$201,MATCH($A143,'Annex 4 LDNO charges'!$A$11:$A$201,0))) -> 0, 3, 4, 5-8 | F143: 0.80732906
...

Sheet Nodal prices
A1: Back to Overview
A2: =Overview!B4& " - Effective from "&Overview!D4&" - "&Overview!E4&" Nodal/Zonal charges" -> South Eastern Power Networks - Effective from 1 April 2024 - Final Nodal/Zonal charges
A3: Node/Zone ID | B3: Geographical name | C3: Local charge 1 £/kVA | D3: Remote charge 1 £/kVA
A4: ABNR31 | B4: SPN 0003 | C4: 0.18411961 | D4: 0.84386475
A5: ABNR32 | B5: SPN 0003 | C5: 0.18411961 | D5: 0.84386475
A6: ADDG51 | B6: Addington Grid | C6: 0.0097082136 | D6: 13.015145
A7: ADDL51 | B7: Addington Local | C7: 0.32167387 | D7: 13.701574
A8: ADDL52 | B8: Addington Local | C8: 0.046557708 | D8: 13.107114
A9: ALLG51 | B9: SPN 0018 | C9: 0 | D9: 12.949182
A10: ANGM51 | B10: Angmering | C10: 1.1322883 | D10: 6.8463121
A11: ANGM52 | B11: Angmering | C11: -0.24210397 | D11: 22.906149
A12: AREP31 | B12: SPN 0084 | C12: 0.64263186 | D12: 21.832747
A13: ARLP31 | B13: SPN 0067 | C13: 0.62778426 | D13: 6.6013186
A14: ASHG31 | B14: SPN 0020 | C14: 0.24554444 | D14: 3.1709709
A15: ASHI51 | B15: Ashington | C15: 0.50717222 | D15: 21.348211
... A402: XWAY51 | B402: Crossways | C402: 0.085791846 | D402: 0.79067565

Sheet SSC unit rate lookup
A1: Back to Overview
A28: Standard Settlement Configuration Id | B28: Standard Settlement Configuration Desc | C28: Common Decode | F28: Change implemented | G28: Date | H28: Comments
A29: 3 | B29: 10-hour OP | C29: A/R | F29: Notes updated | G29: 43626 | H29: Updated to reflect DCP 268 which delinks all tariffs from the TPR bands
A30: 4 | B30: 10-hour OP | C30: A/R | F30: Code 1 & 2 changed to A | G30: 43626 | H30: Updated to reflect DCP 268 which delinks all tariffs from the TPR bands
A31: 5 | B31: 10-hour OP + w/e | C31: A/R | F31: Code O changed to A/R | G31: 43626 | H31: Updated to reflect DCP 268 which delinks all tariffs from the TPR bands
A32: 6 | B32: 10.5-hour OP | C32: A/R | F32: Removed TPR | G32: 43626 | H32: Removed TPR lookup element as this no longer effects which rate to apply
A33: 7 | B33: 10.5-hour OP | C33: A/R
A34: 8 | B34: 10.5-hour OP | C34: A/R
A35: 9 | B35: 10.5-hour OP | C35: A/R
A36: 10 | B36: 10.5-hour OP | C36: A/R
A37: 11 | B37: 10.5-hour OP | C37: A/R
A38: 12 | B38: 10.5-hour OP | C38: A/R
A39: 13 | B39: 11 Hour OP | C39: A/R
A40: 15 | B40: 11 Hour OP | C40: A/R
A41: 16 | B41: 11.5-hour OP | C41: A/R
A42: 17 | B42: 11.5-hour OP | C42: A/R
A43: 18 | B43: 11.5-hour OP | C43: A/R
A44: 19 | B44: 11.5-hour OP | C44: A/R
... A764: 997 | B764: Evening/Weekend - BST | C764: A

Sheet Residual Charging Bands
A1: Back to Overview
A2: =Overview!B4& " - Effective from "&Overview!C4&" - "&Overview!E4&" Residual Charging Bands" -> South Eastern Power Networks - Effective from 2024/25 - Final Residual Charging Bands
A4: Voltage of Connection | B4: Band | C4: Units | D4: Lower Threshold* | E4: Upper Threshold* | F4: Residual Charge per MPAN (£/year)
A5: Domestic Aggregated | B5: Single band | C5: - | D5: - | E5: - | F5: 52.174755
A6: Designated Properties connected at LV, billing with no MIC | B6: 1 | C6: kWh | D6: 0 | E6: 3571 | F6: 20.734363
B7: 2 | C7: kWh | D7: 3571 | E7: 12553 | F7: 113.38255
B8: 3 | C8: kWh | D8: 12553 | E8: 25279 | F8: 263.23867
B9: 4 | C9: kWh | D9: 25279 | E9: ∞ | F9: 816.40922
A10: Designated Properties connected at LV, billing with MIC | B10: 1 | C10: kVA | D10: 0 | E10: 80 | F10: 1536.024
B11: 2 | C11: kVA | D11: 80 | E11: 150 | F11: 2588.1449
B12: 3 | C12: kVA | D12: 150 | E12: 231 | F12: 4226.4916
B13: 4 | C13: kVA | D13: 231 | E13: ∞ | F13: 9406.4079
A14: Designated Properties connected at HV | B14: 1 | C14: kVA | D14: 0 | E14: 422 | F14: 6181.2588
B15: 2 | C15: kVA | D15: 422 | E15: 1000 | F15: 34904.672
B16: 3 | C16: kVA | D16: 1000 | E16: 1800 | F16: 30415.635
B17: 4 | C17: kVA | D17: 1800 | E17: ∞ | F17: 78444.486
A18: Designated EHV Properties | B18: 1 | C18: kVA | D18: 0 | E18: 5000 | F18: 9096.6728
B19: 2 | C19: kVA | D19: 5000 | E19: 12000 | F19: 57997.455
B20: 3 | C20: kVA | D20: 12000 | E20: 21500 | F20: 129663.1
B21: 4 | C21: kVA | D21: 21500 | E21: ∞ | F21: 244290.8
A22: * All boundaries are inclusive of the upper threshold and exclusive of the lower threshold i.e. Lower < x ≤ Upper.

Sheet Charge Calculator
B1: Back to Overview
B2: =Overview!B4& " - Effective from "&Overview!D4&" - "&Overview!E4 -> South Eastern Power Networks - Effective from 1 April 2024 - Final | AC2: Tariff name | AD2: Red/black unit charge p/kWh | AE2: Amber/yellow unit charge p/kWh | AF2: Green unit charge p/kWh | AG2: Fixed charge p/MPAN/day | AH2: Capacity charge p/kVA/day | AI2: Exceeded capacity charge p/kVA/day | AJ2: Reactive power charge p/kVArh
AC3: Domestic Aggregated with Residual | AD3: Red unit charge p/kWh | AE3: Amber unit charge p/kWh | AF3: Green unit charge p/kWh | AG3: Fixed charge p/MPAN/day | AH3: n/a | AI3: n/a | AJ3: n/a
B4: LV and HV designated properties and Unmetered Supplies tariff calculator | L4: EHV designated property calculator | AC4: Domestic Aggregated (Related MPAN) | AD4: Red unit charge p/kWh | AE4: Amber unit charge p/kWh | AF4: Green unit charge p/kWh | AG4: n/a | AH4: n/a | AI4: n/a | AJ4: n/a
B5: Step 1, Choose your tariff using the drop down list in cell B10 | L5: Step 1, Choose your tariff using the drop down list in cell L10 | AC5: Non-Domestic Aggregated No Residual | AD5: Red unit charge p/kWh | AE5: Amber unit charge p/kWh | AF5: Green unit charge p/kWh | AG5: Fixed charge p/MPAN/day | AH5: n/a | AI5: n/a | AJ5: n/a
B6: Step 2, After selecting a tariff in step 1, Cells C12-I12 will generate headings, please enter your consumption in cells C13:I13 underneath each heading generated (if no heading leave cell blank) | L6: Step 2, After selecting a tariff in step 1, Cells M12-T12 will generate headings, please enter your consumption in cells M13:T13 underneath each heading generated (if no heading leave cell blank) | AC6: Non-Domestic Aggregated Band 1 | AD6: Red unit charge p/kWh | AE6: Amber unit charge p/kWh | AF6: Green unit charge p/kWh | AG6: Fixed charge p/MPAN/day | AH6: n/a | AI6: n/a | AJ6: n/a
B7: Step 3, Enter a forecast of consumption if required in cells C14:I14 | L7: Step 3, Enter a forecast of consumption if required in cells M14:T14 | AC7: Non-Domestic Aggregated Band 2 | AD7: Red unit charge p/kWh | AE7: Amber unit charge p/kWh | AF7: Green unit charge p/kWh | AG7: Fixed charge p/MPAN/day | AH7: n/a | AI7: n/a | AJ7: n/a
AC8: Non-Domestic Aggregated Band 3 | AD8: Red unit charge p/kWh | AE8: Amber unit charge p/kWh | AF8: Green unit charge p/kWh | AG8: Fixed charge p/MPAN/day | AH8: n/a | AI8: n/a | AJ8: n/a
B9: Tariff details Choose tariff name from drop down box below | C9: =IFERROR(VLOOKUP($B$10,$AC$2:$AJ$34,2,FALSE),AD2) -> Red/black unit charge p/kWh | D9: =IFERROR(VLOOKUP($B$10,$AC$2:$AJ$34,3,FALSE),AE2) -> Amber/yellow unit charge p/kWh | E9: =IFERROR(VLOOKUP($B$10,$AC$2:$AJ$34,4,FALSE),AF2) -> Green unit charge p/kWh | F9: =IFERROR(VLOOKUP($B$10,$AC$2:$AJ$34,5,FALSE),AG2) -> Fixed charge p/MPAN/day | G9: =IFERROR(VLOOKUP($B$10,$AC$2:$AJ$34,6,FALSE),AH2) -> Capacity charge p/kVA/day | H9: =IFERROR(VLOOKUP($B$10,$AC$2:$AJ$34,7,FALSE),AI2) -> Exceeded capacity charge p/kVA/day | I9: =IFERROR(VLOOKUP($B$10,$AC$2:$AJ$34,8,FALSE),AJ2) -> Reactive power charge p/kVArh | L9: Site details Choose the site name from the drop down box below | M9: ='Annex 2 EHV charges'!I9 -> Import Super Red unit charge (p/kWh) | N9: ='Annex 2 EHV charges'!J9 -> Import fixed charge (p/day) | O9: ='Annex 2 EHV charges'!K9 -> Import capacity charge (p/kVA/day) | P9: ='Annex 2 EHV charges'!L9 -> Import exceeded capacity charge (p/kVA/day) | Q9: ='Annex 2 EHV charges'!M9 -> Export Super Red unit charge (p/kWh) | R9: ='Annex 2 EHV charges'!N9 -> Export fixed charge (p/day) | S9: ='Annex 2 EHV charges'!O9 -> Export capacity charge (p/kVA/day) | T9: ='Annex 2 EHV charges'!P9 -> Export exceeded capacity charge (p/kVA/day) | AC9: Non-Domestic Aggregated Band 4 | AD9: Red unit charge p/kWh | AE9: Amber unit charge p/kWh | AF9: Green unit charge p/kWh | AG9: Fixed charge p/MPAN/day | AH9: n/a | AI9: n/a | AJ9: n/a
C10: =IFERROR(VLOOKUP($B$10,'Annex 1 LV, HV and UMS charges'!$A:$K,4,FALSE),"") | D10: =IFERROR(VLOOKUP($B$10,'Annex 1 LV, HV and UMS charges'!$A:$K,5,FALSE),"") | E10: =IFERROR(VLOOKUP($B$10,'Annex 1 LV, HV and UMS charges'!$A:$K,6,FALSE),"") | F10: =IFERROR(VLOOKUP($B$10,'Annex 1 LV, HV and UMS charges'!$A:$K,7,FALSE),"") | G10: =IFERROR(VLOOKUP($B$10,'Annex 1 LV, HV and UMS charges'!$A:$K,8,FALSE),"") | H10: =IFERROR(VLOOKUP($B$10,'Annex 1 LV, HV and UMS charges'!$A:$K,9,FALSE),"") | I10: =IFERROR(VLOOKUP($B$10,'Annex 1 LV, HV and UMS charges'!$A:$K,10,FALSE),"") | M10: =IFERROR(VLOOKUP($L$10,'Annex 2 EHV charges'!$G:$O,3,FALSE),"") | N10: =IFERROR(VLOOKUP($L$10,'Annex 2 EHV charges'!$G:$O,4,FALSE),"") | O10: =IFERROR(VLOOKUP($L$10,'Annex 2 EHV charges'!$G:$O,5,FALSE),"") | P10: =IFERROR(VLOOKUP($L$10,'Annex 2 EHV charges'!$G:$O,6,FALSE),"") | Q10: =IFERROR(VLOOKUP($L$10,'Annex 2 EHV charges'!$G:$O,7,FALSE),"") | R10: =IFERROR(VLOOKUP($L$10,'Annex 2 EHV charges'!$G:$O,8,FALSE),"") | S10: =IFERROR(VLOOKUP($L$10,'Annex 2 EHV charges'!$G:$O,9,FALSE),"") | T10: =IFERROR(VLOOKUP($L$10,'Annex 2 EHV charges'!$G:$P,10,FALSE),"") | AC10: Non-Domestic Aggregated (related MPAN) | AD10: Red unit charge p/kWh | AE10: Amber unit charge p/kWh | AF10: Green unit charge p/kWh | AG10: n/a | AH10: n/a | AI10: n/a | AJ10: n/a
AC11: LV Site Specific No Residual | AD11: Red unit charge p/kWh | AE11: Amber unit charge p/kWh | AF11: Green unit charge p/kWh | AG11: Fixed charge p/MPAN/day | AH11: Capacity charge p/kVA/day | AI11: Exceeded Capacity charge p/kVA/day | AJ11: Reactive power charge p/kVArh
B12: Tariff components | C12: =C9 -> Red/black unit charge p/kWh | D12: =D9 -> Amber/yellow unit charge p/kWh | E12: =E9 -> Green unit charge p/kWh | F12: Number of days in consumption period i.e. 365 if one year | G12: Maximum import or export capacity kVA | H12: Average daily exceeded capacity kVA | I12: Excess reactive units kVArh | L12: Tariff components | M12: Import super red kWh | N12: Number of days in consumption period i.e. 365 if one year | O12: Maximum import capacity kVA | P12: Average daily exceeded capacity kVA | Q12: Export Super Red kWh | R12: Number of days in consumption period i.e. 365 if one year | S12: Maximum export capacity kVA | T12: Average daily exceeded capacity kVA | AC12: LV Site Specific Band 1 | AD12: Red unit charge p/kWh | AE12: Amber unit charge p/kWh | AF12: Green unit charge p/kWh | AG12: Fixed charge p/MPAN/day | AH12: Capacity charge p/kVA/day | AI12: Exceeded Capacity charge p/kVA/day | AJ12: Reactive power charge p/kVArh
B13: Enter current consumption details | L13: Enter current consumption details | R13: =N13 -> 0 | AC13: LV Site Specific Band 2 | AD13: Red unit charge p/kWh | AE13: Amber unit charge p/kWh | AF13: Green unit charge p/kWh | AG13: Fixed charge p/MPAN/day | AH13: Capacity charge p/kVA/day | AI13: Exceeded Capacity charge p/kVA/day | AJ13: Reactive power charge p/kVArh
B14: Enter forecast consumption details (if different) | C14: =C13 -> 0 | D14: =D13 -> 0 | E14: =E13 -> 0 | F14: =F13 -> 0 | G14: =G13 -> 0 | H14: =H13 -> 0 | I14: =I13 -> 0 | L14: Enter forecast consumption details (if different) | M14: =M13 -> 0 | N14: =N13 -> 0 | O14: =O13 -> 0 | P14: =P13 -> 0 | Q14: =Q13 -> 0 | R14: =R13 -> 0 | S14: =S13 -> 0 | T14: =T13 -> 0 | AC14: LV Site Specific Band 3 | AD14: Red unit charge p/kWh | AE14: Amber unit charge p/kWh | AF14: Green unit charge p/kWh | AG14: Fixed charge p/MPAN/day | AH14: Capacity charge p/kVA/day | AI14: Exceeded Capacity charge p/kVA/day | AJ14: Reactive power charge p/kVArh
AC15: LV Site Specific Band 4 | AD15: Red unit charge p/kWh | AE15: Amber unit charge p/kWh | AF15: Green unit charge p/kWh | AG15: Fixed charge p/MPAN/day | AH15: Capacity charge p/kVA/day | AI15: Exceeded Capacity charge p/kVA/day | AJ15: Reactive power charge p/kVArh
B16: Charge components | C16: Unit 1 £ | D16: Unit 2 £ | E16: Unit 3 £ | F16: Fixed charge £ | G16: Capacity charge £ | H16: Exceeded capacity charge £ | I16: Reactive power charge £ | L16: Charge components | M16: Import super red charge £ | N16: Import fixed charge £ | O16: Import capacity charge £ | P16: Import exceeded capacity charge £ | Q16: Export super red charge £ | R16: Export fixed charge £ | S16: Export capacity charge £ | T16: Export exceeded capacity charge £ | AC16: LV Sub Site Specific No Residual | AD16: Red unit charge p/kWh | AE16: Amber unit charge p/kWh | AF16: Green unit charge p/kWh | AG16: Fixed charge p/MPAN/day | AH16: Capacity charge p/kVA/day | AI16: Exceeded Capacity charge p/kVA/day | AJ16: Reactive power charge p/kVArh
B17: Current consumption period charges | C17: =IFERROR(C10*C13/100,"") | D17: =IFERROR(D10*D13/100,"") | E17: =IFERROR(E10*E13/100,"") | F17: =IFERROR(F10*F13/100,"") | G17: =IFERROR(G10*G13*F13/100,"") | H17: =IFERROR(H10*H13*F13/100,"") | I17: =IFERROR(I10*I13/100,"") | L17: Current consumption period charges | M17: =IFERROR(M10*M13/100,"") | N17: =IFERROR(N10*N13/100,"") | O17: =IFERROR(O10*O13*N13/100,"") | P17: =IFERROR(P10*P13*N13/100,"") | Q17: =IFERROR(Q10*Q13/100,"") | R17: =IFERROR(R10*R13/100,"") | S17: =IFERROR(S10*S13*R13/100,"") | T17: =IFERROR(T10*T13*R13/100,"") | AC17: LV Sub Site Specific Band 1 | AD17: Red unit charge p/kWh | AE17: Amber unit charge p/kWh | AF17: Green unit charge p/kWh | AG17: Fixed charge p/MPAN/day | AH17: Capacity charge p/kVA/day | AI17: Exceeded Capacity charge p/kVA/day | AJ17: Reactive power charge p/kVArh
B18: Forecast consumption period charges | C18: =IFERROR(C10*C14/100,"") | D18: =IFERROR(D10*D14/100,"") | E18: =IFERROR(E10*E14/100,"") | F18: =IFERROR(F10*F14/100,"") | G18: =IFERROR(G10*G14*F14/100,"") | H18: =IFERROR(H10*H14*F14/100,"") | I18: =IFERROR(I10*I14/100,"") | L18: Forecast consumption period charges | M18: =IFERROR(M10*M14/100,"") | N18: =IFERROR(N10*N14/100,"") | O18: =IFERROR(O10*O14*N14/100,"") | P18: =IFERROR(P10*P14*N14/100,"") | Q18: =IFERROR(Q10*Q14/100,"") | R18: =IFERROR(R10*R14/100,"") | S18: =IFERROR(S10*S14*R14/100,"") | T18: =IFERROR(T10*T14*R14/100,"") | AC18: LV Sub Site Specific Band 2 | AD18: Red unit charge p/kWh | AE18: Amber unit charge p/kWh | AF18: Green unit charge p/kWh | AG18: Fixed charge p/MPAN/day | AH18: Capacity charge p/kVA/day | AI18: Exceeded Capacity charge p/kVA/day | AJ18: Reactive power charge p/kVArh
AC19: LV Sub Site Specific Band 3 | AD19: Red unit charge p/kWh | AE19: Amber unit charge p/kWh | AF19: Green unit charge p/kWh | AG19: Fixed charge p/MPAN/day | AH19: Capacity charge p/kVA/day | AI19: Exceeded Capacity charge p/kVA/day | AJ19: Reactive power charge p/kVArh
C20: Total charge £ | M20: Import total charge £ | N20: Export total charge £ | AC20: LV Sub Site Specific Band 4 | AD20: Red unit charge p/kWh | AE20: Amber unit charge p/kWh | AF20: Green unit charge p/kWh | AG20: Fixed charge p/MPAN/day | AH20: Capacity charge p/kVA/day | AI20: Exceeded Capacity charge p/kVA/day | AJ20: Reactive power charge p/kVArh
B21: Current consumption period charges | C21: =SUM(C17:I17) -> 0 | L21: Current consumption period charges | M21: =SUM(M17:P17) -> 0 | N21: =SUM(Q17:T17) -> 0 | AC21: HV Site Specific No Residual | AD21: Red unit charge p/kWh | AE21: Amber unit charge p/kWh | AF21: Green unit charge p/kWh | AG21: Fixed charge p/MPAN/day | AH21: Capacity charge p/kVA/day | AI21: Exceeded Capacity charge p/kVA/day | AJ21: Reactive power charge p/kVArh
B22: Forecast consumption period charges | C22: =SUM(C18:I18) -> 0 | L22: Forecast consumption period charges | M22: =SUM(M18:P18) -> 0 | N22: =SUM(Q18:T18) -> 0 | AC22: HV Site Specific Band 1 | AD22: Red unit charge p/kWh | AE22: Amber unit charge p/kWh | AF22: Green unit charge p/kWh | AG22: Fixed charge p/MPAN/day | AH22: Capacity charge p/kVA/day | AI22: Exceeded Capacity charge p/kVA/day | AJ22: Reactive power charge p/kVArh
AC23: HV Site Specific Band 2 | AD23: Red unit charge p/kWh | AE23: Amber unit charge p/kWh | AF23: Green unit charge p/kWh | AG23: Fixed charge p/MPAN/day | AH23: Capacity charge p/kVA/day | AI23: Exceeded Capacity charge p/kVA/day | AJ23: Reactive power charge p/kVArh
B24: These charges are estimates based on tariff selected and consumption values entered. | L24: These charges are estimates based on site selected and consumption values entered. | AC24: HV Site Specific Band 3 | AD24: Red unit charge p/kWh | AE24: Amber unit charge p/kWh | AF24: Green unit charge p/kWh | AG24: Fixed charge p/MPAN/day | AH24: Capacity charge p/kVA/day | AI24: Exceeded Capacity charge p/kVA/day | AJ24: Reactive power charge p/kVArh
AC25: HV Site Specific Band 4 | AD25: Red unit charge p/kWh | AE25: Amber unit charge p/kWh | AF25: Green unit charge p/kWh | AG25: Fixed charge p/MPAN/day | AH25: Capacity charge p/kVA/day | AI25: Exceeded Capacity charge p/kVA/day | AJ25: Reactive power charge p/kVArh
AC26: Unmetered Supplies | AD26: Black unit charge p/kWh | AE26: Yellow unit charge p/kWh | AF26: Green unit charge p/kWh | AG26: n/a | AH26: n/a | AI26: n/a | AJ26: n/a
AC27: LV Generation Aggregated | AD27: Red unit charge p/kWh | AE27: Amber unit charge p/kWh | AF27: Green unit charge p/kWh | AG27: Fixed charge p/MPAN/day | AH27: n/a | AI27: n/a | AJ27: n/a
AC28: LV Sub Generation Aggregated | AD28: Red unit charge p/kWh | AE28: Amber unit charge p/kWh | AF28: Green unit charge p/kWh | AG28: Fixed charge p/MPAN/day | AH28: n/a | AI28: n/a | AJ28: n/a
AC29: LV Generation Site Specific | AD29: Red unit charge p/kWh | AE29: Amber unit charge p/kWh | AF29: Green unit charge p/kWh | AG29: Fixed charge p/MPAN/day | AH29: n/a | AI29: n/a | AJ29: Reactive power charge p/kVArh
AC30: LV Generation Site Specific no RP charge | AD30: Red unit charge p/kWh | AE30: Amber unit charge p/kWh | AF30: Green unit charge p/kWh | AG30: Fixed charge p/MPAN/day | AH30: n/a | AI30: n/a | AJ30: n/a
AC31: LV Sub Generation Site Specific | AD31: Red unit charge p/kWh | AE31: Amber unit charge p/kWh | AF31: Green unit charge p/kWh | AG31: Fixed charge p/MPAN/day | AH31: n/a | AI31: n/a | AJ31: Reactive power charge p/kVArh
AC32: LV Sub Generation Site Specific no RP charge | AD32: Red unit charge p/kWh | AE32: Amber unit charge p/kWh | AF32: Green unit charge p/kWh | AG32: Fixed charge p/MPAN/day | AH32: n/a | AI32: n/a | AJ32: n/a
AC33: HV Generation Site Specific | AD33: Red unit charge p/kWh | AE33: Amber unit charge p/kWh | AF33: Green unit charge p/kWh | AG33: Fixed charge p/MPAN/day | AH33: n/a | AI33: n/a | AJ33: Reactive power charge p/kVArh
AC34: HV Generation Site Specific no RP charge | AD34: Red unit charge p/kWh | AE34: Amber unit charge p/kWh | AF34: Green unit charge p/kWh | AG34: Fixed charge p/MPAN/day | AH34: n/a | AI34: n/a | AJ34: n/a
