Workbook
Name OLE_LINK1: 'Annex 3 Preserved charges'!#REF!

Sheet Overview
A2: Company and Licence name, charging year, effective from, status
B3: Company and Licence name | C3: Year | D3: Effective From | E3: Status
A4: Company and Licence name, charging year, effective from, status | B4: South Eastern Power Networks | C4: 2021/22 | D4: 1 April 2021 | E4: Final
A6: List of data tables in this workbook
A7: Worksheet | B7: Information
A8: Annex 1 LV, HV and Unmetered Supplies charges | B8: Annex 1 contains the charges to LV and HV Designated Properties and Unmetered Supplies.
A9: Annex 2 EHV charges | B9: ="Annex 2 contains the charges to Designated EHV Properties and charges applied to LDNOs with Designated EHV Properties/end-users embedded in networks within the " &B4 &" Licence area." -> Annex 2 contains the charges to Designated EHV Properties and charges applied to LDNOs with Designated EHV Properties/end-users embedded in networks within the South Eastern Power Networks Licence area.
A10: Annex 3 Preserved charges | B10: Annex 3 contains details of any preserved and additional charges that are valid at this time.
A11: Annex 4 LDNO charges | B11: ="Annex 4 contains charges that are levied on the owner of an embedded network within the "&B4&" Licence area. "&"Electricity suppliers and consumers who have properties connected to an embedded network should contact the embedded network owner to determine their distribution charges."&" The charges listed in this table are not payable by domestic consumers, business consumers or electricity suppliers." -> Annex 4 contains charges that are levied on the owner of an embedded network within the South Eastern Power Networks Licence area. Electricity suppliers and consumers who have properties connected to an embedded network should contact the embedded network owner to determine their distribution charges. The charges listed in this table are not payable by domestic consumers, business consumers or electricity suppliers.
A12: Annex 5 LLFs | B12: Annex 5 has been intentionally left blank as this charging statement is published a complete year before the LLFs have been audited. The line loss factors that are approved by the BSC Panel for the applicable year and consequently published on the Elexon website will take precedence and be used in Settlement. This annex will be re-published with these values once they are available.
A13: Annex 6 Charges for New or Amended Designated EHV Properties | B13: ="Annex 6 contains the charges for new or amended Designated EHV Properties and charges applied to LDNOs with new or amended Designated EHV Properties/end-users embedded in networks within the " &B4 &" Licence area." -> Annex 6 contains the charges for new or amended Designated EHV Properties and charges applied to LDNOs with new or amended Designated EHV Properties/end-users embedded in networks within the South Eastern Power Networks Licence area.
A14: Annex 7 Fixed adders for Supplier of Last Resort and Eligible Bad Debt pass-through costs | B14: Annex 7 contains the fixed adders to recover Supplier of Last Resort and Eligible Bad Debt pass-through costs. The Excess Supplier of Last Resort fixed adder relates to an increase to previously published charges only.
A15: Nodal prices | B15: Contains the underlying [nodal/network group] costs used to calculate the current EDCM charges.
A16: Charge calculator | B16: Charge calculator is a tool to help you estimate your distribution charges using current consumption data and forecast consumption data.
A18: Notes to users of this spreadsheet
A20: Please use this spreadsheet with reference to the LC14 use of system charging statement.
A22: Notes to DNOs populating this spreadsheet
A24: DNOs must endeavour to maintain consistency in the structure of this spreadsheet. Any changes to the structure must be noted in the 'Notes to users of this spreadsheet'
A25: The drop down list on the charge calculator can be expanded by unprotecting the charge calculator sheet and selecting 'data', 'data validation...' and then expanding the 'source' data range. The sheet can then be protected.

Sheet Annex 1 LV, HV and UMS charges
A1: Back to Overview | B1: 'DNOs paste value cells A15:J47 from CDCM 3701 into cells A14:J46
A2: =Overview!B4& " - Effective from "&Overview!D4&" - "&Overview!E4&" LV and HV charges" -> South Eastern Power Networks - Effective from 1 April 2021 - Final LV and HV charges
A4: Time Bands for LV and HV Designated Properties | G4: Time Bands for Unmetered Properties
A5: Time periods | B5: Red Time Band | C5: Amber Time Band | E5: Green Time Band | I5: Black Time Band | J5: Yellow Time Band | K5: Green Time Band
A6: Monday to Friday (Including Bank Holidays) All Year | B6: 16:00 - 19:00 | C6: 07:00 - 16:00 19:00 - 23:00 | E6: 00:00 - 07:00 23:00 - 24:00 | G6: Monday to Friday (Including Bank Holidays) November to February Inclusive | I6: 16:00 - 19:00 | J6: 07:00 - 16:00 19:00 - 23:00 | K6: 00:00 - 07:00 23:00 - 24:00
A7: Saturday and Sunday All Year | E7: 00:00 - 24:00 | G7: Monday to Friday (Including Bank Holidays) March to October Inclusive | J7: 07:00 - 23:00 | K7: 00:00 - 07:00 23:00 - 24:00
A8: Notes | B8: All times are in UK Clock time | G8: Saturday and Sunday All Year | K8: 00:00 - 24:00
G9: Notes | I9: All times are in UK Clock time
A11: Tariff name | B11: Open LLFCs | C11: PCs | D11: Red/black unit charge p/kWh | E11: Amber/yellow unit charge p/kWh | F11: Green unit charge p/kWh | G11: Fixed charge p/MPAN/day | H11: Capacity charge p/kVA/day | I11: Exceeded capacity charge p/kVA/day | J11: Reactive power charge p/kVArh | K11: Closed LLFCs
A12: Domestic Aggregated | B12: 1, 100, 300 | C12: 1, 2 or 0 | D12: 16.865 | E12: 1.208 | F12: 0.665 | G12: 3.99 | K12: 101, 250, 301
A13: Domestic Aggregated (related MPAN) | B13: 2, 251 | C13: 2 | D13: 16.865 | E13: 1.208 | F13: 0.665 | K13: 283, 296
A14: Non-Domestic Aggregated | B14: 120, 200, 201, 202, 203, 204, 320, 480 | C14: 3-8 or 0 | D14: 13.204 | E14: 1.062 | F14: 0.641 | G14: 4.14 | K14: 124, 270, 274, 324, 484
A15: Non-Domestic Aggregated (related MPAN) | B15: 287 | C15: 4 | D15: 13.204 | E15: 1.062 | F15: 0.641 | K15: 297
A16: LV Site Specific | B16: 71, 72, 73, 74, 550 | C16: 0 | D16: 9.09 | E16: 0.881 | F16: 0.61 | G16: 11.31 | H16: 3.68 | I16: 7.12 | J16: 0.276
A17: LV Sub Site Specific | B17: 81, 82, 83, 84, 756 | C17: 0 | D17: 5.848 | E17: 0.735 | F17: 0.585 | G17: 8.39 | H17: 5.7 | I17: 7.43 | J17: 0.161
A18: HV Site Specific | B18: 91, 92, 93, 94, 650 | C18: 0 | D18: 5.471 | E18: 0.713 | F18: 0.58 | G18: 111.11 | H18: 4.27 | I18: 6.63 | J18: 0.151
A19: LV Site Specific Storage Import | B19: 19, 70 | C19: 0 | D19: 8.531 | E19: 0.321 | F19: 0.05 | G19: 11.31 | H19: 3.68 | I19: 7.12 | J19: 0.276
A20: LV Sub Site Specific Storage Import | B20: 79, 80 | C20: 0 | D20: 5.289 | E20: 0.176 | F20: 0.025 | G20: 8.39 | H20: 5.7 | I20: 7.43 | J20: 0.161
A21: HV Site Specific Storage Import | B21: 89, 90 | C21: 0 | D21: 4.911 | E21: 0.153 | F21: 0.021 | G21: 111.11 | H21: 4.27 | I21: 6.63 | J21: 0.151
A22: Unmetered Supplies | B22: 350, 351, 352, 353, 354, 355, 356, 357, 358, 359, 360, 361, 362, 363, 364, 365, 366 | C22: 1, 8 or 0 | D22: 40.302 | E22: 1.789 | F22: 1.317
A23: LV Generation Aggregated | B23: 932 | C23: 8 or 0 | D23: -9.262 | E23: -0.368 | F23: -0.06 | G23: 0 | K23: 922, 933
A24: LV Sub Generation Aggregated | C24: 0 | D24: -8.273 | E24: -0.318 | F24: -0.051 | G24: 0
A25: LV Generation Site Specific | B25: 980, 982 | C25: 0 | D25: -9.262 | E25: -0.368 | F25: -0.06 | G25: 0 | J25: 0.267
A26: LV Generation Site Specific no RP charge | B26: 981, 983 | C26: 0 | D26: -9.262 | E26: -0.368 | F26: -0.06 | G26: 0
A27: LV Sub Generation Site Specific | B27: 984, 986 | C27: 0 | D27: -8.273 | E27: -0.318 | F27: -0.051 | G27: 0 | J27: 0.243
A28: LV Sub Generation Site Specific no RP charge | B28: 985, 987 | C28: 0 | D28: -8.273 | E28: -0.318 | F28: -0.051 | G28: 0
A29: HV Generation Site Specific | B29: 988, 990 | C29: 0 | D29: -5.769 | E29: -0.189 | F29: -0.027 | G29: 9.39 | J29: 0.196
A30: HV Generation Site Specific no RP charge | B30: 989, 991 | C30: 0 | D30: -5.769 | E30: -0.189 | F30: -0.027 | G30: 9.39

Sheet Annex 2 EHV charges
A1: Back to Overview | C1: Copy EDCM table 5001 range starting B101 and paste into G11. Extend or reduce print area as required. | F1: Note: The list of MPANs / MSIDs provided may be incomplete; the DNO reserves the right to apply the listed charges to any other MPANs / MSIDs associated with the site.
A2: =Overview!B4& " - Effective from "&Overview!D4&" - "&Overview!E4&" EDCM charges" -> South Eastern Power Networks - Effective from 1 April 2021 - Final EDCM charges
A4: Time Periods for Designated EHV Properties
A5: Time periods | D5: Super Red Time Band
A6: Monday to Friday (Including Bank Holidays) November to February Inclusive | D6: 16:00 - 19:00
A7: Notes | D7: All times are in UK Clock time
A9: Import Unique Identifier | B9: LLFC | C9: Import MPANs/MSIDs | D9: Export Unique Identifier | E9: LLFC | F9: Export MPANs/MSIDs | G9: Name | H9: Import Super Red unit charge (p/kWh) | I9: Import fixed charge (p/day) | J9: Import capacity charge (p/kVA/day) | K9: Import exceeded capacity charge (p/kVA/day) | L9: Export Super Red unit charge (p/kWh) | M9: Export fixed charge (p/day) | N9: Export capacity charge (p/kVA/day) | O9: Export exceeded capacity charge (p/kVA/day)
A10: B&RLTD | B10: 834 | C10: 1900035000482 1900035425153 | G10: B&RLTD | H10: 2.862 | I10: 218.82 | J10: 5.37 | K10: 5.37
A11: BEDDIN | B11: 889 | C11: 1900070745640 1900070745650 1900070745669 1900070745678 | G11: BEDDIN | H11: 0 | I11: 109.41 | J11: 1.26 | K11: 1.26
A12: BP_OIL | B12: 835 | C12: 1900017426438 1900017426447 | G12: BP_OIL | H12: 1.109 | I12: 218.82 | J12: 1.84 | K12: 1.84
A13: CHESDC | B13: ENET | C13: 1999000002228 1999000002237 | G13: CHESDC | H13: 0 | I13: 627.76 | J13: 1.55 | K13: 1.55
A14: DIGREA | B14: 833 | C14: 1900091200323 1900091200332 | G14: DIGREA | H14: 0 | I14: 1536.48 | J14: 3.48 | K14: 3.48
A15: EUROTU | B15: 874 | C15: 1900060219605 | G15: EUROTU | H15: 0 | I15: 90359.38 | J15: 0.65 | K15: 0.65
A16: GAT_AF | B16: 869 | C16: 1900017427938 1900017427947 1900060576620 | G16: GAT_AF | H16: 2.138 | I16: 2443.9 | J16: 7.42 | K16: 7.42
A17: GAT_BF | B17: 870 | C17: 1900060690231 1900060690240 | G17: GAT_BF | H17: 0.723 | I17: 627.76 | J17: 4.84 | K17: 4.84
A18: KNGSPN | C18: MSID: 1027 | G18: KNGSPN | H18: 0 | I18: 0 | J18: 2.7 | K18: 2.7
A19: NP_LAB | B19: 837 | C19: 1900047386380 | G19: NP_LAB | H19: 2.398 | I19: 437.64 | J19: 4.49 | K19: 4.49
A20: NR_3BR | B20: 866 | C20: 1900060219145 | G20: NR_3BR | H20: 0.863 | I20: 941.64 | J20: 4.66 | K20: 4.66
A21: NR_AFD | B21: 851 | C21: 1900060219377 | G21: NR_AFD | H21: 0.176 | I21: 627.76 | J21: 2.4 | K21: 2.4
A22: NR_ASH | B22: 879 | C22: 1900070068129 | G22: NR_ASH | H22: 0.224 | I22: 627.76 | J22: 4.41 | K22: 4.41
A23: NR_BRI | B23: 852 | C23: 1900060218675 | G23: NR_BRI | H23: 0 | I23: 941.64 | J23: 2.44 | K23: 2.44
A24: NR_BYF | B24: 853 | C24: 1900060218727 | G24: NR_BYF | H24: 0.263 | I24: 941.64 | J24: 2.17 | K24: 2.17
A25: NR_CAN | B25: 854 | C25: 1900060218790 | G25: NR_CAN | H25: 0.017 | I25: 627.76 | J25: 3.01 | K25: 3.01
A26: NR_CRO | B26: 855 | C26: 1900060218815 | G26: NR_CRO | H26: 0 | I26: 627.76 | J26: 2.88 | K26: 2.88
A27: NR_DOR | B27: 856 | C27: 1900060219303 | G27: NR_DOR | H27: 2.343 | I27: 627.76 | J27: 3.19 | K27: 3.19
A28: NR_EAS | B28: 857 | C28: 1900060218912 | G28: NR_EAS | H28: 3.464 | I28: 627.76 | J28: 3.86 | K28: 3.86
A29: NR_FOK | B29: 858 | C29: 1900060218959 | G29: NR_FOK | H29: 0.102 | I29: 627.76 | J29: 3.01 | K29: 3.01
A30: NR_HAS | B30: 859 | C30: 1900060218986 | G30: NR_HAS | H30: 0.267 | I30: 3900.36 | J30: 3.64 | K30: 3.64
... A34: NR_QUE | B34: 863 | C34: 1900060219084 | G34: NR_QUE | H34: 0 | I34: 329.74 | J34: 3.27 | K34: 3.27
A35: NR_SIT | B35: 864 | C35: 1900060219819 1900060219855 | G35: NR_SIT | H35: 0.002 | I35: 627.76 | J35: 1.64 | K35: 1.64
A36: NR_THA | B36: 865 | C36: 1900060219720 1900060219794 | G36: NR_THA | H36: 0.732 | I36: 627.76 | J36: 4.1 | K36: 4.1
A37: NR_TUN | B37: 867 | C37: 1900060219206 | G37: NR_TUN | H37: 1.17 | I37: 627.76 | J37: 2.9 | K37: 2.9
A38: PFIZER | B38: 881 | C38: 1900060219544 | G38: PFIZER | H38: 0.142 | I38: 2082.9 | J38: 1.06 | K38: 1.06
A39: SENTIV | B39: 888 | C39: 1900090497281 1900090497290 1900090497306 1900090497315 | G39: SENTIV | H39: 0.005 | I39: 68659.26 | J39: 1.42 | K39: 1.42
A40: THAMEM | B40: 838 | C40: 1900090872672 1900090872681 | D40: THAMEM | E40: 691 | F40: 1900090876979 1900090876988 | G40: THAMEM | H40: 0 | I40: 3839.52 | J40: 2.26 | K40: 2.26 | L40: 0 | M40: 2879.64 | N40: 0.05 | O40: 0.05
A41: THAMES | B41: 884 | C41: 1900016424857 | D41: THAMES | E41: 732 | F41: 1900060576611 | G41: THAMES | H41: 0 | I41: 2942.58 | J41: 4.59 | K41: 4.59 | L41: 0 | M41: 1726.31 | N41: 0.05 | O41: 0.05
A42: TWHK66 | B42: 839 | C42: 1900091206176 | D42: TWHK66 | E42: 692 | F42: 1900091206194 | G42: TWHK66 | H42: 3.008 | I42: 188.64 | J42: 1.88 | K42: 1.88 | L42: -2.957 | M42: 30.18 | N42: 0.05 | O42: 0.05
A43: ASHBYS | B43: 809 | C43: 1900091216963 | D43: ASHBYS | E43: 741 | F43: 1900091216972 | G43: ASHBYS | H43: 0.051 | I43: 9.63 | J43: 4.22 | K43: 4.22 | L43: 0 | M43: 982.39 | N43: 0.05 | O43: 0.05
A44: ASHGEN | B44: 801 | C44: 1900090978866 | D44: ASHGEN | E44: 734 | F44: 1900090978875 | G44: ASHGEN | H44: 0 | I44: 91.9 | J44: 1.25 | K44: 1.25 | L44: 0 | M44: 2756.96 | N44: 0.05 | O44: 0.05
A45: AYLESF | B45: 868 | C45: 1900060216613 | D45: AYLESF | E45: 725 | F45: 1900060436880 | G45: AYLESF | H45: 0 | I45: 313.88 | J45: 0.87 | K45: 0.87 | L45: 0 | M45: 0 | N45: 0 | O45: 0
A46: BEDERF | B46: 840 | C46: 1900091482588 | D46: BEDERF | E46: 693 | F46: 1900091482597 | G46: BEDERF | H46: 0 | I46: 338.93 | J46: 1.47 | K46: 1.47 | L46: -0.175 | M46: 2408.15 | N46: 0.05 | O46: 0.05
A47: BESAYL | B47: 841 | C47: 1900091632775 | D47: BESAYL | E47: 694 | F47: 1900091632784 | G47: BESAYL | H47: 0.168 | I47: 345.61 | J47: 0.9 | K47: 0.9 | L47: -0.209 | M47: 345.61 | N47: 0.05 | O47: 0.05
A48: BNTLEY | B48: 890 | C48: 1900091343778 | D48: BNTLEY | E48: 713 | F48: 1900091343787 | G48: BNTLEY | H48: 9.223 | I48: 8.67 | J48: 1.67 | K48: 1.67 | L48: 0 | M48: 866.59 | N48: 0.05 | O48: 0.05
A49: BNTLY2 | B49: 830 | C49: 1900091463646 | D49: BNTLY2 | E49: 712 | F49: 1900091463655 | G49: BNTLY2 | H49: 9.223 | I49: 6.6 | J49: 1.55 | K49: 1.55 | L49: 0 | M49: 554.77 | N49: 0.05 | O49: 0.05
A50: BOBBNG | B50: 891 | C50: 1900091395508 | D50: BOBBNG | E50: 705 | F50: 1900091395517 | G50: BOBBNG | H50: 0.002 | I50: 4.7 | J50: 3.27 | K50: 3.27 | L50: 0 | M50: 940.36 | N50: 0.05 | O50: 0.05
A51: BRAMBS | B51: 842 | C51: 1900091566810 | D51: BRAMBS | E51: 695 | F51: 1900091566820 | G51: BRAMBS | H51: 0.075 | I51: 345.61 | J51: 1.5 | K51: 1.5 | L51: -0.085 | M51: 345.61 | N51: 0.05 | O51: 0.05
A52: BRELLE | B52: 843 | C52: 1900091523116 | D52: BRELLE | E52: 696 | F52: 1900091523125 | G52: BRELLE | H52: 0 | I52: 33.79 | J52: 2.11 | K52: 2.11 | L52: 0 | M52: 720.89 | N52: 0.05 | O52: 0.05
A53: BRETSH | B53: 871 | C53: 1900061003393 1900090466576 | D53: BRETSH | E53: 726 | F53: 1900060866064 1900060866082 | G53: BRETSH | H53: 0.001 | I53: 22.5 | J53: 1.26 | K53: 1.26 | L53: 0 | M53: 0 | N53: 0 | O53: 0
A54: BRKHST | B54: 802 | C54: 1900090834409 | D54: BRKHST | E54: 738 | F54: 1900090834418 | G54: BRKHST | H54: 0.357 | I54: 1628.32 | J54: 2.12 | K54: 2.12 | L54: -0.532 | M54: 4837.77 | N54: 0.05 | O54: 0.05
A55: BTBRKS | B55: 810 | C55: 1900091199350 | D55: BTBRKS | E55: 742 | F55: 1900091199379 | G55: BTBRKS | H55: 1.127 | I55: 48.75 | J55: 1.33 | K55: 1.33 | L55: 0 | M55: 1083.27 | N55: 0.05 | O55: 0.05
A56: CAPELG | B56: 893 | C56: 1900091353298 | D56: CAPELG | E56: 706 | F56: 1900091353303 | G56: CAPELG | H56: 0.616 | I56: 0.86 | J56: 4.57 | K56: 4.57 | L56: 0 | M56: 703.05 | N56: 0.05 | O56: 0.05
A57: CLYHLL | B57: 894 | C57: 1900091343750 | D57: CLYHLL | E57: 716 | F57: 1900091343769 | G57: CLYHLL | H57: 0.577 | I57: 6.53 | J57: 1.99 | K57: 1.99 | L57: 0 | M57: 652.96 | N57: 0.05 | O57: 0.05
A58: CRYENG | B58: 872 | C58: 1900060831692 | D58: CRYENG | E58: 730 | F58: 1900060831708 | G58: CRYENG | H58: 0 | I58: 112.13 | J58: 1.15 | K58: 1.15 | L58: -0.004 | M58: 299.01 | N58: 0.05 | O58: 0.05
A59: DSCPRK | B59: 804 | C59: 1900091057568 1900091637072 | D59: DSCPRK | E59: 704 | F59: 1900091057559 1900091637081 | G59: DSCPRK | H59: 0.142 | I59: 1387.09 | J59: 1.01 | K59: 1.01 | L59: -0.143 | M59: 2854.23 | N59: 0.05 | O59: 0.05
A60: FORDSF | B60: 895 | C60: 1900091361962 | D60: FORDSF | E60: 707 | F60: 1900091361971 | G60: FORDSF | H60: 0 | I60: 11.34 | J60: 1.63 | K60: 1.63 | L60: 0 | M60: 648.14 | N60: 0.05 | O60: 0.05
A61: FRWOOD | B61: 811 | C61: 1900091200388 | D61: FRWOOD | E61: 743 | F61: 1900091200397 | G61: FRWOOD | H61: 0 | I61: 17.91 | J61: 1.54 | K61: 1.54 | L61: 0 | M61: 895.42 | N61: 0.05 | O61: 0.05
A62: GROVEH | B62: 875 | C62: 1900060225185 | D62: GROVEH | E62: 727 | F62: 1900060225194 | G62: GROVEH | H62: 0 | I62: 411.64 | J62: 1 | K62: 1 | L62: 0 | M62: 0 | N62: 0 | O62: 0
A63: GUSTON | B63: 831 | C63: 1900091338040 | D63: GUSTON | E63: 708 | F63: 1900091338059 | G63: GUSTON | H63: 0.01 | I63: 15.15 | J63: 1.7 | K63: 1.7 | L63: 0 | M63: 1515.01 | N63: 0.05 | O63: 0.05
A64: HADLOW | B64: 812 | C64: 1900091217043 | D64: HADLOW | E64: 744 | F64: 1900091217052 | G64: HADLOW | H64: 0.526 | I64: 1.82 | J64: 3.85 | K64: 3.85 | L64: 0 | M64: 689.39 | N64: 0.05 | O64: 0.05
A65: HANSTA | B65: 876 | C65: 1900004383769 1900031426056 | D65: HANSTA | E65: 728 | F65: 1900060442174 1900060512032 | G65: HANSTA | H65: 0 | I65: 1.8 | J65: 1.11 | K65: 1.11 | L65: 0 | M65: 0 | N65: 0 | O65: 0
A66: HLLMBY | B66: 813 | C66: 1900091217070 | D66: HLLMBY | E66: 745 | F66: 1900091217080 | G66: HLLMBY | H66: 0 | I66: 9.41 | J66: 1.5 | K66: 1.5 | L66: 0 | M66: 758.83 | N66: 0.05 | O66: 0.05
A67: HORAMS | B67: 824 | C67: 1900091200068 | D67: HORAMS | E67: 701 | F67: 1900091200077 | G67: HORAMS | H67: 0.14 | I67: 13.17 | J67: 7.66 | K67: 7.66 | L67: 0 | M67: 1712.45 | N67: 0.05 | O67: 0.05
A68: KENTI2 | B68: 814 | C68: 1900091199519 | D68: KENTI2 | E68: 746 | F68: 1900091199528 | G68: KENTI2 | H68: 0.16 | I68: 8.28 | J68: 0.9 | K68: 0.9 | L68: 0 | M68: 305.6 | N68: 0.05 | O68: 0.05
A69: KENTIS | B69: 877 | C69: 1900070122273 | D69: KENTIS | E69: 722 | F69: 1900070122343 | G69: KENTIS | H69: 0.16 | I69: 6.82 | J69: 0.93 | K69: 0.93 | L69: 0 | M69: 0 | N69: 0 | O69: 0
A70: KM3CHP | B70: 846 | C70: 1900091669720 | D70: KM3CHP | E70: 699 | F70: 1900091669739 | G70: KM3CHP | H70: 0 | I70: 260.46 | J70: 1.07 | K70: 1.07 | L70: 0 | M70: 2467.91 | N70: 0.05 | O70: 0.05
A71: KNWLTN | B71: 803 | C71: 1900091091930 | D71: KNWLTN | E71: 735 | F71: 1900091091940 | G71: KNWLTN | H71: 0.009 | I71: 13.55 | J71: 2.01 | K71: 2.01 | L71: 0 | M71: 1280.54 | N71: 0.05 | O71: 0.05
A72: LBOURN | B72: 815 | C72: 1900091171267 | D72: LBOURN | E72: 747 | F72: 1900091171276 | G72: LBOURN | H72: 0.001 | I72: 7.86 | J72: 2.05 | K72: 2.05 | L72: 0 | M72: 737.29 | N72: 0.05 | O72: 0.05
A73: LCHEYI | B73: 878 | C73: 1900090194653 | D73: LCHEYI | E73: 721 | F73: 1900090194644 | G73: LCHEYI | H73: 0.006 | I73: 5.87 | J73: 1.16 | K73: 1.16 | L73: 0 | M73: 762.37 | N73: 0.05 | O73: 0.05
A74: LENHAM | B74: 808 | C74: 1900091081560 | D74: LENHAM | E74: 736 | F74: 1900091081570 | G74: LENHAM | H74: 0.095 | I74: 12.81 | J74: 2.9 | K74: 2.9 | L74: 0 | M74: 1281.28 | N74: 0.05 | O74: 0.05
A75: LGHTON | B75: 816 | C75: 1900091200138 | D75: LGHTON | E75: 748 | F75: 1900091200147 | G75: LGHTON | H75: 1.128 | I75: 10.99 | J75: 2.08 | K75: 2.08 | L75: 0 | M75: 769.07 | N75: 0.05 | O75: 0.05
A76: MARSHB | B76: 896 | C76: 1900091310596 | D76: MARSHB | E76: 709 | F76: 1900091310601 | G76: MARSHB | H76: 0.059 | I76: 20.03 | J76: 1.82 | K76: 1.82 | L76: 0 | M76: 817.15 | N76: 0.05 | O76: 0.05
A77: MLEHLL | B77: 819 | C77: 1900091183402 | D77: MLEHLL | E77: 751 | F77: 1900091183411 | G77: MLEHLL | H77: 0.211 | I77: 2.49 | J77: 1.79 | K77: 1.79 | L77: 0 | M77: 311.39 | N77: 0.05 | O77: 0.05
... A83: OLDRSF | B83: 805 | C83: 1900091024517 | D83: OLDRSF | E83: 739 | F83: 1900091024526 | G83: OLDRSF | H83: 0.002 | I83: 4.13 | J83: 2.59 | K83: 2.59 | L83: 0 | M83: 826.7 | N83: 0.05 | O83: 0.05
A84: ORCHRD | B84: 898 | C84: 1900091085120 1900091473662 | D84: ORCHRD | E84: 753 | F84: 1900091085110 1900091349724 1900091349733 1900091473671 | G84: ORCHRD | H84: 0.002 | I84: 5.19 | J84: 2.56 | K84: 2.56 | L84: 0 | M84: 933.53 | N84: 0.05 | O84: 0.05
A85: ORCHR2 | B85: 898 | C85: 1900091349715 1900091349706 | G85: ORCHRD | H85: 0.002 | L85: 0
A86: PADWSF | B86: 822 | C86: 1900091216634 | D86: PADWSF | E86: 754 | F86: 1900091216643 | G86: PADWSF | H86: 0.59 | I86: 4.34 | J86: 1.99 | K86: 1.99 | L86: 0 | M86: 686.88 | N86: 0.05 | O86: 0.05
A87: POSHWF | B87: 827 | C87: 1900091227307 | D87: POSHWF | E87: 719 | F87: 1900091227316 | G87: POSHWF | H87: 0 | I87: 6.15 | J87: 1.26 | K87: 1.26 | L87: 0 | M87: 307.72 | N87: 0.05 | O87: 0.05
A88: PRIORS | B88: 899 | C88: 1900091319942 | D88: PRIORS | E88: 717 | F88: 1900091320006 | G88: PRIORS | H88: 0 | I88: 4.31 | J88: 2.14 | K88: 2.14 | L88: 0 | M88: 648.83 | N88: 0.05 | O88: 0.05
A89: PSHLEY | B89: 826 | C89: 1900091178954 | D89: PSHLEY | E89: 703 | F89: 1900091178963 | G89: PSHLEY | H89: 0 | I89: 11.71 | J89: 2.31 | K89: 2.31 | L89: 0 | M89: 1171.32 | N89: 0.05 | O89: 0.05
A90: SELLSF | B90: 900 | C90: 1900091360950 | D90: SELLSF | E90: 720 | F90: 1900091360969 | G90: SELLSF | H90: 0.026 | I90: 3.71 | J90: 2.95 | K90: 2.95 | L90: 0 | M90: 719.24 | N90: 0.05 | O90: 0.05
A91: SEVIND | C91: MSID: 7160 | D91: SEVIND | F91: MSID: 7160 | G91: SEVIND | H91: 0.607 | I91: 1.35 | J91: 1.15 | K91: 1.15 | L91: -0.65 | M91: 108.06 | N91: 0.05 | O91: 0.05
A92: SHEPHM | B92: 832 | C92: 1900091420128 | D92: SHEPHM | E92: 718 | F92: 1900091420137 | G92: SHEPHM | H92: 2.178 | I92: 45.89 | J92: 1.3 | K92: 1.3 | L92: 0 | M92: 1720.73 | N92: 0.05 | O92: 0.05
A93: SHORHM | C93: MSID: 7104 | D93: SHORHM | F93: MSID: 7105 | G93: SHORHM | H93: 0 | I93: 273.63 | J93: 1.42 | K93: 1.42 | L93: 0 | M93: 0 | N93: 0 | O93: 0
A94: SOLEES | B94: 823 | C94: 1900091121257 1900091121275 | D94: SOLEES | E94: 755 | F94: 1900091121266 1900091121284 | G94: SOLEES | H94: 0.016 | I94: 38.05 | J94: 1.55 | K94: 1.55 | L94: 0 | M94: 1598.22 | N94: 0.05 | O94: 0.05
A95: STAREN | B95: 883 | C95: 1900060830217 | D95: STAREN | E95: 729 | F95: 1900060830226 | G95: STAREN | H95: 0 | I95: 1299.22 | J95: 1.6 | K95: 1.6 | L95: 0 | M95: 0 | N95: 0 | O95: 0
A96: SYCAMR | B96: 807 | C96: 1900091090096 | D96: SYCAMR | E96: 737 | F96: 1900091090101 | G96: SYCAMR | H96: 0.057 | I96: 57.7 | J96: 2.01 | K96: 2.01 | L96: 0 | M96: 2077.24 | N96: 0.05 | O96: 0.05
A97: THAEAR | B97: 850 | C97: 1900090417081 1900090417106 1900090417133 1900090417142 1900090417151 | D97: THAEAR | E97: 733 | F97: 1900090417160 1900090417189 1900090417212 1900090417221 1900090417230 | G97: THAEAR | H97: 0.009 | I97: 3211.71 | J97: 1.36 | K97: 1.36 | L97: 0 | M97: 3211.71 | N97: 0.05 | O97: 0.05
A98: THANET | C98: MSID: 7230 | D98: THANET | F98: MSID: 7230 | G98: THANET | H98: 0.015 | I98: 14.45 | J98: 1.3 | K98: 1.3 | L98: 0 | M98: 1522.03 | N98: 0.05 | O98: 0.05
A99: THORNE | B99: 818 | C99: 1900091171364 | D99: THORNE | E99: 750 | F99: 1900091171373 | G99: THORNE | H99: 0.013 | I99: 19.55 | J99: 2.37 | K99: 2.37 | L99: 0 | M99: 2032.89 | N99: 0.05 | O99: 0.05
A100: TONGSF | B100: 828 | C100: 1900091363000 | D100: TONGSF | E100: 711 | F100: 1900091363019 | G100: TONGSF | H100: 0 | I100: 29.72 | J100: 1.96 | K100: 1.96 | L100: 0 | M100: 2311.46 | N100: 0.05 | O100: 0.05
A101: WDLNDS | B101: 825 | C101: 1900091207124 | D101: WDLNDS | E101: 702 | F101: 1900091207133 | G101: WDLNDS | H101: 0.009 | I101: 21.97 | J101: 2.38 | K101: 2.38 | L101: 0 | M101: 2636.51 | N101: 0.05 | O101: 0.05
A102: WIDHFM | B102: 821 | C102: 1900091478493 | D102: WIDHFM | E102: 714 | F102: 1900091478509 | G102: WIDHFM | H102: 0.204 | I102: 17.15 | J102: 3.77 | K102: 3.77 | L102: 0 | M102: 1372.13 | N102: 0.05 | O102: 0.05
A103: WLBEES | B103: 829 | C103: 1900091315238 | D103: WLBEES | E103: 715 | F103: 1900091315229 | G103: WLBEES | H103: 0.563 | I103: 3.11 | J103: 1.96 | K103: 1.96 | L103: 0 | M103: 310.77 | N103: 0.05 | O103: 0.05
A104: WRGALL | B104: 887 | C104: 1900070394457 | D104: WRGALL | E104: 731 | F104: 1900070394466 | G104: WRGALL | H104: 0 | I104: 724.14 | J104: 0.88 | K104: 0.88 | L104: 0 | M104: 0 | N104: 0 | O104: 0
A105: WSTWDX | B105: 806 | C105: 1900091086531 | D105: WSTWDX | E105: 740 | F105: 1900091086540 | G105: WSTWDX | H105: 0.013 | I105: 12.81 | J105: 1.96 | K105: 1.96 | L105: 0 | M105: 1281.28 | N105: 0.05 | O105: 0.05

Sheet Annex 2a Import
A1: Note: The list of MPANs / MSIDs provided may be incomplete; the DNO reserves the right to apply the listed charges to any other MPANs / MSIDs associated with the site. Note: This table is automatically populated based on the content of the tab entitled 'Annex 2 EHV Charges'. The timebands are as shown in Annex 2.
A2: =Overview!B4& " - Effective from "&Overview!D4&" - "&Overview!E4&" EDCM import charges" -> South Eastern Power Networks - Effective from 1 April 2021 - Final EDCM import charges
A4: Import Unique Identifier | B4: LLFC | C4: Import MPANs/MSIDs | D4: Name | E4: ='Annex 2 EHV charges'!H9 -> Import Super Red unit charge (p/kWh) | F4: ='Annex 2 EHV charges'!I9 -> Import fixed charge (p/day) | G4: ='Annex 2 EHV charges'!J9 -> Import capacity charge (p/kVA/day) | H4: ='Annex 2 EHV charges'!K9 -> Import exceeded capacity charge (p/kVA/day)
A5: {=IFERROR(INDEX('Annex 2 EHV charges'!$A$10:$A$259, MATCH(0, IF(ISBLANK('Annex 2 EHV charges'!$A$10:$A$259),1, COUNTIF(A$4:$A4, 'Annex 2 EHV charges'!$A$10:$A$259)), 0)),"")} -> B&RLTD | B5: =IF($A5="","",VLOOKUP($A5,'Annex 2 EHV charges'!$A:$O,2,0)) -> 834 | C5: =IF($A5="","",VLOOKUP($A5,'Annex 2 EHV charges'!$A:$O,3,0)) -> 1900035000482 1900035425153 | D5: =IF($A5="","",VLOOKUP($A5,'Annex 2 EHV charges'!$A:$O,7,0)) -> B&RLTD | E5: =IFERROR(IF(VLOOKUP($A5,'Annex 2 EHV charges'!$A:$O,8,FALSE)=0,"",VLOOKUP($A5,'Annex 2 EHV charges'!$A:$O,8,FALSE)),"") -> 2.862 | F5: =IFERROR(IF(VLOOKUP($A5,'Annex 2 EHV charges'!$A:$O,9,FALSE)=0,"",VLOOKUP($A5,'Annex 2 EHV charges'!$A:$O,9,FALSE)),"") -> 218.82 | G5: =IFERROR(IF(VLOOKUP($A5,'Annex 2 EHV charges'!$A:$O,10,FALSE)=0,"",VLOOKUP($A5,'Annex 2 EHV charges'!$A:$O,10,FALSE)),"") -> 5.37 | H5: =IFERROR(IF(VLOOKUP($A5,'Annex 2 EHV charges'!$A:$O,11,FALSE)=0,"",VLOOKUP($A5,'Annex 2 EHV charges'!$A:$O,11,FALSE)),"") -> 5.37
A6: {=IFERROR(INDEX('Annex 2 EHV charges'!$A$10:$A$259, MATCH(0, IF(ISBLANK('Annex 2 EHV charges'!$A$10:$A$259),1, COUNTIF(A$4:$A5, 'Annex 2 EHV charges'!$A$10:$A$259)), 0)),"")} -> BEDDIN | B6: =IF($A6="","",VLOOKUP($A6,'Annex 2 EHV charges'!$A:$O,2,0)) -> 889 | C6: =IF($A6="","",VLOOKUP($A6,'Annex 2 EHV charges'!$A:$O,3,0)) -> 1900070745640 1900070745650 1900070745669 1900070745678 | D6: =IF($A6="","",VLOOKUP($A6,'Annex 2 EHV charges'!$A:$O,7,0)) -> BEDDIN | E6: =IFERROR(IF(VLOOKUP($A6,'Annex 2 EHV charges'!$A:$O,8,FALSE)=0,"",VLOOKUP($A6,'Annex 2 EHV charges'!$A:$O,8,FALSE)),"") | F6: =IFERROR(IF(VLOOKUP($A6,'Annex 2 EHV charges'!$A:$O,9,FALSE)=0,"",VLOOKUP($A6,'Annex 2 EHV charges'!$A:$O,9,FALSE)),"") -> 109.41 | G6: =IFERROR(IF(VLOOKUP($A6,'Annex 2 EHV charges'!$A:$O,10,FALSE)=0,"",VLOOKUP($A6,'Annex 2 EHV charges'!$A:$O,10,FALSE)),"") -> 1.26 | H6: =IFERROR(IF(VLOOKUP($A6,'Annex 2 EHV charges'!$A:$O,11,FALSE)=0,"",VLOOKUP($A6,'Annex 2 EHV charges'!$A:$O,11,FALSE)),"") -> 1.26
A7: {=IFERROR(INDEX('Annex 2 EHV charges'!$A$10:$A$259, MATCH(0, IF(ISBLANK('Annex 2 EHV charges'!$A$10:$A$259),1, COUNTIF(A$4:$A6, 'Annex 2 EHV charges'!$A$10:$A$259)), 0)),"")} -> BP_OIL | B7: =IF($A7="","",VLOOKUP($A7,'Annex 2 EHV charges'!$A:$O,2,0)) -> 835 | C7: =IF($A7="","",VLOOKUP($A7,'Annex 2 EHV charges'!$A:$O,3,0)) -> 1900017426438 1900017426447 | D7: =IF($A7="","",VLOOKUP($A7,'Annex 2 EHV charges'!$A:$O,7,0)) -> BP_OIL | E7: =IFERROR(IF(VLOOKUP($A7,'Annex 2 EHV charges'!$A:$O,8,FALSE)=0,"",VLOOKUP($A7,'Annex 2 EHV charges'!$A:$O,8,FALSE)),"") -> 1.109 | F7: =IFERROR(IF(VLOOKUP($A7,'Annex 2 EHV charges'!$A:$O,9,FALSE)=0,"",VLOOKUP($A7,'Annex 2 EHV charges'!$A:$O,9,FALSE)),"") -> 218.82 | G7: =IFERROR(IF(VLOOKUP($A7,'Annex 2 EHV charges'!$A:$O,10,FALSE)=0,"",VLOOKUP($A7,'Annex 2 EHV charges'!$A:$O,10,FALSE)),"") -> 1.84 | H7: =IFERROR(IF(VLOOKUP($A7,'Annex 2 EHV charges'!$A:$O,11,FALSE)=0,"",VLOOKUP($A7,'Annex 2 EHV charges'!$A:$O,11,FALSE)),"") -> 1.84
A8: {=IFERROR(INDEX('Annex 2 EHV charges'!$A$10:$A$259, MATCH(0, IF(ISBLANK('Annex 2 EHV charges'!$A$10:$A$259),1, COUNTIF(A$4:$A7, 'Annex 2 EHV charges'!$A$10:$A$259)), 0)),"")} -> CHESDC | B8: =IF($A8="","",VLOOKUP($A8,'Annex 2 EHV charges'!$A:$O,2,0)) -> ENET | C8: =IF($A8="","",VLOOKUP($A8,'Annex 2 EHV charges'!$A:$O,3,0)) -> 1999000002228 1999000002237 | D8: =IF($A8="","",VLOOKUP($A8,'Annex 2 EHV charges'!$A:$O,7,0)) -> CHESDC | E8: =IFERROR(IF(VLOOKUP($A8,'Annex 2 EHV charges'!$A:$O,8,FALSE)=0,"",VLOOKUP($A8,'Annex 2 EHV charges'!$A:$O,8,FALSE)),"") | F8: =IFERROR(IF(VLOOKUP($A8,'Annex 2 EHV charges'!$A:$O,9,FALSE)=0,"",VLOOKUP($A8,'Annex 2 EHV charges'!$A:$O,9,FALSE)),"") -> 627.76 | G8: =IFERROR(IF(VLOOKUP($A8,'Annex 2 EHV charges'!$A:$O,10,FALSE)=0,"",VLOOKUP($A8,'Annex 2 EHV charges'!$A:$O,10,FALSE)),"") -> 1.55 | H8: =IFERROR(IF(VLOOKUP($A8,'Annex 2 EHV charges'!$A:$O,11,FALSE)=0,"",VLOOKUP($A8,'Annex 2 EHV charges'!$A:$O,11,FALSE)),"") -> 1.55
A9: {=IFERROR(INDEX('Annex 2 EHV charges'!$A$10:$A$259, MATCH(0, IF(ISBLANK('Annex 2 EHV charges'!$A$10:$A$259),1, COUNTIF(A$4:$A8, 'Annex 2 EHV charges'!$A$10:$A$259)), 0)),"")} -> DIGREA | B9: =IF($A9="","",VLOOKUP($A9,'Annex 2 EHV charges'!$A:$O,2,0)) -> 833 | C9: =IF($A9="","",VLOOKUP($A9,'Annex 2 EHV charges'!$A:$O,3,0)) -> 1900091200323 1900091200332 | D9: =IF($A9="","",VLOOKUP($A9,'Annex 2 EHV charges'!$A:$O,7,0)) -> DIGREA | E9: =IFERROR(IF(VLOOKUP($A9,'Annex 2 EHV charges'!$A:$O,8,FALSE)=0,"",VLOOKUP($A9,'Annex 2 EHV charges'!$A:$O,8,FALSE)),"") | F9: =IFERROR(IF(VLOOKUP($A9,'Annex 2 EHV charges'!$A:$O,9,FALSE)=0,"",VLOOKUP($A9,'Annex 2 EHV charges'!$A:$O,9,FALSE)),"") -> 1536.48 | G9: =IFERROR(IF(VLOOKUP($A9,'Annex 2 EHV charges'!$A:$O,10,FALSE)=0,"",VLOOKUP($A9,'Annex 2 EHV charges'!$A:$O,10,FALSE)),"") -> 3.48 | H9: =IFERROR(IF(VLOOKUP($A9,'Annex 2 EHV charges'!$A:$O,11,FALSE)=0,"",VLOOKUP($A9,'Annex 2 EHV charges'!$A:$O,11,FALSE)),"") -> 3.48
A10: {=IFERROR(INDEX('Annex 2 EHV charges'!$A$10:$A$259, MATCH(0, IF(ISBLANK('Annex 2 EHV charges'!$A$10:$A$259),1, COUNTIF(A$4:$A9, 'Annex 2 EHV charges'!$A$10:$A$259)), 0)),"")} -> EUROTU | B10: =IF($A10="","",VLOOKUP($A10,'Annex 2 EHV charges'!$A:$O,2,0)) -> 874 | C10: =IF($A10="","",VLOOKUP($A10,'Annex 2 EHV charges'!$A:$O,3,0)) -> 1900060219605 | D10: =IF($A10="","",VLOOKUP($A10,'Annex 2 EHV charges'!$A:$O,7,0)) -> EUROTU | E10: =IFERROR(IF(VLOOKUP($A10,'Annex 2 EHV charges'!$A:$O,8,FALSE)=0,"",VLOOKUP($A10,'Annex 2 EHV charges'!$A:$O,8,FALSE)),"") | F10: =IFERROR(IF(VLOOKUP($A10,'Annex 2 EHV charges'!$A:$O,9,FALSE)=0,"",VLOOKUP($A10,'Annex 2 EHV charges'!$A:$O,9,FALSE)),"") -> 90359.38 | G10: =IFERROR(IF(VLOOKUP($A10,'Annex 2 EHV charges'!$A:$O,10,FALSE)=0,"",VLOOKUP($A10,'Annex 2 EHV charges'!$A:$O,10,FALSE)),"") -> 0.65 | H10: =IFERROR(IF(VLOOKUP($A10,'Annex 2 EHV charges'!$A:$O,11,FALSE)=0,"",VLOOKUP($A10,'Annex 2 EHV charges'!$A:$O,11,FALSE)),"") -> 0.65
A11: {=IFERROR(INDEX('Annex 2 EHV charges'!$A$10:$A$259, MATCH(0, IF(ISBLANK('Annex 2 EHV charges'!$A$10:$A$259),1, COUNTIF(A$4:$A10, 'Annex 2 EHV charges'!$A$10:$A$259)), 0)),"")} -> GAT_AF | B11: =IF($A11="","",VLOOKUP($A11,'Annex 2 EHV charges'!$A:$O,2,0)) -> 869 | C11: =IF($A11="","",VLOOKUP($A11,'Annex 2 EHV charges'!$A:$O,3,0)) -> 1900017427938 1900017427947 1900060576620 | D11: =IF($A11="","",VLOOKUP($A11,'Annex 2 EHV charges'!$A:$O,7,0)) -> GAT_AF | E11: =IFERROR(IF(VLOOKUP($A11,'Annex 2 EHV charges'!$A:$O,8,FALSE)=0,"",VLOOKUP($A11,'Annex 2 EHV charges'!$A:$O,8,FALSE)),"") -> 2.138 | F11: =IFERROR(IF(VLOOKUP($A11,'Annex 2 EHV charges'!$A:$O,9,FALSE)=0,"",VLOOKUP($A11,'Annex 2 EHV charges'!$A:$O,9,FALSE)),"") -> 2443.9 | G11: =IFERROR(IF(VLOOKUP($A11,'Annex 2 EHV charges'!$A:$O,10,FALSE)=0,"",VLOOKUP($A11,'Annex 2 EHV charges'!$A:$O,10,FALSE)),"") -> 7.42 | H11: =IFERROR(IF(VLOOKUP($A11,'Annex 2 EHV charges'!$A:$O,11,FALSE)=0,"",VLOOKUP($A11,'Annex 2 EHV charges'!$A:$O,11,FALSE)),"") -> 7.42
A12: {=IFERROR(INDEX('Annex 2 EHV charges'!$A$10:$A$259, MATCH(0, IF(ISBLANK('Annex 2 EHV charges'!$A$10:$A$259),1, COUNTIF(A$4:$A11, 'Annex 2 EHV charges'!$A$10:$A$259)), 0)),"")} -> GAT_BF | B12: =IF($A12="","",VLOOKUP($A12,'Annex 2 EHV charges'!$A:$O,2,0)) -> 870 | C12: =IF($A12="","",VLOOKUP($A12,'Annex 2 EHV charges'!$A:$O,3,0)) -> 1900060690231 1900060690240 | D12: =IF($A12="","",VLOOKUP($A12,'Annex 2 EHV charges'!$A:$O,7,0)) -> GAT_BF | E12: =IFERROR(IF(VLOOKUP($A12,'Annex 2 EHV charges'!$A:$O,8,FALSE)=0,"",VLOOKUP($A12,'Annex 2 EHV charges'!$A:$O,8,FALSE)),"") -> 0.723 | F12: =IFERROR(IF(VLOOKUP($A12,'Annex 2 EHV charges'!$A:$O,9,FALSE)=0,"",VLOOKUP($A12,'Annex 2 EHV charges'!$A:$O,9,FALSE)),"") -> 627.76 | G12: =IFERROR(IF(VLOOKUP($A12,'Annex 2 EHV charges'!$A:$O,10,FALSE)=0,"",VLOOKUP($A12,'Annex 2 EHV charges'!$A:$O,10,FALSE)),"") -> 4.84 | H12: =IFERROR(IF(VLOOKUP($A12,'Annex 2 EHV charges'!$A:$O,11,FALSE)=0,"",VLOOKUP($A12,'Annex 2 EHV charges'!$A:$O,11,FALSE)),"") -> 4.84
A13: {=IFERROR(INDEX('Annex 2 EHV charges'!$A$10:$A$259, MATCH(0, IF(ISBLANK('Annex 2 EHV charges'!$A$10:$A$259),1, COUNTIF(A$4:$A12, 'Annex 2 EHV charges'!$A$10:$A$259)), 0)),"")} -> KNGSPN | B13: =IF($A13="","",VLOOKUP($A13,'Annex 2 EHV charges'!$A:$O,2,0)) -> 0 | C13: =IF($A13="","",VLOOKUP($A13,'Annex 2 EHV charges'!$A:$O,3,0)) -> MSID: 1027 | D13: =IF($A13="","",VLOOKUP($A13,'Annex 2 EHV charges'!$A:$O,7,0)) -> KNGSPN | E13: =IFERROR(IF(VLOOKUP($A13,'Annex 2 EHV charges'!$A:$O,8,FALSE)=0,"",VLOOKUP($A13,'Annex 2 EHV charges'!$A:$O,8,FALSE)),"") | F13: =IFERROR(IF(VLOOKUP($A13,'Annex 2 EHV charges'!$A:$O,9,FALSE)=0,"",VLOOKUP($A13,'Annex 2 EHV charges'!$A:$O,9,FALSE)),"") | G13: =IFERROR(IF(VLOOKUP($A13,'Annex 2 EHV charges'!$A:$O,10,FALSE)=0,"",VLOOKUP($A13,'Annex 2 EHV charges'!$A:$O,10,FALSE)),"") -> 2.7 | H13: =IFERROR(IF(VLOOKUP($A13,'Annex 2 EHV charges'!$A:$O,11,FALSE)=0,"",VLOOKUP($A13,'Annex 2 EHV charges'!$A:$O,11,FALSE)),"") -> 2.7
A14: {=IFERROR(INDEX('Annex 2 EHV charges'!$A$10:$A$259, MATCH(0, IF(ISBLANK('Annex 2 EHV charges'!$A$10:$A$259),1, COUNTIF(A$4:$A13, 'Annex 2 EHV charges'!$A$10:$A$259)), 0)),"")} -> NP_LAB | B14: =IF($A14="","",VLOOKUP($A14,'Annex 2 EHV charges'!$A:$O,2,0)) -> 837 | C14: =IF($A14="","",VLOOKUP($A14,'Annex 2 EHV charges'!$A:$O,3,0)) -> 1900047386380 | D14: =IF($A14="","",VLOOKUP($A14,'Annex 2 EHV charges'!$A:$O,7,0)) -> NP_LAB | E14: =IFERROR(IF(VLOOKUP($A14,'Annex 2 EHV charges'!$A:$O,8,FALSE)=0,"",VLOOKUP($A14,'Annex 2 EHV charges'!$A:$O,8,FALSE)),"") -> 2.398 | F14: =IFERROR(IF(VLOOKUP($A14,'Annex 2 EHV charges'!$A:$O,9,FALSE)=0,"",VLOOKUP($A14,'Annex 2 EHV charges'!$A:$O,9,FALSE)),"") -> 437.64 | G14: =IFERROR(IF(VLOOKUP($A14,'Annex 2 EHV charges'!$A:$O,10,FALSE)=0,"",VLOOKUP($A14,'Annex 2 EHV charges'!$A:$O,10,FALSE)),"") -> 4.49 | H14: =IFERROR(IF(VLOOKUP($A14,'Annex 2 EHV charges'!$A:$O,11,FALSE)=0,"",VLOOKUP($A14,'Annex 2 EHV charges'!$A:$O,11,FALSE)),"") -> 4.49
A15: {=IFERROR(INDEX('Annex 2 EHV charges'!$A$10:$A$259, MATCH(0, IF(ISBLANK('Annex 2 EHV charges'!$A$10:$A$259),1, COUNTIF(A$4:$A14, 'Annex 2 EHV charges'!$A$10:$A$259)), 0)),"")} -> NR_3BR | B15: =IF($A15="","",VLOOKUP($A15,'Annex 2 EHV charges'!$A:$O,2,0)) -> 866 | C15: =IF($A15="","",VLOOKUP($A15,'Annex 2 EHV charges'!$A:$O,3,0)) -> 1900060219145 | D15: =IF($A15="","",VLOOKUP($A15,'Annex 2 EHV charges'!$A:$O,7,0)) -> NR_3BR | E15: =IFERROR(IF(VLOOKUP($A15,'Annex 2 EHV charges'!$A:$O,8,FALSE)=0,"",VLOOKUP($A15,'Annex 2 EHV charges'!$A:$O,8,FALSE)),"") -> 0.863 | F15: =IFERROR(IF(VLOOKUP($A15,'Annex 2 EHV charges'!$A:$O,9,FALSE)=0,"",VLOOKUP($A15,'Annex 2 EHV charges'!$A:$O,9,FALSE)),"") -> 941.64 | G15: =IFERROR(IF(VLOOKUP($A15,'Annex 2 EHV charges'!$A:$O,10,FALSE)=0,"",VLOOKUP($A15,'Annex 2 EHV charges'!$A:$O,10,FALSE)),"") -> 4.66 | H15: =IFERROR(IF(VLOOKUP($A15,'Annex 2 EHV charges'!$A:$O,11,FALSE)=0,"",VLOOKUP($A15,'Annex 2 EHV charges'!$A:$O,11,FALSE)),"") -> 4.66
A16: {=IFERROR(INDEX('Annex 2 EHV charges'!$A$10:$A$259, MATCH(0, IF(ISBLANK('Annex 2 EHV charges'!$A$10:$A$259),1, COUNTIF(A$4:$A15, 'Annex 2 EHV charges'!$A$10:$A$259)), 0)),"")} -> NR_AFD | B16: =IF($A16="","",VLOOKUP($A16,'Annex 2 EHV charges'!$A:$O,2,0)) -> 851 | C16: =IF($A16="","",VLOOKUP($A16,'Annex 2 EHV charges'!$A:$O,3,0)) -> 1900060219377 | D16: =IF($A16="","",VLOOKUP($A16,'Annex 2 EHV charges'!$A:$O,7,0)) -> NR_AFD | E16: =IFERROR(IF(VLOOKUP($A16,'Annex 2 EHV charges'!$A:$O,8,FALSE)=0,"",VLOOKUP($A16,'Annex 2 EHV charges'!$A:$O,8,FALSE)),"") -> 0.176 | F16: =IFERROR(IF(VLOOKUP($A16,'Annex 2 EHV charges'!$A:$O,9,FALSE)=0,"",VLOOKUP($A16,'Annex 2 EHV charges'!$A:$O,9,FALSE)),"") -> 627.76 | G16: =IFERROR(IF(VLOOKUP($A16,'Annex 2 EHV charges'!$A:$O,10,FALSE)=0,"",VLOOKUP($A16,'Annex 2 EHV charges'!$A:$O,10,FALSE)),"") -> 2.4 | H16: =IFERROR(IF(VLOOKUP($A16,'Annex 2 EHV charges'!$A:$O,11,FALSE)=0,"",VLOOKUP($A16,'Annex 2 EHV charges'!$A:$O,11,FALSE)),"") -> 2.4
... A254: {=IFERROR(INDEX('Annex 2 EHV charges'!$A$10:$A$259, MATCH(0, IF(ISBLANK('Annex 2 EHV charges'!$A$10:$A$259),1, COUNTIF(A$4:$A253, 'Annex 2 EHV charges'!$A$10:$A$259)), 0)),"")} | B254: =IF($A254="","",VLOOKUP($A254,'Annex 2 EHV charges'!$A:$O,2,0)) | C254: =IF($A254="","",VLOOKUP($A254,'Annex 2 EHV charges'!$A:$O,3,0)) | D254: =IF($A254="","",VLOOKUP($A254,'Annex 2 EHV charges'!$A:$O,7,0)) | E254: =IFERROR(IF(VLOOKUP($A254,'Annex 2 EHV charges'!$A:$O,8,FALSE)=0,"",VLOOKUP($A254,'Annex 2 EHV charges'!$A:$O,8,FALSE)),"") | F254: =IFERROR(IF(VLOOKUP($A254,'Annex 2 EHV charges'!$A:$O,9,FALSE)=0,"",VLOOKUP($A254,'Annex 2 EHV charges'!$A:$O,9,FALSE)),"") | G254: =IFERROR(IF(VLOOKUP($A254,'Annex 2 EHV charges'!$A:$O,10,FALSE)=0,"",VLOOKUP($A254,'Annex 2 EHV charges'!$A:$O,10,FALSE)),"") | H254: =IFERROR(IF(VLOOKUP($A254,'Annex 2 EHV charges'!$A:$O,11,FALSE)=0,"",VLOOKUP($A254,'Annex 2 EHV charges'!$A:$O,11,FALSE)),"")

Sheet Annex 2b Export
A1: Note: The list of MPANs / MSIDs provided may be incomplete; the DNO reserves the right to apply the listed charges to any other MPANs / MSIDs associated with the site. Note: This table is automatically populated based on the content of the tab entitled 'Annex 2 EHV Charges'. The timebands are as shown in Annex 2.
A2: =Overview!B4& " - Effective from "&Overview!D4&" - "&Overview!E4&" EDCM export charges" -> South Eastern Power Networks - Effective from 1 April 2021 - Final EDCM export charges
A4: Export Unique Identifier | B4: LLFC | C4: Export MPANs/MSIDs | D4: Name | E4: ='Annex 2 EHV charges'!L9 -> Export Super Red unit charge (p/kWh) | F4: ='Annex 2 EHV charges'!M9 -> Export fixed charge (p/day) | G4: ='Annex 2 EHV charges'!N9 -> Export capacity charge (p/kVA/day) | H4: ='Annex 2 EHV charges'!O9 -> Export exceeded capacity charge (p/kVA/day)
A5: {=IFERROR(INDEX('Annex 2 EHV charges'!$D$10:$D$259, MATCH(0, IF(ISBLANK('Annex 2 EHV charges'!$D$10:$D$259),1, COUNTIF(A$4:$A4, 'Annex 2 EHV charges'!$D$10:$D$259)), 0)),"")} -> THAMEM | B5: =IF($A5="","",VLOOKUP($A5,'Annex 2 EHV charges'!$D:$O,2,0)) -> 691 | C5: =IF($A5="","",VLOOKUP($A5,'Annex 2 EHV charges'!$D:$O,3,0)) -> 1900090876979 1900090876988 | D5: =IF($A5="","",VLOOKUP($A5,'Annex 2 EHV charges'!$D:$O,4,0)) -> THAMEM | E5: =IFERROR(IF(VLOOKUP($A5,'Annex 2 EHV charges'!$D:$O,9,FALSE)=0,"",VLOOKUP($A5,'Annex 2 EHV charges'!$D:$O,9,FALSE)),"") | F5: =IFERROR(IF(VLOOKUP($A5,'Annex 2 EHV charges'!$D:$O,10,FALSE)=0,"",VLOOKUP($A5,'Annex 2 EHV charges'!$D:$O,10,FALSE)),"") -> 2879.64 | G5: =IFERROR(IF(VLOOKUP($A5,'Annex 2 EHV charges'!$D:$O,11,FALSE)=0,"",VLOOKUP($A5,'Annex 2 EHV charges'!$D:$O,11,FALSE)),"") -> 0.05 | H5: =IFERROR(IF(VLOOKUP($A5,'Annex 2 EHV charges'!$D:$O,12,FALSE)=0,"",VLOOKUP($A5,'Annex 2 EHV charges'!$D:$O,12,FALSE)),"") -> 0.05
A6: {=IFERROR(INDEX('Annex 2 EHV charges'!$D$10:$D$259, MATCH(0, IF(ISBLANK('Annex 2 EHV charges'!$D$10:$D$259),1, COUNTIF(A$4:$A5, 'Annex 2 EHV charges'!$D$10:$D$259)), 0)),"")} -> THAMES | B6: =IF($A6="","",VLOOKUP($A6,'Annex 2 EHV charges'!$D:$O,2,0)) -> 732 | C6: =IF($A6="","",VLOOKUP($A6,'Annex 2 EHV charges'!$D:$O,3,0)) -> 1900060576611 | D6: =IF($A6="","",VLOOKUP($A6,'Annex 2 EHV charges'!$D:$O,4,0)) -> THAMES | E6: =IFERROR(IF(VLOOKUP($A6,'Annex 2 EHV charges'!$D:$O,9,FALSE)=0,"",VLOOKUP($A6,'Annex 2 EHV charges'!$D:$O,9,FALSE)),"") | F6: =IFERROR(IF(VLOOKUP($A6,'Annex 2 EHV charges'!$D:$O,10,FALSE)=0,"",VLOOKUP($A6,'Annex 2 EHV charges'!$D:$O,10,FALSE)),"") -> 1726.31 | G6: =IFERROR(IF(VLOOKUP($A6,'Annex 2 EHV charges'!$D:$O,11,FALSE)=0,"",VLOOKUP($A6,'Annex 2 EHV charges'!$D:$O,11,FALSE)),"") -> 0.05 | H6: =IFERROR(IF(VLOOKUP($A6,'Annex 2 EHV charges'!$D:$O,12,FALSE)=0,"",VLOOKUP($A6,'Annex 2 EHV charges'!$D:$O,12,FALSE)),"") -> 0.05
A7: {=IFERROR(INDEX('Annex 2 EHV charges'!$D$10:$D$259, MATCH(0, IF(ISBLANK('Annex 2 EHV charges'!$D$10:$D$259),1, COUNTIF(A$4:$A6, 'Annex 2 EHV charges'!$D$10:$D$259)), 0)),"")} -> TWHK66 | B7: =IF($A7="","",VLOOKUP($A7,'Annex 2 EHV charges'!$D:$O,2,0)) -> 692 | C7: =IF($A7="","",VLOOKUP($A7,'Annex 2 EHV charges'!$D:$O,3,0)) -> 1900091206194 | D7: =IF($A7="","",VLOOKUP($A7,'Annex 2 EHV charges'!$D:$O,4,0)) -> TWHK66 | E7: =IFERROR(IF(VLOOKUP($A7,'Annex 2 EHV charges'!$D:$O,9,FALSE)=0,"",VLOOKUP($A7,'Annex 2 EHV charges'!$D:$O,9,FALSE)),"") -> -2.957 | F7: =IFERROR(IF(VLOOKUP($A7,'Annex 2 EHV charges'!$D:$O,10,FALSE)=0,"",VLOOKUP($A7,'Annex 2 EHV charges'!$D:$O,10,FALSE)),"") -> 30.18 | G7: =IFERROR(IF(VLOOKUP($A7,'Annex 2 EHV charges'!$D:$O,11,FALSE)=0,"",VLOOKUP($A7,'Annex 2 EHV charges'!$D:$O,11,FALSE)),"") -> 0.05 | H7: =IFERROR(IF(VLOOKUP($A7,'Annex 2 EHV charges'!$D:$O,12,FALSE)=0,"",VLOOKUP($A7,'Annex 2 EHV charges'!$D:$O,12,FALSE)),"") -> 0.05
A8: {=IFERROR(INDEX('Annex 2 EHV charges'!$D$10:$D$259, MATCH(0, IF(ISBLANK('Annex 2 EHV charges'!$D$10:$D$259),1, COUNTIF(A$4:$A7, 'Annex 2 EHV charges'!$D$10:$D$259)), 0)),"")} -> ASHBYS | B8: =IF($A8="","",VLOOKUP($A8,'Annex 2 EHV charges'!$D:$O,2,0)) -> 741 | C8: =IF($A8="","",VLOOKUP($A8,'Annex 2 EHV charges'!$D:$O,3,0)) -> 1900091216972 | D8: =IF($A8="","",VLOOKUP($A8,'Annex 2 EHV charges'!$D:$O,4,0)) -> ASHBYS | E8: =IFERROR(IF(VLOOKUP($A8,'Annex 2 EHV charges'!$D:$O,9,FALSE)=0,"",VLOOKUP($A8,'Annex 2 EHV charges'!$D:$O,9,FALSE)),"") | F8: =IFERROR(IF(VLOOKUP($A8,'Annex 2 EHV charges'!$D:$O,10,FALSE)=0,"",VLOOKUP($A8,'Annex 2 EHV charges'!$D:$O,10,FALSE)),"") -> 982.39 | G8: =IFERROR(IF(VLOOKUP($A8,'Annex 2 EHV charges'!$D:$O,11,FALSE)=0,"",VLOOKUP($A8,'Annex 2 EHV charges'!$D:$O,11,FALSE)),"") -> 0.05 | H8: =IFERROR(IF(VLOOKUP($A8,'Annex 2 EHV charges'!$D:$O,12,FALSE)=0,"",VLOOKUP($A8,'Annex 2 EHV charges'!$D:$O,12,FALSE)),"") -> 0.05
A9: {=IFERROR(INDEX('Annex 2 EHV charges'!$D$10:$D$259, MATCH(0, IF(ISBLANK('Annex 2 EHV charges'!$D$10:$D$259),1, COUNTIF(A$4:$A8, 'Annex 2 EHV charges'!$D$10:$D$259)), 0)),"")} -> ASHGEN | B9: =IF($A9="","",VLOOKUP($A9,'Annex 2 EHV charges'!$D:$O,2,0)) -> 734 | C9: =IF($A9="","",VLOOKUP($A9,'Annex 2 EHV charges'!$D:$O,3,0)) -> 1900090978875 | D9: =IF($A9="","",VLOOKUP($A9,'Annex 2 EHV charges'!$D:$O,4,0)) -> ASHGEN | E9: =IFERROR(IF(VLOOKUP($A9,'Annex 2 EHV charges'!$D:$O,9,FALSE)=0,"",VLOOKUP($A9,'Annex 2 EHV charges'!$D:$O,9,FALSE)),"") | F9: =IFERROR(IF(VLOOKUP($A9,'Annex 2 EHV charges'!$D:$O,10,FALSE)=0,"",VLOOKUP($A9,'Annex 2 EHV charges'!$D:$O,10,FALSE)),"") -> 2756.96 | G9: =IFERROR(IF(VLOOKUP($A9,'Annex 2 EHV charges'!$D:$O,11,FALSE)=0,"",VLOOKUP($A9,'Annex 2 EHV charges'!$D:$O,11,FALSE)),"") -> 0.05 | H9: =IFERROR(IF(VLOOKUP($A9,'Annex 2 EHV charges'!$D:$O,12,FALSE)=0,"",VLOOKUP($A9,'Annex 2 EHV charges'!$D:$O,12,FALSE)),"") -> 0.05
A10: {=IFERROR(INDEX('Annex 2 EHV charges'!$D$10:$D$259, MATCH(0, IF(ISBLANK('Annex 2 EHV charges'!$D$10:$D$259),1, COUNTIF(A$4:$A9, 'Annex 2 EHV charges'!$D$10:$D$259)), 0)),"")} -> AYLESF | B10: =IF($A10="","",VLOOKUP($A10,'Annex 2 EHV charges'!$D:$O,2,0)) -> 725 | C10: =IF($A10="","",VLOOKUP($A10,'Annex 2 EHV charges'!$D:$O,3,0)) -> 1900060436880 | D10: =IF($A10="","",VLOOKUP($A10,'Annex 2 EHV charges'!$D:$O,4,0)) -> AYLESF | E10: =IFERROR(IF(VLOOKUP($A10,'Annex 2 EHV charges'!$D:$O,9,FALSE)=0,"",VLOOKUP($A10,'Annex 2 EHV charges'!$D:$O,9,FALSE)),"") | F10: =IFERROR(IF(VLOOKUP($A10,'Annex 2 EHV charges'!$D:$O,10,FALSE)=0,"",VLOOKUP($A10,'Annex 2 EHV charges'!$D:$O,10,FALSE)),"") | G10: =IFERROR(IF(VLOOKUP($A10,'Annex 2 EHV charges'!$D:$O,11,FALSE)=0,"",VLOOKUP($A10,'Annex 2 EHV charges'!$D:$O,11,FALSE)),"") | H10: =IFERROR(IF(VLOOKUP($A10,'Annex 2 EHV charges'!$D:$O,12,FALSE)=0,"",VLOOKUP($A10,'Annex 2 EHV charges'!$D:$O,12,FALSE)),"")
A11: {=IFERROR(INDEX('Annex 2 EHV charges'!$D$10:$D$259, MATCH(0, IF(ISBLANK('Annex 2 EHV charges'!$D$10:$D$259),1, COUNTIF(A$4:$A10, 'Annex 2 EHV charges'!$D$10:$D$259)), 0)),"")} -> BEDERF | B11: =IF($A11="","",VLOOKUP($A11,'Annex 2 EHV charges'!$D:$O,2,0)) -> 693 | C11: =IF($A11="","",VLOOKUP($A11,'Annex 2 EHV charges'!$D:$O,3,0)) -> 1900091482597 | D11: =IF($A11="","",VLOOKUP($A11,'Annex 2 EHV charges'!$D:$O,4,0)) -> BEDERF | E11: =IFERROR(IF(VLOOKUP($A11,'Annex 2 EHV charges'!$D:$O,9,FALSE)=0,"",VLOOKUP($A11,'Annex 2 EHV charges'!$D:$O,9,FALSE)),"") -> -0.175 | F11: =IFERROR(IF(VLOOKUP($A11,'Annex 2 EHV charges'!$D:$O,10,FALSE)=0,"",VLOOKUP($A11,'Annex 2 EHV charges'!$D:$O,10,FALSE)),"") -> 2408.15 | G11: =IFERROR(IF(VLOOKUP($A11,'Annex 2 EHV charges'!$D:$O,11,FALSE)=0,"",VLOOKUP($A11,'Annex 2 EHV charges'!$D:$O,11,FALSE)),"") -> 0.05 | H11: =IFERROR(IF(VLOOKUP($A11,'Annex 2 EHV charges'!$D:$O,12,FALSE)=0,"",VLOOKUP($A11,'Annex 2 EHV charges'!$D:$O,12,FALSE)),"") -> 0.05
A12: {=IFERROR(INDEX('Annex 2 EHV charges'!$D$10:$D$259, MATCH(0, IF(ISBLANK('Annex 2 EHV charges'!$D$10:$D$259),1, COUNTIF(A$4:$A11, 'Annex 2 EHV charges'!$D$10:$D$259)), 0)),"")} -> BESAYL | B12: =IF($A12="","",VLOOKUP($A12,'Annex 2 EHV charges'!$D:$O,2,0)) -> 694 | C12: =IF($A12="","",VLOOKUP($A12,'Annex 2 EHV charges'!$D:$O,3,0)) -> 1900091632784 | D12: =IF($A12="","",VLOOKUP($A12,'Annex 2 EHV charges'!$D:$O,4,0)) -> BESAYL | E12: =IFERROR(IF(VLOOKUP($A12,'Annex 2 EHV charges'!$D:$O,9,FALSE)=0,"",VLOOKUP($A12,'Annex 2 EHV charges'!$D:$O,9,FALSE)),"") -> -0.209 | F12: =IFERROR(IF(VLOOKUP($A12,'Annex 2 EHV charges'!$D:$O,10,FALSE)=0,"",VLOOKUP($A12,'Annex 2 EHV charges'!$D:$O,10,FALSE)),"") -> 345.61 | G12: =IFERROR(IF(VLOOKUP($A12,'Annex 2 EHV charges'!$D:$O,11,FALSE)=0,"",VLOOKUP($A12,'Annex 2 EHV charges'!$D:$O,11,FALSE)),"") -> 0.05 | H12: =IFERROR(IF(VLOOKUP($A12,'Annex 2 EHV charges'!$D:$O,12,FALSE)=0,"",VLOOKUP($A12,'Annex 2 EHV charges'!$D:$O,12,FALSE)),"") -> 0.05
A13: {=IFERROR(INDEX('Annex 2 EHV charges'!$D$10:$D$259, MATCH(0, IF(ISBLANK('Annex 2 EHV charges'!$D$10:$D$259),1, COUNTIF(A$4:$A12, 'Annex 2 EHV charges'!$D$10:$D$259)), 0)),"")} -> BNTLEY | B13: =IF($A13="","",VLOOKUP($A13,'Annex 2 EHV charges'!$D:$O,2,0)) -> 713 | C13: =IF($A13="","",VLOOKUP($A13,'Annex 2 EHV charges'!$D:$O,3,0)) -> 1900091343787 | D13: =IF($A13="","",VLOOKUP($A13,'Annex 2 EHV charges'!$D:$O,4,0)) -> BNTLEY | E13: =IFERROR(IF(VLOOKUP($A13,'Annex 2 EHV charges'!$D:$O,9,FALSE)=0,"",VLOOKUP($A13,'Annex 2 EHV charges'!$D:$O,9,FALSE)),"") | F13: =IFERROR(IF(VLOOKUP($A13,'Annex 2 EHV charges'!$D:$O,10,FALSE)=0,"",VLOOKUP($A13,'Annex 2 EHV charges'!$D:$O,10,FALSE)),"") -> 866.59 | G13: =IFERROR(IF(VLOOKUP($A13,'Annex 2 EHV charges'!$D:$O,11,FALSE)=0,"",VLOOKUP($A13,'Annex 2 EHV charges'!$D:$O,11,FALSE)),"") -> 0.05 | H13: =IFERROR(IF(VLOOKUP($A13,'Annex 2 EHV charges'!$D:$O,12,FALSE)=0,"",VLOOKUP($A13,'Annex 2 EHV charges'!$D:$O,12,FALSE)),"") -> 0.05
A14: {=IFERROR(INDEX('Annex 2 EHV charges'!$D$10:$D$259, MATCH(0, IF(ISBLANK('Annex 2 EHV charges'!$D$10:$D$259),1, COUNTIF(A$4:$A13, 'Annex 2 EHV charges'!$D$10:$D$259)), 0)),"")} -> BNTLY2 | B14: =IF($A14="","",VLOOKUP($A14,'Annex 2 EHV charges'!$D:$O,2,0)) -> 712 | C14: =IF($A14="","",VLOOKUP($A14,'Annex 2 EHV charges'!$D:$O,3,0)) -> 1900091463655 | D14: =IF($A14="","",VLOOKUP($A14,'Annex 2 EHV charges'!$D:$O,4,0)) -> BNTLY2 | E14: =IFERROR(IF(VLOOKUP($A14,'Annex 2 EHV charges'!$D:$O,9,FALSE)=0,"",VLOOKUP($A14,'Annex 2 EHV charges'!$D:$O,9,FALSE)),"") | F14: =IFERROR(IF(VLOOKUP($A14,'Annex 2 EHV charges'!$D:$O,10,FALSE)=0,"",VLOOKUP($A14,'Annex 2 EHV charges'!$D:$O,10,FALSE)),"") -> 554.77 | G14: =IFERROR(IF(VLOOKUP($A14,'Annex 2 EHV charges'!$D:$O,11,FALSE)=0,"",VLOOKUP($A14,'Annex 2 EHV charges'!$D:$O,11,FALSE)),"") -> 0.05 | H14: =IFERROR(IF(VLOOKUP($A14,'Annex 2 EHV charges'!$D:$O,12,FALSE)=0,"",VLOOKUP($A14,'Annex 2 EHV charges'!$D:$O,12,FALSE)),"") -> 0.05
A15: {=IFERROR(INDEX('Annex 2 EHV charges'!$D$10:$D$259, MATCH(0, IF(ISBLANK('Annex 2 EHV charges'!$D$10:$D$259),1, COUNTIF(A$4:$A14, 'Annex 2 EHV charges'!$D$10:$D$259)), 0)),"")} -> BOBBNG | B15: =IF($A15="","",VLOOKUP($A15,'Annex 2 EHV charges'!$D:$O,2,0)) -> 705 | C15: =IF($A15="","",VLOOKUP($A15,'Annex 2 EHV charges'!$D:$O,3,0)) -> 1900091395517 | D15: =IF($A15="","",VLOOKUP($A15,'Annex 2 EHV charges'!$D:$O,4,0)) -> BOBBNG | E15: =IFERROR(IF(VLOOKUP($A15,'Annex 2 EHV charges'!$D:$O,9,FALSE)=0,"",VLOOKUP($A15,'Annex 2 EHV charges'!$D:$O,9,FALSE)),"") | F15: =IFERROR(IF(VLOOKUP($A15,'Annex 2 EHV charges'!$D:$O,10,FALSE)=0,"",VLOOKUP($A15,'Annex 2 EHV charges'!$D:$O,10,FALSE)),"") -> 940.36 | G15: =IFERROR(IF(VLOOKUP($A15,'Annex 2 EHV charges'!$D:$O,11,FALSE)=0,"",VLOOKUP($A15,'Annex 2 EHV charges'!$D:$O,11,FALSE)),"") -> 0.05 | H15: =IFERROR(IF(VLOOKUP($A15,'Annex 2 EHV charges'!$D:$O,12,FALSE)=0,"",VLOOKUP($A15,'Annex 2 EHV charges'!$D:$O,12,FALSE)),"") -> 0.05
A16: {=IFERROR(INDEX('Annex 2 EHV charges'!$D$10:$D$259, MATCH(0, IF(ISBLANK('Annex 2 EHV charges'!$D$10:$D$259),1, COUNTIF(A$4:$A15, 'Annex 2 EHV charges'!$D$10:$D$259)), 0)),"")} -> BRAMBS | B16: =IF($A16="","",VLOOKUP($A16,'Annex 2 EHV charges'!$D:$O,2,0)) -> 695 | C16: =IF($A16="","",VLOOKUP($A16,'Annex 2 EHV charges'!$D:$O,3,0)) -> 1900091566820 | D16: =IF($A16="","",VLOOKUP($A16,'Annex 2 EHV charges'!$D:$O,4,0)) -> BRAMBS | E16: =IFERROR(IF(VLOOKUP($A16,'Annex 2 EHV charges'!$D:$O,9,FALSE)=0,"",VLOOKUP($A16,'Annex 2 EHV charges'!$D:$O,9,FALSE)),"") -> -0.085 | F16: =IFERROR(IF(VLOOKUP($A16,'Annex 2 EHV charges'!$D:$O,10,FALSE)=0,"",VLOOKUP($A16,'Annex 2 EHV charges'!$D:$O,10,FALSE)),"") -> 345.61 | G16: =IFERROR(IF(VLOOKUP($A16,'Annex 2 EHV charges'!$D:$O,11,FALSE)=0,"",VLOOKUP($A16,'Annex 2 EHV charges'!$D:$O,11,FALSE)),"") -> 0.05 | H16: =IFERROR(IF(VLOOKUP($A16,'Annex 2 EHV charges'!$D:$O,12,FALSE)=0,"",VLOOKUP($A16,'Annex 2 EHV charges'!$D:$O,12,FALSE)),"") -> 0.05
... A254: {=IFERROR(INDEX('Annex 2 EHV charges'!$D$10:$D$259, MATCH(0, IF(ISBLANK('Annex 2 EHV charges'!$D$10:$D$259),1, COUNTIF(A$4:$A253, 'Annex 2 EHV charges'!$D$10:$D$259)), 0)),"")} | B254: =IF($A254="","",VLOOKUP($A254,'Annex 2 EHV charges'!$D:$O,2,0)) | C254: =IF($A254="","",VLOOKUP($A254,'Annex 2 EHV charges'!$D:$O,3,0)) | D254: =IF($A254="","",VLOOKUP($A254,'Annex 2 EHV charges'!$D:$O,4,0)) | E254: =IFERROR(IF(VLOOKUP($A254,'Annex 2 EHV charges'!$D:$O,9,FALSE)=0,"",VLOOKUP($A254,'Annex 2 EHV charges'!$D:$O,9,FALSE)),"") | F254: =IFERROR(IF(VLOOKUP($A254,'Annex 2 EHV charges'!$D:$O,10,FALSE)=0,"",VLOOKUP($A254,'Annex 2 EHV charges'!$D:$O,10,FALSE)),"") | G254: =IFERROR(IF(VLOOKUP($A254,'Annex 2 EHV charges'!$D:$O,11,FALSE)=0,"",VLOOKUP($A254,'Annex 2 EHV charges'!$D:$O,11,FALSE)),"") | H254: =IFERROR(IF(VLOOKUP($A254,'Annex 2 EHV charges'!$D:$O,12,FALSE)=0,"",VLOOKUP($A254,'Annex 2 EHV charges'!$D:$O,12,FALSE)),"")

Sheet Annex 3 Preserved charges
A1: Back to Overview
A2: =Overview!B4& " - Effective from "&Overview!D4&" - "&Overview!E4&" LV and HV tariffs" -> South Eastern Power Networks - Effective from 1 April 2021 - Final LV and HV tariffs
A3: Supercustomer preserved charges/additional LLFCs
B4: Closed LLFCs | C4: PCs | D4: Red/black unit charge p/kWh | E4: Amber/yellow unit charge p/kWh | F4: Green unit charge p/kWh | G4: Fixed charge p/MPAN/day
A6: Notes: | B6: South Eastern Power Networks has no Preserved NHH Tariffs/Additional LLFC classes
A11: Site Specific preserved charges/additional LLFCs
B12: Closed LLFCs | C12: PCs | D12: Red/black unit charge p/kWh | E12: Amber/yellow unit charge p/kWh | F12: Green unit charge p/kWh | G12: Fixed charge p/MPAN/day | H12: Capacity charge p/kVA/day | I12: Exceeded capacity charge p/kVA/day | J12: Reactive power charge p/kVArh
C13: 0
A14: Notes: | B14: South Eastern Power Networks has no Preserved HH Tariffs/Additional LLFC classes

Sheet Annex 4 LDNO charges
A1: Back to Overview | B1: Copy from CDCM table 3701 "Tariffs!A42:I84" and paste values into A14 | F1: Copy from EDCM table 6005 "LDNORev!B549:G683" and paste values into D57
A2: =Overview!B4& " - Effective from "&Overview!D4&" - "&Overview!E4&" LDNO tariffs" -> South Eastern Power Networks - Effective from 1 April 2021 - Final LDNO tariffs
A4: Time Bands for LV and HV Designated Properties | F4: Time Bands for Unmetered Properties
A5: Time periods | B5: Red Time Band | C5: Amber Time Band | D5: Green Time Band | H5: Black Time Band | I5: Yellow Time Band | J5: Green Time Band
A6: Monday to Friday (Including Bank Holidays) All Year | B6: 16:00 - 19:00 | C6: 07:00 - 16:00 19:00 - 23:00 | D6: 00:00 - 07:00 23:00 - 24:00 | F6: Monday to Friday (Including Bank Holidays) November to February Inclusive | H6: 16:00 - 19:00 | I6: 07:00 - 16:00 19:00 - 23:00 | J6: 00:00 - 07:00 23:00 - 24:00
A7: Saturday and Sunday All Year | D7: 00:00 - 24:00 | F7: Monday to Friday (Including Bank Holidays) March to October Inclusive | I7: 07:00 - 23:00 | J7: 00:00 - 07:00 23:00 - 24:00
A8: Notes | B8: All times are in UK Clock time | F8: Saturday and Sunday All Year | J8: 00:00 - 24:00
F9: Notes | H9: All times are in UK Clock time
A11: Tariff name | B11: Unique billing identifier | C11: PCs | D11: Red/black unit charge p/kWh | E11: Amber/yellow unit charge p/kWh | F11: Green unit charge p/kWh | G11: Fixed charge p/MPAN/day | H11: Capacity charge p/kVA/day | I11: Exceeded capacity charge p/kVA/day | J11: Reactive power charge p/kVArh
A12: LDNO LV: Domestic Aggregated | B12: A00 | C12: 1, 2 or 0 | D12: 11.484 | E12: 0.822 | F12: 0.453 | G12: 2.78
A13: LDNO LV: Domestic Aggregated (related MPAN) | B13: B00 | C13: 2 | D13: 11.484 | E13: 0.822 | F13: 0.453
A14: LDNO LV: Non-Domestic Aggregated | B14: C00, C01, C02, C03, C04 | C14: 3-8 or 0 | D14: 8.991 | E14: 0.723 | F14: 0.437 | G14: 2.88
A15: LDNO LV: Non-Domestic Aggregated (related MPAN) | B15: D00 | C15: 4 | D15: 8.991 | E15: 0.723 | F15: 0.437
A16: LDNO LV: LV Site Specific | B16: E01, E02, E03, E04 | C16: 0 | D16: 6.19 | E16: 0.6 | F16: 0.415 | G16: 7.76 | H16: 2.5 | I16: 4.85 | J16: 0.188
A17: LDNO LV: LV Site Specific Storage Import | B17: E00 | C17: 0 | D17: 5.809 | E17: 0.219 | F17: 0.034 | G17: 7.76 | H17: 2.5 | I17: 4.85 | J17: 0.188
A18: LDNO LV: Unmetered Supplies | B18: U00 | C18: 1, 8 or 0 | D18: 27.443 | E18: 1.218 | F18: 0.896
A19: LDNO LV: LV Generation Aggregated | B19: F00 | C19: 8 or 0 | D19: -9.262 | E19: -0.368 | F19: -0.06 | G19: 0
A20: LDNO LV: LV Generation Site Specific | B20: G00 | C20: 0 | D20: -9.262 | E20: -0.368 | F20: -0.06 | G20: 0 | J20: 0.267
A21: LDNO HV: Domestic Aggregated | B21: A10 | C21: 1, 2 or 0 | D21: 8.715 | E21: 0.624 | F21: 0.344 | G21: 2.16
A22: LDNO HV: Domestic Aggregated (related MPAN) | B22: B10 | C22: 2 | D22: 8.715 | E22: 0.624 | F22: 0.344
A23: LDNO HV: Non-Domestic Aggregated | B23: C10, C11, C12, C13, C14 | C23: 3-8 or 0 | D23: 6.823 | E23: 0.549 | F23: 0.331 | G23: 2.23
A24: LDNO HV: Non-Domestic Aggregated (related MPAN) | B24: D10 | C24: 4 | D24: 6.823 | E24: 0.549 | F24: 0.331
A25: LDNO HV: LV Site Specific | B25: E11, E12, E13, E14 | C25: 0 | D25: 4.697 | E25: 0.455 | F25: 0.315 | G25: 5.94 | H25: 1.9 | I25: 3.68 | J25: 0.143
A26: LDNO HV: LV Sub Site Specific | B26: J11, J12, J13, J14 | C26: 0 | D26: 4.531 | E26: 0.57 | F26: 0.453 | G26: 6.54 | H26: 4.41 | I26: 5.76 | J26: 0.125
A27: LDNO HV: HV Site Specific | B27: K11, K12, K13, K14 | C27: 0 | D27: 4.732 | E27: 0.616 | F27: 0.502 | G27: 96.14 | H27: 3.69 | I27: 5.73 | J27: 0.131
A28: LDNO HV: LV Site Specific Storage Import | B28: E10 | C28: 0 | D28: 4.408 | E28: 0.166 | F28: 0.026 | G28: 5.94 | H28: 1.9 | I28: 3.68 | J28: 0.143
A29: LDNO HV: LV Sub Site Specific Storage Import | B29: J10 | C29: 0 | D29: 4.098 | E29: 0.136 | F29: 0.02 | G29: 6.54 | H29: 4.41 | I29: 5.76 | J29: 0.125
A30: LDNO HV: HV Site Specific Storage Import | B30: K10 | C30: 0 | D30: 4.248 | E30: 0.132 | F30: 0.018 | G30: 96.14 | H30: 3.69 | I30: 5.73 | J30: 0.131
A31: LDNO HV: Unmetered Supplies | B31: U10 | C31: 1, 8 or 0 | D31: 20.826 | E31: 0.924 | F31: 0.68
A32: LDNO HV: LV Generation Aggregated | B32: F10 | C32: 8 or 0 | D32: -9.262 | E32: -0.368 | F32: -0.06 | G32: 0
A33: LDNO HV: LV Sub Generation Aggregated | B33: H10 | C33: 0 | D33: -8.273 | E33: -0.318 | F33: -0.051 | G33: 0
A34: LDNO HV: LV Generation Site Specific | B34: G10 | C34: 0 | D34: -9.262 | E34: -0.368 | F34: -0.06 | G34: 0 | J34: 0.267
A35: LDNO HV: LV Sub Generation Site Specific | B35: L10 | C35: 0 | D35: -8.273 | E35: -0.318 | F35: -0.051 | G35: 0 | J35: 0.243
A36: LDNO HV: HV Generation Site Specific | B36: M10 | C36: 0 | D36: -5.769 | E36: -0.189 | F36: -0.027 | G36: 0 | J36: 0.196
A37: LDNO HVplus: Domestic Aggregated | B37: A20 | C37: 1, 2 or 0 | D37: 6.392 | E37: 0.458 | F37: 0.252 | G37: 1.63
A38: LDNO HVplus: Domestic Aggregated (related MPAN) | B38: B20 | C38: 2 | D38: 6.392 | E38: 0.458 | F38: 0.252
A39: LDNO HVplus: Non-Domestic Aggregated | B39: C20, C21, C22, C23, C24 | C39: 3-8 or 0 | D39: 5.004 | E39: 0.403 | F39: 0.243 | G39: 1.69
A40: LDNO HVplus: Non-Domestic Aggregated (related MPAN) | B40: D20 | C40: 4 | D40: 5.004 | E40: 0.403 | F40: 0.243
A41: LDNO HVplus: LV Site Specific | B41: E21, E22, E23, E24 | C41: 0 | D41: 3.445 | E41: 0.334 | F41: 0.231 | G41: 4.41 | H41: 1.39 | I41: 2.7 | J41: 0.105
A42: LDNO HVplus: LV Sub Site Specific | B42: J21, J22, J23, J24 | C42: 0 | D42: 3.288 | E42: 0.413 | F42: 0.329 | G42: 4.8 | H42: 3.2 | I42: 4.18 | J42: 0.091
A43: LDNO HVplus: HV Site Specific | B43: K21, K22, K23, K24 | C43: 0 | D43: 3.42 | E43: 0.445 | F43: 0.363 | G43: 69.54 | H43: 2.67 | I43: 4.14 | J43: 0.095
A44: LDNO HVplus: LV Site Specific Storage Import | B44: E20 | C44: 0 | D44: 3.233 | E44: 0.122 | F44: 0.019 | G44: 4.41 | H44: 1.39 | I44: 2.7 | J44: 0.105
A45: LDNO HVplus: LV Sub Site Specific Storage Import | B45: J20 | C45: 0 | D45: 2.973 | E45: 0.099 | F45: 0.014 | G45: 4.8 | H45: 3.2 | I45: 4.18 | J45: 0.091
A46: LDNO HVplus: HV Site Specific Storage Import | B46: K20 | C46: 0 | D46: 3.07 | E46: 0.096 | F46: 0.013 | G46: 69.54 | H46: 2.67 | I46: 4.14 | J46: 0.095
A47: LDNO HVplus: Unmetered Supplies | B47: U20 | C47: 1, 8 or 0 | D47: 15.274 | E47: 0.678 | F47: 0.499
A48: LDNO HVplus: LV Generation Aggregated | B48: F20 | C48: 8 or 0 | D48: -5.207 | E48: -0.207 | F48: -0.034 | G48: 0
A49: LDNO HVplus: LV Sub Generation Aggregated | B49: H20 | C49: 0 | D49: -5.172 | E49: -0.199 | F49: -0.032 | G49: 0
A50: LDNO HVplus: LV Generation Site Specific | B50: G20 | C50: 0 | D50: -5.207 | E50: -0.207 | F50: -0.034 | G50: 0 | J50: 0.15
A51: LDNO HVplus: LV Sub Generation Site Specific | B51: L20 | C51: 0 | D51: -5.172 | E51: -0.199 | F51: -0.032 | G51: 0 | J51: 0.152
A52: LDNO HVplus: HV Generation Site Specific | B52: M20 | C52: 0 | D52: -5.769 | E52: -0.189 | F52: -0.027 | G52: 9.39 | J52: 0.196
A53: LDNO EHV: Domestic Aggregated | B53: A30 | C53: 1, 2 or 0 | D53: 5.186 | E53: 0.371 | F53: 0.204 | G53: 1.36
A54: LDNO EHV: Domestic Aggregated (related MPAN) | B54: B30 | C54: 2 | D54: 5.186 | E54: 0.371 | F54: 0.204
A55: LDNO EHV: Non-Domestic Aggregated | B55: C30, C31, C32, C33, C34 | C55: 3-8 or 0 | D55: 4.06 | E55: 0.327 | F55: 0.197 | G55: 1.4
A56: LDNO EHV: Non-Domestic Aggregated (related MPAN) | B56: D30 | C56: 4 | D56: 4.06 | E56: 0.327 | F56: 0.197
A57: LDNO EHV: LV Site Specific | B57: E31, E32, E33, E34 | C57: 0 | D57: 2.795 | E57: 0.271 | F57: 0.188 | G57: 3.61 | H57: 1.13 | I57: 2.19 | J57: 0.085
A58: LDNO EHV: LV Sub Site Specific | B58: J31, J32, J33, J34 | C58: 0 | D58: 2.668 | E58: 0.335 | F58: 0.267 | G58: 3.93 | H58: 2.6 | I58: 3.39 | J58: 0.074
A59: LDNO EHV: HV Site Specific | B59: K31, K32, K33, K34 | C59: 0 | D59: 2.775 | E59: 0.361 | F59: 0.294 | G59: 56.46 | H59: 2.17 | I59: 3.36 | J59: 0.077
A60: LDNO EHV: LV Site Specific Storage Import | B60: E30 | C60: 0 | D60: 2.623 | E60: 0.099 | F60: 0.016 | G60: 3.61 | H60: 1.13 | I60: 2.19 | J60: 0.085
A61: LDNO EHV: LV Sub Site Specific Storage Import | B61: J30 | C61: 0 | D61: 2.412 | E61: 0.08 | F61: 0.012 | G61: 3.93 | H61: 2.6 | I61: 3.39 | J61: 0.074
A62: LDNO EHV: HV Site Specific Storage Import | B62: K30 | C62: 0 | D62: 2.491 | E62: 0.078 | F62: 0.01 | G62: 56.46 | H62: 2.17 | I62: 3.36 | J62: 0.077
A63: LDNO EHV: Unmetered Supplies | B63: U30 | C63: 1, 8 or 0 | D63: 12.393 | E63: 0.55 | F63: 0.405
A64: LDNO EHV: LV Generation Aggregated | B64: F30 | C64: 8 or 0 | D64: -4.225 | E64: -0.168 | F64: -0.027 | G64: 0
A65: LDNO EHV: LV Sub Generation Aggregated | B65: H30 | C65: 0 | D65: -4.197 | E65: -0.161 | F65: -0.026 | G65: 0
A66: LDNO EHV: LV Generation Site Specific | B66: G30 | C66: 0 | D66: -4.225 | E66: -0.168 | F66: -0.027 | G66: 0 | J66: 0.122
A67: LDNO EHV: LV Sub Generation Site Specific | B67: L30 | C67: 0 | D67: -4.197 | E67: -0.161 | F67: -0.026 | G67: 0 | J67: 0.123
A68: LDNO EHV: HV Generation Site Specific | B68: M30 | C68: 0 | D68: -4.681 | E68: -0.153 | F68: -0.022 | G68: 7.62 | J68: 0.159
A69: LDNO 132kV/EHV: Domestic Aggregated | B69: A40 | C69: 1, 2 or 0 | D69: 4.333 | E69: 0.31 | F69: 0.171 | G69: 1.17
A70: LDNO 132kV/EHV: Domestic Aggregated (related MPAN) | B70: B40 | C70: 2 | D70: 4.333 | E70: 0.31 | F70: 0.171
A71: LDNO 132kV/EHV: Non-Domestic Aggregated | B71: C40, C41, C42, C43, C44 | C71: 3-8 or 0 | D71: 3.392 | E71: 0.273 | F71: 0.165 | G71: 1.2
A72: LDNO 132kV/EHV: Non-Domestic Aggregated (related MPAN) | B72: D40 | C72: 4 | D72: 3.392 | E72: 0.273 | F72: 0.165
A73: LDNO 132kV/EHV: LV Site Specific | B73: E41, E42, E43, E44 | C73: 0 | D73: 2.336 | E73: 0.226 | F73: 0.157 | G73: 3.05 | H73: 0.94 | I73: 1.83 | J73: 0.071
A74: LDNO 132kV/EHV: LV Sub Site Specific | B74: J41, J42, J43, J44 | C74: 0 | D74: 2.229 | E74: 0.28 | F74: 0.223 | G74: 3.31 | H74: 2.17 | I74: 2.83 | J74: 0.062
A75: LDNO 132kV/EHV: HV Site Specific | B75: K41, K42, K43, K44 | C75: 0 | D75: 2.319 | E75: 0.302 | F75: 0.246 | G75: 47.2 | H75: 1.81 | I75: 2.81 | J75: 0.064
A76: LDNO 132kV/EHV: LV Site Specific Storage Import | B76: E40 | C76: 0 | D76: 2.192 | E76: 0.082 | F76: 0.013 | G76: 3.05 | H76: 0.94 | I76: 1.83 | J76: 0.071
A77: LDNO 132kV/EHV: LV Sub Site Specific Storage Import | B77: J40 | C77: 0 | D77: 2.016 | E77: 0.067 | F77: 0.01 | G77: 3.31 | H77: 2.17 | I77: 2.83 | J77: 0.062
A78: LDNO 132kV/EHV: HV Site Specific Storage Import | B78: K40 | C78: 0 | D78: 2.082 | E78: 0.065 | F78: 0.009 | G78: 47.2 | H78: 1.81 | I78: 2.81 | J78: 0.064
A79: LDNO 132kV/EHV: Unmetered Supplies | B79: U40 | C79: 1, 8 or 0 | D79: 10.355 | E79: 0.46 | F79: 0.338
A80: LDNO 132kV/EHV: LV Generation Aggregated | B80: F40 | C80: 8 or 0 | D80: -3.53 | E80: -0.14 | F80: -0.023 | G80: 0
A81: LDNO 132kV/EHV: LV Sub Generation Aggregated | B81: H40 | C81: 0 | D81: -3.506 | E81: -0.135 | F81: -0.021 | G81: 0
A82: LDNO 132kV/EHV: LV Generation Site Specific | B82: G40 | C82: 0 | D82: -3.53 | E82: -0.14 | F82: -0.023 | G82: 0 | J82: 0.102
A83: LDNO 132kV/EHV: LV Sub Generation Site Specific | B83: L40 | C83: 0 | D83: -3.506 | E83: -0.135 | F83: -0.021 | G83: 0 | J83: 0.103
A84: LDNO 132kV/EHV: HV Generation Site Specific | B84: M40 | C84: 0 | D84: -3.911 | E84: -0.128 | F84: -0.018 | G84: 6.37 | J84: 0.133
A85: LDNO 132kV: Domestic Aggregated | B85: A50 | C85: 1, 2 or 0 | D85: 3.078 | E85: 0.22 | F85: 0.121 | G85: 0.89
A86: LDNO 132kV: Domestic Aggregated (related MPAN) | B86: B50 | C86: 2 | D86: 3.078 | E86: 0.22 | F86: 0.121
A87: LDNO 132kV: Non-Domestic Aggregated | B87: C50, C51, C52, C53, C54 | C87: 3-8 or 0 | D87: 2.409 | E87: 0.194 | F87: 0.117 | G87: 0.91
A88: LDNO 132kV: Non-Domestic Aggregated (related MPAN) | B88: D50 | C88: 4 | D88: 2.409 | E88: 0.194 | F88: 0.117
A89: LDNO 132kV: LV Site Specific | B89: E51, E52, E53, E54 | C89: 0 | D89: 1.659 | E89: 0.161 | F89: 0.111 | G89: 2.22 | H89: 0.67 | I89: 1.3 | J89: 0.05
A90: LDNO 132kV: LV Sub Site Specific | B90: J51, J52, J53, J54 | C90: 0 | D90: 1.583 | E90: 0.199 | F90: 0.158 | G90: 2.41 | H90: 1.54 | I90: 2.01 | J90: 0.044
A91: LDNO 132kV: HV Site Specific | B91: K51, K52, K53, K54 | C91: 0 | D91: 1.647 | E91: 0.214 | F91: 0.175 | G91: 33.58 | H91: 1.29 | I91: 2 | J91: 0.046
A92: LDNO 132kV: LV Site Specific Storage Import | B92: E50 | C92: 0 | D92: 1.557 | E92: 0.059 | F92: 0.009 | G92: 2.22 | H92: 0.67 | I92: 1.3 | J92: 0.05
A93: LDNO 132kV: LV Sub Site Specific Storage Import | B93: J50 | C93: 0 | D93: 1.432 | E93: 0.048 | F93: 0.007 | G93: 2.41 | H93: 1.54 | I93: 2.01 | J93: 0.044
A94: LDNO 132kV: HV Site Specific Storage Import | B94: K50 | C94: 0 | D94: 1.478 | E94: 0.046 | F94: 0.006 | G94: 33.58 | H94: 1.29 | I94: 2 | J94: 0.046
A95: LDNO 132kV: Unmetered Supplies | B95: U50 | C95: 1, 8 or 0 | D95: 7.354 | E95: 0.326 | F95: 0.24
A96: LDNO 132kV: LV Generation Aggregated | B96: F50 | C96: 8 or 0 | D96: -2.507 | E96: -0.1 | F96: -0.016 | G96: 0
A97: LDNO 132kV: LV Sub Generation Aggregated | B97: H50 | C97: 0 | D97: -2.49 | E97: -0.096 | F97: -0.015 | G97: 0
A98: LDNO 132kV: LV Generation Site Specific | B98: G50 | C98: 0 | D98: -2.507 | E98: -0.1 | F98: -0.016 | G98: 0 | J98: 0.072
A99: LDNO 132kV: LV Sub Generation Site Specific | B99: L50 | C99: 0 | D99: -2.49 | E99: -0.096 | F99: -0.015 | G99: 0 | J99: 0.073
A100: LDNO 132kV: HV Generation Site Specific | B100: M50 | C100: 0 | D100: -2.778 | E100: -0.091 | F100: -0.013 | G100: 4.52 | J100: 0.094
A101: LDNO 0000: Domestic Aggregated | B101: A60 | C101: 1, 2 or 0 | D101: 1.124 | E101: 0.08 | F101: 0.044 | G101: 0.45
A102: LDNO 0000: Domestic Aggregated (related MPAN) | B102: B60 | C102: 2 | D102: 1.124 | E102: 0.08 | F102: 0.044
...

Sheet Annex 5 LLFs
A1: Back to Overview
A2: These line loss factors are illustrative based on the latest calculated values and are published in good faith. However, the line loss factors that are approved by the BSC Panel for the applicable year and consequently published on the Elexon website will take precedence and will be used in Settlement if they differ from these values.
A3: =Overview!B4& " - Illustrative LLFs for year beginning "&Overview!D4 -> South Eastern Power Networks - Illustrative LLFs for year beginning 1 April 2021
A4: Time periods | C4: Period 1 | D4: Period 2 | E4: Period 3 | F4: Period 4 | G4: Period 5
C5: Winter Peak | D5: Summer Peak | E5: Winter Shoulder | F5: Night | G5: Other
A6: Monday to Friday November to February | C6: 16:00 - 19:59 | E6: 07:00 - 15:59
A7: Monday to Friday June to August | D7: 07:00 - 19:59
A8: Monday to Friday March | E8: 07:00 - 19:59
A9: All Year | F9: 00:00 - 06:59 | G9: All Other Times
A10: Notes | C10: All times are in UK Clock time
A12: Generic demand and generation LLFs
A13: Metered voltage, respective periods and associated LLFCs
A14: Metered voltage | B14: Period 1 | C14: Period 2 | D14: Period 3 | E14: Period 4 | F14: Period 5 | G14: Associated LLFC
A15: Low-voltage network | B15: 1.098 | C15: 1.074 | D15: 1.087 | E15: 1.067 | F15: 1.078 | G15: 1, 2, 19, 69, 71, 72, 73, 74, 100, 120, 199, 200, 201, 202, 203, 204, 251, 287, 300, 320, 350, 351, 352, 353, 354, 355, 356, 357, 358, 359, 360, 361, 362, 363, 364, 365, 366, 480, 550, 921, 932, 935, 980, 981, 982, 983
A16: Low-voltage substation | B16: 1.073 | C16: 1.057 | D16: 1.066 | E16: 1.052 | F16: 1.059 | G16: 79, 81, 82, 83, 84, 756, 781, 782, 984, 985, 986, 987
A17: High-voltage network | B17: 1.057 | C17: 1.042 | D17: 1.051 | E17: 1.036 | F17: 1.044 | G17: 89, 91, 92, 93, 94, 650, 926, 937, 988, 989, 990, 991
A18: High-voltage substation | B18: 1.059 | C18: 1.043 | D18: 1.052 | E18: 1.037 | F18: 1.045 | G18: 771, 791, 792
A19: 33kV generic | B19: 1.019 | C19: 1.015 | D19: 1.017 | E19: 1.014 | F19: 1.016 | G19: 796, 797
A20: 132kV generic | B20: 1.006 | C20: 1.005 | D20: 1.006 | E20: 1.004 | F20: 1.005 | G20: 798, 799
A22: EHV site specific LLFs
A23: Demand
A24: Site | B24: Period 1 | C24: Period 2 | D24: Period 3 | E24: Period 4 | F24: Period 5 | G24: Associated LLFC
A25: NEWHVN - Import | B25: 1.035 | C25: 1.05 | D25: 1.049 | E25: 1.046 | F25: 1.048 | G25: 800
A26: ASHGEN - Import | B26: 0.991 | C26: 0.996 | D26: 0.996 | E26: 0.996 | F26: 0.997 | G26: 801
A27: BRKHST - Import | B27: 1.042 | C27: 1.034 | D27: 1.048 | E27: 1.023 | F27: 1.037 | G27: 802
A28: KNWLTN - Import | B28: 1.019 | C28: 1.015 | D28: 1.017 | E28: 1.014 | F28: 1.016 | G28: 803
A29: DSCPRK - Import | B29: 1.007 | C29: 1.012 | D29: 1.007 | E29: 1.01 | F29: 1.01 | G29: 804
A30: OLDRSF - Import | B30: 1.019 | C30: 1.015 | D30: 1.017 | E30: 1.014 | F30: 1.016 | G30: 805
A31: WSTWDX - Import | B31: 1.019 | C31: 1.015 | D31: 1.017 | E31: 1.014 | F31: 1.016 | G31: 806
A32: SYCAMR - Import | B32: 1.019 | C32: 1.015 | D32: 1.017 | E32: 1.014 | F32: 1.016 | G32: 807
A33: LENHAM - Import | B33: 1.019 | C33: 1.015 | D33: 1.017 | E33: 1.014 | F33: 1.016 | G33: 808
A34: ASHBYS - Import | B34: 1.035 | C34: 1.022 | D34: 1.031 | E34: 1.026 | F34: 1.029 | G34: 809
A35: BTBRKS - Import | B35: 1.009 | C35: 1.007 | D35: 1.008 | E35: 1.008 | F35: 1.008 | G35: 810
A36: FRWOOD - Import | B36: 1.019 | C36: 1.015 | D36: 1.017 | E36: 1.014 | F36: 1.016 | G36: 811
... A115: SELLSF - Import | B115: 1.006 | C115: 1.006 | D115: 1.006 | E115: 1.006 | F115: 1.006 | G115: 900
A117: EHV site specific LLFs
A118: Generation
A119: Site | B119: Period 1 | C119: Period 2 | D119: Period 3 | E119: Period 4 | F119: Period 5 | G119: Associated LLFC
A120: THAMEM - Export | B120: 1.059 | C120: 1.043 | D120: 1.052 | E120: 1.037 | F120: 1.045 | G120: 691
A121: TWHK66 - Export | B121: 1.059 | C121: 1.043 | D121: 1.052 | E121: 1.037 | F121: 1.045 | G121: 692
A122: BEDERF - Export | B122: 0.998 | C122: 1 | D122: 0.997 | E122: 0.997 | F122: 0.997 | G122: 693
A123: BESAYL - Export | B123: 0.999 | C123: 1 | D123: 1 | E123: 1 | F123: 1 | G123: 694
A124: BRAMBS - Export | B124: 1.001 | C124: 1 | D124: 1 | E124: 0.997 | F124: 1 | G124: 695
A125: BRELLE - Export | B125: 0.999 | C125: 0.998 | D125: 0.999 | E125: 0.999 | F125: 0.999 | G125: 696
A126: GLASSN - Export | B126: 0.993 | C126: 0.999 | D126: 0.999 | E126: 0.999 | F126: 0.999 | G126: 697
A127: NEWRID - Export | B127: 1 | C127: 0.999 | D127: 1 | E127: 1 | F127: 1 | G127: 698
A128: KM3CHP - Export | B128: 1.006 | C128: 1.005 | D128: 1.006 | E128: 1.004 | F128: 1.005 | G128: 699
A129: NEWHVN - Export | B129: 1.014 | C129: 1.009 | D129: 1.013 | E129: 1.009 | F129: 1.011 | G129: 700
A130: HORAMS - Export | B130: 1.056 | C130: 1.037 | D130: 1.037 | E130: 1.03 | F130: 1.045 | G130: 701
A131: WDLNDS - Export | B131: 1 | C131: 0.994 | D131: 0.996 | E131: 0.999 | F131: 0.995 | G131: 702
... A183: SOLEES - Export | B183: 0.999 | C183: 0.994 | D183: 0.996 | E183: 0.999 | F183: 0.995 | G183: 755
A185: CVA site specific LLFs
A186: MSID | B186: Site | C186: Period 1 | D186: Period 2 | E186: Period 3 | F186: Period 4 | G186: Period 5
A187: 1032 | B187: Dartford _J DSCP | C187: 1.018 | D187: 1.014 | E187: 1.017 | F187: 1.013 | G187: 1.015
A188: 1630 | B188: Bromley DSCP | C188: 1.006 | D188: 1.005 | E188: 1.006 | F188: 1.005 | G188: 1.006
A189: 7104 | B189: Shoreham Power Station - Export | C189: 1.004 | D189: 1 | E189: 1.003 | F189: 1 | G189: 1.003
A190: 7105 | B190: Shoreham Power Station - Import | C190: 1.057 | D190: 1.042 | E190: 1.051 | F190: 1.036 | G190: 1.044
A191: 7160 | B191: Sevington District Energy | C191: 1.059 | D191: 1.043 | E191: 1.052 | F191: 1.037 | G191: 1.045
A192: 7425 | B192: Contego BESS | C192: 1.019 | D192: 1.015 | E192: 1.017 | F192: 1.014 | G192: 1.016
A193: 7436 | B193: Contego BESS | C193: 1.019 | D193: 1.015 | E193: 1.017 | F193: 1.014 | G193: 1.016

Sheet Annex 6 New or Amended EHV
A1: Back to Overview | H1: Note: The list of MPANs/MSIDs provided may be incomplete; the DNO reserves the right to apply the listed charges to any other MPANs/MSIDs associated with the site. If sites appear in both Annex 2 and Annex 6, the charges in Annex 6 take precedence. Where an existing Designated EHV Property is modified and energised in the charging year, we may revise the EDCM charges for the modified Designated EHV Property.
A2: Annex 6 - Charges for New or Amended Designated EHV Properties
A4: =Overview!B4& " - Effective from "&Overview!D4&" - "&Overview!E4&" new designated EHV charges" -> South Eastern Power Networks - Effective from 1 April 2021 - Final new designated EHV charges
A5: Effective from date | B5: Import Unique Identifier | C5: LLFC | D5: Import MPANs/MSIDs | E5: Export Unique Identifier | F5: LLFC | G5: Export MPANs/MSIDs | H5: Name | I5: ='Annex 2 EHV charges'!H9 -> Import Super Red unit charge (p/kWh) | J5: ='Annex 2 EHV charges'!I9 -> Import fixed charge (p/day) | K5: ='Annex 2 EHV charges'!J9 -> Import capacity charge (p/kVA/day) | L5: ='Annex 2 EHV charges'!K9 -> Import exceeded capacity charge (p/kVA/day) | M5: ='Annex 2 EHV charges'!L9 -> Export Super Red unit charge (p/kWh) | N5: ='Annex 2 EHV charges'!M9 -> Export fixed charge (p/day) | O5: ='Annex 2 EHV charges'!N9 -> Export capacity charge (p/kVA/day) | P5: ='Annex 2 EHV charges'!O9 -> Export exceeded capacity charge (p/kVA/day)
A6: 44287 | B6: ANMSTR | C6: 873 | D6: 1900091919588 | E6: ANMSTR | F6: 780 | G6: 1900091919597 | H6: ANMSTR | I6: 0.732 | J6: 35.87 | K6: 1.78 | L6: 1.78 | M6: -1.238 | N6: 956.47 | O6: 0.05 | P6: 0.05
A7: 44287 | B7: GLASSN | C7: 844 | D7: 1900091523301 | E7: GLASSN | F7: 697 | G7: 1900091523310 | H7: GLASSN | I7: 0 | J7: 384.06 | K7: 0.67 | L7: 0.67 | M7: 0 | N7: 384.06 | O7: 0.05 | P7: 0.05
A8: 44287 | B8: KNTSFM | D8: MSID: 7425 | E8: KNTSFM | G8: MSID: 7436 | H8: KNTSFM | I8: 2.872 | J8: 738.2 | K8: 1.05 | L8: 1.05 | M8: -2.884 | N8: 777.28 | O8: 0.05 | P8: 0.05
A9: 44378 | B9: KNTSFM | D9: MSID: 7425 | E9: KNTSFM | G9: MSID: 7436 | H9: KNTSFM | I9: 2.872 | J9: 737.74 | K9: 0.69 | L9: 0.69 | M9: -2.884 | N9: 776.79 | O9: 0.05 | P9: 0.05
A10: 44409 | B10: BESAYL | C10: 841 | D10: 1900091632775 | E10: BESAYL | F10: 694 | G10: 1900091632784 | H10: BESAYL | I10: 0.168 | J10: 345.23 | K10: 0.57 | L10: 0.57 | M10: -0.209 | N10: 345.23 | O10: 0.05 | P10: 0.05
A11: 44409 | B11: BRAMBS | C11: 842 | D11: 1900091566810 | E11: BRAMBS | F11: 695 | G11: 1900091566820 | H11: BRAMBS | I11: 0.075 | J11: 345.23 | K11: 0.83 | L11: 0.83 | M11: -0.085 | N11: 345.23 | O11: 0.05 | P11: 0.05
A17: =Overview!B4& " - Effective from "&Overview!D4&" - "&Overview!E4&" new designated EHV line loss factors" -> South Eastern Power Networks - Effective from 1 April 2021 - Final new designated EHV line loss factors
A18: Effective from date | B18: Import Unique Identifier | C18: LLFC | D18: Import MPANs/MSIDs | E18: Export Unique Identifier | F18: LLFC | G18: Export MPANs/MSIDs | H18: Name | I18: Import LLF period 1 | J18: Import LLF period 2 | K18: Import LLF period 3 | L18: Import LLF period 4 | M18: Import LLF period 5 | N18: Export LLF period 1 | O18: Export LLF period 2 | P18: Export LLF period 3 | Q18: Export LLF period 4 | R18: Export LLF period 5
A19: 44287 | B19: ANMSTR | C19: 873 | D19: 1900091919588 | E19: ANMSTR | F19: 780 | G19: 1900091919597 | H19: ANMSTR | I19: 1.019 | J19: 1.015 | K19: 1.017 | L19: 1.014 | M19: 1.016 | N19: 1.019 | O19: 1.015 | P19: 1.017 | Q19: 1.014 | R19: 1.016
A20: 44287 | B20: KNTSFM | C20: 907 | D20: 1900092045475 | E20: KNTSFM | F20: 768 | G20: 1900092045484 | H20: KNTSFM | I20: 1.019 | J20: 1.015 | K20: 1.017 | L20: 1.014 | M20: 1.016 | N20: 1.019 | O20: 1.015 | P20: 1.017 | Q20: 1.014 | R20: 1.016

Sheet Annex 7 Pass-Through Costs
A1: Back to Overview
A2: =Overview!B4& " - Effective from "&Overview!D4&" - "&Overview!E4&" Supplier of Last Resort and Eligible Bad Debt Pass-Through Costs" -> South Eastern Power Networks - Effective from 1 April 2021 - Final Supplier of Last Resort and Eligible Bad Debt Pass-Through Costs
A4: Tariff name | B4: Open LLFCs / LDNO unique billing identifier | C4: PCs | D4: Supplier of Last Resort Fixed charge adder* p/MPAN/day | E4: Excess Supplier of Last Resort Fixed charge adder** p/MPAN/day | F4: Eligible Bad Debt Fixed charge adder*** p/MPAN/day
A5: Domestic Aggregated | B5: =IFERROR(INDEX('Annex 1 LV, HV and UMS charges'!$B$12:$B$30,MATCH($A5,'Annex 1 LV, HV and UMS charges'!$A$12:$A$295,0)),INDEX('Annex 4 LDNO charges'!$B$12:$B$116,MATCH($A5,'Annex 4 LDNO charges'!$A$12:$A$116,0))) -> 1, 100, 300 | C5: =IFERROR(INDEX('Annex 1 LV, HV and UMS charges'!$C$12:$C$30,MATCH($A5,'Annex 1 LV, HV and UMS charges'!$A$12:$A$295,0)),INDEX('Annex 4 LDNO charges'!$C$12:$C$116,MATCH($A5,'Annex 4 LDNO charges'!$A$12:$A$116,0))) -> 1, 2 or 0 | D5: 0.0079313589 | F5: 0.18871621
A6: Non-Domestic Aggregated | B6: =IFERROR(INDEX('Annex 1 LV, HV and UMS charges'!$B$12:$B$30,MATCH($A6,'Annex 1 LV, HV and UMS charges'!$A$12:$A$295,0)),INDEX('Annex 4 LDNO charges'!$B$12:$B$116,MATCH($A6,'Annex 4 LDNO charges'!$A$12:$A$116,0))) -> 120, 200, 201, 202, 203, 204, 320, 480 | C6: =IFERROR(INDEX('Annex 1 LV, HV and UMS charges'!$C$12:$C$30,MATCH($A6,'Annex 1 LV, HV and UMS charges'!$A$12:$A$295,0)),INDEX('Annex 4 LDNO charges'!$C$12:$C$116,MATCH($A6,'Annex 4 LDNO charges'!$A$12:$A$116,0))) -> 3-8 or 0 | F6: 0.18871621
A7: LV Site Specific | B7: =IFERROR(INDEX('Annex 1 LV, HV and UMS charges'!$B$12:$B$30,MATCH($A7,'Annex 1 LV, HV and UMS charges'!$A$12:$A$295,0)),INDEX('Annex 4 LDNO charges'!$B$12:$B$116,MATCH($A7,'Annex 4 LDNO charges'!$A$12:$A$116,0))) -> 71, 72, 73, 74, 550 | C7: =IFERROR(INDEX('Annex 1 LV, HV and UMS charges'!$C$12:$C$30,MATCH($A7,'Annex 1 LV, HV and UMS charges'!$A$12:$A$295,0)),INDEX('Annex 4 LDNO charges'!$C$12:$C$116,MATCH($A7,'Annex 4 LDNO charges'!$A$12:$A$116,0))) -> 0 | F7: 0.18871621
A8: LV Sub Site Specific | B8: =IFERROR(INDEX('Annex 1 LV, HV and UMS charges'!$B$12:$B$30,MATCH($A8,'Annex 1 LV, HV and UMS charges'!$A$12:$A$295,0)),INDEX('Annex 4 LDNO charges'!$B$12:$B$116,MATCH($A8,'Annex 4 LDNO charges'!$A$12:$A$116,0))) -> 81, 82, 83, 84, 756 | C8: =IFERROR(INDEX('Annex 1 LV, HV and UMS charges'!$C$12:$C$30,MATCH($A8,'Annex 1 LV, HV and UMS charges'!$A$12:$A$295,0)),INDEX('Annex 4 LDNO charges'!$C$12:$C$116,MATCH($A8,'Annex 4 LDNO charges'!$A$12:$A$116,0))) -> 0 | F8: 0.18871621
A9: HV Site Specific | B9: =IFERROR(INDEX('Annex 1 LV, HV and UMS charges'!$B$12:$B$30,MATCH($A9,'Annex 1 LV, HV and UMS charges'!$A$12:$A$295,0)),INDEX('Annex 4 LDNO charges'!$B$12:$B$116,MATCH($A9,'Annex 4 LDNO charges'!$A$12:$A$116,0))) -> 91, 92, 93, 94, 650 | C9: =IFERROR(INDEX('Annex 1 LV, HV and UMS charges'!$C$12:$C$30,MATCH($A9,'Annex 1 LV, HV and UMS charges'!$A$12:$A$295,0)),INDEX('Annex 4 LDNO charges'!$C$12:$C$116,MATCH($A9,'Annex 4 LDNO charges'!$A$12:$A$116,0))) -> 0 | F9: 0.18871621
A10: LV Site Specific Storage Import | B10: =IFERROR(INDEX('Annex 1 LV, HV and UMS charges'!$B$12:$B$30,MATCH($A10,'Annex 1 LV, HV and UMS charges'!$A$12:$A$295,0)),INDEX('Annex 4 LDNO charges'!$B$12:$B$116,MATCH($A10,'Annex 4 LDNO charges'!$A$12:$A$116,0))) -> 19, 70 | C10: =IFERROR(INDEX('Annex 1 LV, HV and UMS charges'!$C$12:$C$30,MATCH($A10,'Annex 1 LV, HV and UMS charges'!$A$12:$A$295,0)),INDEX('Annex 4 LDNO charges'!$C$12:$C$116,MATCH($A10,'Annex 4 LDNO charges'!$A$12:$A$116,0))) -> 0 | F10: 0.18871621
A11: LV Sub Site Specific Storage Import | B11: =IFERROR(INDEX('Annex 1 LV, HV and UMS charges'!$B$12:$B$30,MATCH($A11,'Annex 1 LV, HV and UMS charges'!$A$12:$A$295,0)),INDEX('Annex 4 LDNO charges'!$B$12:$B$116,MATCH($A11,'Annex 4 LDNO charges'!$A$12:$A$116,0))) -> 79, 80 | C11: =IFERROR(INDEX('Annex 1 LV, HV and UMS charges'!$C$12:$C$30,MATCH($A11,'Annex 1 LV, HV and UMS charges'!$A$12:$A$295,0)),INDEX('Annex 4 LDNO charges'!$C$12:$C$116,MATCH($A11,'Annex 4 LDNO charges'!$A$12:$A$116,0))) -> 0 | F11: 0.18871621
A12: HV Site Specific Storage Import | B12: =IFERROR(INDEX('Annex 1 LV, HV and UMS charges'!$B$12:$B$30,MATCH($A12,'Annex 1 LV, HV and UMS charges'!$A$12:$A$295,0)),INDEX('Annex 4 LDNO charges'!$B$12:$B$116,MATCH($A12,'Annex 4 LDNO charges'!$A$12:$A$116,0))) -> 89, 90 | C12: =IFERROR(INDEX('Annex 1 LV, HV and UMS charges'!$C$12:$C$30,MATCH($A12,'Annex 1 LV, HV and UMS charges'!$A$12:$A$295,0)),INDEX('Annex 4 LDNO charges'!$C$12:$C$116,MATCH($A12,'Annex 4 LDNO charges'!$A$12:$A$116,0))) -> 0 | F12: 0.18871621
A13: LDNO LV: Domestic Aggregated | B13: =IFERROR(INDEX('Annex 1 LV, HV and UMS charges'!$B$12:$B$30,MATCH($A13,'Annex 1 LV, HV and UMS charges'!$A$12:$A$295,0)),INDEX('Annex 4 LDNO charges'!$B$12:$B$116,MATCH($A13,'Annex 4 LDNO charges'!$A$12:$A$116,0))) -> A00 | C13: =IFERROR(INDEX('Annex 1 LV, HV and UMS charges'!$C$12:$C$30,MATCH($A13,'Annex 1 LV, HV and UMS charges'!$A$12:$A$295,0)),INDEX('Annex 4 LDNO charges'!$C$12:$C$116,MATCH($A13,'Annex 4 LDNO charges'!$A$12:$A$116,0))) -> 1, 2 or 0 | D13: 0.0079313589 | F13: 0.18871621
A14: LDNO LV: Non-Domestic Aggregated | B14: =IFERROR(INDEX('Annex 1 LV, HV and UMS charges'!$B$12:$B$30,MATCH($A14,'Annex 1 LV, HV and UMS charges'!$A$12:$A$295,0)),INDEX('Annex 4 LDNO charges'!$B$12:$B$116,MATCH($A14,'Annex 4 LDNO charges'!$A$12:$A$116,0))) -> C00, C01, C02, C03, C04 | C14: =IFERROR(INDEX('Annex 1 LV, HV and UMS charges'!$C$12:$C$30,MATCH($A14,'Annex 1 LV, HV and UMS charges'!$A$12:$A$295,0)),INDEX('Annex 4 LDNO charges'!$C$12:$C$116,MATCH($A14,'Annex 4 LDNO charges'!$A$12:$A$116,0))) -> 3-8 or 0 | F14: 0.18871621
A15: LDNO LV: LV Site Specific | B15: =IFERROR(INDEX('Annex 1 LV, HV and UMS charges'!$B$12:$B$30,MATCH($A15,'Annex 1 LV, HV and UMS charges'!$A$12:$A$295,0)),INDEX('Annex 4 LDNO charges'!$B$12:$B$116,MATCH($A15,'Annex 4 LDNO charges'!$A$12:$A$116,0))) -> E01, E02, E03, E04 | C15: =IFERROR(INDEX('Annex 1 LV, HV and UMS charges'!$C$12:$C$30,MATCH($A15,'Annex 1 LV, HV and UMS charges'!$A$12:$A$295,0)),INDEX('Annex 4 LDNO charges'!$C$12:$C$116,MATCH($A15,'Annex 4 LDNO charges'!$A$12:$A$116,0))) -> 0 | F15: 0.18871621
A16: LDNO LV: LV Site Specific Storage Import | B16: =IFERROR(INDEX('Annex 1 LV, HV and UMS charges'!$B$12:$B$30,MATCH($A16,'Annex 1 LV, HV and UMS charges'!$A$12:$A$295,0)),INDEX('Annex 4 LDNO charges'!$B$12:$B$116,MATCH($A16,'Annex 4 LDNO charges'!$A$12:$A$116,0))) -> E00 | C16: =IFERROR(INDEX('Annex 1 LV, HV and UMS charges'!$C$12:$C$30,MATCH($A16,'Annex 1 LV, HV and UMS charges'!$A$12:$A$295,0)),INDEX('Annex 4 LDNO charges'!$C$12:$C$116,MATCH($A16,'Annex 4 LDNO charges'!$A$12:$A$116,0))) -> 0 | F16: 0.18871621
A17: LDNO HV: Domestic Aggregated | B17: =IFERROR(INDEX('Annex 1 LV, HV and UMS charges'!$B$12:$B$30,MATCH($A17,'Annex 1 LV, HV and UMS charges'!$A$12:$A$295,0)),INDEX('Annex 4 LDNO charges'!$B$12:$B$116,MATCH($A17,'Annex 4 LDNO charges'!$A$12:$A$116,0))) -> A10 | C17: =IFERROR(INDEX('Annex 1 LV, HV and UMS charges'!$C$12:$C$30,MATCH($A17,'Annex 1 LV, HV and UMS charges'!$A$12:$A$295,0)),INDEX('Annex 4 LDNO charges'!$C$12:$C$116,MATCH($A17,'Annex 4 LDNO charges'!$A$12:$A$116,0))) -> 1, 2 or 0 | D17: 0.0079313589 | F17: 0.18871621
A18: LDNO HV: Non-Domestic Aggregated | B18: =IFERROR(INDEX('Annex 1 LV, HV and UMS charges'!$B$12:$B$30,MATCH($A18,'Annex 1 LV, HV and UMS charges'!$A$12:$A$295,0)),INDEX('Annex 4 LDNO charges'!$B$12:$B$116,MATCH($A18,'Annex 4 LDNO charges'!$A$12:$A$116,0))) -> C10, C11, C12, C13, C14 | C18: =IFERROR(INDEX('Annex 1 LV, HV and UMS charges'!$C$12:$C$30,MATCH($A18,'Annex 1 LV, HV and UMS charges'!$A$12:$A$295,0)),INDEX('Annex 4 LDNO charges'!$C$12:$C$116,MATCH($A18,'Annex 4 LDNO charges'!$A$12:$A$116,0))) -> 3-8 or 0 | F18: 0.18871621
A19: LDNO HV: LV Site Specific | B19: =IFERROR(INDEX('Annex 1 LV, HV and UMS charges'!$B$12:$B$30,MATCH($A19,'Annex 1 LV, HV and UMS charges'!$A$12:$A$295,0)),INDEX('Annex 4 LDNO charges'!$B$12:$B$116,MATCH($A19,'Annex 4 LDNO charges'!$A$12:$A$116,0))) -> E11, E12, E13, E14 | C19: =IFERROR(INDEX('Annex 1 LV, HV and UMS charges'!$C$12:$C$30,MATCH($A19,'Annex 1 LV, HV and UMS charges'!$A$12:$A$295,0)),INDEX('Annex 4 LDNO charges'!$C$12:$C$116,MATCH($A19,'Annex 4 LDNO charges'!$A$12:$A$116,0))) -> 0 | F19: 0.18871621
A20: LDNO HV: LV Sub Site Specific | B20: =IFERROR(INDEX('Annex 1 LV, HV and UMS charges'!$B$12:$B$30,MATCH($A20,'Annex 1 LV, HV and UMS charges'!$A$12:$A$295,0)),INDEX('Annex 4 LDNO charges'!$B$12:$B$116,MATCH($A20,'Annex 4 LDNO charges'!$A$12:$A$116,0))) -> J11, J12, J13, J14 | C20: =IFERROR(INDEX('Annex 1 LV, HV and UMS charges'!$C$12:$C$30,MATCH($A20,'Annex 1 LV, HV and UMS charges'!$A$12:$A$295,0)),INDEX('Annex 4 LDNO charges'!$C$12:$C$116,MATCH($A20,'Annex 4 LDNO charges'!$A$12:$A$116,0))) -> 0 | F20: 0.18871621
A21: LDNO HV: HV Site Specific | B21: =IFERROR(INDEX('Annex 1 LV, HV and UMS charges'!$B$12:$B$30,MATCH($A21,'Annex 1 LV, HV and UMS charges'!$A$12:$A$295,0)),INDEX('Annex 4 LDNO charges'!$B$12:$B$116,MATCH($A21,'Annex 4 LDNO charges'!$A$12:$A$116,0))) -> K11, K12, K13, K14 | C21: =IFERROR(INDEX('Annex 1 LV, HV and UMS charges'!$C$12:$C$30,MATCH($A21,'Annex 1 LV, HV and UMS charges'!$A$12:$A$295,0)),INDEX('Annex 4 LDNO charges'!$C$12:$C$116,MATCH($A21,'Annex 4 LDNO charges'!$A$12:$A$116,0))) -> 0 | F21: 0.18871621
A22: LDNO HV: LV Site Specific Storage Import | B22: =IFERROR(INDEX('Annex 1 LV, HV and UMS charges'!$B$12:$B$30,MATCH($A22,'Annex 1 LV, HV and UMS charges'!$A$12:$A$295,0)),INDEX('Annex 4 LDNO charges'!$B$12:$B$116,MATCH($A22,'Annex 4 LDNO charges'!$A$12:$A$116,0))) -> E10 | C22: =IFERROR(INDEX('Annex 1 LV, HV and UMS charges'!$C$12:$C$30,MATCH($A22,'Annex 1 LV, HV and UMS charges'!$A$12:$A$295,0)),INDEX('Annex 4 LDNO charges'!$C$12:$C$116,MATCH($A22,'Annex 4 LDNO charges'!$A$12:$A$116,0))) -> 0 | F22: 0.18871621
A23: LDNO HV: LV Sub Site Specific Storage Import | B23: =IFERROR(INDEX('Annex 1 LV, HV and UMS charges'!$B$12:$B$30,MATCH($A23,'Annex 1 LV, HV and UMS charges'!$A$12:$A$295,0)),INDEX('Annex 4 LDNO charges'!$B$12:$B$116,MATCH($A23,'Annex 4 LDNO charges'!$A$12:$A$116,0))) -> J10 | C23: =IFERROR(INDEX('Annex 1 LV, HV and UMS charges'!$C$12:$C$30,MATCH($A23,'Annex 1 LV, HV and UMS charges'!$A$12:$A$295,0)),INDEX('Annex 4 LDNO charges'!$C$12:$C$116,MATCH($A23,'Annex 4 LDNO charges'!$A$12:$A$116,0))) -> 0 | F23: 0.18871621
A24: LDNO HV: HV Site Specific Storage Import | B24: =IFERROR(INDEX('Annex 1 LV, HV and UMS charges'!$B$12:$B$30,MATCH($A24,'Annex 1 LV, HV and UMS charges'!$A$12:$A$295,0)),INDEX('Annex 4 LDNO charges'!$B$12:$B$116,MATCH($A24,'Annex 4 LDNO charges'!$A$12:$A$116,0))) -> K10 | C24: =IFERROR(INDEX('Annex 1 LV, HV and UMS charges'!$C$12:$C$30,MATCH($A24,'Annex 1 LV, HV and UMS charges'!$A$12:$A$295,0)),INDEX('Annex 4 LDNO charges'!$C$12:$C$116,MATCH($A24,'Annex 4 LDNO charges'!$A$12:$A$116,0))) -> 0 | F24: 0.18871621
A25: LDNO HVplus: Domestic Aggregated | B25: =IFERROR(INDEX('Annex 1 LV, HV and UMS charges'!$B$12:$B$30,MATCH($A25,'Annex 1 LV, HV and UMS charges'!$A$12:$A$295,0)),INDEX('Annex 4 LDNO charges'!$B$12:$B$116,MATCH($A25,'Annex 4 LDNO charges'!$A$12:$A$116,0))) -> A20 | C25: =IFERROR(INDEX('Annex 1 LV, HV and UMS charges'!$C$12:$C$30,MATCH($A25,'Annex 1 LV, HV and UMS charges'!$A$12:$A$295,0)),INDEX('Annex 4 LDNO charges'!$C$12:$C$116,MATCH($A25,'Annex 4 LDNO charges'!$A$12:$A$116,0))) -> 1, 2 or 0 | D25: 0.0079313589 | F25: 0.18871621
A26: LDNO HVplus: Non-Domestic Aggregated | B26: =IFERROR(INDEX('Annex 1 LV, HV and UMS charges'!$B$12:$B$30,MATCH($A26,'Annex 1 LV, HV and UMS charges'!$A$12:$A$295,0)),INDEX('Annex 4 LDNO charges'!$B$12:$B$116,MATCH($A26,'Annex 4 LDNO charges'!$A$12:$A$116,0))) -> C20, C21, C22, C23, C24 | C26: =IFERROR(INDEX('Annex 1 LV, HV and UMS charges'!$C$12:$C$30,MATCH($A26,'Annex 1 LV, HV and UMS charges'!$A$12:$A$295,0)),INDEX('Annex 4 LDNO charges'!$C$12:$C$116,MATCH($A26,'Annex 4 LDNO charges'!$A$12:$A$116,0))) -> 3-8 or 0 | F26: 0.18871621
A27: LDNO HVplus: LV Site Specific | B27: =IFERROR(INDEX('Annex 1 LV, HV and UMS charges'!$B$12:$B$30,MATCH($A27,'Annex 1 LV, HV and UMS charges'!$A$12:$A$295,0)),INDEX('Annex 4 LDNO charges'!$B$12:$B$116,MATCH($A27,'Annex 4 LDNO charges'!$A$12:$A$116,0))) -> E21, E22, E23, E24 | C27: =IFERROR(INDEX('Annex 1 LV, HV and UMS charges'!$C$12:$C$30,MATCH($A27,'Annex 1 LV, HV and UMS charges'!$A$12:$A$295,0)),INDEX('Annex 4 LDNO charges'!$C$12:$C$116,MATCH($A27,'Annex 4 LDNO charges'!$A$12:$A$116,0))) -> 0 | F27: 0.18871621
A28: LDNO HVplus: LV Sub Site Specific | B28: =IFERROR(INDEX('Annex 1 LV, HV and UMS charges'!$B$12:$B$30,MATCH($A28,'Annex 1 LV, HV and UMS charges'!$A$12:$A$295,0)),INDEX('Annex 4 LDNO charges'!$B$12:$B$116,MATCH($A28,'Annex 4 LDNO charges'!$A$12:$A$116,0))) -> J21, J22, J23, J24 | C28: =IFERROR(INDEX('Annex 1 LV, HV and UMS charges'!$C$12:$C$30,MATCH($A28,'Annex 1 LV, HV and UMS charges'!$A$12:$A$295,0)),INDEX('Annex 4 LDNO charges'!$C$12:$C$116,MATCH($A28,'Annex 4 LDNO charges'!$A$12:$A$116,0))) -> 0 | F28: 0.18871621
A29: LDNO HVplus: HV Site Specific | B29: =IFERROR(INDEX('Annex 1 LV, HV and UMS charges'!$B$12:$B$30,MATCH($A29,'Annex 1 LV, HV and UMS charges'!$A$12:$A$295,0)),INDEX('Annex 4 LDNO charges'!$B$12:$B$116,MATCH($A29,'Annex 4 LDNO charges'!$A$12:$A$116,0))) -> K21, K22, K23, K24 | C29: =IFERROR(INDEX('Annex 1 LV, HV and UMS charges'!$C$12:$C$30,MATCH($A29,'Annex 1 LV, HV and UMS charges'!$A$12:$A$295,0)),INDEX('Annex 4 LDNO charges'!$C$12:$C$116,MATCH($A29,'Annex 4 LDNO charges'!$A$12:$A$116,0))) -> 0 | F29: 0.18871621
A30: LDNO HVplus: LV Site Specific Storage Import | B30: =IFERROR(INDEX('Annex 1 LV, HV and UMS charges'!$B$12:$B$30,MATCH($A30,'Annex 1 LV, HV and UMS charges'!$A$12:$A$295,0)),INDEX('Annex 4 LDNO charges'!$B$12:$B$116,MATCH($A30,'Annex 4 LDNO charges'!$A$12:$A$116,0))) -> E20 | C30: =IFERROR(INDEX('Annex 1 LV, HV and UMS charges'!$C$12:$C$30,MATCH($A30,'Annex 1 LV, HV and UMS charges'!$A$12:$A$295,0)),INDEX('Annex 4 LDNO charges'!$C$12:$C$116,MATCH($A30,'Annex 4 LDNO charges'!$A$12:$A$116,0))) -> 0 | F30: 0.18871621
A31: LDNO HVplus: LV Sub Site Specific Storage Import | B31: =IFERROR(INDEX('Annex 1 LV, HV and UMS charges'!$B$12:$B$30,MATCH($A31,'Annex 1 LV, HV and UMS charges'!$A$12:$A$295,0)),INDEX('Annex 4 LDNO charges'!$B$12:$B$116,MATCH($A31,'Annex 4 LDNO charges'!$A$12:$A$116,0))) -> J20 | C31: =IFERROR(INDEX('Annex 1 LV, HV and UMS charges'!$C$12:$C$30,MATCH($A31,'Annex 1 LV, HV and UMS charges'!$A$12:$A$295,0)),INDEX('Annex 4 LDNO charges'!$C$12:$C$116,MATCH($A31,'Annex 4 LDNO charges'!$A$12:$A$116,0))) -> 0 | F31: 0.18871621
A32: LDNO HVplus: HV Site Specific Storage Import | B32: =IFERROR(INDEX('Annex 1 LV, HV and UMS charges'!$B$12:$B$30,MATCH($A32,'Annex 1 LV, HV and UMS charges'!$A$12:$A$295,0)),INDEX('Annex 4 LDNO charges'!$B$12:$B$116,MATCH($A32,'Annex 4 LDNO charges'!$A$12:$A$116,0))) -> K20 | C32: =IFERROR(INDEX('Annex 1 LV, HV and UMS charges'!$C$12:$C$30,MATCH($A32,'Annex 1 LV, HV and UMS charges'!$A$12:$A$295,0)),INDEX('Annex 4 LDNO charges'!$C$12:$C$116,MATCH($A32,'Annex 4 LDNO charges'!$A$12:$A$116,0))) -> 0 | F32: 0.18871621
A33: LDNO EHV: Domestic Aggregated | B33: =IFERROR(INDEX('Annex 1 LV, HV and UMS charges'!$B$12:$B$30,MATCH($A33,'Annex 1 LV, HV and UMS charges'!$A$12:$A$295,0)),INDEX('Annex 4 LDNO charges'!$B$12:$B$116,MATCH($A33,'Annex 4 LDNO charges'!$A$12:$A$116,0))) -> A30 | C33: =IFERROR(INDEX('Annex 1 LV, HV and UMS charges'!$C$12:$C$30,MATCH($A33,'Annex 1 LV, HV and UMS charges'!$A$12:$A$295,0)),INDEX('Annex 4 LDNO charges'!$C$12:$C$116,MATCH($A33,'Annex 4 LDNO charges'!$A$12:$A$116,0))) -> 1, 2 or 0 | D33: 0.0079313589 | F33: 0.18871621
A34: LDNO EHV: Non-Domestic Aggregated | B34: =IFERROR(INDEX('Annex 1 LV, HV and UMS charges'!$B$12:$B$30,MATCH($A34,'Annex 1 LV, HV and UMS charges'!$A$12:$A$295,0)),INDEX('Annex 4 LDNO charges'!$B$12:$B$116,MATCH($A34,'Annex 4 LDNO charges'!$A$12:$A$116,0))) -> C30, C31, C32, C33, C34 | C34: =IFERROR(INDEX('Annex 1 LV, HV and UMS charges'!$C$12:$C$30,MATCH($A34,'Annex 1 LV, HV and UMS charges'!$A$12:$A$295,0)),INDEX('Annex 4 LDNO charges'!$C$12:$C$116,MATCH($A34,'Annex 4 LDNO charges'!$A$12:$A$116,0))) -> 3-8 or 0 | F34: 0.18871621
A35: LDNO EHV: LV Site Specific | B35: =IFERROR(INDEX('Annex 1 LV, HV and UMS charges'!$B$12:$B$30,MATCH($A35,'Annex 1 LV, HV and UMS charges'!$A$12:$A$295,0)),INDEX('Annex 4 LDNO charges'!$B$12:$B$116,MATCH($A35,'Annex 4 LDNO charges'!$A$12:$A$116,0))) -> E31, E32, E33, E34 | C35: =IFERROR(INDEX('Annex 1 LV, HV and UMS charges'!$C$12:$C$30,MATCH($A35,'Annex 1 LV, HV and UMS charges'!$A$12:$A$295,0)),INDEX('Annex 4 LDNO charges'!$C$12:$C$116,MATCH($A35,'Annex 4 LDNO charges'!$A$12:$A$116,0))) -> 0 | F35: 0.18871621
A36: LDNO EHV: LV Sub Site Specific | B36: =IFERROR(INDEX('Annex 1 LV, HV and UMS charges'!$B$12:$B$30,MATCH($A36,'Annex 1 LV, HV and UMS charges'!$A$12:$A$295,0)),INDEX('Annex 4 LDNO charges'!$B$12:$B$116,MATCH($A36,'Annex 4 LDNO charges'!$A$12:$A$116,0))) -> J31, J32, J33, J34 | C36: =IFERROR(INDEX('Annex 1 LV, HV and UMS charges'!$C$12:$C$30,MATCH($A36,'Annex 1 LV, HV and UMS charges'!$A$12:$A$295,0)),INDEX('Annex 4 LDNO charges'!$C$12:$C$116,MATCH($A36,'Annex 4 LDNO charges'!$A$12:$A$116,0))) -> 0 | F36: 0.18871621
A37: LDNO EHV: HV Site Specific | B37: =IFERROR(INDEX('Annex 1 LV, HV and UMS charges'!$B$12:$B$30,MATCH($A37,'Annex 1 LV, HV and UMS charges'!$A$12:$A$295,0)),INDEX('Annex 4 LDNO charges'!$B$12:$B$116,MATCH($A37,'Annex 4 LDNO charges'!$A$12:$A$116,0))) -> K31, K32, K33, K34 | C37: =IFERROR(INDEX('Annex 1 LV, HV and UMS charges'!$C$12:$C$30,MATCH($A37,'Annex 1 LV, HV and UMS charges'!$A$12:$A$295,0)),INDEX('Annex 4 LDNO charges'!$C$12:$C$116,MATCH($A37,'Annex 4 LDNO charges'!$A$12:$A$116,0))) -> 0 | F37: 0.18871621
A38: LDNO EHV: LV Site Specific Storage Import | B38: =IFERROR(INDEX('Annex 1 LV, HV and UMS charges'!$B$12:$B$30,MATCH($A38,'Annex 1 LV, HV and UMS charges'!$A$12:$A$295,0)),INDEX('Annex 4 LDNO charges'!$B$12:$B$116,MATCH($A38,'Annex 4 LDNO charges'!$A$12:$A$116,0))) -> E30 | C38: =IFERROR(INDEX('Annex 1 LV, HV and UMS charges'!$C$12:$C$30,MATCH($A38,'Annex 1 LV, HV and UMS charges'!$A$12:$A$295,0)),INDEX('Annex 4 LDNO charges'!$C$12:$C$116,MATCH($A38,'Annex 4 LDNO charges'!$A$12:$A$116,0))) -> 0 | F38: 0.18871621
A39: LDNO EHV: LV Sub Site Specific Storage Import | B39: =IFERROR(INDEX('Annex 1 LV, HV and UMS charges'!$B$12:$B$30,MATCH($A39,'Annex 1 LV, HV and UMS charges'!$A$12:$A$295,0)),INDEX('Annex 4 LDNO charges'!$B$12:$B$116,MATCH($A39,'Annex 4 LDNO charges'!$A$12:$A$116,0))) -> J30 | C39: =IFERROR(INDEX('Annex 1 LV, HV and UMS charges'!$C$12:$C$30,MATCH($A39,'Annex 1 LV, HV and UMS charges'!$A$12:$A$295,0)),INDEX('Annex 4 LDNO charges'!$C$12:$C$116,MATCH($A39,'Annex 4 LDNO charges'!$A$12:$A$116,0))) -> 0 | F39: 0.18871621
A40: LDNO EHV: HV Site Specific Storage Import | B40: =IFERROR(INDEX('Annex 1 LV, HV and UMS charges'!$B$12:$B$30,MATCH($A40,'Annex 1 LV, HV and UMS charges'!$A$12:$A$295,0)),INDEX('Annex 4 LDNO charges'!$B$12:$B$116,MATCH($A40,'Annex 4 LDNO charges'!$A$12:$A$116,0))) -> K30 | C40: =IFERROR(INDEX('Annex 1 LV, HV and UMS charges'!$C$12:$C$30,MATCH($A40,'Annex 1 LV, HV and UMS charges'!$A$12:$A$295,0)),INDEX('Annex 4 LDNO charges'!$C$12:$C$116,MATCH($A40,'Annex 4 LDNO charges'!$A$12:$A$116,0))) -> 0 | F40: 0.18871621
A41: LDNO 132kV/EHV: Domestic Aggregated | B41: =IFERROR(INDEX('Annex 1 LV, HV and UMS charges'!$B$12:$B$30,MATCH($A41,'Annex 1 LV, HV and UMS charges'!$A$12:$A$295,0)),INDEX('Annex 4 LDNO charges'!$B$12:$B$116,MATCH($A41,'Annex 4 LDNO charges'!$A$12:$A$116,0))) -> A40 | C41: =IFERROR(INDEX('Annex 1 LV, HV and UMS charges'!$C$12:$C$30,MATCH($A41,'Annex 1 LV, HV and UMS charges'!$A$12:$A$295,0)),INDEX('Annex 4 LDNO charges'!$C$12:$C$116,MATCH($A41,'Annex 4 LDNO charges'!$A$12:$A$116,0))) -> 1, 2 or 0 | D41: 0.0079313589 | F41: 0.18871621
A42: LDNO 132kV/EHV: Non-Domestic Aggregated | B42: =IFERROR(INDEX('Annex 1 LV, HV and UMS charges'!$B$12:$B$30,MATCH($A42,'Annex 1 LV, HV and UMS charges'!$A$12:$A$295,0)),INDEX('Annex 4 LDNO charges'!$B$12:$B$116,MATCH($A42,'Annex 4 LDNO charges'!$A$12:$A$116,0))) -> C40, C41, C42, C43, C44 | C42: =IFERROR(INDEX('Annex 1 LV, HV and UMS charges'!$C$12:$C$30,MATCH($A42,'Annex 1 LV, HV and UMS charges'!$A$12:$A$295,0)),INDEX('Annex 4 LDNO charges'!$C$12:$C$116,MATCH($A42,'Annex 4 LDNO charges'!$A$12:$A$116,0))) -> 3-8 or 0 | F42: 0.18871621
A43: LDNO 132kV/EHV: LV Site Specific | B43: =IFERROR(INDEX('Annex 1 LV, HV and UMS charges'!$B$12:$B$30,MATCH($A43,'Annex 1 LV, HV and UMS charges'!$A$12:$A$295,0)),INDEX('Annex 4 LDNO charges'!$B$12:$B$116,MATCH($A43,'Annex 4 LDNO charges'!$A$12:$A$116,0))) -> E41, E42, E43, E44 | C43: =IFERROR(INDEX('Annex 1 LV, HV and UMS charges'!$C$12:$C$30,MATCH($A43,'Annex 1 LV, HV and UMS charges'!$A$12:$A$295,0)),INDEX('Annex 4 LDNO charges'!$C$12:$C$116,MATCH($A43,'Annex 4 LDNO charges'!$A$12:$A$116,0))) -> 0 | F43: 0.18871621
A44: LDNO 132kV/EHV: LV Sub Site Specific | B44: =IFERROR(INDEX('Annex 1 LV, HV and UMS charges'!$B$12:$B$30,MATCH($A44,'Annex 1 LV, HV and UMS charges'!$A$12:$A$295,0)),INDEX('Annex 4 LDNO charges'!$B$12:$B$116,MATCH($A44,'Annex 4 LDNO charges'!$A$12:$A$116,0))) -> J41, J42, J43, J44 | C44: =IFERROR(INDEX('Annex 1 LV, HV and UMS charges'!$C$12:$C$30,MATCH($A44,'Annex 1 LV, HV and UMS charges'!$A$12:$A$295,0)),INDEX('Annex 4 LDNO charges'!$C$12:$C$116,MATCH($A44,'Annex 4 LDNO charges'!$A$12:$A$116,0))) -> 0 | F44: 0.18871621
A45: LDNO 132kV/EHV: HV Site Specific | B45: =IFERROR(INDEX('Annex 1 LV, HV and UMS charges'!$B$12:$B$30,MATCH($A45,'Annex 1 LV, HV and UMS charges'!$A$12:$A$295,0)),INDEX('Annex 4 LDNO charges'!$B$12:$B$116,MATCH($A45,'Annex 4 LDNO charges'!$A$12:$A$116,0))) -> K41, K42, K43, K44 | C45: =IFERROR(INDEX('Annex 1 LV, HV and UMS charges'!$C$12:$C$30,MATCH($A45,'Annex 1 LV, HV and UMS charges'!$A$12:$A$295,0)),INDEX('Annex 4 LDNO charges'!$C$12:$C$116,MATCH($A45,'Annex 4 LDNO charges'!$A$12:$A$116,0))) -> 0 | F45: 0.18871621
A46: LDNO 132kV/EHV: LV Site Specific Storage Import | B46: =IFERROR(INDEX('Annex 1 LV, HV and UMS charges'!$B$12:$B$30,MATCH($A46,'Annex 1 LV, HV and UMS charges'!$A$12:$A$295,0)),INDEX('Annex 4 LDNO charges'!$B$12:$B$116,MATCH($A46,'Annex 4 LDNO charges'!$A$12:$A$116,0))) -> E40 | C46: =IFERROR(INDEX('Annex 1 LV, HV and UMS charges'!$C$12:$C$30,MATCH($A46,'Annex 1 LV, HV and UMS charges'!$A$12:$A$295,0)),INDEX('Annex 4 LDNO charges'!$C$12:$C$116,MATCH($A46,'Annex 4 LDNO charges'!$A$12:$A$116,0))) -> 0 | F46: 0.18871621
A47: LDNO 132kV/EHV: LV Sub Site Specific Storage Import | B47: =IFERROR(INDEX('Annex 1 LV, HV and UMS charges'!$B$12:$B$30,MATCH($A47,'Annex 1 LV, HV and UMS charges'!$A$12:$A$295,0)),INDEX('Annex 4 LDNO charges'!$B$12:$B$116,MATCH($A47,'Annex 4 LDNO charges'!$A$12:$A$116,0))) -> J40 | C47: =IFERROR(INDEX('Annex 1 LV, HV and UMS charges'!$C$12:$C$30,MATCH($A47,'Annex 1 LV, HV and UMS charges'!$A$12:$A$295,0)),INDEX('Annex 4 LDNO charges'!$C$12:$C$116,MATCH($A47,'Annex 4 LDNO charges'!$A$12:$A$116,0))) -> 0 | F47: 0.18871621
A48: LDNO 132kV/EHV: HV Site Specific Storage Import | B48: =IFERROR(INDEX('Annex 1 LV, HV and UMS charges'!$B$12:$B$30,MATCH($A48,'Annex 1 LV, HV and UMS charges'!$A$12:$A$295,0)),INDEX('Annex 4 LDNO charges'!$B$12:$B$116,MATCH($A48,'Annex 4 LDNO charges'!$A$12:$A$116,0))) -> K40 | C48: =IFERROR(INDEX('Annex 1 LV, HV and UMS charges'!$C$12:$C$30,MATCH($A48,'Annex 1 LV, HV and UMS charges'!$A$12:$A$295,0)),INDEX('Annex 4 LDNO charges'!$C$12:$C$116,MATCH($A48,'Annex 4 LDNO charges'!$A$12:$A$116,0))) -> 0 | F48: 0.18871621
A49: LDNO 132kV: Domestic Aggregated | B49: =IFERROR(INDEX('Annex 1 LV, HV and UMS charges'!$B$12:$B$30,MATCH($A49,'Annex 1 LV, HV and UMS charges'!$A$12:$A$295,0)),INDEX('Annex 4 LDNO charges'!$B$12:$B$116,MATCH($A49,'Annex 4 LDNO charges'!$A$12:$A$116,0))) -> A50 | C49: =IFERROR(INDEX('Annex 1 LV, HV and UMS charges'!$C$12:$C$30,MATCH($A49,'Annex 1 LV, HV and UMS charges'!$A$12:$A$295,0)),INDEX('Annex 4 LDNO charges'!$C$12:$C$116,MATCH($A49,'Annex 4 LDNO charges'!$A$12:$A$116,0))) -> 1, 2 or 0 | D49: 0.0079313589 | F49: 0.18871621
A50: LDNO 132kV: Non-Domestic Aggregated | B50: =IFERROR(INDEX('Annex 1 LV, HV and UMS charges'!$B$12:$B$30,MATCH($A50,'Annex 1 LV, HV and UMS charges'!$A$12:$A$295,0)),INDEX('Annex 4 LDNO charges'!$B$12:$B$116,MATCH($A50,'Annex 4 LDNO charges'!$A$12:$A$116,0))) -> C50, C51, C52, C53, C54 | C50: =IFERROR(INDEX('Annex 1 LV, HV and UMS charges'!$C$12:$C$30,MATCH($A50,'Annex 1 LV, HV and UMS charges'!$A$12:$A$295,0)),INDEX('Annex 4 LDNO charges'!$C$12:$C$116,MATCH($A50,'Annex 4 LDNO charges'!$A$12:$A$116,0))) -> 3-8 or 0 | F50: 0.18871621
A51: LDNO 132kV: LV Site Specific | B51: =IFERROR(INDEX('Annex 1 LV, HV and UMS charges'!$B$12:$B$30,MATCH($A51,'Annex 1 LV, HV and UMS charges'!$A$12:$A$295,0)),INDEX('Annex 4 LDNO charges'!$B$12:$B$116,MATCH($A51,'Annex 4 LDNO charges'!$A$12:$A$116,0))) -> E51, E52, E53, E54 | C51: =IFERROR(INDEX('Annex 1 LV, HV and UMS charges'!$C$12:$C$30,MATCH($A51,'Annex 1 LV, HV and UMS charges'!$A$12:$A$295,0)),INDEX('Annex 4 LDNO charges'!$C$12:$C$116,MATCH($A51,'Annex 4 LDNO charges'!$A$12:$A$116,0))) -> 0 | F51: 0.18871621
A52: LDNO 132kV: LV Sub Site Specific | B52: =IFERROR(INDEX('Annex 1 LV, HV and UMS charges'!$B$12:$B$30,MATCH($A52,'Annex 1 LV, HV and UMS charges'!$A$12:$A$295,0)),INDEX('Annex 4 LDNO charges'!$B$12:$B$116,MATCH($A52,'Annex 4 LDNO charges'!$A$12:$A$116,0))) -> J51, J52, J53, J54 | C52: =IFERROR(INDEX('Annex 1 LV, HV and UMS charges'!$C$12:$C$30,MATCH($A52,'Annex 1 LV, HV and UMS charges'!$A$12:$A$295,0)),INDEX('Annex 4 LDNO charges'!$C$12:$C$116,MATCH($A52,'Annex 4 LDNO charges'!$A$12:$A$116,0))) -> 0 | F52: 0.18871621
A53: LDNO 132kV: HV Site Specific | B53: =IFERROR(INDEX('Annex 1 LV, HV and UMS charges'!$B$12:$B$30,MATCH($A53,'Annex 1 LV, HV and UMS charges'!$A$12:$A$295,0)),INDEX('Annex 4 LDNO charges'!$B$12:$B$116,MATCH($A53,'Annex 4 LDNO charges'!$A$12:$A$116,0))) -> K51, K52, K53, K54 | C53: =IFERROR(INDEX('Annex 1 LV, HV and UMS charges'!$C$12:$C$30,MATCH($A53,'Annex 1 LV, HV and UMS charges'!$A$12:$A$295,0)),INDEX('Annex 4 LDNO charges'!$C$12:$C$116,MATCH($A53,'Annex 4 LDNO charges'!$A$12:$A$116,0))) -> 0 | F53: 0.18871621
A54: LDNO 132kV: LV Site Specific Storage Import | B54: =IFERROR(INDEX('Annex 1 LV, HV and UMS charges'!$B$12:$B$30,MATCH($A54,'Annex 1 LV, HV and UMS charges'!$A$12:$A$295,0)),INDEX('Annex 4 LDNO charges'!$B$12:$B$116,MATCH($A54,'Annex 4 LDNO charges'!$A$12:$A$116,0))) -> E50 | C54: =IFERROR(INDEX('Annex 1 LV, HV and UMS charges'!$C$12:$C$30,MATCH($A54,'Annex 1 LV, HV and UMS charges'!$A$12:$A$295,0)),INDEX('Annex 4 LDNO charges'!$C$12:$C$116,MATCH($A54,'Annex 4 LDNO charges'!$A$12:$A$116,0))) -> 0 | F54: 0.18871621
A55: LDNO 132kV: LV Sub Site Specific Storage Import | B55: =IFERROR(INDEX('Annex 1 LV, HV and UMS charges'!$B$12:$B$30,MATCH($A55,'Annex 1 LV, HV and UMS charges'!$A$12:$A$295,0)),INDEX('Annex 4 LDNO charges'!$B$12:$B$116,MATCH($A55,'Annex 4 LDNO charges'!$A$12:$A$116,0))) -> J50 | C55: =IFERROR(INDEX('Annex 1 LV, HV and UMS charges'!$C$12:$C$30,MATCH($A55,'Annex 1 LV, HV and UMS charges'!$A$12:$A$295,0)),INDEX('Annex 4 LDNO charges'!$C$12:$C$116,MATCH($A55,'Annex 4 LDNO charges'!$A$12:$A$116,0))) -> 0 | F55: 0.18871621
A56: LDNO 132kV: HV Site Specific Storage Import | B56: =IFERROR(INDEX('Annex 1 LV, HV and UMS charges'!$B$12:$B$30,MATCH($A56,'Annex 1 LV, HV and UMS charges'!$A$12:$A$295,0)),INDEX('Annex 4 LDNO charges'!$B$12:$B$116,MATCH($A56,'Annex 4 LDNO charges'!$A$12:$A$116,0))) -> K50 | C56: =IFERROR(INDEX('Annex 1 LV, HV and UMS charges'!$C$12:$C$30,MATCH($A56,'Annex 1 LV, HV and UMS charges'!$A$12:$A$295,0)),INDEX('Annex 4 LDNO charges'!$C$12:$C$116,MATCH($A56,'Annex 4 LDNO charges'!$A$12:$A$116,0))) -> 0 | F56: 0.18871621
A57: LDNO 0000: Domestic Aggregated | B57: =IFERROR(INDEX('Annex 1 LV, HV and UMS charges'!$B$12:$B$30,MATCH($A57,'Annex 1 LV, HV and UMS charges'!$A$12:$A$295,0)),INDEX('Annex 4 LDNO charges'!$B$12:$B$116,MATCH($A57,'Annex 4 LDNO charges'!$A$12:$A$116,0))) -> A60 | C57: =IFERROR(INDEX('Annex 1 LV, HV and UMS charges'!$C$12:$C$30,MATCH($A57,'Annex 1 LV, HV and UMS charges'!$A$12:$A$295,0)),INDEX('Annex 4 LDNO charges'!$C$12:$C$116,MATCH($A57,'Annex 4 LDNO charges'!$A$12:$A$116,0))) -> 1, 2 or 0 | D57: 0.0079313589 | F57: 0.18871621
A58: LDNO 0000: Non-Domestic Aggregated | B58: =IFERROR(INDEX('Annex 1 LV, HV and UMS charges'!$B$12:$B$30,MATCH($A58,'Annex 1 LV, HV and UMS charges'!$A$12:$A$295,0)),INDEX('Annex 4 LDNO charges'!$B$12:$B$116,MATCH($A58,'Annex 4 LDNO charges'!$A$12:$A$116,0))) -> C60, C61, C62, C63, C64 | C58: =IFERROR(INDEX('Annex 1 LV, HV and UMS charges'!$C$12:$C$30,MATCH($A58,'Annex 1 LV, HV and UMS charges'!$A$12:$A$295,0)),INDEX('Annex 4 LDNO charges'!$C$12:$C$116,MATCH($A58,'Annex 4 LDNO charges'!$A$12:$A$116,0))) -> 3-8 or 0 | F58: 0.18871621
A59: LDNO 0000: LV Site Specific | B59: =IFERROR(INDEX('Annex 1 LV, HV and UMS charges'!$B$12:$B$30,MATCH($A59,'Annex 1 LV, HV and UMS charges'!$A$12:$A$295,0)),INDEX('Annex 4 LDNO charges'!$B$12:$B$116,MATCH($A59,'Annex 4 LDNO charges'!$A$12:$A$116,0))) -> E61, E62, E63, E64 | C59: =IFERROR(INDEX('Annex 1 LV, HV and UMS charges'!$C$12:$C$30,MATCH($A59,'Annex 1 LV, HV and UMS charges'!$A$12:$A$295,0)),INDEX('Annex 4 LDNO charges'!$C$12:$C$116,MATCH($A59,'Annex 4 LDNO charges'!$A$12:$A$116,0))) -> 0 | F59: 0.18871621
A60: LDNO 0000: LV Sub Site Specific | B60: =IFERROR(INDEX('Annex 1 LV, HV and UMS charges'!$B$12:$B$30,MATCH($A60,'Annex 1 LV, HV and UMS charges'!$A$12:$A$295,0)),INDEX('Annex 4 LDNO charges'!$B$12:$B$116,MATCH($A60,'Annex 4 LDNO charges'!$A$12:$A$116,0))) -> J61, J62, J63, J64 | C60: =IFERROR(INDEX('Annex 1 LV, HV and UMS charges'!$C$12:$C$30,MATCH($A60,'Annex 1 LV, HV and UMS charges'!$A$12:$A$295,0)),INDEX('Annex 4 LDNO charges'!$C$12:$C$116,MATCH($A60,'Annex 4 LDNO charges'!$A$12:$A$116,0))) -> 0 | F60: 0.18871621
A61: LDNO 0000: HV Site Specific | B61: =IFERROR(INDEX('Annex 1 LV, HV and UMS charges'!$B$12:$B$30,MATCH($A61,'Annex 1 LV, HV and UMS charges'!$A$12:$A$295,0)),INDEX('Annex 4 LDNO charges'!$B$12:$B$116,MATCH($A61,'Annex 4 LDNO charges'!$A$12:$A$116,0))) -> K61, K62, K63, K64 | C61: =IFERROR(INDEX('Annex 1 LV, HV and UMS charges'!$C$12:$C$30,MATCH($A61,'Annex 1 LV, HV and UMS charges'!$A$12:$A$295,0)),INDEX('Annex 4 LDNO charges'!$C$12:$C$116,MATCH($A61,'Annex 4 LDNO charges'!$A$12:$A$116,0))) -> 0 | F61: 0.18871621
A62: LDNO 0000: LV Site Specific Storage Import | B62: =IFERROR(INDEX('Annex 1 LV, HV and UMS charges'!$B$12:$B$30,MATCH($A62,'Annex 1 LV, HV and UMS charges'!$A$12:$A$295,0)),INDEX('Annex 4 LDNO charges'!$B$12:$B$116,MATCH($A62,'Annex 4 LDNO charges'!$A$12:$A$116,0))) -> E60 | C62: =IFERROR(INDEX('Annex 1 LV, HV and UMS charges'!$C$12:$C$30,MATCH($A62,'Annex 1 LV, HV and UMS charges'!$A$12:$A$295,0)),INDEX('Annex 4 LDNO charges'!$C$12:$C$116,MATCH($A62,'Annex 4 LDNO charges'!$A$12:$A$116,0))) -> 0 | F62: 0.18871621
A63: LDNO 0000: LV Sub Site Specific Storage Import | B63: =IFERROR(INDEX('Annex 1 LV, HV and UMS charges'!$B$12:$B$30,MATCH($A63,'Annex 1 LV, HV and UMS charges'!$A$12:$A$295,0)),INDEX('Annex 4 LDNO charges'!$B$12:$B$116,MATCH($A63,'Annex 4 LDNO charges'!$A$12:$A$116,0))) -> J60 | C63: =IFERROR(INDEX('Annex 1 LV, HV and UMS charges'!$C$12:$C$30,MATCH($A63,'Annex 1 LV, HV and UMS charges'!$A$12:$A$295,0)),INDEX('Annex 4 LDNO charges'!$C$12:$C$116,MATCH($A63,'Annex 4 LDNO charges'!$A$12:$A$116,0))) -> 0 | F63: 0.18871621
A64: LDNO 0000: HV Site Specific Storage Import | B64: =IFERROR(INDEX('Annex 1 LV, HV and UMS charges'!$B$12:$B$30,MATCH($A64,'Annex 1 LV, HV and UMS charges'!$A$12:$A$295,0)),INDEX('Annex 4 LDNO charges'!$B$12:$B$116,MATCH($A64,'Annex 4 LDNO charges'!$A$12:$A$116,0))) -> K60 | C64: =IFERROR(INDEX('Annex 1 LV, HV and UMS charges'!$C$12:$C$30,MATCH($A64,'Annex 1 LV, HV and UMS charges'!$A$12:$A$295,0)),INDEX('Annex 4 LDNO charges'!$C$12:$C$116,MATCH($A64,'Annex 4 LDNO charges'!$A$12:$A$116,0))) -> 0 | F64: 0.18871621
A65: *Supplier of Last Resort pass-through costs which are recovered on a two year lag allocated to all domestic tariffs with a fixed charge (including LDNO)
A66: **Supplier of Last Resort pass-through costs which are not recovered on a two year lag allocated to all domestic tariffs with a fixed charge (including LDNO)
A67: ***Eligible Bad Debt pass-through costs allocated to all metered demand tariffs (including LDNO)

Sheet Nodal prices
A1: Back to Overview
A2: =Overview!B4& " - Effective from "&Overview!D4&" - "&Overview!E4&" Nodal/Zonal charges" -> South Eastern Power Networks - Effective from 1 April 2021 - Final Nodal/Zonal charges
A3: Node/Zone ID | B3: Geographical name | C3: Local charge 1 £/kVA | D3: Remote charge 1 £/kVA
A4: ABNR31 | B4: SPN 0003 | C4: 0.15085038 | D4: 0.57745168
A5: ABNR32 | B5: SPN 0003 | C5: 0.15085038 | D5: 0.57745168
A6: ADDG51 | B6: Addington Grid | C6: 0 | D6: 8.3999824
A7: ADDL51 | B7: Addington Local | C7: 0.21257181 | D7: 8.5967273
A8: ADDL52 | B8: Addington Local | C8: 0.032849622 | D8: 8.4855916
A9: ALLG51 | B9: SPN 0018 | C9: 0 | D9: 0
A10: ANGM51 | B10: Angmering | C10: -0.98762528 | D10: 3.7099884
A11: ANGM52 | B11: Angmering | C11: -0.054859679 | D11: 15.11743
A12: AREP31 | B12: SPN 0084 | C12: 0.85185084 | D12: 1.4517702
A13: AREP91 | B13: SPN 0084 | C13: 0 | D13: 3.8286703
A14: ARLP31 | B14: SPN 0084 | C14: 0 | D14: 0
A15: ARLP91 | B15: SPN 0067 | C15: -0.22493662 | D15: 2.9064819
... A446: XWAY51 | B446: Crossways | C446: 0.051677687 | D446: 2.9085064

Sheet SSC unit rate lookup
A1: Back to Overview
A28: Standard Settlement Configuration Id | B28: Standard Settlement Configuration Desc | C28: Common Decode | F28: Change implemented | G28: Date | H28: Comments
A29: 3 | B29: 10-hour OP | C29: A/R | F29: Notes updated | G29: 43626 | H29: Updated to reflect DCP 268 which delinks all tariffs from the TPR bands
A30: 4 | B30: 10-hour OP | C30: A/R | F30: Code 1 & 2 changed to A | G30: 43626 | H30: Updated to reflect DCP 268 which delinks all tariffs from the TPR bands
A31: 5 | B31: 10-hour OP + w/e | C31: A/R | F31: Code O changed to A/R | G31: 43626 | H31: Updated to reflect DCP 268 which delinks all tariffs from the TPR bands
A32: 6 | B32: 10.5-hour OP | C32: A/R | F32: Removed TPR | G32: 43626 | H32: Removed TPR lookup element as this no longer effects which rate to apply
A33: 7 | B33: 10.5-hour OP | C33: A/R
A34: 8 | B34: 10.5-hour OP | C34: A/R
A35: 9 | B35: 10.5-hour OP | C35: A/R
A36: 10 | B36: 10.5-hour OP | C36: A/R
A37: 11 | B37: 10.5-hour OP | C37: A/R
A38: 12 | B38: 10.5-hour OP | C38: A/R
A39: 13 | B39: 11 Hour OP | C39: A/R
A40: 15 | B40: 11 Hour OP | C40: A/R
A41: 16 | B41: 11.5-hour OP | C41: A/R
A42: 17 | B42: 11.5-hour OP | C42: A/R
A43: 18 | B43: 11.5-hour OP | C43: A/R
A44: 19 | B44: 11.5-hour OP | C44: A/R
... A764: 997 | B764: Evening/Weekend - BST | C764: A

Sheet Charge Calculator
B1: Back to Overview
B2: =Overview!B4& " - Effective from "&Overview!D4&" - "&Overview!E4 -> South Eastern Power Networks - Effective from 1 April 2021 - Final | AC2: Red/black unit charge p/kWh | AD2: Amber/yellow unit charge p/kWh | AE2: Green unit charge p/kWh | AF2: Fixed charge p/MPAN/day | AG2: Capacity charge p/kVA/day | AH2: Exceeded capacity charge p/kVA/day | AI2: Reactive power charge p/kVArh
AB3: Domestic Aggregated | AC3: Red unit charge p/kWh | AD3: Amber unit charge p/kWh | AE3: Green unit charge p/kWh | AF3: Fixed charge p/MPAN/day | AG3: n/a | AH3: n/a | AI3: n/a
B4: LV and HV designated properties and Unmetered Supplies tariff calculator | L4: EHV designated property calculator | AB4: Domestic Aggregated (related MPAN) | AC4: Red unit charge p/kWh | AD4: Amber unit charge p/kWh | AE4: Green unit charge p/kWh | AF4: n/a | AG4: n/a | AH4: n/a | AI4: n/a
B5: Step 1, Choose your tariff using the drop down list in cell B10 | L5: Step 1, Choose your tariff using the drop down list in cell L10 | AB5: Non-Domestic Aggregated | AC5: Red unit charge p/kWh | AD5: Amber unit charge p/kWh | AE5: Green unit charge p/kWh | AF5: Fixed charge p/MPAN/day | AG5: n/a | AH5: n/a | AI5: n/a
B6: Step 2, After selecting a tariff in step 1, Cells C12-I12 will generate headings, please enter your consumption in cells C13:I13 underneath each heading generated (if no heading leave cell blank) | L6: Step 2, After selecting a tariff in step 1, Cells M12-T12 will generate headings, please enter your consumption in cells M13:T13 underneath each heading generated (if no heading leave cell blank) | AB6: Non-Domestic Aggregated (related MPAN) | AC6: Red unit charge p/kWh | AD6: Amber unit charge p/kWh | AE6: Green unit charge p/kWh | AF6: n/a | AG6: n/a | AH6: n/a | AI6: n/a
B7: Step 3, Enter a forecast of consumption if required in cells C14:I14 | L7: Step 3, Enter a forecast of consumption if required in cells M14:T14 | AB7: LV Site Specific | AC7: Red unit charge p/kWh | AD7: Amber unit charge p/kWh | AE7: Green unit charge p/kWh | AF7: Fixed charge p/MPAN/day | AG7: Capacity charge p/kVA/day | AH7: Exceeded Capacity charge p/kVA/day | AI7: Reactive power charge p/kVArh
AB8: LV Sub Site Specific | AC8: Red unit charge p/kWh | AD8: Amber unit charge p/kWh | AE8: Green unit charge p/kWh | AF8: Fixed charge p/MPAN/day | AG8: Capacity charge p/kVA/day | AH8: Exceeded Capacity charge p/kVA/day | AI8: Reactive power charge p/kVArh
B9: Tariff details Choose tariff name from drop down box below | C9: =IFERROR(VLOOKUP($B$10,$AB$2:$AI$18,2,FALSE),AC2) -> Red unit charge p/kWh | D9: =IFERROR(VLOOKUP($B$10,$AB$2:$AI$18,3,FALSE),AD2) -> Amber unit charge p/kWh | E9: =IFERROR(VLOOKUP($B$10,$AB$2:$AI$18,4,FALSE),AE2) -> Green unit charge p/kWh | F9: =IFERROR(VLOOKUP($B$10,$AB$2:$AI$18,5,FALSE),AF2) -> Fixed charge p/MPAN/day | G9: =IFERROR(VLOOKUP($B$10,$AB$2:$AI$18,6,FALSE),AG2) -> Capacity charge p/kVA/day | H9: =IFERROR(VLOOKUP($B$10,$AB$2:$AI$18,7,FALSE),AH2) -> Exceeded Capacity charge p/kVA/day | I9: =IFERROR(VLOOKUP($B$10,$AB$2:$AI$18,8,FALSE),AI2) -> Reactive power charge p/kVArh | L9: Site details Choose the site name from the drop down box below | M9: ='Annex 2 EHV charges'!H9 -> Import Super Red unit charge (p/kWh) | N9: ='Annex 2 EHV charges'!I9 -> Import fixed charge (p/day) | O9: ='Annex 2 EHV charges'!J9 -> Import capacity charge (p/kVA/day) | P9: ='Annex 2 EHV charges'!K9 -> Import exceeded capacity charge (p/kVA/day) | Q9: ='Annex 2 EHV charges'!L9 -> Export Super Red unit charge (p/kWh) | R9: ='Annex 2 EHV charges'!M9 -> Export fixed charge (p/day) | S9: ='Annex 2 EHV charges'!N9 -> Export capacity charge (p/kVA/day) | T9: ='Annex 2 EHV charges'!O9 -> Export exceeded capacity charge (p/kVA/day) | AB9: HV Site Specific | AC9: Red unit charge p/kWh | AD9: Amber unit charge p/kWh | AE9: Green unit charge p/kWh | AF9: Fixed charge p/MPAN/day | AG9: Capacity charge p/kVA/day | AH9: Exceeded Capacity charge p/kVA/day | AI9: Reactive power charge p/kVArh
B10: LV Site Specific | C10: =IFERROR(VLOOKUP($B$10,'Annex 1 LV, HV and UMS charges'!$A:$K,4,FALSE),"") -> 9.09 | D10: =IFERROR(VLOOKUP($B$10,'Annex 1 LV, HV and UMS charges'!$A:$K,5,FALSE),"") -> 0.881 | E10: =IFERROR(VLOOKUP($B$10,'Annex 1 LV, HV and UMS charges'!$A:$K,6,FALSE),"") -> 0.61 | F10: =IFERROR(VLOOKUP($B$10,'Annex 1 LV, HV and UMS charges'!$A:$K,7,FALSE),"") -> 11.31 | G10: =IFERROR(VLOOKUP($B$10,'Annex 1 LV, HV and UMS charges'!$A:$K,8,FALSE),"") -> 3.68 | H10: =IFERROR(VLOOKUP($B$10,'Annex 1 LV, HV and UMS charges'!$A:$K,9,FALSE),"") -> 7.12 | I10: =IFERROR(VLOOKUP($B$10,'Annex 1 LV, HV and UMS charges'!$A:$K,10,FALSE),"") -> 0.276 | M10: =IFERROR(VLOOKUP($L$10,'Annex 2 EHV charges'!$G:$O,2,FALSE),"") | N10: =IFERROR(VLOOKUP($L$10,'Annex 2 EHV charges'!$G:$O,3,FALSE),"") | O10: =IFERROR(VLOOKUP($L$10,'Annex 2 EHV charges'!$G:$O,4,FALSE),"") | P10: =IFERROR(VLOOKUP($L$10,'Annex 2 EHV charges'!$G:$O,5,FALSE),"") | Q10: =IFERROR(VLOOKUP($L$10,'Annex 2 EHV charges'!$G:$O,6,FALSE),"") | R10: =IFERROR(VLOOKUP($L$10,'Annex 2 EHV charges'!$G:$O,7,FALSE),"") | S10: =IFERROR(VLOOKUP($L$10,'Annex 2 EHV charges'!$G:$O,8,FALSE),"") | T10: =IFERROR(VLOOKUP($L$10,'Annex 2 EHV charges'!$G:$O,9,FALSE),"") | AB10: Unmetered Supplies | AC10: Black unit charge p/kWh | AD10: Yellow unit charge p/kWh | AE10: Green unit charge p/kWh | AF10: n/a | AG10: n/a | AH10: n/a | AI10: n/a
AB11: LV Generation Aggregated | AC11: Red unit charge p/kWh | AD11: Amber unit charge p/kWh | AE11: Green unit charge p/kWh | AF11: Fixed charge p/MPAN/day | AG11: n/a | AH11: n/a | AI11: n/a
B12: Tariff components | C12: =C9 -> Red unit charge p/kWh | D12: =D9 -> Amber unit charge p/kWh | E12: =E9 -> Green unit charge p/kWh | F12: Number of days in consumption period i.e. 365 if one year | G12: Maximum import or export capacity kVA | H12: Average daily exceeded capacity kVA | I12: Excess reactive units kVArh | L12: Tariff components | M12: Import super red kWh | N12: Number of days in consumption period i.e. 365 if one year | O12: Maximum import capacity kVA | P12: Average daily exceeded capacity kVA | Q12: Export Super Red kWh | R12: Number of days in consumption period i.e. 365 if one year | S12: Maximum export capacity kVA | T12: Average daily exceeded capacity kVA | AB12: LV Sub Generation Aggregated | AC12: Red unit charge p/kWh | AD12: Amber unit charge p/kWh | AE12: Green unit charge p/kWh | AF12: Fixed charge p/MPAN/day | AG12: n/a | AH12: n/a | AI12: n/a
B13: Enter current consumption details | L13: Enter current consumption details | R13: =N13 -> 0 | AB13: LV Generation Site Specific | AC13: Red unit charge p/kWh | AD13: Amber unit charge p/kWh | AE13: Green unit charge p/kWh | AF13: Fixed charge p/MPAN/day | AG13: n/a | AH13: n/a | AI13: Reactive power charge p/kVArh
B14: Enter forecast consumption details (if different) | C14: =C13 -> 0 | D14: =D13 -> 0 | E14: =E13 -> 0 | F14: =F13 -> 0 | G14: =G13 -> 0 | H14: =H13 -> 0 | I14: =I13 -> 0 | L14: Enter forecast consumption details (if different) | M14: =M13 -> 0 | N14: =N13 -> 0 | O14: =O13 -> 0 | P14: =P13 -> 0 | Q14: =Q13 -> 0 | R14: =R13 -> 0 | S14: =S13 -> 0 | T14: =T13 -> 0 | AB14: LV Generation Site Specific no RP charge | AC14: Red unit charge p/kWh | AD14: Amber unit charge p/kWh | AE14: Green unit charge p/kWh | AF14: Fixed charge p/MPAN/day | AG14: n/a | AH14: n/a | AI14: n/a
AB15: LV Sub Generation Site Specific | AC15: Red unit charge p/kWh | AD15: Amber unit charge p/kWh | AE15: Green unit charge p/kWh | AF15: Fixed charge p/MPAN/day | AG15: n/a | AH15: n/a | AI15: Reactive power charge p/kVArh
B16: Charge components | C16: Unit 1 £ | D16: Unit 2 £ | E16: Unit 3 £ | F16: Fixed charge £ | G16: Capacity charge £ | H16: Exceeded capacity charge £ | I16: Reactive power charge £ | L16: Charge components | M16: Import super red charge £ | N16: Import fixed charge £ | O16: Import capacity charge £ | P16: Import exceeded capacity charge £ | Q16: Export super red charge £ | R16: Export fixed charge £ | S16: Export capacity charge £ | T16: Export exceeded capacity charge £ | AB16: LV Sub Generation Site Specific no RP charge | AC16: Red unit charge p/kWh | AD16: Amber unit charge p/kWh | AE16: Green unit charge p/kWh | AF16: Fixed charge p/MPAN/day | AG16: n/a | AH16: n/a | AI16: n/a
B17: Current consumption period charges | C17: =IFERROR(C10*C13/100,"") -> 0 | D17: =IFERROR(D10*D13/100,"") -> 0 | E17: =IFERROR(E10*E13/100,"") -> 0 | F17: =IFERROR(F10*F13/100,"") -> 0 | G17: =IFERROR(G10*G13*F13/100,"") -> 0 | H17: =IFERROR(H10*H13*F13/100,"") -> 0 | I17: =IFERROR(I10*I13/100,"") -> 0 | L17: Current consumption period charges | M17: =IFERROR(M10*M13/100,"") | N17: =IFERROR(N10*N13/100,"") | O17: =IFERROR(O10*O13*N13/100,"") | P17: =IFERROR(P10*P13*N13/100,"") | Q17: =IFERROR(Q10*Q13/100,"") | R17: =IFERROR(R10*R13/100,"") | S17: =IFERROR(S10*S13*R13/100,"") | T17: =IFERROR(T10*T13*R13/100,"") | AB17: HV Generation Site Specific | AC17: Red unit charge p/kWh | AD17: Amber unit charge p/kWh | AE17: Green unit charge p/kWh | AF17: Fixed charge p/MPAN/day | AG17: n/a | AH17: n/a | AI17: Reactive power charge p/kVArh
B18: Forecast consumption period charges | C18: =IFERROR(C10*C14/100,"") -> 0 | D18: =IFERROR(D10*D14/100,"") -> 0 | E18: =IFERROR(E10*E14/100,"") -> 0 | F18: =IFERROR(F10*F14/100,"") -> 0 | G18: =IFERROR(G10*G14*F14/100,"") -> 0 | H18: =IFERROR(H10*H14*F14/100,"") -> 0 | I18: =IFERROR(I10*I14/100,"") -> 0 | L18: Forecast consumption period charges | M18: =IFERROR(M10*M14/100,"") | N18: =IFERROR(N10*N14/100,"") | O18: =IFERROR(O10*O14*N14/100,"") | P18: =IFERROR(P10*P14*N14/100,"") | Q18: =IFERROR(Q10*Q14/100,"") | R18: =IFERROR(R10*R14/100,"") | S18: =IFERROR(S10*S14*R14/100,"") | T18: =IFERROR(T10*T14*R14/100,"") | AB18: HV Generation Site Specific no RP charge | AC18: Red unit charge p/kWh | AD18: Amber unit charge p/kWh | AE18: Green unit charge p/kWh | AF18: Fixed charge p/MPAN/day | AG18: n/a | AH18: n/a | AI18: n/a
C20: Total charge £ | M20: Import total charge £ | N20: Export total charge £
B21: Current consumption period charges | C21: =SUM(C17:I17) -> 0 | L21: Current consumption period charges | M21: =SUM(M17:P17) -> 0 | N21: =SUM(Q17:T17) -> 0
B22: Forecast consumption period charges | C22: =SUM(C18:I18) -> 0 | L22: Forecast consumption period charges | M22: =SUM(M18:P18) -> 0 | N22: =SUM(Q18:T18) -> 0
B24: These charges are estimates based on tariff selected and consumption values entered. | L24: These charges are estimates based on site selected and consumption values entered.
